Workbook

Sheet Totals
A1: Account Category | B1: Jan | C1: Feb | D1: Mar | E1: Apr | F1: May | G1: Jun | H1: Jul | I1: Aug | J1: Sep | K1: Oct | L1: Nov | M1: Dec | N1: TOTAL | P1: Budget | Q1: Goal | R1: AVG/MONTH | S1: BUDGET AVG/MONTH
A2: 2021 Year
A4: SOS | B4: ='Revnue - Spot On Supplies 2022'!$I$34 -> 0 | C4: ='Revnue - Spot On Supplies 2022'!$J$34 -> 78.93 | D4: ='Revnue - Spot On Supplies 2022'!$K$34 -> 303.02 | E4: ='Revnue - Spot On Supplies 2022'!$L$34 -> 260.79 | F4: ='Revnue - Spot On Supplies 2022'!$M$34 -> 698.58 | G4: ='Revnue - Spot On Supplies 2022'!$N$34 -> 321.26 | H4: ='Revnue - Spot On Supplies 2022'!$O$34 -> 1160.82 | I4: ='Revnue - Spot On Supplies 2022'!$P$34 -> 325.16 | J4: ='Revnue - Spot On Supplies 2022'!$Q$34 -> 1529.58 | K4: ='Revnue - Spot On Supplies 2022'!$R$34 -> 845.82 | L4: 0 | M4: 0 | N4: ='Revnue - Spot On Supplies 2022'!$U$34 -> 5775.42 | P4: ='Revnue - Spot On Supplies 2022'!$W$34 -> 25051 | Q4: ='Revnue - Spot On Supplies 2022'!$X$34 -> 37551 | R4: ='Revnue - Spot On Supplies 2022'!$Y$34 -> 481.285 | S4: =P4/12 -> 2087.5833
A5: SOE | B5: ='SO Equipment 2022'!$I$17 -> 0 | C5: ='SO Equipment 2022'!$J$17 -> 0 | D5: ='SO Equipment 2022'!$K$17 -> 0 | E5: ='SO Equipment 2022'!$L$17 -> 0 | F5: ='SO Equipment 2022'!$M$17 -> 0 | G5: ='SO Equipment 2022'!$N$17 -> 0 | H5: ='SO Equipment 2022'!$O$17 -> 0 | I5: ='SO Equipment 2022'!$P$17 -> 0 | J5: ='SO Equipment 2022'!$Q$17 -> 0 | K5: ='SO Equipment 2022'!$R$17 -> 0 | L5: ='SO Equipment 2022'!$R$17 -> 0 | M5: ='SO Equipment 2022'!$R$17 -> 0 | N5: ='SO Equipment 2022'!$U$17 -> 0 | P5: ='SO Equipment 2022'!$W$17 -> 120000 | Q5: ='SO Equipment 2022'!$X$17 -> 240000 | R5: ='SO Equipment 2022'!$Y$17 -> 0 | S5: =P5/12 -> 10000
A6: NSO Supplies | B6: ='Revnue - NSO Supplies 2021'!$I$990 -> 3452.69 | C6: ='Revnue - NSO Supplies 2021'!$J$990 -> 11731.19 | D6: ='Revnue - NSO Supplies 2021'!$K$990 -> 26055.33 | E6: ='Revnue - NSO Supplies 2021'!$L$990 -> 32150.805 | F6: ='Revnue - NSO Supplies 2021'!$M$990 -> 15623.35 | G6: ='Revnue - NSO Supplies 2021'!$N$990 -> 24178.67 | H6: ='Revnue - NSO Supplies 2021'!$O$990 -> 19129.72 | I6: ='Revnue - NSO Supplies 2021'!$P$990 -> 17865.57 | J6: ='Revnue - NSO Supplies 2021'!$Q$990 -> 15961.28 | K6: ='Revnue - NSO Supplies 2021'!$R$990 -> 21294.66 | L6: 21385.78 | M6: 18005 | N6: ='Revnue - NSO Supplies 2021'!$U$990 -> 187443.27 | P6: ='Revnue - NSO Supplies 2021'!$W$990 -> 281656 | Q6: ='Revnue - NSO Supplies 2021'!$X$990 -> 437656 | R6: ='Revnue - NSO Supplies 2021'!$Y$990 -> 15620.272 | S6: =P6/12 -> 23471.333
A7: Equipment | B7: ='Revenue - Equipment 2022'!$I$28 -> 2079.41 | C7: ='Revenue - Equipment 2022'!$J$28 -> 5678.35 | D7: ='Revenue - Equipment 2022'!$K$28 -> 0 | E7: ='Revenue - Equipment 2022'!$L$28 -> 0 | F7: ='Revenue - Equipment 2022'!$M$28 -> 0 | G7: ='Revenue - Equipment 2022'!$N$28 -> 795 | H7: ='Revenue - Equipment 2022'!$O$28 -> 5239.23 | I7: ='Revenue - Equipment 2022'!$P$28 -> 2845.74 | J7: ='Revenue - Equipment 2022'!$Q$28 -> 325 | K7: ='Revenue - Equipment 2022'!$R$28 -> 2885 | L7: ='Revenue - Equipment 2022'!$S$28 -> 0 | M7: ='Revenue - Equipment 2022'!$T$28 -> 10465 | N7: ='Revenue - Equipment 2022'!$U$28 -> 30312.73 | P7: ='Revenue - Equipment 2022'!$W$28 -> 23153 | Q7: ='Revenue - Equipment 2022'!$X$28 -> 33153 | R7: ='Revenue - Equipment 2022'!$Y$28 -> 2526.0608 | S7: =P7/12 -> 1929.4167
A8: Service | B8: ='Revnue - Service 2022'!$I$15 -> 0 | C8: ='Revnue - Service 2022'!$J$15 -> 270 | D8: ='Revnue - Service 2022'!$K$15 -> 0 | E8: ='Revnue - Service 2022'!$L$15 -> 0 | F8: ='Revnue - Service 2022'!$M$15 -> 0 | G8: ='Revnue - Service 2022'!$N$15 -> 0 | H8: ='Revnue - Service 2022'!$O$15 -> 810 | I8: ='Revnue - Service 2022'!$P$15 -> 975 | J8: ='Revnue - Service 2022'!$Q$15 -> 1530 | K8: ='Revnue - Service 2022'!$R$15 -> 720 | L8: 0 | M8: 0 | N8: ='Revnue - Service 2022'!$U$15 -> 4305 | P8: ='Revnue - Service 2022'!$W$15 -> 900 | Q8: ='Revnue - Service 2022'!$X$15 -> 1500 | R8: ='Revnue - Service 2022'!$Y$15 -> 358.75 | S8: =P8/12 -> 75
A10: ='Revnue - Spot On Supplies 2022'!$A$34 -> *** RUNNING TOTAL *** | B10: =SUM(B4:B8) -> 5532.1 | C10: =SUM(C4:C8) -> 17758.47 | D10: =SUM(D4:D8) -> 26358.35 | E10: =SUM(E4:E8) -> 32411.595 | F10: =SUM(F4:F8) -> 16321.93 | G10: =SUM(G4:G8) -> 25294.93 | H10: =SUM(H4:H8) -> 26339.77 | I10: =SUM(I4:I8) -> 22011.47 | ... N10: =SUM(N4:N8) -> 227836.42 | P10: =SUM(P4:P8) -> 450760 | Q10: =SUM(Q4:Q8) -> 749860 | R10: =N10/12 -> 18986.368 | S10: =SUM(S4:S8) -> 37563.333
A13: Account Category | B13: Jan | C13: Feb | D13: Mar | E13: Apr | F13: May | G13: Jun | H13: Jul | I13: Aug | J13: Sep | K13: Oct | L13: Nov | M13: Dec | N13: TOTAL | P13: Budget | Q13: Goal | R13: AVG/MONTH | S13: BUDGET AVG/MONTH
A14: 2022 Year
A16: SOS | B16: ='Revnue - Spot On Supplies 2022'!$I$98 -> 888.59 | C16: ='Revnue - Spot On Supplies 2022'!$J$98 -> 1979.66 | D16: ='Revnue - Spot On Supplies 2022'!$K$98 -> 3682.17 | E16: ='Revnue - Spot On Supplies 2022'!$L$98 -> 1848.64 | F16: ='Revnue - Spot On Supplies 2022'!$M$98 -> 1684.79 | G16: ='Revnue - Spot On Supplies 2022'!$N$98 -> 3303.3 | H16: ='Revnue - Spot On Supplies 2022'!$O$98 -> 662.82 | I16: ='Revnue - Spot On Supplies 2022'!$P$98 -> 1829.6 | J16: ='Revnue - Spot On Supplies 2022'!$Q$98 -> 1791.53 | K16: ='Revnue - Spot On Supplies 2022'!$R$98 -> 983.6 | L16: ='Revnue - Spot On Supplies 2022'!$S$98 -> 2287.7 | M16: ='Revnue - Spot On Supplies 2022'!$T$98 -> 326.54 | N16: ='Revnue - Spot On Supplies 2022'!$U$98 -> 21017.48 | P16: ='Revnue - Spot On Supplies 2022'!$W$98 -> 19266.023 | Q16: ='Revnue - Spot On Supplies 2022'!$X$98 -> 24520.393 | R16: ='Revnue - Spot On Supplies 2022'!$Y$98 -> 1751.4567 | S16: =P16/12 -> 1605.5019
A17: SOE | B17: ='SO Equipment 2022'!$I$29 -> 0 | C17: ='SO Equipment 2022'!$J$29 -> 0 | D17: ='SO Equipment 2022'!$K$29 -> 0 | E17: ='SO Equipment 2022'!$L$29 -> 0 | F17: ='SO Equipment 2022'!$M$29 -> 0 | G17: ='SO Equipment 2022'!$N$29 -> 0 | H17: ='SO Equipment 2022'!$O$29 -> 0 | I17: ='SO Equipment 2022'!$P$29 -> 0 | J17: ='SO Equipment 2022'!$Q$29 -> 0 | K17: ='SO Equipment 2022'!$R$29 -> 200 | L17: ='SO Equipment 2022'!$S$29 -> 0 | M17: ='SO Equipment 2022'!$T$29 -> 0 | N17: ='SO Equipment 2022'!$U$29 -> 200 | P17: ='SO Equipment 2022'!$W$29 -> 149964 | Q17: ='SO Equipment 2022'!$X$29 -> 294964 | R17: ='SO Equipment 2022'!$Y$29 -> 16.666667 | S17: =P17/12 -> 12497
A18: NSO Supplies | B18: ='Revnue - NAHSO Supplies_2022'!$I$328 -> 15187.25 | C18: ='Revnue - NAHSO Supplies_2022'!$J$328 -> 15998 | D18: ='Revnue - NAHSO Supplies_2022'!$K$328 -> 15424.5 | E18: ='Revnue - NAHSO Supplies_2022'!$L$328 -> 23055 | F18: ='Revnue - NAHSO Supplies_2022'!$M$328 -> 11812.38 | G18: ='Revnue - NAHSO Supplies_2022'!$N$328 -> 17417 | H18: ='Revnue - NAHSO Supplies_2022'!$O$328 -> 26475.84 | I18: ='Revnue - NAHSO Supplies_2022'!$P$328 -> 24642 | J18: ='Revnue - NAHSO Supplies_2022'!$Q$328 -> 20533 | K18: ='Revnue - NAHSO Supplies_2022'!$R$328 -> 16663.5 | L18: ='Revnue - NAHSO Supplies_2022'!$S$328 -> 26155 | M18: ='Revnue - NAHSO Supplies_2022'!$T$328 -> 12002 | N18: ='Revnue - NAHSO Supplies_2022'!$U$328 -> 225365.47 | P18: ='Revnue - NAHSO Supplies_2022'!$W$328 -> 206585.01 | Q18: ='Revnue - NAHSO Supplies_2022'!$X$328 -> 262926.38 | R18: ='Revnue - NAHSO Supplies_2022'!$Y$328 -> 18780.456 | S18: =P18/12 -> 17215.418
A19: Equipment | B19: ='Revenue - Equipment 2022'!$I$82 -> 1191 | C19: ='Revenue - Equipment 2022'!$J$82 -> 11902 | D19: ='Revenue - Equipment 2022'!$K$82 -> 3100 | E19: ='Revenue - Equipment 2022'!$L$82 -> 4511 | F19: ='Revenue - Equipment 2022'!$M$82 -> 99 | G19: ='Revenue - Equipment 2022'!$N$82 -> 2584 | H19: ='Revenue - Equipment 2022'!$O$82 -> 1189 | I19: ='Revenue - Equipment 2022'!$P$82 -> 5709 | J19: ='Revenue - Equipment 2022'!$Q$82 -> 3895 | K19: ='Revenue - Equipment 2022'!$R$82 -> 11727.16 | L19: ='Revenue - Equipment 2022'!$S$82 -> 4797 | M19: ='Revenue - Equipment 2022'!$T$82 -> 7404 | N19: ='Revenue - Equipment 2022'!$U$82 -> 58108.16 | P19: ='Revenue - Equipment 2022'!$W$82 -> 83386 | Q19: ='Revenue - Equipment 2022'!$X$82 -> 108096 | R19: ='Revenue - Equipment 2022'!$Y$82 -> 7952.5742 | S19: =P19/12 -> 6948.8333
A20: Service | B20: ='Revnue - Service 2022'!$I$78 -> 4250 | C20: ='Revnue - Service 2022'!$J$78 -> 810 | D20: ='Revnue - Service 2022'!$K$78 -> 900 | E20: ='Revnue - Service 2022'!$L$78 -> 810 | F20: ='Revnue - Service 2022'!$M$78 -> 480 | G20: ='Revnue - Service 2022'!$N$78 -> 3600 | H20: ='Revnue - Service 2022'!$O$78 -> 945 | I20: ='Revnue - Service 2022'!$P$78 -> 1495 | J20: ='Revnue - Service 2022'!$Q$78 -> 415 | K20: ='Revnue - Service 2022'!$R$78 -> 2013 | L20: ='Revnue - Service 2022'!$S$78 -> 1620 | M20: ='Revnue - Service 2022'!$T$78 -> 1160 | N20: ='Revnue - Service 2022'!$U$78 -> 18498 | P20: ='Revnue - Service 2022'!$W$78 -> 17856.5 | Q20: ='Revnue - Service 2022'!$X$78 -> 23081 | R20: ='Revnue - Service 2022'!$Y$78 -> 1900.25 | S20: =P20/12 -> 1488.0417
A22: *** RUNNING TOTAL *** | B22: =SUM(B16:B20) -> 21516.84 | C22: =SUM(C16:C20) -> 30689.66 | D22: =SUM(D16:D20) -> 23106.67 | E22: =SUM(E16:E20) -> 30224.64 | F22: =SUM(F16:F20) -> 14076.17 | G22: =SUM(G16:G20) -> 26904.3 | H22: =SUM(H16:H20) -> 29272.66 | I22: =SUM(I16:I20) -> 33675.6 | ... N22: =SUM(N16:N20) -> 323189.11 | P22: 441958 | Q22: 735858 | R22: 18174.138 | S22: 36829.833
A25: =Totals!$A$13 -> Account Category | B25: =Totals!$B$13 -> Jan | C25: =Totals!$C$13 -> Feb | D25: =Totals!$D$13 -> Mar | E25: =Totals!$E$13 -> Apr | F25: =Totals!$F$13 -> May | G25: =Totals!$G$13 -> Jun | H25: =Totals!$H$13 -> Jul | I25: =Totals!$I$13 -> Aug | J25: =Totals!$J$13 -> Sep | K25: =Totals!$K$13 -> Oct | L25: =Totals!$L$13 -> Nov | M25: =Totals!$M$13 -> Dec | N25: =Totals!$N$13 -> TOTAL | P25: =Totals!$P$13 -> Budget | Q25: =Totals!$Q$13 -> Goal | R25: =Totals!$R$13 -> AVG/MONTH | S25: =Totals!$S$13 -> BUDGET AVG/MONTH
A26: =Sheet15!$A$3 -> 2023 Year
A28: =Totals!$A$16 -> SOS | B28: ='Revnue - Spot On Supplies 2022'!$I$116 -> 0 | C28: ='Revnue - Spot On Supplies 2022'!$J$116 -> 0 | D28: ='Revnue - Spot On Supplies 2022'!$K$116 -> 0 | E28: ='Revnue - Spot On Supplies 2022'!$L$116 -> 0 | F28: ='Revnue - Spot On Supplies 2022'!$M$116 -> 0 | G28: ='Revnue - Spot On Supplies 2022'!$N$116 -> 0 | H28: ='Revnue - Spot On Supplies 2022'!$O$116 -> 0 | I28: ='Revnue - Spot On Supplies 2022'!$P$116 -> 0 | J28: ='Revnue - Spot On Supplies 2022'!$Q$116 -> 0 | K28: ='Revnue - Spot On Supplies 2022'!$R$116 -> 0 | L28: ='Revnue - Spot On Supplies 2022'!$S$116 -> 0 | M28: ='Revnue - Spot On Supplies 2022'!$T$116 -> 0 | N28: ='Revnue - Spot On Supplies 2022'!$U$116 -> 0 | P28: ='Revnue - Spot On Supplies 2022'!$W$116 -> 40203.412 | Q28: ='Revnue - Spot On Supplies 2022'!$X$116 -> 54854.525 | R28: ='Revnue - Spot On Supplies 2022'!$Y$116 -> 2217.0375 | S28: =Totals!$S$16 -> 1605.5019
A29: =Totals!$A$17 -> SOE | B29: ='SO Equipment 2022'!$I$46 -> 0 | C29: ='SO Equipment 2022'!$J$46 -> 0 | D29: ='SO Equipment 2022'!$K$46 -> 0 | E29: ='SO Equipment 2022'!$L$46 -> 0 | F29: ='SO Equipment 2022'!$M$46 -> 0 | G29: ='SO Equipment 2022'!$N$46 -> 0 | H29: ='SO Equipment 2022'!$O$46 -> 0 | I29: ='SO Equipment 2022'!$P$46 -> 0 | J29: ='SO Equipment 2022'!$Q$46 -> 0 | K29: ='SO Equipment 2022'!$R$46 -> 0 | L29: ='SO Equipment 2022'!$S$46 -> 0 | M29: ='SO Equipment 2022'!$T$46 -> 0 | N29: ='SO Equipment 2022'!$U$46 -> 0 | P29: ='SO Equipment 2022'!$W$46 -> 992 | Q29: ='SO Equipment 2022'!$X$46 -> 1492 | R29: ='SO Equipment 2022'!$Y$46 -> 0 | S29: =Totals!$S$17 -> 12497
A30: =Totals!$A$18 -> NSO Supplies | B30: ='Revnue - NAHSO Supplies_2022'!$I$1234 -> 14604.5 | C30: ='Revnue - NAHSO Supplies_2022'!$J$1234 -> 15994 | D30: ='Revnue - NAHSO Supplies_2022'!$K$1234 -> 18183.69 | E30: ='Revnue - NAHSO Supplies_2022'!$L$1234 -> 20411.54 | F30: ='Revnue - NAHSO Supplies_2022'!$M$1234 -> 30794.14 | G30: ='Revnue - NAHSO Supplies_2022'!$N$1234 -> 19291.02 | H30: ='Revnue - NAHSO Supplies_2022'!$O$1234 -> 0 | I30: ='Revnue - NAHSO Supplies_2022'!$P$1234 -> 19095 | J30: ='Revnue - NAHSO Supplies_2022'!$Q$1234 -> 0 | K30: ='Revnue - NAHSO Supplies_2022'!$R$1234 -> 0 | L30: ='Revnue - NAHSO Supplies_2022'!$S$1234 -> 0 | M30: ='Revnue - NAHSO Supplies_2022'!$T$1234 -> 0 | N30: ='Revnue - NAHSO Supplies_2022'!$U$1234 -> 138373.89 | P30: ='Revnue - NAHSO Supplies_2022'!$W$1044 -> 0 | Q30: ='Revnue - NAHSO Supplies_2022'!$X$1044 -> 0 | R30: ='Revnue - NAHSO Supplies_2022'!$Y$1044 -> 0 | S30: =Totals!$S$18 -> 17215.418
A31: =Totals!$A$19 -> Equipment | B31: ='Revenue - Equipment 2022'!$I$239 -> 5274 | C31: ='Revenue - Equipment 2022'!$J$239 -> 6262 | D31: ='Revenue - Equipment 2022'!$K$239 -> 13184.37 | E31: ='Revenue - Equipment 2022'!$L$239 -> 1569 | F31: ='Revenue - Equipment 2022'!$M$239 -> 5876.79 | G31: ='Revenue - Equipment 2022'!$N$239 -> 99 | H31: ='Revenue - Equipment 2022'!$O$239 -> 12448.63 | I31: ='Revenue - Equipment 2022'!$P$239 -> 99 | J31: ='Revenue - Equipment 2022'!$Q$239 -> 99 | K31: ='Revenue - Equipment 2022'!$R$239 -> 99 | L31: ='Revenue - Equipment 2022'!$S$239 -> 3832.51 | M31: ='Revenue - Equipment 2022'!$T$239 -> 12448.63 | N31: ='Revenue - Equipment 2022'!$U$239 -> 35790.77 | P31: ='Revenue - Equipment 2022'!$W$239 -> 113013 | Q31: ='Revenue - Equipment 2022'!$X$239 -> 133613 | R31: ='Revenue - Equipment 2022'!$Y$239 -> 218.12083 | S31: =Totals!$S$19 -> 6948.8333
A32: =Totals!$A$20 -> Service | B32: ='Revnue - Service 2022'!$I$96 -> 1350 | C32: ='Revnue - Service 2022'!$J$96 -> 720 | D32: ='Revnue - Service 2022'!$K$96 -> 2733 | E32: ='Revnue - Service 2022'!$L$96 -> 720 | F32: ='Revnue - Service 2022'!$M$96 -> 0 | G32: ='Revnue - Service 2022'!$N$96 -> 0 | H32: ='Revnue - Service 2022'!$O$96 -> 0 | I32: ='Revnue - Service 2022'!$P$96 -> 0 | J32: ='Revnue - Service 2022'!$Q$96 -> 0 | K32: ='Revnue - Service 2022'!$R$96 -> 0 | L32: ='Revnue - Service 2022'!$S$96 -> 0 | M32: ='Revnue - Service 2022'!$T$96 -> 0 | N32: ='Revnue - Service 2022'!$U$96 -> 4153 | P32: ='Revnue - Service 2022'!$W$96 -> 29085.25 | Q32: ='Revnue - Service 2022'!$X$96 -> 5322.1667 | R32: ='Revnue - Service 2022'!$Y$96 -> 2879.5 | S32: =Totals!$S$20 -> 1488.0417
A34: *** RUNNING TOTAL *** | B34: =SUM(B28:B32) -> 21228.5 | C34: =SUM(C28:C32) -> 22976 | D34: =SUM(D28:D32) -> 34101.06 | E34: =SUM(E28:E32) -> 22700.54 | F34: =SUM(F28:F32) -> 36670.93 | G34: =SUM(G28:G32) -> 19390.02 | H34: =SUM(H28:H32) -> 12448.63 | I34: =SUM(I28:I32) -> 19194 | ... N34: =SUM(N28:N32) -> 178317.66 | P34: 441958 | Q34: 735858 | R34: 18174.138 | S34: 36829.833
A37: =Totals!$A$13 -> Account Category | B37: =Totals!$B$13 -> Jan | C37: =Totals!$C$13 -> Feb | D37: =Totals!$D$13 -> Mar | E37: =Totals!$E$13 -> Apr | F37: =Totals!$F$13 -> May | G37: =Totals!$G$13 -> Jun | H37: =Totals!$H$13 -> Jul | I37: =Totals!$I$13 -> Aug | J37: =Totals!$J$13 -> Sep | K37: =Totals!$K$13 -> Oct | L37: =Totals!$L$13 -> Nov | M37: =Totals!$M$13 -> Dec | N37: =Totals!$N$13 -> TOTAL | P37: =Totals!$P$13 -> Budget | Q37: =Totals!$Q$13 -> Goal | R37: =Totals!$R$13 -> AVG/MONTH | S37: =Totals!$S$13 -> BUDGET AVG/MONTH
A38: =Sheet15!$A$4 -> 2024 Year
A40: =Totals!$A$28 -> SOS | B40: =Totals!$B$28 -> 0 | C40: =Totals!$C$28 -> 0 | D40: =Totals!$D$28 -> 0 | E40: =Totals!$E$28 -> 0 | F40: =Totals!$F$28 -> 0 | G40: =Totals!$G$28 -> 0 | H40: =Totals!$H$28 -> 0 | I40: =Totals!$I$28 -> 0 | J40: =Totals!$J$28 -> 0 | K40: =Totals!$K$28 -> 0 | L40: =Totals!$L$28 -> 0 | M40: =Totals!$M$28 -> 0 | N40: =Totals!$N$28 -> 0 | P40: =Totals!$P$28 -> 40203.412 | Q40: =Totals!$Q$28 -> 54854.525 | R40: =Totals!$R$28 -> 2217.0375 | S40: =Totals!$S$28 -> 1605.5019
A41: =Totals!$A$29 -> SOE | B41: =Totals!$B$29 -> 0 | C41: =Totals!$C$29 -> 0 | D41: =Totals!$D$29 -> 0 | E41: =Totals!$E$29 -> 0 | F41: =Totals!$F$29 -> 0 | G41: =Totals!$G$29 -> 0 | H41: =Totals!$H$29 -> 0 | I41: =Totals!$I$29 -> 0 | J41: =Totals!$J$29 -> 0 | K41: =Totals!$K$29 -> 0 | L41: =Totals!$L$29 -> 0 | M41: =Totals!$M$29 -> 0 | N41: =Totals!$N$29 -> 0 | P41: =Totals!$P$29 -> 992 | Q41: =Totals!$Q$29 -> 1492 | R41: =Totals!$R$29 -> 0 | S41: =Totals!$S$29 -> 12497
A42: =Totals!$A$30 -> NSO Supplies | B42: =Totals!$B$30 -> 14604.5 | C42: =Totals!$C$30 -> 15994 | D42: =Totals!$D$30 -> 18183.69 | E42: =Totals!$E$30 -> 20411.54 | F42: =Totals!$F$30 -> 30794.14 | G42: =Totals!$G$30 -> 19291.02 | H42: =Totals!$H$30 -> 0 | I42: =Totals!$I$30 -> 19095 | J42: =Totals!$J$30 -> 0 | K42: =Totals!$K$30 -> 0 | L42: =Totals!$L$30 -> 0 | M42: =Totals!$M$30 -> 0 | N42: =Totals!$N$30 -> 138373.89 | P42: =Totals!$P$30 -> 0 | Q42: =Totals!$Q$30 -> 0 | R42: =Totals!$R$30 -> 0 | S42: =Totals!$S$30 -> 17215.418
A43: =Totals!$A$31 -> Equipment | B43: =Totals!$B$31 -> 5274 | C43: =Totals!$C$31 -> 6262 | D43: =Totals!$D$31 -> 13184.37 | E43: =Totals!$E$31 -> 1569 | F43: =Totals!$F$31 -> 5876.79 | G43: =Totals!$G$31 -> 99 | H43: =Totals!$H$31 -> 12448.63 | I43: =Totals!$I$31 -> 99 | J43: =Totals!$J$31 -> 99 | K43: =Totals!$K$31 -> 99 | L43: =Totals!$L$31 -> 3832.51 | M43: =Totals!$M$31 -> 12448.63 | N43: =Totals!$N$31 -> 35790.77 | P43: =Totals!$P$31 -> 113013 | Q43: =Totals!$Q$31 -> 133613 | R43: =Totals!$R$31 -> 218.12083 | S43: =Totals!$S$31 -> 6948.8333
A44: =Totals!$A$32 -> Service | B44: =Totals!$B$32 -> 1350 | C44: =Totals!$C$32 -> 720 | D44: =Totals!$D$32 -> 2733 | E44: =Totals!$E$32 -> 720 | F44: =Totals!$F$32 -> 0 | G44: =Totals!$G$32 -> 0 | H44: =Totals!$H$32 -> 0 | I44: =Totals!$I$32 -> 0 | J44: =Totals!$J$32 -> 0 | K44: =Totals!$K$32 -> 0 | L44: =Totals!$L$32 -> 0 | M44: =Totals!$M$32 -> 0 | N44: =Totals!$N$32 -> 4153 | P44: =Totals!$P$32 -> 29085.25 | Q44: =Totals!$Q$32 -> 5322.1667 | R44: =Totals!$R$32 -> 2879.5 | S44: =Totals!$S$32 -> 1488.0417
A46: =Totals!$A$34 -> *** RUNNING TOTAL *** | B46: =Totals!$B$34 -> 21228.5 | C46: =Totals!$C$34 -> 22976 | D46: =Totals!$D$34 -> 34101.06 | E46: =Totals!$E$34 -> 22700.54 | F46: =Totals!$F$34 -> 36670.93 | G46: =Totals!$G$34 -> 19390.02 | H46: =Totals!$H$34 -> 12448.63 | I46: =Totals!$I$34 -> 19194 | J46: =Totals!$J$34 -> 99 | K46: =Totals!$K$34 -> 99 | L46: =Totals!$L$34 -> 3832.51 | M46: =Totals!$M$34 -> 12448.63 | N46: =Totals!$N$34 -> 178317.66 | P46: =Totals!$P$34 -> 441958 | Q46: =Totals!$Q$34 -> 735858 | R46: =Totals!$R$34 -> 18174.138 | S46: =Totals!$S$34 -> 36829.833
S124: ='Revnue - Spot On Supplies 2022'!$Y$98 -> 1751.4567

Sheet SO Equipment 2022
A1: Account Name | B1: A/E | C1: CONTACT | D1: Subscription | E1: NOTES / STATUS | F1: Close Date | G1: Amount | H1: Status | I1: Jan | J1: Feb | K1: Mar | L1: Apr | M1: May | N1: Jun | O1: Jul | P1: Aug | Q1: Sep | R1: Oct | S1: Nov | T1: Dec | U1: TOTAL | W1: Budget | X1: Goal | Y1: AVG/MONTH
A2: *** ONBOARD ***
A4: Ruiz Auto | B4: AH | U4: =SUM(I4:T4) -> 0 | W4: 10000 | X4: 20000 | Y4: =U4/12 -> 0
U5: =SUM(I5:T5) -> 0 | W5: 10000 | X5: 20000 | Y5: =U5/12 -> 0
U6: =SUM(I6:T6) -> 0 | W6: 10000 | X6: 20000 | Y6: =U6/12 -> 0
U7: =SUM(I7:T7) -> 0 | W7: 10000 | X7: 20000 | Y7: =U7/12 -> 0
U8: =SUM(I8:T8) -> 0 | W8: 10000 | X8: 20000 | Y8: =U8/12 -> 0
U9: =SUM(I9:T9) -> 0 | W9: 10000 | X9: 20000 | Y9: =U9/12 -> 0
U10: =SUM(I10:T10) -> 0 | W10: 10000 | X10: 20000 | Y10: =U10/12 -> 0
U11: =SUM(I11:T11) -> 0 | W11: 10000 | X11: 20000 | Y11: =U11/12 -> 0
U12: =SUM(I12:T12) -> 0 | W12: 10000 | X12: 20000 | Y12: =U12/12 -> 0
U13: =SUM(I13:T13) -> 0 | W13: 10000 | X13: 20000 | Y13: =U13/12 -> 0
U14: =SUM(I14:T14) -> 0 | W14: 10000 | X14: 20000 | Y14: =U14/12 -> 0
U15: =SUM(I15:T15) -> 0 | W15: 10000 | X15: 20000 | Y15: =U15/12 -> 0
Y16: =U16/12 -> 0
A17: *** RUNNING TOTAL *** | I17: =SUM(I2:I16) -> 0 | J17: =SUM(J2:J16) -> 0 | K17: =SUM(K2:K16) -> 0 | L17: =SUM(L2:L16) -> 0 | M17: =SUM(M2:M16) -> 0 | N17: =SUM(N2:N16) -> 0 | O17: =SUM(O2:O16) -> 0 | P17: =SUM(P2:P16) -> 0 | ... X17: =SUM(X2:X16) -> 240000 | Y17: =U17/12 -> 0
A18: Bruno's Deli, Market, Café | E18: Spoke to Steve 415-785-7487
A19: Fire Island Grill - Palmdale | D19: Toast | E19: Patrick @661-802-6071 pburke@fireislandgrill.com | U19: =SUM(I19:T19) -> 0 | W19: 992 | X19: 1492 | Y19: =U19/12 -> 0
A20: Fire Island Grill - Simi Valley | U20: =SUM(I20:T20) -> 0 | W20: 993 | X20: 1493 | Y20: =U20/12 -> 0
A21: Stony Point Market | R21: 200 | U21: =SUM(I21:T21) -> 200 | W21: 994 | X21: 1494 | Y21: =U21/12 -> 16.666667
U22: =SUM(I22:T22) -> 0 | W22: 995 | X22: 1495 | Y22: =U22/12 -> 0
U23: =SUM(I23:T23) -> 0 | W23: 996 | X23: 1496 | Y23: =U23/12 -> 0
U24: =SUM(I24:T24) -> 0 | W24: 997 | X24: 1497 | Y24: =U24/12 -> 0
U25: =SUM(I25:T25) -> 0 | W25: 998 | X25: 1498 | Y25: =U25/12 -> 0
U26: =SUM(I26:T26) -> 0 | W26: 999 | X26: 1499 | Y26: =U26/12 -> 0
U27: =SUM(I27:T27) -> 0 | W27: 1000 | X27: 1500 | Y27: =U27/12 -> 0
U28: =SUM(I28:T28) -> 0 | W28: 1000 | X28: 1500 | Y28: =U28/12 -> 0
I29: =SUM( I14:I28) -> 0 | J29: =SUM( J14:J28) -> 0 | K29: =SUM( K14:K28) -> 0 | L29: =SUM( L14:L28) -> 0 | M29: =SUM( M14:M28) -> 0 | N29: =SUM( N14:N28) -> 0 | O29: =SUM( O14:O28) -> 0 | P29: =SUM( P14:P28) -> 0 | ... Y29: =SUM( Y14:Y28) -> 16.666667
I31: 0 | J31: 0 | K31: 0 | L31: 0 | M31: 0 | N31: 0 | O31: 0 | P31: 0 | Q31: 0 | R31: 0 | S31: 0 | T31: 0 | U31: =SUM(I31:T31) -> 0 | W31: 992 | X31: 1492 | Y31: =U31/12 -> 0
A46: *** RUNNING TOTAL *** | I46: =SUM( I31:I45) -> 0 | J46: =SUM( J31:J45) -> 0 | K46: =SUM( K31:K45) -> 0 | L46: =SUM( L31:L45) -> 0 | M46: =SUM( M31:M45) -> 0 | N46: =SUM( N31:N45) -> 0 | O46: =SUM( O31:O45) -> 0 | P46: =SUM( P31:P45) -> 0 | ... U46: =SUM( U31:U45) -> 0 | W46: =SUM( W31:W45) -> 992 | X46: =SUM( X31:X45) -> 1492 | Y46: =SUM( Y31:Y45) -> 0

Sheet Revnue - Spot On Supplies 2022
A1: Account Name | B1: A/E | C1: Primary tech | D1: INSTALL STATUS | E1: NOTES | F1: Close Date | G1: Amount | H1: Status | I1: Jan | J1: Feb | K1: Mar | L1: Apr | M1: May | N1: Jun | O1: Jul | P1: Aug | Q1: Sep | R1: Oct | S1: Nov | T1: Dec | U1: TOTAL | W1: Budget | X1: Goal | Y1: AVG/MONTH
A2: *** ONBOARD ***
A4: La Costanera | B4: Stephen | C4: Jeremy | D4: LIVE 6/21 | M4: 291.65 | O4: 329.84 | P4: 74.88 | Q4: 345.31 | U4: =SUM(I4:T4) -> 1041.68 | W4: 1000 | X4: 1500 | Y4: =U4/12 -> 86.806667
A5: The Forge Handcrafted Pizza | B5: Dave | C5: Jeremy | D5: LIVE 6/21 | N5: 170.25 | O5: 131.2 | Q5: 339.21 | U5: =SUM(I5:T5) -> 640.66 | W5: 1000 | X5: 1500 | Y5: =U5/12 -> 53.388333
A6: BARREL HOUSE TAVERN | Q6: 543.75 | U6: =SUM(I6:T6) -> 543.75 | Y6: =U6/12 -> 45.3125
A7: Cote Ouest | B7: Suzie | C7: Jeremy | D7: Live 3/21 | K7: 151.51 | N7: 108.5 | Q7: 57.88 | U7: =SUM(I7:T7) -> 317.89 | W7: 1000 | X7: 1500 | Y7: =U7/12 -> 26.490833
A8: Troy Greek Cuisine- Martinez | B8: Cory | C8: Nima | D8: LIVE 7/21 | O8: 165.43 | R8: 138.73 | U8: =SUM(I8:T8) -> 304.16 | W8: 1000 | X8: 1500 | Y8: =U8/12 -> 25.346667
A9: Papalote- 2 loc | B9: Dave | C9: Rick | D9: LIVE 4/21 | L9: 86 | M9: 213 | U9: =SUM(I9:T9) -> 299 | W9: 1000 | X9: 1500 | Y9: =U9/12 -> 24.916667
A10: Bacco- Sf | B10: Bill | C10: Rick | D10: LIVE 1/21 | J10: 78.93 | M10: 70.93 | Q10: 129 | U10: =SUM(I10:T10) -> 278.86 | W10: 1000 | X10: 1500 | Y10: =U10/12 -> 23.238333
A11: Via Piccola | B11: Jeremy | C11: Jeremy | D11: Pedro | E11: Suzie C | O11: 212.76 | U11: =SUM(I11:T11) -> 212.76 | W11: 1000 | X11: 1500 | Y11: =U11/12 -> 17.73
A12: PRIMAVERA RESTAURANT | R12: 211.35 | U12: =SUM(I12:T12) -> 211.35 | W12: 1004 | X12: 1504 | Y12: =U12/12 -> 17.6125
A13: Isabel’s Vintage Cafe | P13: 202.95 | U13: =SUM(I13:T13) -> 202.95 | W13: 1000 | X13: 1500 | Y13: =U13/12 -> 16.9125
A14: Gilroy Garlic Festival | B14: James H | C14: Terry | D14: Live 7/21 | O14: 175.69 | U14: =SUM(I14:T14) -> 175.69 | W14: 1000 | X14: 1500 | Y14: =U14/12 -> 14.640833
A15: The Caviar Company | E15: FLUP 7/28 Petra 806-777-5864 | K15: 151.51 | U15: =SUM(I15:T15) -> 151.51 | W15: 1000 | X15: 1500 | Y15: =U15/12 -> 12.625833
A16: El Huarache Loco | B16: Suzie | C16: Milton | D16: Live | L16: 140.61 | S16: 251.46 | U16: =SUM(I16:T16) -> 392.07 | W16: 1000 | X16: 1500 | Y16: =U16/12 -> 32.6725
A17: Bolinas People's Store ( NCC) | B17: Rich | C17: Lowell | D17: Live 5/21 | M17: 123 | U17: =SUM(I17:T17) -> 123 | W17: 1000 | X17: 1500 | Y17: =U17/12 -> 10.25
A18: KITCHEN + KOCKTAILS CHICAGO | R18: 116.59 | U18: =SUM(I18:T18) -> 116.59 | W18: 1005 | X18: 1505 | Y18: =U18/12 -> 9.7158333
A19: VIA PICCOLA TRATTORIA | Q19: 114.43 | U19: =SUM(I19:T19) -> 114.43 | W19: 1001 | X19: 1501 | Y19: =U19/12 -> 9.5358333
A20: Buffalo Billiards | B20: Milton | C20: Milton | D20: Live 7/26 | E20: Mike bombace@buffalo-billiards.com has pricing on supplies Buffalo Billiards Lee Simon +17075858992 246 Petaluma Blvd N Petaluma, CA 94952 | O20: 103.29 | U20: =SUM(I20:T20) -> 103.29 | W20: 1000 | X20: 1500 | Y20: =U20/12 -> 8.6075
A21: PRIMAVERA RESTAURANT | R21: 93.83 | U21: =SUM(I21:T21) -> 93.83 | W21: 1011 | X21: 1511 | Y21: =U21/12 -> 7.8191667
A22: PRIMAVERA RESTAURANT | R22: 68.81 | U22: =SUM(I22:T22) -> 68.81 | W22: 1009 | X22: 1509 | Y22: =U22/12 -> 5.7341667
A23: Troy Greek Express | B23: Cory | C23: Nima | D23: LIVE 7/21 | R23: 68.61 | U23: =SUM(I23:T23) -> 68.61 | W23: 1000 | X23: 1500 | Y23: 25.346667
A24: SARA'S SOUTHERN KITCHEN | R24: 50.61 | U24: =SUM(I24:T24) -> 50.61 | W24: 1007 | X24: 1507 | Y24: =U24/12 -> 4.2175
A25: SARA WILLIAMS | R25: 50.27 | U25: =SUM(I25:T25) -> 50.27 | W25: 1008 | X25: 1508 | Y25: =U25/12 -> 4.1891667
A26: BEYOND THE GLORY | B26: AH | P26: 47.33 | U26: =SUM(I26:T26) -> 47.33 | Y26: =U26/12 -> 3.9441667
A27: DAVRE CLUB | R27: 47.02 | U27: =SUM(I27:T27) -> 47.02 | W27: 1006 | X27: 1506 | Y27: =U27/12 -> 3.9183333
A28: Sausage Emporium | B28: Jeremy | C28: Jeremy | D28: LIVE 7/21 | O28: 42.61 | U28: =SUM(I28:T28) -> 42.61 | W28: 1000 | X28: 1500 | Y28: =U28/12 -> 3.5508333
A29: La Meza Mediteranean | B29: Corp | C29: Nikaela | D29: Live 2020 | N29: 42.51 | U29: =SUM(I29:T29) -> 42.51 | W29: 1000 | X29: 1500 | Y29: =U29/12 -> 3.5425
A30: Kell's Irish | B30: Jose | C30: Rick | D30: Live 4/21 | L30: 34.18 | U30: =SUM(I30:T30) -> 34.18 | W30: 1000 | X30: 1500 | Y30: =U30/12 -> 2.8483333
Y33: =U33/12 -> 0
A34: *** RUNNING TOTAL *** | I34: =SUM(I2:I33) -> 0 | J34: =SUM(J2:J33) -> 78.93 | K34: =SUM(K2:K33) -> 303.02 | L34: =SUM(L2:L33) -> 260.79 | M34: =SUM(M2:M33) -> 698.58 | N34: =SUM(N2:N33) -> 321.26 | O34: =SUM(O2:O33) -> 1160.82 | P34: =SUM(P2:P33) -> 325.16 | ... X34: =SUM(X2:X33) -> 37551 | Y34: =U34/12 -> 481.285
A36: BARREL HOUSE TAVERN | I36: 338.63 | K36: 598.13 | N36: 1051 | Q36: 1170 | U36: =SUM(I36:T36) -> 3157.76 | W36: {=MMULT(Y36,11)} -> 2894.6133 | X36: =MMULT(Y36,14) -> 3684.0533 | Y36: =U36/12 -> 263.14667
A37: THE FORGE HANDCRAFTED | J37: 221.22 | K37: 269.04 | M37: 215.22 | N37: 313.5 | P37: 339.88 | R37: 356.5 | U37: =SUM(I37:T37) -> 1715.36 | W37: {=MMULT(Y37,11)} -> 1572.4133 | X37: =MMULT(Y37,14) -> 2001.2533 | Y37: =U37/12 -> 142.94667
A38: LA COSTANERA | J38: 216.88 | K38: 112.25 | L38: 520.88 | P38: 502.03 | U38: =SUM(I38:T38) -> 1352.04 | W38: {=MMULT(Y38,11)} -> 1239.37 | X38: =MMULT(Y38,14) -> 1577.38 | Y38: =U38/12 -> 112.67
A39: OCEANVIEW | M39: 264.91 | N39: 519.82 | S39: 519.82 | U39: =SUM(I39:T39) -> 1304.55 | W39: {=MMULT(Y39,11)} -> 1195.8375 | X39: =MMULT(Y39,14) -> 1521.975 | Y39: =U39/12 -> 108.7125
A40: RABALAIS BISTRO | J40: 358.4 | K40: 662.49 | U40: =SUM(I40:T40) -> 1020.89 | W40: {=MMULT(Y40,11)} -> 935.81583 | X40: =MMULT(Y40,14) -> 1191.0383 | Y40: =U40/12 -> 85.074167
A41: Key’s Jazz Bistro | S41: 781 | U41: =SUM(I41:T41) -> 781 | W41: {=MMULT(Y41,11)} -> 715.91667 | X41: =MMULT(Y41,14) -> 911.16667 | Y41: =U41/12 -> 65.083333
A42: VIA PICCALO TRATTORIA | K42: 237.17 | L42: 277.6 | P42: 212.52 | U42: =SUM(I42:T42) -> 727.29 | W42: {=MMULT(Y42,11)} -> 666.6825 | X42: =MMULT(Y42,14) -> 848.505 | Y42: =U42/12 -> 60.6075
A43: PHO REAL KITCHEN | J43: 219 | K43: 480 | U43: =SUM(I43:T43) -> 699 | W43: {=MMULT(Y43,11)} -> 640.75 | X43: =MMULT(Y43,14) -> 815.5 | Y43: =U43/12 -> 58.25
A44: FATTORIA E MARE | M44: 529.38 | N44: 162.19 | U44: =SUM(I44:T44) -> 691.57 | W44: {=MMULT(Y44,11)} -> 633.93917 | X44: =MMULT(Y44,14) -> 806.83167 | Y44: =U44/12 -> 57.630833
A45: EL HUARACHE LOCO | N45: 374.08 | S45: 194 | U45: =SUM(I45:T45) -> 568.08 | W45: {=MMULT(Y45,11)} -> 520.74 | X45: =MMULT(Y45,14) -> 662.76 | Y45: =U45/12 -> 47.34
A46: SALT & PEPPER | I46: 119.08 | K46: 244.17 | Q46: 138.8 | U46: =SUM(I46:T46) -> 502.05 | W46: {=MMULT(Y46,11)} -> 460.2125 | X46: =MMULT(Y46,14) -> 585.725 | Y46: =U46/12 -> 41.8375
A47: ACE WASABI | J47: 97.76 | M47: 108.62 | N47: 247.25 | U47: =SUM(I47:T47) -> 453.63 | W47: {=MMULT(Y47,11)} -> 415.8275 | X47: =MMULT(Y47,14) -> 529.235 | Y47: =U47/12 -> 37.8025
A48: COTE OUEST BISTRO | I48: 177.99 | J48: 126.63 | L48: 69.74 | O48: 69.74 | U48: =SUM(I48:T48) -> 444.1 | W48: {=MMULT(Y48,11)} -> 407.09167 | X48: =MMULT(Y48,14) -> 518.11667 | Y48: =U48/12 -> 37.008333
A49: MI CASA GRILL | J49: 53.78 | K49: 220.77 | P49: 108.29 | Q49: 59 | U49: =SUM(I49:T49) -> 441.84 | W49: {=MMULT(Y49,11)} -> 405.02 | X49: =MMULT(Y49,14) -> 515.48 | Y49: =U49/12 -> 36.82
A50: GASPARE'S | J50: 150.99 | K50: 286.77 | U50: =SUM(I50:T50) -> 437.76 | W50: {=MMULT(Y50,11)} -> 401.28 | X50: =MMULT(Y50,14) -> 510.72 | Y50: =U50/12 -> 36.48
A51: DOLAN'S DEN | K51: 47.24 | N51: 81.01 | P51: 133.62 | Q51: 52.61 | R51: 81.01 | U51: =SUM(I51:T51) -> 395.49 | W51: {=MMULT(Y51,11)} -> 362.5325 | X51: =MMULT(Y51,14) -> 461.405 | Y51: =U51/12 -> 32.9575
A52: SEABREEZE | M52: 191.85 | P52: 191.85 | U52: =SUM(I52:T52) -> 383.7 | W52: {=MMULT(Y52,11)} -> 351.725 | X52: =MMULT(Y52,14) -> 447.65 | Y52: =U52/12 -> 31.975
A53: THE CHEESE PARLOR | J53: 63.02 | L53: 141.28 | P53: 150.1 | U53: =SUM(I53:T53) -> 354.4 | W53: {=MMULT(Y53,11)} -> 324.86667 | X53: =MMULT(Y53,14) -> 413.46667 | Y53: =U53/12 -> 29.533333
A54: ODD TEA & MORE | J54: 87 | L54: 67.5 | M54: 49 | O54: 93 | U54: =SUM(I54:T54) -> 296.5 | W54: {=MMULT(Y54,11)} -> 271.79167 | X54: =MMULT(Y54,14) -> 345.91667 | Y54: =U54/12 -> 24.708333
A55: AURORA | J55: 109.35 | N55: 160.92 | U55: =SUM(I55:T55) -> 270.27 | W55: {=MMULT(Y55,11)} -> 247.7475 | X55: =MMULT(Y55,14) -> 315.315 | Y55: =U55/12 -> 22.5225
A56: VILLAGE GRILL | O56: 249.84 | U56: =SUM(I56:T56) -> 249.84 | W56: {=MMULT(Y56,11)} -> 229.02 | X56: =MMULT(Y56,14) -> 291.48 | Y56: =U56/12 -> 20.82
A57: CHAMA NATIVA | T57: 245.93 | U57: =SUM(I57:T57) -> 245.93 | W57: {=MMULT(Y57,11)} -> 225.43583 | X57: =MMULT(Y57,14) -> 286.91833 | Y57: =U57/12 -> 20.494167
A58: BUFFALO BILLIARDS POOL HALL | M58: 193.16 | S58: 52.71 | U58: =SUM(I58:T58) -> 245.87 | W58: {=MMULT(Y58,11)} -> 225.38083 | X58: =MMULT(Y58,14) -> 286.84833 | Y58: =U58/12 -> 20.489167
A59: THE CHEESE PARLOR | J59: 63.02 | S59: 150.1 | U59: =SUM(I59:T59) -> 213.12 | W59: {=MMULT(Y59,11)} -> 195.36 | X59: =MMULT(Y59,14) -> 248.64 | Y59: =U59/12 -> 17.76
A60: Blue Barn Marin | S60: 208.61 | U60: =SUM(I60:T60) -> 208.61 | W60: {=MMULT(Y60,11)} -> 191.22583 | X60: =MMULT(Y60,14) -> 243.37833 | Y60: =U60/12 -> 17.384167
A61: LAS GUITARRAS | N61: 70.2 | Q61: 80 | R61: 48.83 | U61: =SUM(I61:T61) -> 199.03 | W61: {=MMULT(Y61,11)} -> 182.44417 | X61: =MMULT(Y61,14) -> 232.20167 | Y61: =U61/12 -> 16.585833
A62: DRAGON BISTRO | L62: 198.31 | U62: =SUM(I62:T62) -> 198.31 | W62: {=MMULT(Y62,11)} -> 181.78417 | X62: =MMULT(Y62,14) -> 231.36167 | Y62: =U62/12 -> 16.525833
A63: TROY GREEK CUISINE | L63: 198.31 | U63: =SUM(I63:T63) -> 198.31 | W63: {=MMULT(Y63,11)} -> 181.78417 | X63: =MMULT(Y63,14) -> 231.36167 | Y63: =U63/12 -> 16.525833
A64: LITTLE SAINT | K64: 187.48 | U64: =SUM(I64:T64) -> 187.48 | W64: {=MMULT(Y64,11)} -> 171.85667 | X64: =MMULT(Y64,14) -> 218.72667 | Y64: =U64/12 -> 15.623333
A65: LUNA RESTAURANT | K65: 177.36 | U65: =SUM(I65:T65) -> 177.36 | W65: {=MMULT(Y65,11)} -> 162.58 | X65: =MMULT(Y65,14) -> 206.92 | Y65: =U65/12 -> 14.78
A66: ACHILLES BY THE SEA | L66: 124.07 | M66: 52.61 | U66: =SUM(I66:T66) -> 176.68 | W66: {=MMULT(Y66,11)} -> 161.95667 | X66: =MMULT(Y66,14) -> 206.12667 | Y66: =U66/12 -> 14.723333
A67: CONVIVIUM ENOTECA | R67: 172.72 | U67: =SUM(I67:T67) -> 172.72 | W67: {=MMULT(Y67,11)} -> 158.32667 | X67: =MMULT(Y67,14) -> 201.50667 | Y67: =U67/12 -> 14.393333
A68: FULTON NAILS | I68: 36.31 | K68: 45.24 | O68: 86.48 | U68: =SUM(I68:T68) -> 168.03 | W68: {=MMULT(Y68,11)} -> 154.0275 | X68: =MMULT(Y68,14) -> 196.035 | Y68: =U68/12 -> 14.0025
A69: RIVER TIME RESTAURANT | I69: 166.97 | U69: =SUM(I69:T69) -> 166.97 | W69: {=MMULT(Y69,11)} -> 153.05583 | X69: =MMULT(Y69,14) -> 194.79833 | Y69: =U69/12 -> 13.914167
A70: FOGO DE MINAS | O70: 163.76 | U70: =SUM(I70:T70) -> 163.76 | W70: {=MMULT(Y70,11)} -> 150.11333 | X70: =MMULT(Y70,14) -> 191.05333 | Y70: =U70/12 -> 13.646667
A71: DONATO ENOTECA | R71: 162.84 | U71: =SUM(I71:T71) -> 162.84 | W71: {=MMULT(Y71,11)} -> 149.27 | X71: =MMULT(Y71,14) -> 189.98 | Y71: =U71/12 -> 13.57
A72: CLUB FUGAZI | J72: 160.61 | U72: =SUM(I72:T72) -> 160.61 | W72: {=MMULT(Y72,11)} -> 147.22583 | X72: =MMULT(Y72,14) -> 187.37833 | Y72: =U72/12 -> 13.384167
A73: SARA'S SOUTHERN KITCHEN | N73: 137.82 | U73: =SUM(I73:T73) -> 137.82 | W73: {=MMULT(Y73,11)} -> 126.335 | X73: =MMULT(Y73,14) -> 160.79 | Y73: =U73/12 -> 11.485
A74: Isabel’s Vintage Cafe | Q74: 136.07 | U74: =SUM(I74:T74) -> 136.07 | W74: {=MMULT(Y74,11)} -> 124.73083 | X74: =MMULT(Y74,14) -> 158.74833 | Y74: =U74/12 -> 11.339167
A75: LOST MARBLES | S75: 130 | U75: =SUM(I75:T75) -> 130 | W75: {=MMULT(Y75,11)} -> 119.16667 | X75: =MMULT(Y75,14) -> 151.66667 | Y75: =U75/12 -> 10.833333
A76: TROY GREEK CUISINE | L76: 125.54 | U76: =SUM(I76:T76) -> 125.54 | W76: {=MMULT(Y76,11)} -> 115.07833 | X76: =MMULT(Y76,14) -> 146.46333 | Y76: =U76/12 -> 10.461667
A77: ARTHUR MAC'S | I77: 49.61 | J77: 52 | U77: =SUM(I77:T77) -> 101.61 | W77: {=MMULT(Y77,11)} -> 93.1425 | X77: =MMULT(Y77,14) -> 118.545 | Y77: =U77/12 -> 8.4675
A78: DOVRE CLUB | K78: 46.02 | L78: 51.36 | U78: =SUM(I78:T78) -> 97.38 | W78: {=MMULT(Y78,11)} -> 89.265 | X78: =MMULT(Y78,14) -> 113.61 | Y78: =U78/12 -> 8.115
A79: FAMOUS TOASTERY | N79: 90 | U79: =SUM(I79:T79) -> 90 | W79: {=MMULT(Y79,11)} -> 82.5 | X79: =MMULT(Y79,14) -> 105 | Y79: =U79/12 -> 7.5
A80: JULIAN'S RESTAURANT | R80: 81.34 | U80: =SUM(I80:T80) -> 81.34 | W80: {=MMULT(Y80,11)} -> 74.561667 | X80: =MMULT(Y80,14) -> 94.896667 | Y80: =U80/12 -> 6.7783333
A81: JAVA HUT | P81: 80.69 | U81: =SUM(I81:T81) -> 80.69 | W81: {=MMULT(Y81,11)} -> 73.965833 | X81: =MMULT(Y81,14) -> 94.138333 | Y81: =U81/12 -> 6.7241667
A82: CASAVA | T82: 80.61 | U82: =SUM(I82:T82) -> 80.61 | W82: {=MMULT(Y82,11)} -> 73.8925 | X82: =MMULT(Y82,14) -> 94.045 | Y82: =U82/12 -> 6.7175
A83: THE VILLAGE PIZZERIA | R83: 80.36 | U83: =SUM(I83:T83) -> 80.36 | W83: {=MMULT(Y83,11)} -> 73.663333 | X83: =MMULT(Y83,14) -> 93.753333 | Y83: =U83/12 -> 6.6966667
A84: COCINA TEX MEX | M84: 80.04 | U84: =SUM(I84:T84) -> 80.04 | W84: {=MMULT(Y84,11)} -> 73.37 | X84: =MMULT(Y84,14) -> 93.38 | Y84: =U84/12 -> 6.67
A85: TROY GREEK CUISINE | L85: 74.05 | U85: =SUM(I85:T85) -> 74.05 | W85: {=MMULT(Y85,11)} -> 67.879167 | X85: =MMULT(Y85,14) -> 86.391667 | Y85: =U85/12 -> 6.1708333
A86: TABLE CULTURE PROVISIONS | Q86: 71.18 | U86: =SUM(I86:T86) -> 71.18 | W86: {=MMULT(Y86,11)} -> 65.248333 | X86: =MMULT(Y86,14) -> 83.043333 | Y86: =U86/12 -> 5.9316667
A87: WHITE RABBIT RESTAURANT | K87: 68.04 | U87: =SUM(I87:T87) -> 68.04 | W87: {=MMULT(Y87,11)} -> 62.37 | X87: =MMULT(Y87,14) -> 79.38 | Y87: =U87/12 -> 5.67
A88: TREE HOUSE CAFÉ | P88: 58.26 | U88: =SUM(I88:T88) -> 58.26 | W88: {=MMULT(Y88,11)} -> 53.405 | X88: =MMULT(Y88,14) -> 67.97 | Y88: =U88/12 -> 4.855
A89: RICE & BONES | N89: 53 | U89: =SUM(I89:T89) -> 53 | W89: {=MMULT(Y89,11)} -> 48.583333 | X89: =MMULT(Y89,14) -> 61.833333 | Y89: =U89/12 -> 4.4166667
A90: EUROPEAN MOTOR WORKS | Q90: 52.37 | U90: =SUM(I90:T90) -> 52.37 | W90: {=MMULT(Y90,11)} -> 48.005833 | X90: =MMULT(Y90,14) -> 61.098333 | Y90: =U90/12 -> 4.3641667
A91: STINKING ROSE | P91: 52.36 | U91: =SUM(I91:T91) -> 52.36 | W91: {=MMULT(Y91,11)} -> 47.996667 | X91: =MMULT(Y91,14) -> 61.086667 | Y91: =U91/12 -> 4.3633333
A92: CAFÉ SCOOTERIA | N92: 42.51 | U92: =SUM(I92:T92) -> 42.51 | W92: {=MMULT(Y92,11)} -> 38.9675 | X92: =MMULT(Y92,14) -> 49.595 | Y92: =U92/12 -> 3.5425
A93: SF BAY CONCESSION | Q93: 31.5 | U93: =SUM(I93:T93) -> 31.5 | W93: {=MMULT(Y93,11)} -> 28.875 | X93: =MMULT(Y93,14) -> 36.75 | Y93: =U93/12 -> 2.625
U94: =SUM(I94:T94) -> 0 | W94: {=MMULT(Y94,11)} -> 0 | X94: =MMULT(Y94,14) -> 0 | Y94: =U94/12 -> 0
U95: =SUM(I95:T95) -> 0 | W95: {=MMULT(Y95,11)} -> 0 | X95: =MMULT(Y95,14) -> 0 | Y95: =U95/12 -> 0
U96: =SUM(I96:T96) -> 0 | W96: {=MMULT(Y96,11)} -> 0 | X96: =MMULT(Y96,14) -> 0 | Y96: =U96/12 -> 0
U97: =SUM(I97:T97) -> 0 | W97: {=MMULT(Y97,11)} -> 0 | X97: =MMULT(Y97,14) -> 0 | Y97: =U97/12 -> 0
I98: =SUM( I36:I97) -> 888.59 | J98: =SUM( J36:J97) -> 1979.66 | K98: =SUM( K36:K97) -> 3682.17 | L98: =SUM( L36:L97) -> 1848.64 | M98: =SUM( M36:M97) -> 1684.79 | N98: =SUM( N36:N97) -> 3303.3 | O98: =SUM( O36:O97) -> 662.82 | P98: =SUM( P36:P97) -> 1829.6 | ... R98: =SUM( R36:R97) -> 983.6 | S98: =SUM( S26:S97) -> 2287.7 | T98: =SUM( T26:T97) -> 326.54 | U98: =SUM( U36:U97) -> 21017.48 | V98: =SUM( V26:V97) -> 0 | W98: =SUM( W36:W97) -> 19266.023 | X98: =SUM( X36:X97) -> 24520.393 | Y98: =SUM( Y36:Y97) -> 1751.4567
A99: Account Name | B99: A/E | C99: Primary tech | D99: INSTALL STATUS | E99: NOTES | F99: Close Date | G99: Amount | H99: Status | I99: Jan | J99: Feb | K99: Mar | L99: Apr | M99: May | N99: Jun | O99: Jul | P99: Aug | Q99: Sep | R99: Oct | S99: Nov | T99: Dec | U99: TOTAL | W99: Budget | X99: Goal | Y99: AVG/MONTH
U100: =SUM(I100:T100) -> 0 | W100: 981 | X100: 1481 | Y100: =U100/12 -> 0
U101: =SUM(I101:T101) -> 0 | W101: 982 | X101: 1482 | Y101: =U101/12 -> 0
U102: =SUM(I102:T102) -> 0 | W102: 983 | X102: 1483 | Y102: =U102/12 -> 0
U103: =SUM(I103:T103) -> 0 | W103: 984 | X103: 1484 | Y103: =U103/12 -> 0
U104: =SUM(I104:T104) -> 0 | W104: 985 | X104: 1485 | Y104: =U104/12 -> 0
...

Sheet Revenue - Equipment 2022
A1: Account Name | B1: A/E | C1: CONTACT | D1: EQUIPMENT | E1: NOTES / STATUS | F1: Close Date | G1: Amount | H1: Status | I1: Jan | J1: Feb | K1: Mar | L1: Apr | M1: May | N1: Jun | O1: Jul | P1: Aug | Q1: Sep | R1: Oct | S1: Nov | T1: Dec | U1: TOTAL | W1: Budget | X1: Goal | Y1: AVG/MONTH
A2: *** ONBOARD ***
A4: Antigua Cocina | B4: AH | O4: 1101 | U4: =SUM(I4:T4) -> 1101 | W4: 1002 | X4: 1502 | Y4: =U4/12 -> 91.75
A5: Busters Cheese Steak | B5: AH | D5: Awaiting customer call | E5: NCC | O5: 1500 | U5: =SUM(I5:T5) -> 1500 | W5: 1008 | X5: 1508 | Y5: =U5/12 -> 125
A6: Cafe Greco – 415-397-6261 / 415-990-7613 | B6: AH | O6: 1043.57 | U6: =SUM(I6:T6) -> 1043.57 | W6: 1000 | X6: 1500 | Y6: =U6/12 -> 86.964167
A7: Candy Heaven | B7: AH | I7: 864.56 | U7: =SUM(I7:T7) -> 864.56 | W7: 1010 | X7: 1510 | Y7: =U7/12 -> 72.046667
A8: Cigarettes Cheaper Arcata | B8: AH | C8: Mohammad | D8: Fusion Scanner | E8: 369 | P8: 400.37 | U8: =SUM(I8:T8) -> 400.37 | W8: 1004 | X8: 1504 | Y8: =U8/12 -> 33.364167
A9: Cigarettes Cheaper Arcata | B9: AH | C9: Mohammad | D9: Fusion Scanner | P9: 400.37 | U9: =SUM(I9:T9) -> 400.37 | W9: 1005 | X9: 1505 | Y9: =U9/12 -> 33.364167
A10: Davis Plaza Liquor | J10: 305.2 | U10: =SUM(I10:T10) -> 305.2 | W10: 1016 | X10: 1516 | Y10: =U10/12 -> 25.433333
A11: DEPARTMENT OF AGRICULTURE/WEIGHTS & MEASURES | B11: AH | E11: 3500 | P11: 2045 | U11: =SUM(I11:T11) -> 2045 | W11: 1003 | X11: 1503 | Y11: =U11/12 -> 170.41667
A12: EL CAMARON DE SINALOA | B12: AH | J12: 4844.19 | U12: =SUM(I12:T12) -> 4844.19 | W12: 1011 | X12: 1511 | Y12: =U12/12 -> 403.6825
A13: Grand Express | T13: 5490 | U13: =SUM(I13:T13) -> 5490 | W13: 1000 | X13: 1200 | Y13: =U13/12 -> 457.5
A14: HOUSE OF SOUL | B14: AH | I14: 1214.85 | U14: =SUM(I14:T14) -> 1214.85 | W14: 1013 | X14: 1513 | Y14: =U14/12 -> 101.2375
A15: MURSHED ABDUL | B15: AH | J15: 528.96 | U15: =SUM(I15:T15) -> 528.96 | W15: 1012 | X15: 1512 | Y15: =U15/12 -> 44.08
A16: New Delhi Cuisine | N16: 795 | U16: =SUM(I16:T16) -> 795 | W16: 1015 | X16: 1515 | Y16: =U16/12 -> 66.25
A17: Nieves Mangoman | Q17: 325 | U17: =SUM(I17:T17) -> 325 | W17: 1017 | X17: 1517 | Y17: =U17/12 -> 27.083333
A18: Point Richmond Market | R18: 2390 | U18: =SUM(I18:T18) -> 2390 | W18: 1014 | X18: 1514 | Y18: =U18/12 -> 199.16667
A19: Robata Grill | B19: AH | E19: ALOHA 2 TMU220B | O19: 546.66 | U19: =SUM(I19:T19) -> 546.66 | W19: 1006 | X19: 1506 | Y19: =U19/12 -> 45.555
A20: Smoke City | R20: 495 | U20: =SUM(I20:T20) -> 495 | W20: 1000 | X20: 1200 | Y20: =U20/12 -> 41.25
A21: Soultrans | T21: 4580 | U21: =SUM(I21:T21) -> 4580 | W21: 1000 | X21: 1200 | Y21: =U21/12 -> 381.66667
A22: Syufy | B22: AH | O22: 1048 | U22: =SUM(I22:T22) -> 1048 | W22: 1001 | X22: 1501 | Y22: =U22/12 -> 87.333333
A23: Uncle Sams Liquor | T23: 395 | U23: =SUM(I23:T23) -> 395 | W23: 1000 | X23: 1200 | Y23: =U23/12 -> 32.916667
U24: =SUM(I24:T24) -> 0 | W24: 1007 | X24: 1507 | Y24: =U24/12 -> 0
U25: =SUM(I25:T25) -> 0 | W25: 1009 | X25: 1509 | Y25: =U25/12 -> 0
U26: =SUM(I26:T26) -> 0 | W26: 1000 | X26: 1200 | Y26: =U26/12 -> 0
Y27: =U27/12 -> 0
A28: *** RUNNING TOTAL *** | I28: =SUM(I2:I27) -> 2079.41 | J28: =SUM(J2:J27) -> 5678.35 | K28: =SUM(K2:K27) -> 0 | L28: =SUM(L2:L27) -> 0 | M28: =SUM(M2:M27) -> 0 | N28: =SUM(N2:N27) -> 795 | O28: =SUM(O2:O27) -> 5239.23 | P28: =SUM(P2:P27) -> 2845.74 | ... Y28: =SUM(Y2:Y27) -> 2526.0608
A29: Account Name | B29: A/E | C29: CONTACT | D29: EQUIPMENT | E29: NOTES / STATUS | F29: Close Date | G29: Amount | H29: Status | I29: Jan | J29: Feb | K29: Mar | L29: Apr | M29: May | N29: Jun | O29: Jul | P29: Aug | Q29: Sep | R29: Oct | S29: Nov | T29: Dec | U29: TOTAL | W29: Budget | X29: Goal | Y29: AVG/MONTH
A30: TACOS SINALOA | B30: AH | D30: NCC (3) | E30: sold | M30: 7010 | U30: =SUM(I30:T30) -> 7010 | W30: 1021 | X30: 1221 | Y30: =U30/12 -> 584.16667
A31: STONY POINT MARKET | B31: AH | C31: Tony | D31: Sam4s SAP6600 | E31: sold | G31: 4200 | R31: 5950 | U31: =SUM(I31:T31) -> 5950 | W31: 1041 | X31: 1241 | Y31: =U31/12 -> 495.83333
A32: San Pablo Market | B32: AH | E32: sold | T32: 5715 | U32: =SUM(I32:T32) -> 5715 | W32: 1019 | X32: 1219 | Y32: =U32/12 -> 476.25
A33: GRAND EXPRESS | B33: AH | D33: tablet | E33: sold | L33: 3212 | T33: 1590 | U33: =SUM(I33:T33) -> 4802 | W33: 1015 | X33: 1215 | Y33: =U33/12 -> 400.16667
A34: STONY POINT MARKET | B34: AH | D34: SAM4S SAP6600 | E34: sold | J34: 2745 | U34: =SUM(I34:T34) -> 2745 | W34: 1002 | X34: 1202 | Y34: =U34/12 -> 228.75
A35: EL MAZATLECO | B35: AH | D35: NCC-2 | E35: sold | J35: 2150 | U35: =SUM(I35:T35) -> 2150 | W35: 1000 | X35: 1200 | Y35: =U35/12 -> 179.16667
A36: SANCHO'S TAQUERIA | B36: AH | D36: NCC-1 | E36: sold | J36: 2050 | U36: =SUM(I36:T36) -> 2050 | W36: 1000 | X36: 1200 | Y36: =U36/12 -> 170.83333
A37: WEST WIND | B37: AH | D37: ER-940 | E37: sold | P37: 995 | R37: 945 | U37: =SUM(I37:T37) -> 1940 | W37: 1033 | X37: 1233 | Y37: =U37/12 -> 161.66667
A38: Star Grocery | B38: AH | E38: sold | R38: 1790 | U38: =SUM(I38:T38) -> 1790 | W38: 1053 | X38: 1253 | Y38: =U38/12 -> 149.16667
A39: STONY POINT MARKET | B39: AH | C39: Tony | D39: Sam4s SAP6600 | E39: sold | G39: 1553.16 | R39: 1553.16 | U39: =SUM(I39:T39) -> 1553.16 | W39: 1040 | X39: 1240 | Y39: =U39/12 -> 129.43
A40: La Hacienda | B40: AH | C40: Armando | D40: NCC -1 | E40: sold | S40: 1538 | U40: =SUM(I40:T40) -> 1538 | W40: 1039 | X40: 1239 | Y40: =U40/12 -> 128.16667
A41: SOULTRANS SEAFOOD | B41: AH | D41: Scanner | E41: sold | P41: 1535 | U41: =SUM(I41:T41) -> 1535 | W41: 1036 | X41: 1236 | Y41: =U41/12 -> 127.91667
A42: Theresa & Johnny’s Cafe | B42: AH | D42: NCC -1 | E42: sold | N42: 1430 | U42: =SUM(I42:T42) -> 1430 | W42: 1022 | X42: 1222 | Y42: =U42/12 -> 119.16667
A43: Donut King | B43: AH | E43: sold | S43: 1370 | U43: =SUM(I43:T43) -> 1370 | W43: 1049 | X43: 1249 | Y43: =U43/12 -> 114.16667
A44: SANCHO'S TAQUERIA | B44: AH | D44: NCC -1 | E44: sold | K44: 1350 | U44: =SUM(I44:T44) -> 1350 | W44: 1009 | X44: 1209 | Y44: =U44/12 -> 112.5
A45: SANCHO'S TAQUERIA | B45: AH | D45: NCC -1 | E45: sold | K45: 1350 | U45: =SUM(I45:T45) -> 1350 | W45: 1010 | X45: 1210 | Y45: =U45/12 -> 112.5
A46: PET FOOD EXPRESS | B46: AH | D46: SCALE | E46: sold | J46: 1137 | U46: =SUM(I46:T46) -> 1137 | W46: 1003 | X46: 1203 | Y46: =U46/12 -> 94.75
A47: BUTLER AMUSEMENTS | B47: AH | E47: sold | N47: 1055 | U47: =SUM(I47:T47) -> 1055 | W47: 1027 | X47: 1227 | Y47: =U47/12 -> 87.916667
A48: BELLAM PRODUCE | B48: AH | D48: SAM4S ER945 | E48: sold | J48: 895 | U48: =SUM(I48:T48) -> 895 | W48: 1001 | X48: 1201 | Y48: =U48/12 -> 74.583333
A49: HAPPY TACO | B49: AH | D49: ER-940 | E49: sold | P49: 895 | U49: =SUM(I49:T49) -> 895 | W49: 1032 | X49: 1232 | Y49: =U49/12 -> 74.583333
A50: LOS MEXICANOS CARNICERIA | B50: AH | E50: sold | K50: 895 | U50: =SUM(I50:T50) -> 895 | W50: 1014 | X50: 1214 | Y50: =U50/12 -> 74.583333
A51: POINT RICHMOND MARKET | B51: AH | D51: License | E51: sold | P51: 895 | U51: =SUM(I51:T51) -> 895 | W51: 1035 | X51: 1235 | Y51: =U51/12 -> 74.583333
A52: Star Grocery | B52: AH | E52: sold | O52: 895 | U52: =SUM(I52:T52) -> 895 | W52: 1029 | X52: 1229 | Y52: =U52/12 -> 74.583333
A53: TAQUERIA TEPA | B53: AH | D53: SAM4S ER940 | E53: sold | J53: 895 | U53: =SUM(I53:T53) -> 895 | W53: 1000 | X53: 1200 | Y53: =U53/12 -> 74.583333
A54: El Patron | B54: AH | D54: ER-940 | E54: sold | R54: 895 | U54: =SUM(I54:T54) -> 895 | W54: 1050 | X54: 1250 | Y54: =U54/12 -> 74.583333
A55: GEARY & HYDE MKT | B55: AH | E55: sold | Q55: 895 | U55: =SUM(I55:T55) -> 895 | W55: 1047 | X55: 1247 | Y55: =U55/12 -> 74.583333
A56: Woerners Liquor | B56: AH | D56: ER-945 | E56: sold | Q56: 895 | U56: =SUM(I56:T56) -> 895 | W56: 1037 | X56: 1237 | Y56: =U56/12 -> 74.583333
A57: WOERNERS LIQUORS | B57: AH | E57: sold | Q57: 895 | U57: =SUM(I57:T57) -> 895 | W57: 1048 | X57: 1248 | Y57: =U57/12 -> 74.583333
A58: Marina Parkeway Liquors | B58: AH | C58: 1st Machine | D58: Customer robber | E58: sold | S58: 895 | U58: =SUM(I58:T58) -> 895 | W58: 1054 | X58: 1254 | Y58: =U58/12 -> 74.583333
A59: Marina Parkeway Liquors | B59: AH | C59: 2nd Machine | D59: Customer robber | E59: sold | S59: 895 | U59: =SUM(I59:T59) -> 895 | W59: 1054 | X59: 1254 | Y59: =U59/12 -> 74.583333
A60: PETRIFIED FOREST | B60: AH | D60: rental | E60: sold | L60: 99 | M60: 99 | N60: 99 | O60: 99 | P60: 99 | Q60: 99 | R60: 99 | S60: 99 | T60: 99 | U60: =SUM(I60:T60) -> 891 | W60: 1018 | X60: 1218 | Y60: =U60/12 -> 74.25
A61: LA TIENDITA | B61: AH | D61: ER-265 | E61: sold | P61: 795 | U61: =SUM(I61:T61) -> 795 | W61: 1034 | X61: 1234 | Y61: =U61/12 -> 66.25
A62: US LIQUOR | B62: AH | D62: ONSITE SVC | E62: sold | J62: 695 | U62: =SUM(I62:T62) -> 695 | W62: 2500 | X62: 3500 | Y62: =U62/12 -> 57.916667
A63: BAR BOCCE | B63: AH | E63: sold | Q63: 616 | U63: =SUM(I63:T63) -> 616 | W63: 1051 | X63: 1251 | Y63: =U63/12 -> 51.333333
A64: EDEN MEDICAL CENTER | B64: AH | D64: SAM4S ER265 | E64: sold | L64: 495 | U64: =SUM(I64:T64) -> 495 | W64: 1020 | X64: 1220 | Y64: =U64/12 -> 41.25
A65: FOOD 24 MARKET | B65: AH | D65: SAM4S ER265 | E65: sold | L65: 495 | U65: =SUM(I65:T65) -> 495 | W65: 1019 | X65: 1219 | Y65: =U65/12 -> 41.25
A66: PUPUSERIA BLANKITA | B66: AH | D66: SAM4S ER265 | E66: sold | J66: 495 | U66: =SUM(I66:T66) -> 495 | W66: 5500 | X66: 8100 | Y66: =U66/12 -> 41.25
A67: SUTTER NOVATO HEALTH | B67: AH | D67: ER-265 | E67: sold | P67: 495 | U67: =SUM(I67:T67) -> 495 | W67: 1031 | X67: 1231 | Y67: =U67/12 -> 41.25
A68: Ace Hardware | B68: AH | D68: ER-260 | E68: sold | Q68: 495 | U68: =SUM(I68:T68) -> 495 | W68: 1036 | X68: 1236 | Y68: =U68/12 -> 41.25
A69: ALL STAR DONUT | B69: AH | E69: sold | R69: 495 | U69: =SUM(I69:T69) -> 495 | W69: 1052 | X69: 1252 | Y69: =U69/12 -> 41.25
A70: CORTE MADERA SHOE REPAIR | B70: AH | D70: ECR | E70: sold | J70: 450 | U70: =SUM(I70:T70) -> 450 | W70: 999 | X70: 1199 | Y70: =U70/12 -> 37.5
A71: PETRIFIED FOREST GIFT SHOP | B71: AH | D71: NCC -1 | E71: sold | I71: 400 | U71: =SUM(I71:T71) -> 400 | W71: 1020 | X71: 1220 | Y71: =U71/12 -> 33.333333
A72: U SAVE LIQUOR | B72: AH | D72: SCANNER | E72: sold | I72: 396 | U72: =SUM(I72:T72) -> 396 | W72: 1005 | X72: 1205 | Y72: =U72/12 -> 33
A73: TARTINE BAKERY | B73: AH | D73: TMU220B | E73: sold | I73: 395 | U73: =SUM(I73:T73) -> 395 | W73: 1006 | X73: 1206 | Y73: =U73/12 -> 32.916667
A74: POINT RICHMOND MARKET | B74: AH | D74: ONSITE SVC | E74: sold | J74: 390 | U74: =SUM(I74:T74) -> 390 | W74: 1000 | X74: 1200 | Y74: =U74/12 -> 32.5
A75: CHICKEN EXPRESS | B75: AH | D75: printer | E75: sold | L75: 210 | U75: =SUM(I75:T75) -> 210 | W75: 1017 | X75: 1227 | Y75: =U75/12 -> 17.5
A76: WAGON WHEEL | B76: AH | E76: sold | O76: 195 | U76: =SUM(I76:T76) -> 195 | W76: 1028 | X76: 1228 | Y76: =U76/12 -> 16.25
A77: EL CAMARON DE SINALOA | B77: AH | D77: NCC -1 | E77: sold | K77: -495 | U77: =SUM(I77:T77) -> -495 | W77: 1012 | X77: 1212 | Y77: =U77/12 -> -41.25
U79: =SUM(I79:T79) -> 0 | W79: 1056 | X79: 1256 | Y79: =U79/12 -> 0
U80: =SUM(I80:T80) -> 0 | W80: 1000 | X80: 1500 | Y80: =U80/12 -> 0
U81: =SUM(I81:T81) -> 0 | W81: 1000 | X81: 1500 | Y81: =U81/12 -> 0
A82: Total 2022 | I82: =SUM( I31:I81) -> 1191 | J82: =SUM( J31:J81) -> 11902 | K82: =SUM( K31:K81) -> 3100 | L82: =SUM( L31:L81) -> 4511 | M82: =SUM( M31:M81) -> 99 | N82: =SUM( N31:N81) -> 2584 | O82: =SUM( O31:O81) -> 1189 | P82: =SUM( P31:P81) -> 5709 | ... U82: =SUM( U31:U81) -> 58108.16 | V82: =SUM( V25:V81) -> 0 | W82: =SUM( W25:W81) -> 83386 | X82: =SUM( X25:X81) -> 108096 | Y82: =SUM( Y25:Y81) -> 7952.5742
A84: Sales 2023
A85: Account Name | B85: A/E | C85: CONTACT | D85: EQUIPMENT | E85: NOTES / STATUS | F85: Close Date | G85: Amount | H85: Status | I85: Jan | J85: Feb | K85: Mar | L85: Apr | M85: May | N85: Jun | O85: Jul | P85: Aug | Q85: Sep | R85: Oct | S85: Nov | T85: Dec | U85: TOTAL | W85: Budget | X85: Goal | Y85: AVG/MONTH
U86: =SUM(I86:T86) -> 0 | W86: 1018 | X86: 1218 | Y86: =U86/12 -> 0
A88: Solano Market | B88: AH | D88: Scale | E88: Won | H88: WON | I88: 1695 | U88: =SUM(I88:T88) -> 1695 | W88: 1500 | X88: 2000 | Y88: =U88/12 -> 141.25
A89: PETRIFIED FOREST | B89: AH | D89: rental | E89: sold | H89: WON | I89: 99 | J89: 99 | K89: 99 | L89: 99 | M89: 99 | N89: 99 | O89: 99 | P89: 99 | Q89: 99 | R89: 99 | S89: 99 | T89: 99 | U89: =SUM(I89:T89) -> 1188 | W89: 1018 | X89: 1218 | Y89: =U89/12 -> 99
A90: WEST WIND | B90: AH | D90: ER-940 | E90: sold | H90: WON | J90: 995 | U90: =SUM(I90:T90) -> 995 | W90: 1033 | X90: 1233 | Y90: =U90/12 -> 82.916667
A91: Coco’s Mercado | B91: AH | D91: CL5500 | H91: WON | K91: 3990
A92: UC Market | B92: AH | D92: ER-945 | H92: WON | J92: 995
A93: Estrella Market | B93: AH | D93: CL7200 | E93: sold | H93: WON | K93: 2995
A94: L&L RWC | B94: AH | E94: sold | H94: WON | J94: 295
A95: POINT RICHMOND MKT | B95: AH | H95: WON | J95: 398
A96: EUROPA EXPRESS MKT | B96: AH | H96: WON | J96: 3480
A97: Avenue Market | B97: AH | H97: WON | K97: 2981
A98: Soultrans | B98: AH | H98: WON | K98: 520
A99: Busters Cheese Steak | B99: AH | H99: WON | K99: 375
A100: Busters Cheese Steak | B100: AH | H100: WON | K100: 195
A101: Fred’s Liquor | B101: AH | H101: WON | K101: 225
A102: Fred’s Liquor | B102: AH | H102: WON | K102: 1804.37
A103: Hawaiian Drive Inn | B103: AH | G103: 2316.79 | H103: WON | L103: 1470
A104: Mikes Market | B104: AH | G104: 2653.78 | M104: 2090
...

Sheet Revnue - NAHSO Supplies_2022
A1: Account Name | B1: A/E | C1: CONTACT | D1: EQUIPMENT | E1: NOTES / STATUS | F1: Close Date | G1: Amount | H1: Status | I1: Jan | J1: Feb | K1: Mar | L1: Apr | M1: May | N1: Jun | O1: Jul | P1: Aug | Q1: Sep | R1: Oct | S1: Nov | T1: Dec | U1: TOTAL | W1: Budget | X1: Goal | Y1: AVG/MONTH
A2: *** ONBOARD ***
A3: COASTAL PACIFIC | L3: 919 | M3: 1302 | N3: 918 | O3: 779 | P3: 1027 | Q3: 2310 | R3: 2228 | S3: 690 | T3: 1035 | U3: =SUM(I3:T3) -> 11208 | W3: {=MMULT(Y3,11)} -> 10274 | X3: {=MMULT(Y3,14)} -> 13076 | Y3: =U3/12 -> 934
A4: CASS INC | O4: 6258.84 | U4: =SUM(I4:T4) -> 6258.84 | W4: {=MMULT(Y4,11)} -> 5737.27 | X4: {=MMULT(Y4,14)} -> 7301.98 | Y4: =U4/12 -> 521.57
A5: SOL FOOD COMMISSARY | I5: 2075 | O5: 1650 | S5: 2250 | U5: =SUM(I5:T5) -> 5975 | W5: {=MMULT(Y5,11)} -> 5477.0833 | X5: {=MMULT(Y5,14)} -> 6970.8333 | Y5: =U5/12 -> 497.91667
A6: SOL FOOD | L6: 1639 | N6: 1350 | Q6: 2175 | U6: =SUM(I6:T6) -> 5164 | W6: {=MMULT(Y6,11)} -> 4733.6667 | X6: {=MMULT(Y6,14)} -> 6024.6667 | Y6: =U6/12 -> 430.33333
A7: CASA LUPE | I7: 550 | L7: 708 | O7: 1670 | Q7: 650 | S7: 1340 | U7: =SUM(I7:T7) -> 4918 | W7: {=MMULT(Y7,11)} -> 4508.1667 | X7: {=MMULT(Y7,14)} -> 5737.6667 | Y7: =U7/12 -> 409.83333
A8: BOH-WILDSEED | I8: 612 | J8: 411 | K8: 352 | L8: 460 | M8: 285 | O8: 918 | P8: 117 | Q8: 715 | R8: 405 | T8: 139 | U8: =SUM(I8:T8) -> 4414 | W8: {=MMULT(Y8,11)} -> 4046.1667 | X8: {=MMULT(Y8,14)} -> 5149.6667 | Y8: =U8/12 -> 367.83333
A9: COASTAL PACIFIC | L9: 365 | M9: 690 | N9: 552 | O9: 483 | P9: 207 | Q9: 711 | R9: 690 | U9: =SUM(I9:T9) -> 3698 | W9: {=MMULT(Y9,11)} -> 3389.8333 | X9: {=MMULT(Y9,14)} -> 4314.3333 | Y9: =U9/12 -> 308.16667
A10: CALISTOGA INN | I10: 135 | J10: 100 | K10: 303 | L10: 255 | M10: 165 | N10: 1101 | O10: 198 | P10: 408 | Q10: 276 | R10: 363 | S10: 198 | T10: 165 | U10: =SUM(I10:T10) -> 3667 | W10: {=MMULT(Y10,11)} -> 3361.4167 | X10: {=MMULT(Y10,14)} -> 4278.1667 | Y10: =U10/12 -> 305.58333
A11: COASTAL PACIFIC | N11: 276 | O11: 730 | P11: 828 | Q11: 552 | R11: 790 | S11: 392 | U11: =SUM(I11:T11) -> 3568 | W11: {=MMULT(Y11,11)} -> 3270.6667 | X11: {=MMULT(Y11,14)} -> 4162.6667 | Y11: =U11/12 -> 297.33333
A12: WATERBAR | J12: 615 | L12: 891 | P12: 1089 | R12: 914 | T12: 729 | U12: =SUM(I12:T12) -> 4238 | W12: {=MMULT(Y12,11)} -> 3884.8333 | X12: {=MMULT(Y12,14)} -> 4944.3333 | Y12: =U12/12 -> 353.16667
A13: MARINA SUPER | N13: 410 | P13: 885 | R13: 406 | S13: 674 | T13: 674 | U13: =SUM(I13:T13) -> 3049 | W13: {=MMULT(Y13,11)} -> 2794.9167 | X13: {=MMULT(Y13,14)} -> 3557.1667 | Y13: =U13/12 -> 254.08333
A14: COASTAL PACIFIC | L14: 406 | M14: 86 | N14: 305 | O14: 345 | R14: 474 | S14: 1422 | U14: =SUM(I14:T14) -> 3038 | W14: {=MMULT(Y14,11)} -> 2784.8333 | X14: {=MMULT(Y14,14)} -> 3544.3333 | Y14: =U14/12 -> 253.16667
A15: ROKA AKOR | I15: 296 | J15: 55 | K15: 293 | L15: 94 | M15: 486 | N15: 454 | P15: 180 | Q15: 454 | R15: 156 | S15: 337 | T15: 180 | U15: =SUM(I15:T15) -> 2985 | W15: {=MMULT(Y15,11)} -> 2736.25 | X15: {=MMULT(Y15,14)} -> 3482.5 | Y15: =U15/12 -> 248.75
A16: EPIC STEAK | L16: 1447 | O16: 442 | P16: 945 | U16: =SUM(I16:T16) -> 2834 | W16: {=MMULT(Y16,11)} -> 2597.8333 | X16: {=MMULT(Y16,14)} -> 3306.3333 | Y16: =U16/12 -> 236.16667
A17: HARVEST MARKET | R17: 990 | S17: 1650 | U17: =SUM(I17:T17) -> 2640 | W17: {=MMULT(Y17,11)} -> 2420 | X17: {=MMULT(Y17,14)} -> 3080 | Y17: =U17/12 -> 220
A18: VILLAGE MARKET & PIZZA | K18: 675 | P18: 977 | Q18: 985 | U18: =SUM(I18:T18) -> 2637 | W18: {=MMULT(Y18,11)} -> 2417.25 | X18: {=MMULT(Y18,14)} -> 3076.5 | Y18: =U18/12 -> 219.75
A19: POGGIO | J19: 490 | O19: 862 | Q19: 440 | S19: 784 | U19: =SUM(I19:T19) -> 2576 | W19: {=MMULT(Y19,11)} -> 2361.3333 | X19: {=MMULT(Y19,14)} -> 3005.3333 | Y19: =U19/12 -> 214.66667
A20: STARK'S STEAKHOUSE | I20: 157 | J20: 145 | K20: 157 | L20: 157 | M20: 298 | N20: 285 | O20: 308 | P20: 243 | Q20: 240 | R20: 175 | S20: 298 | U20: =SUM(I20:T20) -> 2463 | W20: {=MMULT(Y20,11)} -> 2257.75 | X20: {=MMULT(Y20,14)} -> 2873.5 | Y20: =U20/12 -> 205.25
A21: TAQUERIA EL GORDO | K21: 590 | L21: 707 | S21: 914 | U21: =SUM(I21:T21) -> 2211 | W21: {=MMULT(Y21,11)} -> 2026.75 | X21: {=MMULT(Y21,14)} -> 2579.5 | Y21: =U21/12 -> 184.25
A22: INSALATA'S | J22: 262 | K22: 225 | L22: 451 | N22: 130 | P22: 90 | Q22: 345 | R22: 78 | S22: 590 | U22: =SUM(I22:T22) -> 2171 | W22: {=MMULT(Y22,11)} -> 1990.0833 | X22: {=MMULT(Y22,14)} -> 2532.8333 | Y22: =U22/12 -> 180.91667
A23: UNCLE YU'S | L23: 1180 | S23: 975 | U23: =SUM(I23:T23) -> 2155 | W23: {=MMULT(Y23,11)} -> 1975.4167 | X23: {=MMULT(Y23,14)} -> 2514.1667 | Y23: =U23/12 -> 179.58333
A24: COCO'S MERCADO | I24: 168 | J24: 139 | K24: 145 | L24: 149 | M24: 222 | N24: 255 | P24: 326 | Q24: 118 | R24: 287 | S24: 255 | U24: =SUM(I24:T24) -> 2064 | W24: {=MMULT(Y24,11)} -> 1892 | X24: {=MMULT(Y24,14)} -> 2408 | Y24: =U24/12 -> 172
A25: THE CANTINA | I25: 297 | J25: 176 | L25: 235 | M25: 130 | O25: 312 | P25: 298 | Q25: 285 | S25: 324 | U25: =SUM(I25:T25) -> 2057 | W25: {=MMULT(Y25,11)} -> 1885.5833 | X25: {=MMULT(Y25,14)} -> 2399.8333 | Y25: =U25/12 -> 171.41667
A26: 5TH ST STEAKHOUSE | J26: 136 | K26: 205 | L26: 234 | N26: 320 | O26: 304 | P26: 223 | Q26: 168 | S26: 457 | U26: =SUM(I26:T26) -> 2047 | W26: {=MMULT(Y26,11)} -> 1876.4167 | X26: {=MMULT(Y26,14)} -> 2388.1667 | Y26: =U26/12 -> 170.58333
A27: THE TRIDENT | K27: 470 | O27: 781 | S27: 726 | U27: =SUM(I27:T27) -> 1977 | W27: {=MMULT(Y27,11)} -> 1812.25 | X27: {=MMULT(Y27,14)} -> 2306.5 | Y27: =U27/12 -> 164.75
A28: FARMHOUSE LOCAL | I28: 55 | K28: 275 | L28: 353 | M28: 338 | N28: 130 | O28: 363 | Q28: 298 | R28: 130 | U28: =SUM(I28:T28) -> 1942 | W28: {=MMULT(Y28,11)} -> 1780.1667 | X28: {=MMULT(Y28,14)} -> 2265.6667 | Y28: =U28/12 -> 161.83333
A29: FISH | J29: 572 | L29: 490 | P29: 480 | S29: 290 | U29: =SUM(I29:T29) -> 1832 | W29: {=MMULT(Y29,11)} -> 1679.3333 | X29: {=MMULT(Y29,14)} -> 2137.3333 | Y29: =U29/12 -> 152.66667
A30: BARREL HOUSE TAVERN | I30: 270 | L30: 390 | Q30: 1170 | U30: =SUM(I30:T30) -> 1830 | W30: {=MMULT(Y30,11)} -> 1677.5 | X30: {=MMULT(Y30,14)} -> 2135 | Y30: =U30/12 -> 152.5
A31: BUNGALOW 44 | I31: 411 | K31: 216 | N31: 350 | P31: 451 | S31: 315 | U31: =SUM(I31:T31) -> 1743 | W31: {=MMULT(Y31,11)} -> 1597.75 | X31: {=MMULT(Y31,14)} -> 2033.5 | Y31: =U31/12 -> 145.25
A32: MI RANCHO MARKET | I32: 165 | J32: 90 | K32: 153 | L32: 223 | M32: 130 | N32: 130 | O32: 143 | P32: 169 | Q32: 143 | R32: 78 | S32: 169 | T32: 65 | U32: =SUM(I32:T32) -> 1658 | W32: {=MMULT(Y32,11)} -> 1519.8333 | X32: {=MMULT(Y32,14)} -> 1934.3333 | Y32: =U32/12 -> 138.16667
A33: ROSE'S CAFÉ | I33: 294 | K33: 314 | N33: 354 | Q33: 399 | T33: 289 | U33: =SUM(I33:T33) -> 1650 | W33: {=MMULT(Y33,11)} -> 1512.5 | X33: {=MMULT(Y33,14)} -> 1925 | Y33: =U33/12 -> 137.5
A34: GUERRA QUALITY MEATS | L34: 195 | M34: 483 | O34: 483 | P34: 483 | U34: =SUM(I34:T34) -> 1644 | W34: {=MMULT(Y34,11)} -> 1507 | X34: {=MMULT(Y34,14)} -> 1918 | Y34: =U34/12 -> 137
A35: STATE BIRD | J35: 162 | K35: 108 | L35: 176 | M35: 159 | N35: 149 | O35: 159 | P35: 149 | Q35: 269 | S35: 308 | U35: =SUM(I35:T35) -> 1639 | W35: {=MMULT(Y35,11)} -> 1502.4167 | X35: {=MMULT(Y35,14)} -> 1912.1667 | Y35: =U35/12 -> 136.58333
A36: EVERGREEN PRODUCE | L36: 745 | P36: 884 | U36: =SUM(I36:T36) -> 1629 | W36: {=MMULT(Y36,11)} -> 1493.25 | X36: {=MMULT(Y36,14)} -> 1900.5 | Y36: =U36/12 -> 135.75
A37: MONTI'S ROTISSERIE | J37: 452 | M37: 410 | N37: 260 | R37: 450 | U37: =SUM(I37:T37) -> 1572 | W37: {=MMULT(Y37,11)} -> 1441 | X37: {=MMULT(Y37,14)} -> 1834 | Y37: =U37/12 -> 131
A38: LEFT BANK | I38: 248 | J38: 307 | K38: 236 | M38: 260 | P38: 195 | S38: 325 | U38: =SUM(I38:T38) -> 1571 | W38: {=MMULT(Y38,11)} -> 1440.0833 | X38: {=MMULT(Y38,14)} -> 1832.8333 | Y38: =U38/12 -> 130.91667
A39: GUEST HOUSE | J39: 223 | M39: 304 | O39: 269 | P39: 441 | T39: 324 | U39: =SUM(I39:T39) -> 1561 | W39: {=MMULT(Y39,11)} -> 1430.9167 | X39: {=MMULT(Y39,14)} -> 1821.1667 | Y39: =U39/12 -> 130.08333
A40: GROSSMAN'S NOSHERY | I40: 270 | K40: 196 | L40: 214 | N40: 220 | Q40: 220 | R40: 175 | T40: 220 | U40: =SUM(I40:T40) -> 1515 | W40: {=MMULT(Y40,11)} -> 1388.75 | X40: {=MMULT(Y40,14)} -> 1767.5 | Y40: =U40/12 -> 126.25
A41: BUCKEYE ROADHOUSE | L41: 117 | N41: 638 | R41: 454 | T41: 295 | U41: =SUM(I41:T41) -> 1504 | W41: {=MMULT(Y41,11)} -> 1378.6667 | X41: {=MMULT(Y41,14)} -> 1754.6667 | Y41: =U41/12 -> 125.33333
A42: TACOS SINALOA | I42: 94 | K42: 196 | M42: 279 | P42: 214 | Q42: 253 | R42: 149 | S42: 104 | T42: 188 | U42: =SUM(I42:T42) -> 1477 | W42: {=MMULT(Y42,11)} -> 1353.9167 | X42: {=MMULT(Y42,14)} -> 1723.1667 | Y42: =U42/12 -> 123.08333
A43: McINNIS GOLF | K43: 203 | M43: 123 | N43: 282 | O43: 240 | Q43: 376 | S43: 227 | U43: =SUM(I43:T43) -> 1451 | W43: {=MMULT(Y43,11)} -> 1330.0833 | X43: {=MMULT(Y43,14)} -> 1692.8333 | Y43: =U43/12 -> 120.91667
A44: ESTRELLA'S MARKET | J44: 590 | K44: 590 | L44: 260 | U44: =SUM(I44:T44) -> 1440 | W44: {=MMULT(Y44,11)} -> 1320 | X44: {=MMULT(Y44,14)} -> 1680 | Y44: =U44/12 -> 120
A45: SILVERS AT WHARF | K45: 266 | L45: 234 | P45: 933 | U45: =SUM(I45:T45) -> 1433 | W45: {=MMULT(Y45,11)} -> 1313.5833 | X45: {=MMULT(Y45,14)} -> 1671.8333 | Y45: =U45/12 -> 119.41667
A46: THREE BROTHERS | L46: 423 | M46: 270 | R46: 660 | U46: =SUM(I46:T46) -> 1353 | W46: {=MMULT(Y46,11)} -> 1240.25 | X46: {=MMULT(Y46,14)} -> 1578.5 | Y46: =U46/12 -> 112.75
A47: PEACOCK GAP | I47: 275 | L47: 325 | O47: 650 | Q47: 84 | U47: =SUM(I47:T47) -> 1334 | W47: {=MMULT(Y47,11)} -> 1222.8333 | X47: {=MMULT(Y47,14)} -> 1556.3333 | Y47: =U47/12 -> 111.16667
A48: PURITY MARKET | J48: 320 | L48: 260 | O48: 330 | P48: 130 | R48: 260 | U48: =SUM(I48:T48) -> 1300 | W48: {=MMULT(Y48,11)} -> 1191.6667 | X48: {=MMULT(Y48,14)} -> 1516.6667 | Y48: =U48/12 -> 108.33333
A49: BOCA PIZZA | L49: 235 | O49: 265 | P49: 198 | Q49: 78 | R49: 288 | S49: 233 | U49: =SUM(I49:T49) -> 1297 | W49: {=MMULT(Y49,11)} -> 1188.9167 | X49: {=MMULT(Y49,14)} -> 1513.1667 | Y49: =U49/12 -> 108.08333
A50: HOUSE OF PRIME RIB | I50: 1100 | O50: 135 | P50: 39 | U50: =SUM(I50:T50) -> 1274 | W50: {=MMULT(Y50,11)} -> 1167.8333 | X50: {=MMULT(Y50,14)} -> 1486.3333 | Y50: =U50/12 -> 106.16667
A51: MOUNTAIN MIKE'S | J51: 235 | M51: 376 | N51: 149 | P51: 337 | R51: 175 | U51: =SUM(I51:T51) -> 1272 | W51: {=MMULT(Y51,11)} -> 1166 | X51: {=MMULT(Y51,14)} -> 1484 | Y51: =U51/12 -> 106
A52: CHUCK CORICA GC | I52: 177 | K52: 177 | M52: 195 | O52: 130 | Q52: 195 | S52: 195 | T52: 195 | U52: =SUM(I52:T52) -> 1264 | W52: {=MMULT(Y52,11)} -> 1158.6667 | X52: {=MMULT(Y52,14)} -> 1474.6667 | Y52: =U52/12 -> 105.33333
A53: BOH-A MANO | I53: 387 | K53: 646 | M53: 220 | U53: =SUM(I53:T53) -> 1253 | W53: {=MMULT(Y53,11)} -> 1148.5833 | X53: {=MMULT(Y53,14)} -> 1461.8333 | Y53: =U53/12 -> 104.41667
A54: LA TOSCANA | I54: 88 | J54: 129 | K54: 118 | L54: 137 | M54: 110 | N54: 65 | O54: 110 | P54: 65 | Q54: 65 | R54: 149 | S54: 65 | T54: 149 | U54: =SUM(I54:T54) -> 1250 | W54: {=MMULT(Y54,11)} -> 1145.8333 | X54: {=MMULT(Y54,14)} -> 1458.3333 | Y54: =U54/12 -> 104.16667
A55: BRAVAS DE TAPAS | I55: 207 | K55: 196 | L55: 235 | N55: 110 | O55: 188 | P55: 175 | T55: 110 | U55: =SUM(I55:T55) -> 1221 | W55: {=MMULT(Y55,11)} -> 1119.25 | X55: {=MMULT(Y55,14)} -> 1424.5 | Y55: =U55/12 -> 101.75
A56: ZAYTOON | K56: 333 | M56: 149 | N56: 298 | R56: 204 | T56: 230 | U56: =SUM(I56:T56) -> 1214 | W56: {=MMULT(Y56,11)} -> 1112.8333 | X56: {=MMULT(Y56,14)} -> 1416.3333 | Y56: =U56/12 -> 101.16667
A57: TARTINE BAKERY | J57: 430 | N57: 776 | U57: =SUM(I57:T57) -> 1206 | W57: {=MMULT(Y57,11)} -> 1105.5 | X57: {=MMULT(Y57,14)} -> 1407 | Y57: =U57/12 -> 100.5
A58: CELIA'S | J58: 181 | K58: 105 | O58: 344 | R58: 230 | T58: 330 | U58: =SUM(I58:T58) -> 1190 | W58: {=MMULT(Y58,11)} -> 1090.8333 | X58: {=MMULT(Y58,14)} -> 1388.3333 | Y58: =U58/12 -> 99.166667
A59: BRET HARTE MARKET | J59: 422 | O59: 156 | P59: 585 | U59: =SUM(I59:T59) -> 1163 | W59: {=MMULT(Y59,11)} -> 1066.0833 | X59: {=MMULT(Y59,14)} -> 1356.8333 | Y59: =U59/12 -> 96.916667
A60: HARMONY | J60: 239 | L60: 147 | O60: 279 | R60: 185 | S60: 279 | U60: =SUM(I60:T60) -> 1129 | W60: {=MMULT(Y60,11)} -> 1034.9167 | X60: {=MMULT(Y60,14)} -> 1317.1667 | Y60: =U60/12 -> 94.083333
A61: DELANCEY STREET | J61: 296 | M61: 285 | P61: 78 | S61: 468 | U61: =SUM(I61:T61) -> 1127 | W61: {=MMULT(Y61,11)} -> 1033.0833 | X61: {=MMULT(Y61,14)} -> 1314.8333 | Y61: =U61/12 -> 93.916667
A62: VALENCIA WHOLE FOODS | I62: 125 | J62: 70 | K62: 188 | M62: 78 | N62: 156 | P62: 169 | R62: 221.5 | T62: 117 | U62: =SUM(I62:T62) -> 1124.5 | W62: {=MMULT(Y62,11)} -> 1030.7917 | X62: {=MMULT(Y62,14)} -> 1311.9167 | Y62: =U62/12 -> 93.708333
A63: LA SALLE'S | J63: 194 | K63: 196 | N63: 175 | O63: 175 | P63: 149 | Q63: 230 | U63: =SUM(I63:T63) -> 1119 | W63: {=MMULT(Y63,11)} -> 1025.75 | X63: {=MMULT(Y63,14)} -> 1305.5 | Y63: =U63/12 -> 93.25
A64: YANK SING | I64: 257 | L64: 117 | O64: 201 | R64: 330 | T64: 201 | U64: =SUM(I64:T64) -> 1106 | W64: {=MMULT(Y64,11)} -> 1013.8333 | X64: {=MMULT(Y64,14)} -> 1290.3333 | Y64: =U64/12 -> 92.166667
A65: LOTUS INDIAN CUISINE | M65: 610 | Q65: 492 | U65: =SUM(I65:T65) -> 1102 | W65: {=MMULT(Y65,11)} -> 1010.1667 | X65: {=MMULT(Y65,14)} -> 1285.6667 | Y65: =U65/12 -> 91.833333
A66: SAN RAFAEL JOE'S | I66: 140 | K66: 146 | L66: 116 | O66: 135 | P66: 70 | Q66: 215 | S66: 170 | T66: 105 | U66: =SUM(I66:T66) -> 1097 | W66: {=MMULT(Y66,11)} -> 1005.5833 | X66: {=MMULT(Y66,14)} -> 1279.8333 | Y66: =U66/12 -> 91.416667
A67: PUB REPUBLIC | I67: 94 | J67: 157 | L67: 39 | M67: 159 | N67: 130 | O67: 149 | Q67: 214 | S67: 149 | U67: =SUM(I67:T67) -> 1091 | W67: {=MMULT(Y67,11)} -> 1000.0833 | X67: {=MMULT(Y67,14)} -> 1272.8333 | Y67: =U67/12 -> 90.916667
A68: TOMATINA | I68: 129 | J68: 98 | K68: 157 | L68: 59 | N68: 110 | O68: 110 | R68: 125 | S68: 123 | T68: 175 | U68: =SUM(I68:T68) -> 1086 | W68: {=MMULT(Y68,11)} -> 995.5 | X68: {=MMULT(Y68,14)} -> 1267 | Y68: =U68/12 -> 90.5
A69: PACIFICO RESTAURANTE | I69: 70 | J69: 118 | L69: 177 | N69: 159 | P69: 159 | Q69: 295 | S69: 104 | U69: =SUM(I69:T69) -> 1082 | W69: {=MMULT(Y69,11)} -> 991.83333 | X69: {=MMULT(Y69,14)} -> 1262.3333 | Y69: =U69/12 -> 90.166667
A70: RILEY'S | I70: 110 | J70: 59 | K70: 66.5 | L70: 124 | M70: 78 | O70: 65 | P70: 130 | Q70: 110 | R70: 65 | S70: 260 | U70: =SUM(I70:T70) -> 1067.5 | W70: {=MMULT(Y70,11)} -> 978.54167 | X70: {=MMULT(Y70,14)} -> 1245.4167 | Y70: =U70/12 -> 88.958333
A71: ATWATER TAVERN | K71: 333 | O71: 349 | S71: 375 | U71: =SUM(I71:T71) -> 1057 | W71: {=MMULT(Y71,11)} -> 968.91667 | X71: {=MMULT(Y71,14)} -> 1233.1667 | Y71: =U71/12 -> 88.083333
A72: KIMONO | I72: 25 | J72: 90 | K72: 314 | N72: 169 | P72: 130 | Q72: 110 | T72: 208 | U72: =SUM(I72:T72) -> 1046 | W72: {=MMULT(Y72,11)} -> 958.83333 | X72: {=MMULT(Y72,14)} -> 1220.3333 | Y72: =U72/12 -> 87.166667
A73: CROSSROADS CAFÉ | P73: 1040 | U73: =SUM(I73:T73) -> 1040 | W73: {=MMULT(Y73,11)} -> 953.33333 | X73: {=MMULT(Y73,14)} -> 1213.3333 | Y73: =U73/12 -> 86.666667
A74: BOH-TAILOR'S SON | I74: 477 | P74: 557 | U74: =SUM(I74:T74) -> 1034 | W74: {=MMULT(Y74,11)} -> 947.83333 | X74: {=MMULT(Y74,14)} -> 1206.3333 | Y74: =U74/12 -> 86.166667
A75: PLAYA RESTAURANT | K75: 196 | N75: 220 | P75: 240 | Q75: 45 | R75: 165 | T75: 165 | U75: =SUM(I75:T75) -> 1031 | W75: {=MMULT(Y75,11)} -> 945.08333 | X75: {=MMULT(Y75,14)} -> 1202.8333 | Y75: =U75/12 -> 85.916667
A76: TOMATINA | I76: 152 | J76: 352 | L76: 98 | N76: 149 | S76: 130 | T76: 149 | U76: =SUM(I76:T76) -> 1030 | W76: {=MMULT(Y76,11)} -> 944.16667 | X76: {=MMULT(Y76,14)} -> 1201.6667 | Y76: =U76/12 -> 85.833333
A77: BELLAM SELF STORAGE | L77: 312 | S77: 710 | U77: =SUM(I77:T77) -> 1022 | W77: {=MMULT(Y77,11)} -> 936.83333 | X77: {=MMULT(Y77,14)} -> 1192.3333 | Y77: =U77/12 -> 85.166667
A78: IT'S ITALIA | K78: 470 | P78: 531 | U78: =SUM(I78:T78) -> 1001 | W78: {=MMULT(Y78,11)} -> 917.58333 | X78: {=MMULT(Y78,14)} -> 1167.8333 | Y78: =U78/12 -> 83.416667
A79: ANDI'S MARKET | I79: 140 | K79: 424 | M79: 149.5 | O79: 156 | Q79: 130 | U79: =SUM(I79:T79) -> 999.5 | W79: {=MMULT(Y79,11)} -> 916.20833 | X79: {=MMULT(Y79,14)} -> 1166.0833 | Y79: =U79/12 -> 83.291667
A80: AMAKARA | I80: 225 | K80: 471 | M80: 295 | U80: =SUM(I80:T80) -> 991 | W80: {=MMULT(Y80,11)} -> 908.41667 | X80: {=MMULT(Y80,14)} -> 1156.1667 | Y80: =U80/12 -> 82.583333
A81: STAR GROCERY | J81: 140 | K81: 118 | L81: 140 | Q81: 221 | S81: 156 | T81: 208 | U81: =SUM(I81:T81) -> 983 | W81: {=MMULT(Y81,11)} -> 901.08333 | X81: {=MMULT(Y81,14)} -> 1146.8333 | Y81: =U81/12 -> 81.916667
A82: BOH- LOLINDA | P82: 970 | U82: =SUM(I82:T82) -> 970 | W82: {=MMULT(Y82,11)} -> 889.16667 | X82: {=MMULT(Y82,14)} -> 1131.6667 | Y82: =U82/12 -> 80.833333
A83: ZIO FRAEDO | M83: 962 | U83: =SUM(I83:T83) -> 962 | W83: {=MMULT(Y83,11)} -> 881.83333 | X83: {=MMULT(Y83,14)} -> 1122.3333 | Y83: =U83/12 -> 80.166667
A84: CELIA'S/XALISCO | I84: 720 | L84: 234 | U84: =SUM(I84:T84) -> 954 | W84: {=MMULT(Y84,11)} -> 874.5 | X84: {=MMULT(Y84,14)} -> 1113 | Y84: =U84/12 -> 79.5
A85: DINO'S | J85: 284 | N85: 328 | T85: 334 | U85: =SUM(I85:T85) -> 946 | W85: {=MMULT(Y85,11)} -> 867.16667 | X85: {=MMULT(Y85,14)} -> 1103.6667 | Y85: =U85/12 -> 78.833333
A86: BOH-FLORES | I86: 113 | J86: 290 | K86: 117 | M86: 162 | N86: 239 | U86: =SUM(I86:T86) -> 921 | W86: {=MMULT(Y86,11)} -> 844.25 | X86: {=MMULT(Y86,14)} -> 1074.5 | Y86: =U86/12 -> 76.75
A87: ARMANDO'S | J87: 234 | K87: 236 | R87: 435 | U87: =SUM(I87:T87) -> 905 | W87: {=MMULT(Y87,11)} -> 829.58333 | X87: {=MMULT(Y87,14)} -> 1055.8333 | Y87: =U87/12 -> 75.416667
A88: SAN BRUNO SUPER | J88: 900 | U88: =SUM(I88:T88) -> 900 | W88: {=MMULT(Y88,11)} -> 825 | X88: {=MMULT(Y88,14)} -> 1050 | Y88: =U88/12 -> 75
A89: THE SEA BY ALEXANDERS | L89: 294 | P89: 330 | R89: 240 | U89: =SUM(I89:T89) -> 864 | W89: {=MMULT(Y89,11)} -> 792 | X89: {=MMULT(Y89,14)} -> 1008 | Y89: =U89/12 -> 72
A90: STATION HOUSE CAFÉ | N90: 498 | S90: 342 | U90: =SUM(I90:T90) -> 840 | W90: {=MMULT(Y90,11)} -> 770 | X90: {=MMULT(Y90,14)} -> 980 | Y90: =U90/12 -> 70
A91: FRANKY'S | I91: 55 | J91: 98 | K91: 66.5 | L91: 110 | M91: 48.88 | O91: 65 | P91: 110 | R91: 110 | S91: 65 | T91: 110 | U91: =SUM(I91:T91) -> 838.38 | W91: {=MMULT(Y91,11)} -> 768.515 | X91: {=MMULT(Y91,14)} -> 978.11 | Y91: =U91/12 -> 69.865
A92: OCEANVIEW DINER | K92: 65 | Q92: 330 | S92: 408 | U92: =SUM(I92:T92) -> 803 | W92: {=MMULT(Y92,11)} -> 736.08333 | X92: {=MMULT(Y92,14)} -> 936.83333 | Y92: =U92/12 -> 66.916667
A93: TOMATINA | I93: 148.5 | J93: 168 | L93: 98 | N93: 130 | Q93: 149 | T93: 65 | U93: =SUM(I93:T93) -> 758.5 | W93: {=MMULT(Y93,11)} -> 695.29167 | X93: {=MMULT(Y93,14)} -> 884.91667 | Y93: =U93/12 -> 63.208333
A94: MARINITAS | K94: 284 | N94: 130 | Q94: 330 | U94: =SUM(I94:T94) -> 744 | W94: {=MMULT(Y94,11)} -> 682 | X94: {=MMULT(Y94,14)} -> 868 | Y94: =U94/12 -> 62
A95: HI DIVE | J95: 186 | N95: 165 | P95: 169 | T95: 210 | U95: =SUM(I95:T95) -> 730 | W95: {=MMULT(Y95,11)} -> 669.16667 | X95: {=MMULT(Y95,14)} -> 851.66667 | Y95: =U95/12 -> 60.833333
A96: KEZAR PUB | L96: 177 | T96: 542 | U96: =SUM(I96:T96) -> 719 | W96: {=MMULT(Y96,11)} -> 659.08333 | X96: {=MMULT(Y96,14)} -> 838.83333 | Y96: =U96/12 -> 59.916667
A97: GRAZIE | J97: 129 | L97: 143 | N97: 155 | P97: 130 | T97: lue b | U97: =SUM(I97:T97) -> 557 | W97: {=MMULT(Y97,11)} -> 510.58333 | X97: {=MMULT(Y97,14)} -> 649.83333 | Y97: =U97/12 -> 46.416667
A98: EASY RIDER | I98: 223 | K98: 176 | Q98: 298 | U98: =SUM(I98:T98) -> 697 | W98: {=MMULT(Y98,11)} -> 638.91667 | X98: {=MMULT(Y98,14)} -> 813.16667 | Y98: =U98/12 -> 58.083333
A99: BULL VALLEY | K99: 235 | O99: 156 | P99: 155 | S99: 149 | U99: =SUM(I99:T99) -> 695 | W99: {=MMULT(Y99,11)} -> 637.08333 | X99: {=MMULT(Y99,14)} -> 810.83333 | Y99: =U99/12 -> 57.916667
A100: MONICA'S LIVERMORE | I100: 258 | L100: 216 | R100: 220 | U100: =SUM(I100:T100) -> 694 | W100: {=MMULT(Y100,11)} -> 636.16667 | X100: {=MMULT(Y100,14)} -> 809.66667 | Y100: =U100/12 -> 57.833333
...

Sheet Revnue - Service 2022
A1: Account Name | B1: A/E | C1: CONTACT | D1: EQUIPMENT | E1: NOTES / STATUS | F1: Close Date | G1: Amount | H1: Status | I1: Jan | J1: Feb | K1: Mar | L1: Apr | M1: May | N1: Jun | O1: Jul | P1: Aug | Q1: Sep | R1: Oct | S1: Nov | T1: Dec | U1: TOTAL | W1: Budget | X1: Goal | Y1: AVG/MONTH
A2: *** ONBOARD ***
A4: Oak Park Liquor | B4: AH | C4: LG | O4: 450 | U4: =SUM(I4:T4) -> 450 | W4: 300 | X4: 500 | Y4: =U4/12 -> 37.5
A5: Point Richmond Market | R5: 720 | U5: =SUM(I5:T5) -> 720
A6: Geary & Hyde Market | B6: AH | C6: EL | D6: In repair bay | E6: Andy Patel – 415-760-9315 | O6: 360 | U6: =SUM(I6:T6) -> 360 | W6: 300 | X6: 500 | Y6: =U6/12 -> 30
A7: KAFFE MOCHA & GRILL | J7: 270 | P7: 45 | U7: =SUM(I7:T7) -> 315 | Y7: =U7/12 -> 26.25
A8: DISCOUNT ALLEY | U8: =SUM(I8:T8) -> 0 | W8: 300 | X8: 500 | Y8: =U8/12 -> 0
A9: DEPARTMENT OF AGRICULTURE/WEIGHTS & MEASURES | B9: AH | E9: 3500 | P9: 750 | U9: =SUM(I9:T9) -> 750 | Y9: =U9/12 -> 62.5
A10: DEPARTMENT OF AGRICULTURE/WEIGHTS & MEASURES | B10: AH | E10: 3500 | P10: 180 | U10: =SUM(I10:T10) -> 180 | Y10: =U10/12 -> 15
A11: Nieves Mangoman | Q11: 90 | U11: =SUM(I11:T11) -> 90
A12: DEPARTMENT OF AGRICULTURE/WEIGHTS & MEASURES | B12: AH | E12: Travel | Q12: 180 | U12: =SUM(I12:T12) -> 180 | Y12: =U12/12 -> 15
A13: DEPARTMENT OF AGRICULTURE/WEIGHTS & MEASURES | B13: AH | E13: Onsite | Q13: 1260 | U13: =SUM(I13:T13) -> 1260 | Y13: =U13/12 -> 105
Y14: =U14/12 -> 0
A15: *** RUNNING TOTAL *** | B15: 2021 | I15: =SUM(I2:I14) -> 0 | J15: =SUM(J2:J14) -> 270 | K15: =SUM(K2:K14) -> 0 | L15: =SUM(L2:L14) -> 0 | M15: =SUM(M2:M14) -> 0 | N15: =SUM(N2:N14) -> 0 | O15: =SUM(O2:O14) -> 810 | P15: =SUM(P2:P14) -> 975 | ... X15: =SUM(X2:X14) -> 1500 | Y15: =U15/12 -> 358.75
A17: DEPARTMENT OF AGRICULTURE/WEIGHTS & MEASURES | N17: 1980 | U17: =SUM(I17:T17) -> 1980 | W17: {=MMULT(Y17,11)} -> 1815 | X17: {=MMULT(Y17,14)} -> 2310 | Y17: =U17/12 -> 165
A18: THERESA & JOHNNY'S | N18: 1440 | U18: =SUM(I18:T18) -> 1440 | W18: {=MMULT(Y18,11)} -> 1320 | X18: {=MMULT(Y18,14)} -> 1680 | Y18: =U18/12 -> 120
A19: STONY POINT MARKET | D19: SAM4S SAP6600 | I19: 720 | R19: 360 | U19: =SUM(I19:T19) -> 1080 | W19: {=MMULT(Y19,11)} -> 990 | X19: {=MMULT(Y19,14)} -> 1260 | Y19: =U19/12 -> 90
A20: San Pablo Market | T20: 990 | U20: =SUM(I20:T20) -> 990 | W20: {=MMULT(Y20,11)} -> 907.5 | X20: {=MMULT(Y20,14)} -> 1155 | Y20: =U20/12 -> 82.5
A21: La Hacienda | B21: AH | C21: Armando | D21: NCC-1 | E21: Reconditioned | F21: 44873 | S21: 810 | U21: =SUM(I21:T21) -> 810 | W21: {=MMULT(Y21,11)} -> 742.5 | X21: {=MMULT(Y21,14)} -> 945 | Y21: =U21/12 -> 67.5
A22: 420 SMOKE PALACE | I22: 795 | U22: =SUM(I22:T22) -> 795 | W22: {=MMULT(Y22,11)} -> 728.75 | X22: {=MMULT(Y22,14)} -> 927.5 | Y22: =U22/12 -> 66.25
A23: STAR GROCERY | O23: 360 | R23: 360 | U23: =SUM(I23:T23) -> 720 | W23: {=MMULT(Y23,11)} -> 660 | X23: {=MMULT(Y23,14)} -> 840 | Y23: =U23/12 -> 60
A24: Donut King | S24: 540 | U24: =SUM(I24:T24) -> 540 | W24: {=MMULT(Y24,11)} -> 495 | X24: {=MMULT(Y24,14)} -> 630 | Y24: =U24/12 -> 45
A25: GRAND EXPRESS | L25: 360 | T25: 170 | U25: =SUM(I25:T25) -> 530 | W25: {=MMULT(Y25,11)} -> 485.83333 | X25: {=MMULT(Y25,14)} -> 618.33333 | Y25: =U25/12 -> 44.166667
A26: STONY POINT MARKET | D26: SAM4S SAP6600 | R26: 495 | U26: =SUM(I26:T26) -> 495 | W26: {=MMULT(Y26,11)} -> 453.75 | X26: {=MMULT(Y26,14)} -> 577.5 | Y26: =U26/12 -> 41.25
A27: POINT RICHMOND MARKET | P27: 405 | U27: =SUM(I27:T27) -> 405 | W27: {=MMULT(Y27,11)} -> 371.25 | X27: {=MMULT(Y27,14)} -> 472.5 | Y27: =U27/12 -> 33.75
A28: U SAVE LIQUOR | I28: 395 | U28: =SUM(I28:T28) -> 395 | W28: {=MMULT(Y28,11)} -> 362.08333 | X28: {=MMULT(Y28,14)} -> 460.83333 | Y28: =U28/12 -> 32.916667
A29: EL MAZATLECO | B29: AH | C29: AH | D29: NCC-2 | I29: 360 | U29: =SUM(I29:T29) -> 360 | W29: {=MMULT(Y29,11)} -> 330 | X29: {=MMULT(Y29,14)} -> 420 | Y29: =U29/12 -> 30
A30: HAPPY TACO | P30: 360 | U30: =SUM(I30:T30) -> 360 | W30: {=MMULT(Y30,11)} -> 330 | X30: {=MMULT(Y30,14)} -> 420 | Y30: =U30/12 -> 30
A31: PETRIFIED FOREST GIFT SHOP | I31: 360 | U31: =SUM(I31:T31) -> 360 | W31: {=MMULT(Y31,11)} -> 330 | X31: {=MMULT(Y31,14)} -> 420 | Y31: =U31/12 -> 30
A32: SPRINGSTOWNE BOTTLE SHOP | I32: 360 | U32: =SUM(I32:T32) -> 360 | W32: {=MMULT(Y32,11)} -> 330 | X32: {=MMULT(Y32,14)} -> 420 | Y32: =U32/12 -> 30
A33: TAQUERIA EL TEJABAN | I33: 360 | U33: =SUM(I33:T33) -> 360 | W33: {=MMULT(Y33,11)} -> 330 | X33: {=MMULT(Y33,14)} -> 420 | Y33: =U33/12 -> 30
A34: TAQUERIA EL TEJABAN | I34: 360 | U34: =SUM(I34:T34) -> 360 | W34: {=MMULT(Y34,11)} -> 330 | X34: {=MMULT(Y34,14)} -> 420 | Y34: =U34/12 -> 30
A35: TAQUERIA EL TEJABAN | K35: 360 | U35: =SUM(I35:T35) -> 360 | W35: {=MMULT(Y35,11)} -> 330 | X35: {=MMULT(Y35,14)} -> 420 | Y35: =U35/12 -> 30
A36: US LIQUOR | D36: ONSITE SVC | J36: 360 | U36: =SUM(I36:T36) -> 360 | W36: {=MMULT(Y36,11)} -> 330 | X36: {=MMULT(Y36,14)} -> 420 | Y36: =U36/12 -> 30
A37: WEST WIND | P37: 360 | U37: =SUM(I37:T37) -> 360 | W37: {=MMULT(Y37,11)} -> 330 | X37: {=MMULT(Y37,14)} -> 420 | Y37: =U37/12 -> 30
A38: WEST WIND | R38: 360 | U38: =SUM(I38:T38) -> 360 | W38: {=MMULT(Y38,11)} -> 330 | X38: {=MMULT(Y38,14)} -> 420 | Y38: =U38/12 -> 30
A39: LAS MONTANAS | M39: 345 | U39: =SUM(I39:T39) -> 345 | W39: {=MMULT(Y39,11)} -> 316.25 | X39: {=MMULT(Y39,14)} -> 402.5 | Y39: =U39/12 -> 28.75
A40: Ace Hardware | B40: AH | D40: ER-260 | Q40: 270 | U40: =SUM(I40:T40) -> 270 | W40: {=MMULT(Y40,11)} -> 247.5 | X40: {=MMULT(Y40,14)} -> 315 | Y40: =U40/12 -> 22.5
A41: POINT RICHMOND MARKET & DELI | L41: 270 | U41: =SUM(I41:T41) -> 270 | W41: {=MMULT(Y41,11)} -> 247.5 | X41: {=MMULT(Y41,14)} -> 315 | Y41: =U41/12 -> 22.5
A42: SANCHO'S TAQUERIA | K42: 270 | U42: =SUM(I42:T42) -> 270 | W42: {=MMULT(Y42,11)} -> 247.5 | X42: {=MMULT(Y42,14)} -> 315 | Y42: =U42/12 -> 22.5
A43: SOULTRANS SEAFOOD | P43: 270 | U43: =SUM(I43:T43) -> 270 | W43: {=MMULT(Y43,11)} -> 247.5 | X43: {=MMULT(Y43,14)} -> 315 | Y43: =U43/12 -> 22.5
A44: Marina Parkway Liquors | S44: 270 | U44: =SUM(I44:T44) -> 270 | W44: {=MMULT(Y44,11)} -> 247.5 | X44: {=MMULT(Y44,14)} -> 315 | Y44: =U44/12 -> 22.5
A45: BRRET HARTE MARKET | O45: 180 | U45: =SUM(I45:T45) -> 180 | W45: {=MMULT(Y45,11)} -> 165 | X45: {=MMULT(Y45,14)} -> 210 | Y45: =U45/12 -> 15
A46: BUTLER AMUSEMENTS | N46: 180 | U46: =SUM(I46:T46) -> 180 | W46: {=MMULT(Y46,11)} -> 165 | X46: {=MMULT(Y46,14)} -> 210 | Y46: =U46/12 -> 15
A47: EDEN MEDICAL CENTER | L47: 180 | U47: =SUM(I47:T47) -> 180 | W47: {=MMULT(Y47,11)} -> 165 | X47: {=MMULT(Y47,14)} -> 210 | Y47: =U47/12 -> 15
A48: PET FOOD EXPRESS | D48: SCALE | I48: 180 | U48: =SUM(I48:T48) -> 180 | W48: {=MMULT(Y48,11)} -> 165 | X48: {=MMULT(Y48,14)} -> 210 | Y48: =U48/12 -> 15
A49: POINT RICHMOND MARKET | D49: ONSITE SVC | J49: 180 | U49: =SUM(I49:T49) -> 180 | W49: {=MMULT(Y49,11)} -> 165 | X49: {=MMULT(Y49,14)} -> 210 | Y49: =U49/12 -> 15
A50: SANCHO'S TAQUERIA | B50: AH | C50: AH | D50: NCC-1 | I50: 180 | U50: =SUM(I50:T50) -> 180 | W50: {=MMULT(Y50,11)} -> 165 | X50: {=MMULT(Y50,14)} -> 210 | Y50: =U50/12 -> 15
A51: SANCHO'S TAQUERIA | K51: 180 | U51: =SUM(I51:T51) -> 180 | W51: {=MMULT(Y51,11)} -> 165 | X51: {=MMULT(Y51,14)} -> 210 | Y51: =U51/12 -> 15
A52: TAQUERIA TEPA | D52: SAM4S ER940 | I52: 180 | U52: =SUM(I52:T52) -> 180 | W52: {=MMULT(Y52,11)} -> 165 | X52: {=MMULT(Y52,14)} -> 210 | Y52: =U52/12 -> 15
A53: U-SAVE LIQUORS | O53: 180 | U53: =SUM(I53:T53) -> 180 | W53: {=MMULT(Y53,11)} -> 165 | X53: {=MMULT(Y53,14)} -> 210 | Y53: =U53/12 -> 15
A54: U-SAVE LIQUORS | O54: 180 | U54: =SUM(I54:T54) -> 180 | W54: {=MMULT(Y54,11)} -> 165 | X54: {=MMULT(Y54,14)} -> 210 | Y54: =U54/12 -> 15
A55: WEST WIND | R55: 180 | U55: =SUM(I55:T55) -> 180 | W55: {=MMULT(Y55,11)} -> 165 | X55: {=MMULT(Y55,14)} -> 210 | Y55: =U55/12 -> 15
A56: El Patron | R56: 180 | U56: =SUM(I56:T56) -> 180 | W56: {=MMULT(Y56,11)} -> 165 | X56: {=MMULT(Y56,14)} -> 210 | Y56: =U56/12 -> 15
A57: LA TIENDITA | P57: 100 | U57: =SUM(I57:T57) -> 100 | W57: {=MMULT(Y57,11)} -> 91.666667 | X57: {=MMULT(Y57,14)} -> 116.66667 | Y57: =U57/12 -> 8.3333333
A58: Woerners Liquor | B58: AH | D58: ER-945 | Q58: 100 | U58: =SUM(I58:T58) -> 100 | W58: {=MMULT(Y58,11)} -> 91.666667 | X58: {=MMULT(Y58,14)} -> 116.66667 | Y58: =U58/12 -> 8.3333333
A59: BELLAM PRODUCE | D59: SAM4S ER945 | J59: 90 | U59: =SUM(I59:T59) -> 90 | W59: {=MMULT(Y59,11)} -> 82.5 | X59: {=MMULT(Y59,14)} -> 105 | Y59: =U59/12 -> 7.5
A60: CORTE MADERA SHOE REPAIR | B60: AH | C60: AH | D60: ECR | J60: 90 | U60: =SUM(I60:T60) -> 90 | W60: {=MMULT(Y60,11)} -> 82.5 | X60: {=MMULT(Y60,14)} -> 105 | Y60: =U60/12 -> 7.5
A61: PUPUSERIA BLANKITA | D61: SAM4S ER265 | J61: 90 | U61: =SUM(I61:T61) -> 90 | W61: {=MMULT(Y61,11)} -> 82.5 | X61: {=MMULT(Y61,14)} -> 105 | Y61: =U61/12 -> 7.5
A62: UNITED FOOD MART | K62: 90 | U62: =SUM(I62:T62) -> 90 | W62: {=MMULT(Y62,11)} -> 82.5 | X62: {=MMULT(Y62,14)} -> 105 | Y62: =U62/12 -> 7.5
A63: BOCA PIZZA | R63: 78 | U63: =SUM(I63:T63) -> 78 | W63: {=MMULT(Y63,11)} -> 71.5 | X63: {=MMULT(Y63,14)} -> 91 | Y63: =U63/12 -> 6.5
A64: RAY'S FOOD CENTER | Q64: 45 | U64: =SUM(I64:T64) -> 45 | W64: {=MMULT(Y64,11)} -> 41.25 | X64: {=MMULT(Y64,14)} -> 52.5 | Y64: =U64/12 -> 3.75
A65: STAR GROCERY | O65: 45 | U65: =SUM(I65:T65) -> 45 | W65: {=MMULT(Y65,11)} -> 41.25 | X65: {=MMULT(Y65,14)} -> 52.5 | Y65: =U65/12 -> 3.75
A66: SUMMERHOUSE | M66: 45 | U66: =SUM(I66:T66) -> 45 | W66: {=MMULT(Y66,11)} -> 41.25 | X66: {=MMULT(Y66,14)} -> 52.5 | Y66: =U66/12 -> 3.75
A67: SUMMERHOUSE | M67: 45 | U67: =SUM(I67:T67) -> 45 | W67: {=MMULT(Y67,11)} -> 41.25 | X67: {=MMULT(Y67,14)} -> 52.5 | Y67: =U67/12 -> 3.75
A68: TAP PLASTICS | M68: 45 | U68: =SUM(I68:T68) -> 45 | W68: {=MMULT(Y68,11)} -> 41.25 | X68: {=MMULT(Y68,14)} -> 52.5 | Y68: =U68/12 -> 3.75
A69: BOH-WILDSEED | U69: =SUM(I69:T69) -> 0 | W69: {=MMULT(Y69,11)} -> 0 | X69: {=MMULT(Y69,14)} -> 0 | Y69: =U69/12 -> 0
A70: MARINITAS | U70: =SUM(I70:T70) -> 0 | W70: {=MMULT(Y70,11)} -> 0 | X70: {=MMULT(Y70,14)} -> 0 | Y70: =U70/12 -> 0
A71: TOMATINA | U71: =SUM(I71:T71) -> 0 | W71: {=MMULT(Y71,11)} -> 0 | X71: {=MMULT(Y71,14)} -> 0 | Y71: =U71/12 -> 0
A72: TABLE CULTURE PROVISIONS | U72: =SUM(I72:T72) -> 0 | W72: {=MMULT(Y72,11)} -> 0 | X72: {=MMULT(Y72,14)} -> 0 | Y72: =U72/12 -> 0
A73: GEARY & HYDE MKT | U73: =SUM(I73:T73) -> 0 | W73: {=MMULT(Y73,11)} -> 0 | X73: {=MMULT(Y73,14)} -> 0 | Y73: =U73/12 -> 0
A74: WOERNERS LIQUORS | U74: =SUM(I74:T74) -> 0 | W74: {=MMULT(Y74,11)} -> 0 | X74: {=MMULT(Y74,14)} -> 0 | Y74: =U74/12 -> 0
U75: =SUM(I75:T75) -> 0 | W75: {=MMULT(Y75,11)} -> 0 | X75: {=MMULT(Y75,14)} -> 0 | Y75: =U75/12 -> 0
U76: =SUM(I76:T76) -> 0 | W76: {=MMULT(Y76,11)} -> 0 | X76: {=MMULT(Y76,14)} -> 0 | Y76: =U76/12 -> 0
U77: =SUM(I77:T77) -> 0 | W77: {=MMULT(Y77,11)} -> 0 | X77: {=MMULT(Y77,14)} -> 0 | Y77: =U77/12 -> 0
A78: Sales Totals 2022 | I78: =SUM( I17:I77) -> 4250 | J78: =SUM( J17:J77) -> 810 | K78: =SUM( K17:K77) -> 900 | L78: =SUM( L17:L77) -> 810 | M78: =SUM( M17:M77) -> 480 | N78: =SUM( N17:N77) -> 3600 | O78: =SUM( O17:O77) -> 945 | P78: =SUM( P17:P77) -> 1495 | ... U78: =SUM( U17:U77) -> 18498 | V78: =SUM( V14:V77) -> 0 | W78: =SUM( W14:W77) -> 17856.5 | X78: =SUM( X14:X77) -> 23081 | Y78: =SUM( Y14:Y77) -> 1900.25
U80: =SUM(I80:T80) -> 0 | W80: {=MMULT(Y80,11)} -> 0 | X80: {=MMULT(Y80,14)} -> 0 | Y80: =U80/12 -> 0
A81: WEST WIND | B81: AH | H81: WON | J81: 360 | U81: =SUM(I81:T81) -> 360 | W81: {=MMULT(Y81,11)} -> 330 | X81: {=MMULT(Y81,14)} -> 420 | Y81: =U81/12 -> 30
A82: Solano Market | B82: AH | D82: Scale | E82: 1 | F82: 44931 | H82: WON | I82: 630 | U82: =SUM(I82:T82) -> 630 | W82: {=MMULT(Y82,11)} -> 577.5 | X82: {=MMULT(Y82,14)} -> 735 | Y82: =U82/12 -> 52.5
A83: Europa Express | B83: AH | C83: Boris | F83: 44956 | G83: 4611.9 | H83: WON | I83: 720 | U83: =SUM(I83:T83) -> 720 | W83: 1117 | X83: 1317 | Y83: =U83/12 -> 60
A84: UC Market | B84: AH | J84: 360 | U84: =SUM(I84:T84) -> 360 | W84: {=MMULT(Y84,11)} -> 330 | X84: {=MMULT(Y84,14)} -> 420 | Y84: =U84/12 -> 30
A85: Estrella Market | B85: AH | D85: CL7200 | E85: sold | H85: WON | K85: 650
A86: Coco’s Mercado | B86: AH | D86: CL-5500 | E86: sold | H86: WON | K86: 630 | U86: =SUM(I86:T86) -> 630 | W86: {=MMULT(Y86,11)} -> 577.5 | X86: {=MMULT(Y86,14)} -> 735 | Y86: =U86/12 -> 52.5
A87: Avenue Liqour | H87: WON | K87: 720 | U87: =SUM(I87:T87) -> 720 | W87: {=MMULT(Y87,11)} -> 660 | X87: {=MMULT(Y87,14)} -> 840 | Y87: =U87/12 -> 60
A88: SOULTRANS SEAFOOD | H88: WON | K88: 193 | U88: =SUM(I88:T88) -> 193 | W88: {=MMULT(Y88,11)} -> 176.91667 | X88: {=MMULT(Y88,14)} -> 225.16667 | Y88: =U88/12 -> 16.083333
A89: Fred’s Liquors | K89: 540 | U89: =SUM(I89:T89) -> 540 | W89: {=MMULT(Y89,11)} -> 495 | X89: {=MMULT(Y89,14)} -> 630 | Y89: =U89/12 -> 45
A90: Hawaiian Drive Inn | B90: AH | G90: 2316.79 | L90: 720
U91: =SUM(I91:T91) -> 0 | W91: {=MMULT(Y91,11)} -> 0 | X91: {=MMULT(Y91,14)} -> 0 | Y91: =U91/12 -> 0
U92: =SUM(I92:T92) -> 0 | W92: {=MMULT(Y92,11)} -> 0 | X92: {=MMULT(Y92,14)} -> 0 | Y92: =U92/12 -> 0
U93: =SUM(I93:T93) -> 0 | W93: {=MMULT(Y93,11)} -> 0 | X93: {=MMULT(Y93,14)} -> 0 | Y93: =U93/12 -> 0
U94: =SUM(I94:T94) -> 0 | W94: {=MMULT(Y94,11)} -> 0 | X94: {=MMULT(Y94,14)} -> 0 | Y94: =U94/12 -> 0
U95: =SUM(I95:T95) -> 0
A96: Sales Totals 2023 | I96: =SUM( I80:I95) -> 1350 | J96: =SUM( J80:J95) -> 720 | K96: =SUM( K80:K95) -> 2733 | L96: =SUM( L80:L95) -> 720 | M96: =SUM( M80:M95) -> 0 | N96: =SUM( N80:N95) -> 0 | O96: =SUM( O80:O95) -> 0 | P96: =SUM( P80:P95) -> 0 | ... U96: =SUM( U80:U95) -> 4153 | V96: =SUM( V31:V95) -> 0 | W96: =SUM( W31:W95) -> 29085.25 | X96: =SUM( X80:X95) -> 5322.1667 | Y96: =SUM( Y31:Y95) -> 2879.5

Sheet Upcoming Installations
A1: Name | B1: Status | C1: Street Address | D1: City | E1: State | F1: Zipcode | G1: PM | H1: Status | I1: Accepted On | J1: Agent | M1: Merchant Id | N1: Profile Link | T1: MID
A3: Ancora | B3: In-Process | C3: 557 Valencia St | D3: San Francisco | E3: CA | F3: 94110 | H3: site walk- dk-5/2 | I3: 44651.339 | J3: Youkilis Scott | M3: 624637999adef3fc5a37f781 | N3: https://hub.spoton.com/merchants/624637999adef3fc5a37f781 | T3: 545500001565340
A4: Andy and Yu's Restaurant and Bar | B4: Pre-Cancellation | C4: 348 Saint Mary St | D4: Pleasanton | E4: CA | F4: 94566 | I4: 44438.639 | J4: Koidal Steve | M4: 612d59c29adef36e02168ad1 | N4: https://hub.spoton.com/merchants/612d59c29adef36e02168ad1 | T4: 545500001442300
A5: Arya Steakhouse | B5: In-Process | C5: 885 Middlefield Rd | D5: Redwood City | E5: CA | F5: 94063 | I5: 44657.537 | J5: Walker Stephen | M5: 624e16d424b4c44267b02422 | N5: https://hub.spoton.com/merchants/624e16d424b4c44267b02422 | T5: 545500001569110
A6: Asian Box (Airport Terminal G) | B6: Pending Active | C6: 7805 Airport Blvd Terminal G G.3 019 D | D6: San Francisco | E6: CA | F6: 94128 | G6: LG | H6: install 5/10? | I6: 44505.493 | J6: Transact SpotOn | M6: 6185af3524b4c46b8afc10ee | N6: https://hub.spoton.com/merchants/6185af3524b4c46b8afc10ee | T6: 545500001484658
A7: Autumn Room | B7: In-Process | C7: 2367 El Camino Real | D7: Santa Clara | E7: CA | F7: 95050 | I7: 44567.373 | J7: =- david zepnick cloud pos solutions -> #VALUE! | M7: 61d7596524b4c47dfb60cfdd | N7: https://hub.spoton.com/merchants/61d7596524b4c47dfb60cfdd | T7: 545500001516178
A8: Babette | B8: Pending Active | C8: 2033 San Pablo Ave | D8: Berkeley | E8: CA | F8: 94702 | G8: TP | H8: install 5/9? | I8: 44603.662 | J8: Walker Stephen | M8: 620ad2ee9adef37ad70ae3fe | N8: https://hub.spoton.com/merchants/620ad2ee9adef37ad70ae3fe | T8: 545500001537216
A9: Bergerac | B9: In-Process | C9: 316 11th St | D9: San Francisco | E9: CA | F9: 94103 | I9: 44651.344 | J9: O'Brien Dave | M9: 6245c81c9adef3c048b94bc6 | N9: https://hub.spoton.com/merchants/6245c81c9adef3c048b94bc6 | T9: 545500001564392
A10: Birrieria Jalisco | B10: Pending Active | C10: 1546 S El Dorado St | D10: Stockton | E10: CA | F10: 95206 | I10: 44662.572 | J10: =- jason geraci datasciencx -> #VALUE! | M10: 6254c4e99adef3075189bb89 | N10: https://hub.spoton.com/merchants/6254c4e99adef3075189bb89 | T10: 545500001571926
A11: Bonita Taqueria + Rotisserie - Polk | B11: Pending Active | C11: 2227 Polk St | D11: San Francisco | E11: CA | F11: 94109 | G11: JC | H11: installed? | I11: 44574.541 | J11: Massis Nimer | M11: 61e0bbae24b4c4347fb800d1 | N11: https://hub.spoton.com/merchants/61e0bbae24b4c4347fb800d1 | T11: 545500001519768
A12: Burmatown | B12: Pre-Cancellation | C12: 18 Tamalpais Dr | D12: Corte Madera | E12: CA | F12: 94925 | I12: 44322.406 | J12: Carter Suzie | M12: 609485dc24b4c47d64715fa2 | N12: https://hub.spoton.com/merchants/609485dc24b4c47d64715fa2 | T12: 545500001373745
A13: Cafe Rosso | B13: Pending Active | C13: 1600 Holloway Ave | D13: San Francisco | E13: CA | F13: 94132 | I13: 44396.435 | J13: Massis Nimer | M13: 60f5ba7224b4c42ae0ff9e10 | N13: https://hub.spoton.com/merchants/60f5ba7224b4c42ae0ff9e10 | T13: 545500001415926
A14: Cantina Los Mayas | B14: In-Process | C14: 431 Balboa St | D14: San Francisco | E14: CA | F14: 94118 | I14: 44684.425 | J14: Lakritz Noah | M14: 62729cd09adef381b945c463 | N14: https://hub.spoton.com/merchants/62729cd09adef381b945c463 | T14: 545500001586247
A15: Curry Leaves Bistro | B15: In-Process | C15: 6003 W Las Positas Blvd | D15: Pleasanton | E15: CA | F15: 94588 | I15: 44662.454 | J15: Lajoie Sarah | M15: 6254a2c424b4c40daaa6c748 | N15: https://hub.spoton.com/merchants/6254a2c424b4c40daaa6c748 | T15: 545500001571686
A16: Danville Brewing Co | B16: In-Process | C16: 200 Railroad Ave | D16: Danville | E16: CA | F16: 94526 | I16: 44679.551 | J16: O'Brien Dave | M16: 626b2ba89adef3d39b241710 | N16: https://hub.spoton.com/merchants/626b2ba89adef3d39b241710 | T16: 545500001582667
A17: Don Rubens Restaurant | B17: Pre-Cancellation | C17: 5109 Hwy 140 | D17: Mariposa | E17: CA | F17: 95338 | I17: 44386.607 | J17: Walburn David | M17: 60e8d01924b4c45d64f19cbd | N17: https://hub.spoton.com/merchants/60e8d01924b4c45d64f19cbd | T17: 545500001411362
A18: Donato & Company | B18: Pending Active | C18: 2635 Ashby Ave | D18: Berkeley | E18: CA | F18: 94705 | I18: 44484.721 | J18: Walker Stephen | M18: 616de0649adef3c99e79c940 | N18: https://hub.spoton.com/merchants/616de0649adef3c99e79c940 | T18: 545500001471325
A19: El Amigo Restaurant | B19: Pre-Cancellation | C19: 13700 Doolittle Dr | D19: San Leandro | E19: CA | F19: 94577 | I19: 44404.525 | J19: Villanueva Daniel | M19: 6100901b9adef3a3e412fb14 | N19: https://hub.spoton.com/merchants/6100901b9adef3a3e412fb14 | T19: 545500001421338
A20: El Brinquito Restaurant | B20: Pre-Cancellation | C20: 810 Piner Rd Ste A | D20: Santa Rosa | E20: CA | F20: 95403 | I20: 44543.649 | J20: Gallegos David | M20: 61ba891324b4c4485e9b1388 | N20: https://hub.spoton.com/merchants/61ba891324b4c4485e9b1388 | T20: 545500001505502
A21: El Kora Restaurant | B21: Pre-Cancellation | C21: 153 Griffin St | D21: Salinas | E21: CA | F21: 93901 | I21: 44544.541 | J21: Dunn Daniel | M21: 61ba2e589adef3d6ca38efc7 | N21: https://hub.spoton.com/merchants/61ba2e589adef3d6ca38efc7 | T21: 545500001505023
A22: El Portal Cocina Mariscos | B22: In-Process | C22: 2108 Story Rd | D22: San Jose | E22: CA | F22: 95122 | I22: 44657.478 | J22: Patterson Aaron | M22: 624ddc1924b4c4267e87b6d2 | N22: https://hub.spoton.com/merchants/624ddc1924b4c4267e87b6d2 | T22: 545500001568716
A23: El Rancho Grande Taqueria | B23: In-Process | C23: 855 Divisadero St | D23: San Francisco | E23: CA | F23: 94117 | I23: 44627.688 | J23: Lakritz Noah | M23: 6227c39224b4c4070ef09014 | N23: https://hub.spoton.com/merchants/6227c39224b4c4070ef09014 | T23: 545500001549955
... A27: Fogo de Minas Steakhouse | B27: In-Process | C27: 2606 Gateway Oaks Dr | D27: Sacramento | E27: CA | F27: 95833 | I27: 44602.621 | J27: Campo Cunha Andre Rennes | M27: 6206994524b4c4168d934840 | N27: https://hub.spoton.com/merchants/6206994524b4c4168d934840 | T27: 545500001535798
A28: Gusto Pinsa Romana | B28: Pending Active | C28: 1000 Bush St | D28: San Francisco | E28: CA | F28: 94109 | I28: 44601.496 | J28: =- dulce castellanos quality solutions -> #VALUE! | M28: 6204594324b4c47f631fb6c2 | N28: https://hub.spoton.com/merchants/6204594324b4c47f631fb6c2 | T28: 545500001534874
A29: Hasu Teriyaki & Sushi | B29: In-Process | C29: 25075 Blue Ravine Rd | D29: Folsom | E29: CA | F29: 95630 | I29: 44616.467 | J29: Ludovina Danny | M29: 6217e5529adef35f92695511 | N29: https://hub.spoton.com/merchants/6217e5529adef35f92695511 | T29: 545500001543123
A30: Hazie's | B30: In-Process | C30: 501 Hayes St | D30: San Francisco | E30: CA | F30: 94102 | I30: 44662.453 | J30: Youkilis Scott | M30: 62546b329adef31eeaee7da1 | N30: https://hub.spoton.com/merchants/62546b329adef31eeaee7da1 | T30: 545500001571355
A31: Headlands Brewing Co. | B31: In-Process | C31: 3420 Mt Diablo Blvd Ste A | D31: Lafayette | E31: CA | F31: 94549 | I31: 44544.435 | J31: Pierce Mike | M31: 61ba32fa9adef3d6ca38f045 | N31: https://hub.spoton.com/merchants/61ba32fa9adef3d6ca38f045 | T31: 545500001505056
A32: House of Prime Rib | B32: In-Process | C32: 1906 Van Ness Ave | D32: San Francisco | E32: CA | F32: 94109 | H32: train 5/9 onsite | I32: 44603.419 | J32: Alden Rich | M32: 6206f25324b4c4316ec485ea | N32: https://hub.spoton.com/merchants/6206f25324b4c4316ec485ea | T32: 545500001536432
A33: Indie Superette | B33: Pre-Cancellation | C33: 3060 Fillmore St | D33: San Francisco | E33: CA | F33: 94123 | I33: 44336.553 | J33: Ouellette Chrissy | M33: 60ac2e8b9adef39ed82af636 | N33: https://hub.spoton.com/merchants/60ac2e8b9adef39ed82af636 | T33: 545500001383017
A34: Insalata's Restaurant | B34: In-Process | C34: 120 Sir Francis Drake Blvd | D34: San Anselmo | E34: CA | F34: 94960 | I34: 44658.674 | J34: Kelly Doug | M34: 6250c3df24b4c46aa6d0679f | N34: https://hub.spoton.com/merchants/6250c3df24b4c46aa6d0679f | T34: 545500001571199
A35: Jalisco's Restaurant | B35: Pre-Cancellation | C35: 618 Main St | D35: Watsonville | E35: CA | F35: 95076 | I35: 44364.697 | J35: Loza Delfina | M35: 60ccc8749adef3696bc9ab1a | N35: https://hub.spoton.com/merchants/60ccc8749adef3696bc9ab1a | T35: 545500001398189
A36: Jantz Cafe & Bakery | B36: In-Process | C36: 987 Bellevue Rd | D36: Atwater | E36: CA | F36: 95301 | I36: 44676.674 | J36: =- dale costa valley business machines -> #VALUE! | M36: 6268671324b4c415467be58b | N36: https://hub.spoton.com/merchants/6268671324b4c415467be58b | T36: 545500001580448
A37: Juice Joint Mexican Deli | B37: In-Process | C37: 332 Frank H Ogawa Plz | D37: Oakland | E37: CA | F37: 94612 | I37: 44606.694 | J37: Palacios Alvarez Jonathan | M37: 620af69124b4c472899427e1 | N37: https://hub.spoton.com/merchants/620af69124b4c472899427e1 | T37: 545500001537406
A38: Lefty's Grill | B38: Pre-Cancellation | C38: 101 Broad St | D38: Nevada City | E38: CA | F38: 95959 | I38: 44341.908 | J38: =- chris kado ck pos solutions -> #VALUE! | M38: 60ae9dbe9adef3d47d721b40 | N38: https://hub.spoton.com/merchants/60ae9dbe9adef3d47d721b40 | T38: 545500001384304
A39: Lefty's Taco House | B39: Pre-Cancellation | C39: 840 E Main St | D39: Grass Valley | E39: CA | F39: 95945 | I39: 44341.917 | J39: =- chris kado ck pos solutions -> #VALUE! | M39: 60ae9aec9adef3b2c4a2f1b5 | N39: https://hub.spoton.com/merchants/60ae9aec9adef3b2c4a2f1b5 | T39: 545500001384288
A40: Los Hermanos | B40: In-Process | C40: 2026 Chestnut St | D40: San Francisco | E40: CA | F40: 94123 | I40: 44559.548 | J40: Alden Rich | M40: 61ccea9e24b4c46d8acbc9c2 | N40: https://hub.spoton.com/merchants/61ccea9e24b4c46d8acbc9c2 | T40: 545500001512490
A41: Mamma Mia's | B41: In-Process | C41: 275 E Dunne Ave | D41: Morgan Hill | E41: CA | F41: 95037 | I41: 44645.6 | J41: LaBonte - Retail Chris | M41: 623e34d59adef3def6fe8dce | N41: https://hub.spoton.com/merchants/623e34d59adef3def6fe8dce | T41: 545500001560937
A42: Manor Grill | B42: In-Process | C42: 526 Manor Blvd | D42: San Leandro | E42: CA | F42: 94579 | I42: 44683.403 | J42: Lefour Alexandre | M42: 62705b5224b4c46662ee37e4 | N42: https://hub.spoton.com/merchants/62705b5224b4c46662ee37e4 | T42: 545500001584853
A43: Margarita's Bar & Grill | B43: In-Process | C43: 411 Vineyard Blvd | D43: Morgan Hill | E43: CA | F43: 95037 | I43: 44607.351 | J43: Valtierra Frank | M43: 620c2d0c24b4c447b52ad959 | N43: https://hub.spoton.com/merchants/620c2d0c24b4c447b52ad959 | T43: 545500001537943
A44: Mia | B44: In-Process | C44: 439 Water St | D44: Oakland | E44: CA | F44: 94607 | I44: 44595.698 | J44: Walker Stephen | M44: 61fd90b624b4c46b630090f0 | N44: https://hub.spoton.com/merchants/61fd90b624b4c46b630090f0 | T44: 545500001532365
A45: Michael's Pizza Bar & Grill | B45: In-Process | C45: 500 N Carpenter Rd | D45: Modesto | E45: CA | F45: 95351 | I45: 44680.411 | J45: =- dale costa valley business machines -> #VALUE! | M45: 626c886c24b4c4214b747da3 | N45: https://hub.spoton.com/merchants/626c886c24b4c4214b747da3 | T45: 545500001584044
A46: Mr. Pho | B46: In-Process | C46: 3360 N State Highway 59 Ste D | D46: Merced | E46: CA | F46: 95348 | I46: 44602.48 | J46: =- dale costa valley business machines -> #VALUE! | M46: 62057de124b4c43ed9e750b9 | N46: https://hub.spoton.com/merchants/62057de124b4c43ed9e750b9 | T46: 545500001535400
A47: Myth Taverna & Lounge | B47: In-Process | C47: 152 Post St | D47: San Jose | E47: CA | F47: 95113 | I47: 44655.589 | J47: Allen Kira | M47: 624c768424b4c44e530069fa | N47: https://hub.spoton.com/merchants/624c768424b4c44e530069fa | T47: 545500001567601
A48: Naan n Curry - San Bruno | B48: Pending Active | C48: 1150 El Camino Real Ste 210 | D48: San Bruno | E48: CA | F48: 94066 | I48: 44651.722 | J48: Palacios Alvarez Jonathan | M48: 62477a2a24b4c4759f3ab634 | N48: https://hub.spoton.com/merchants/62477a2a24b4c4759f3ab634 | T48: 545500001566256
A49: Neceâ€™s GF | B49: In-Process | C49: 25 Soledad Dr | D49: Monterey | E49: CA | F49: 93940 | I49: 44659.515 | J49: Dunn Daniel | M49: 6254559424b4c45b6dc88cb7 | N49: https://hub.spoton.com/merchants/6254559424b4c45b6dc88cb7 | T49: 545500001571298
A50: Pacific St Cafe | B50: Pending Active | C50: 301 Lincoln St | D50: Roseville | E50: CA | F50: 95678 | I50: 44624.339 | J50: =- chris kado ck pos (direct) -> #VALUE! | M50: 62228d0b24b4c47ce993f825 | N50: https://hub.spoton.com/merchants/62228d0b24b4c47ce993f825 | T50: 545500001548387
A51: Palm House | B51: In-Process | C51: 2032 Union St | D51: San Francisco | E51: CA | F51: 94123 | H51: site walk- dk-5/2 | I51: 44648.677 | J51: O'Brien Dave | M51: 62434e4124b4c45297a9b1c0 | N51: https://hub.spoton.com/merchants/62434e4124b4c45297a9b1c0 | T51: 545500001562479
A52: Pho La Sen | B52: In-Process | C52: 2089 E 14th St Ste A | D52: San Leandro | E52: CA | F52: 94577 | I52: 44685.469 | J52: Truong Minh | M52: 627307f424b4c40f6dd7577e | N52: https://hub.spoton.com/merchants/627307f424b4c40f6dd7577e | T52: 545500001586866
A53: Pitch and Fiddle Irish Pub - Fair Oaks | B53: In-Process | C53: 8525 Madison Ave Ste 126 | D53: Fair Oaks | E53: CA | F53: 95628 | I53: 44603.646 | J53: =- chris kado ck pos (direct) -> #VALUE! | M53: 620a8f4324b4c42b00afde36 | N53: https://hub.spoton.com/merchants/620a8f4324b4c42b00afde36 | T53: 545500001536838
A54: Polenteria | B54: In-Process | C54: 10 Victory Ln | D54: Los Gatos | E54: CA | F54: 95030 | I54: 44680.428 | J54: Allen Kira | M54: 626c6dba24b4c41b5f6c0422 | N54: https://hub.spoton.com/merchants/626c6dba24b4c41b5f6c0422 | T54: 545500001583806
A55: Rail Sports Bar and Club | B55: Pre-Cancellation | C55: 612 El Camino Real | D55: San Carlos | E55: CA | F55: 94070 | I55: 44322.537 | J55: Ellison Michael | M55: 609484eb24b4c47d64715f7a | N55: https://hub.spoton.com/merchants/609484eb24b4c47d64715f7a | T55: 545500001373729
A56: Raja Indian Cuisine | B56: In-Process | C56: 1275 W Winton Ave | D56: Hayward | E56: CA | F56: 94545 | I56: 44561.352 | J56: Kelly Doug | M56: 61d34cde9adef3b6b45b2e4f | N56: https://hub.spoton.com/merchants/61d34cde9adef3b6b45b2e4f | T56: 545500001513761
A57: Raja Sweets & Indian Cuisine | B57: Pending Active | C57: 31853 Alvarado Blvd | D57: Union City | E57: CA | F57: 94587 | I57: 44560.647 | J57: Kelly Doug | M57: 61d34ccc9adef3b6b45b2e45 | N57: https://hub.spoton.com/merchants/61d34ccc9adef3b6b45b2e45 | T57: 545500001513753
A58: Roadhouse Cuisine | B58: In-Process | C58: 4200 Redwood Hwy | D58: San Rafael | E58: CA | F58: 94903 | I58: 44651.735 | J58: Barrera Berna-Liza | M58: 6247822f24b4c4792ca0fc5f | N58: https://hub.spoton.com/merchants/6247822f24b4c4792ca0fc5f | T58: 545500001566462
A59: Rubys + Roses | B59: Pre-Cancellation | C59: 855 Main St # 100 | D59: Pleasanton | E59: CA | F59: 94566 | I59: 44497.658 | J59: Koidal Steve | M59: 617c3ef69adef34697caeda8 | N59: https://hub.spoton.com/merchants/617c3ef69adef34697caeda8 | T59: 545500001479435
A60: Secret Garden Restaurant & Lounge | B60: In-Process | C60: 2401 E Orangeburg Ave Ste 20 | D60: Modesto | E60: CA | F60: 95355 | I60: 44664.717 | J60: =- dulce castellanos quality solutions -> #VALUE! | M60: 625889a09adef38d95ed00e0 | N60: https://hub.spoton.com/merchants/625889a09adef38d95ed00e0 | T60: 545500001574060
A61: Self Made Billiards & Taqueria | B61: Pending Active | C61: 14642 Lakeshore Dr | D61: Clearlake | E61: CA | F61: 95422 | I61: 44545.445 | J61: Gallegos David | M61: 61ba891024b4c455215a6305 | N61: https://hub.spoton.com/merchants/61ba891024b4c455215a6305 | T61: 545500001505494
A62: Stacks | B62: In-Process | C62: 361 California Dr | D62: Burlingame | E62: CA | F62: 94010 | I62: 44286.662 | J62: Walker Stephen | M62: 6065fcca9adef3d6ab7a6643 | N62: https://hub.spoton.com/merchants/6065fcca9adef3d6ab7a6643 | T62: 545500001352590
A63: The Dorian | B63: In-Process | C63: 2001 Chestnut St | D63: San Francisco | E63: CA | F63: 94123 | I63: 44650.526 | J63: O'Brien Dave | M63: 6244d70024b4c4404424baac | N63: https://hub.spoton.com/merchants/6244d70024b4c4404424baac | T63: 545500001563949
A64: The Farmers Union | B64: In-Process | C64: 151 W Santa Clara St | D64: San Jose | E64: CA | F64: 95113 | I64: 44565.597 | J64: Koidal Steve | M64: 61d5d0189adef3e7d980ef33 | N64: https://hub.spoton.com/merchants/61d5d0189adef3e7d980ef33 | T64: 545500001515261
A65: The Golden Squirrel | B65: In-Process | C65: 5940 College Ave | D65: Oakland | E65: CA | F65: 94618 | I65: 44655.593 | J65: Pierce Mike | M65: 624c868024b4c4550e23bd5e | N65: https://hub.spoton.com/merchants/624c868024b4c4550e23bd5e | T65: 545500001567783
A66: The Iron Bulldog | B66: In-Process | C66: 303 Iron Point Rd | D66: Folsom | E66: CA | F66: 95630 | I66: 44680.707 | J66: Lively Bryce | M66: 627056389adef31663768810 | N66: https://hub.spoton.com/merchants/627056389adef31663768810 | T66: 545500001584796
A67: The Patio by Alexander's Steakhouse | B67: In-Process | C67: 680 Folsom St | D67: San Francisco | E67: CA | F67: 94107 | I67: 44428.677 | J67: O'Brien Dave | M67: 6123ef1424b4c46a4c9e7f77 | N67: https://hub.spoton.com/merchants/6123ef1424b4c46a4c9e7f77 | T67: 545500001437367
A68: The Sea by Alexander's Steakhouse | B68: In-Process | C68: 4269 El Camino Real | D68: Palo Alto | E68: CA | F68: 94306 | I68: 44428.66 | J68: O'Brien Dave | M68: 6123efd224b4c47617dcf4f4 | N68: https://hub.spoton.com/merchants/6123efd224b4c47617dcf4f4 | T68: 545500001437391
A69: Toast Restaurant | B69: Pre-Cancellation | C69: 5800 Nave Dr | D69: Novato | E69: CA | F69: 94949 | I69: 44532.425 | J69: O'Brien Dave | M69: 61a963e824b4c429b026dbba | N69: https://hub.spoton.com/merchants/61a963e824b4c429b026dbba | T69: 545500001498518
A70: Trade Rite Market - Bacalhau Grill | B70: In-Process | C70: 1555 Alum Rock Ave | D70: San Jose | E70: CA | F70: 95116 | I70: 44553.404 | J70: Campo Cunha Andre Rennes | M70: 61c9ec889adef34f58f9e022 | N70: https://hub.spoton.com/merchants/61c9ec889adef34f58f9e022 | T70: 545500001511120
A71: Trattoria Matrone | B71: In-Process | C71: 1058 Horizon Dr | D71: Fairfield | E71: CA | F71: 94533 | I71: 44637.491 | J71: White Brittney | M71: 62351b7524b4c40a89990d74 | N71: https://hub.spoton.com/merchants/62351b7524b4c40a89990d74 | T71: 545500001557396
A72: T's | B72: Pending Active | C72: 16828 Meekland Ave | D72: San Lorenzo | E72: CA | F72: 94580 | I72: 44651.706 | J72: Lefour Alexandre | M72: 624751909adef31032b22fb3 | N72: https://hub.spoton.com/merchants/624751909adef31032b22fb3 | T72: 545500001565985
A81: *** on hold **
A82: 101 Restaurant & Bar FT1 | B82: Pre-Cancellation | C82: 125 Terminal Ct Ste 44 | D82: South San Francisco | E82: CA | F82: 94080 | I82: 44293.639 | J82: Smith William (Bill) | M82: 606f2c3324b4c474fda26494 | N82: https://hub.spoton.com/merchants/606f2c3324b4c474fda26494 | T82: 545500001356377
A83: 101 Restaurant & Bar FT2 | B83: Pre-Cancellation | C83: 125 Terminal Ct Ste 44 | D83: South San Francisco | E83: CA | F83: 94080 | I83: 44293.645 | J83: Smith William (Bill) | M83: 606f2ce824b4c46f8a75699c | N83: https://hub.spoton.com/merchants/606f2ce824b4c46f8a75699c | T83: 545500001356393
A84: Alexander's Patisserie | B84: Pending Active | C84: 209 Castro St | D84: Mountain View | E84: CA | F84: 94041 | I84: 44428.674 | J84: O'Brien Dave | M84: 6123ef2c24b4c47617dcf4ab | N84: https://hub.spoton.com/merchants/6123ef2c24b4c47617dcf4ab | T84: 545500001437375
A85: Alexander's Steakhouse- San Fran | B85: In-Process | C85: 448 Brannan St | D85: San Francisco | E85: CA | F85: 94107 | I85: 44428.581 | J85: O'Brien Dave | M85: 6123f09a24b4c477fef97eb0 | N85: https://hub.spoton.com/merchants/6123f09a24b4c477fef97eb0 | T85: 545500001437425
A86: Westside Grill | B86: Pre-Cancellation | C86: 8080 Santa Teresa Blvd | D86: Gilroy | E86: CA | F86: 95020 | I86: 44397.681 | J86: Hernandez (Ascend Payments Systems) James | M86: 60f7671d9adef30bf5d60e0e | N86: https://hub.spoton.com/merchants/60f7671d9adef30bf5d60e0e | T86: 545500001417583
A87: Yerbani Bakery | B87: Pre-Cancellation | C87: 901 N Carpenter Rd Ste 18 | D87: Modesto | E87: CA | F87: 95351 | I87: 44530.527 | J87: =- dulce castellanos quality solutions -> #VALUE! | M87: 61a80ee69adef3a04f021879 | N87: https://hub.spoton.com/merchants/61a80ee69adef3a04f021879 | T87: 545500001497676
A88: Straw Hat Pizza | B88: Pre-Cancellation | C88: 46350 Mission Blvd | D88: Fremont | E88: CA | F88: 94539 | I88: 44306.344 | J88: Rojas Chris | M88: 607ef2ed9adef35746e5309c | N88: https://hub.spoton.com/merchants/607ef2ed9adef35746e5309c | T88: 545500001362573
A89: ONE65 Patisserie | B89: Pre-Cancellation | C89: 165 Ofarrell St | D89: San Francisco | E89: CA | F89: 94102 | I89: 44428.669 | J89: O'Brien Dave | M89: 6123f02f9adef31fdae408e0 | N89: https://hub.spoton.com/merchants/6123f02f9adef31fdae408e0 | T89: 545500001437409
A90: ONE65 San Francisco | B90: Pre-Cancellation | C90: 165 Ofarrell St | D90: San Francisco | E90: CA | F90: 94102 | I90: 44428.589 | J90: O'Brien Dave | M90: 6123f05a9adef368e55054c9 | N90: https://hub.spoton.com/merchants/6123f05a9adef368e55054c9 | T90: 545500001437417
A91: High Tech Burrito - Alamo | B91: Pending Active | C91: 120A Alamo Plaza | D91: Alamo | E91: CA | F91: 94507 | I91: 44682.72 | J91: Transact SpotOn | M91: 626f23e224b4c4782b4d94c5 | N91: https://hub.spoton.com/merchants/626f23e224b4c4782b4d94c5 | T91: 545500001584143
A92: High Tech Burrito - Danville | B92: In-Process | C92: 3452 Camino Tassajara | D92: Danville | E92: CA | F92: 94506 | I92: 44682.488 | J92: Transact SpotOn | M92: 626ed5c89adef3b3fff9d047 | N92: https://hub.spoton.com/merchants/626ed5c89adef3b3fff9d047 | T92: 545500001584127
A93: High Tech Burrito - San Anselmo | B93: Pending Active | C93: 914 A Sir Frances Drake Blvd | D93: San Anselmo | E93: CA | F93: 94960 | I93: 44682.478 | J93: Transact SpotOn | M93: 626ed2c39adef3b3fff9cffb | N93: https://hub.spoton.com/merchants/626ed2c39adef3b3fff9cffb | T93: 545500001584119
A94: High Tech Burrito - Walnut Creek | B94: In-Process | C94: 1815-B Ygnacio Valley Rd | D94: Walnut Creek | E94: CA | F94: 94596 | I94: 44682.511 | J94: Transact SpotOn | M94: 626f205b9adef389f78041f4 | N94: https://hub.spoton.com/merchants/626f205b9adef389f78041f4 | T94: 545500001584135
A95: Napario Cafe | B95: Pre-Cancellation | C95: 943 Water St | D95: Napa | E95: CA | F95: 94559 | I95: 44536.574 | J95: Walker Stephen | M95: 61b0e03624b4c43ad9138f5b | N95: https://hub.spoton.com/merchants/61b0e03624b4c43ad9138f5b | T95: 545500001500735
A96: Crab House Monterey | B96: Pre-Cancellation | C96: 60 Fishermans Wharf # 1 | D96: Monterey | E96: CA | F96: 93940 | I96: 44307.515 | J96: Dunn Daniel | M96: 6080b8889adef3ad9f66844f | N96: https://hub.spoton.com/merchants/6080b8889adef3ad9f66844f | T96: 545500001363928
A97: Hard Water | B97: In-Process | C97: 3 Pier Ste 102 | D97: San Francisco | E97: CA | F97: 94111 | I97: 44505.601 | J97: Carter Suzie | M97: 6185a2c424b4c467fe9caa82 | N97: https://hub.spoton.com/merchants/6185a2c424b4c467fe9caa82 | T97: 545500001484534

Sheet Completed Installs
A1: Date | B1: Acct | C1: City | D1: Sell Date | E1: Status
A3: 44683 | B3: Seabreeze | C3: SF | D3: 44524 | E3: Installed
A4: 44684 | B4: Blind Pig | C4: SF | D4: 44593 | E4: Installed | G4: sent email
A5: 44684 | B5: Ocreanview Diner | C5: Berkeley | D5: 44636 | E5: Installed | G5: sent email
A6: 44687 | B6: El Burro Veloz | C6: Martinez | E6: Installed | G6: sent email
A7: 44690 | B7: Babette | C7: Berekeley | E7: Installed | G7: sent email
A8: 44690 | B8: Naan & Curry | C8: Pleasanton | D8: 44651 | E8: Installed | G8: sent email
A9: 44690 | B9: Juice Joint | C9: Oakland | D9: 44606 | E9: Installed | G9: sent email
A10: 44691 | B10: Asian Box- SFO | C10: SFO | E10: Installed | G10: sent email
A11: 44691 | B11: Ocean Grill | C11: Avila Beach | E11: Installed | G11: sent email
A13: 44693 | B13: Toast | C13: Novato | D13: 44897 | G13: sent email
A14: 44697 | B14: House of Prime Rib | C14: SF
A18: 44656 | B18: Craft Roots | C18: Morgan Hill | D18: 44895 | E18: Installed | G18: sent email
A19: 44657 | B19: The Vine & Spirits | C19: Danville | D19: 44630 | E19: Installed | G19: sent email
A20: 44662 | B20: Oasis Wine Lounge | C20: Pleasanton | D20: 44821 | E20: Installed | G20: happy with current supplier
A21: 44662 | B21: Li Li's Hawaiian BBQ & Poke Bowls | C21: Fairfield | D21: 44615 | E21: Installed | G21: sent email
A22: 44662 | B22: Trade Winds | C22: Cotati | D22: 44596 | E22: Installed | G22: sent email
A23: 44663 | B23: Stamp Bar & Grill | C23: San Carlos | D23: 44622 | E23: Installed | G23: sent email
A24: 44664 | B24: Talavera Cocina Mexicana | C24: Berkeley | D24: 44916 | E24: Installed | G24: sent email
A25: 44664 | B25: Little Saint | C25: Healdsburg | D25: 44794 | E25: Installed | G25: sent email
A26: 44669 | B26: Kicks Sports & Grill | C26: Redwood City | D26: 44613 | E26: Installed | G26: sent email
A27: 44672 | B27: Bonita Taqueria - POLK | C27: San Francisco | D27: 44574 | E27: Installed
A28: 44677 | B28: Distrito Federal | C28: Campbell | D28: 44638 | E28: Installed | G28: sent email
A29: 44677 | B29: Chelinos Mexican Restaurant | C29: Santa Rosa | D29: 44607 | E29: Installed | G29: contacted cb set
F30: 12
A32: 44622 | B32: El Cuscalatan Restaurant | C32: San Francisco | D32: 44905 | E32: Installed | G32: sent email
A33: 44627 | B33: Sabella & La Torre | C33: San Francisco | D33: 44916 | E33: Installed | G33: sent email
A34: 44627 | B34: Achillies By The Sea | C34: Santa Cruz | E34: Installed | G34: sent email
A35: 44629 | B35: Miramar Beach Restaurant | C35: Half Moon Bay | D35: 44922 | E35: Installed | G35: sent email
A36: 44629 | B36: Chowders | C36: San Francisco | D36: 44925 | E36: Installed | G36: sent email
A37: 44629 | B37: Donato Enoteca | C37: Redwood City | D37: 44852 | E37: Installed | G37: sent email
A38: 44634 | B38: Pork Store Cafe Valencia | C38: San Francisco | D38: 44916 | E38: Installed | G38: sent email
A39: 44634 | B39: Franco's Latin Table | C39: San Francisco | D39: 44916 | E39: Installed | G39: sent email
A40: 44636 | B40: Sasa | C40: Walnut Creek | D40: 44859 | E40: Installed | G40: sent email
A41: 44641 | B41: Papa's Place | C41: Morgan Hill | D41: 44915 | E41: Installed | G41: sent email
A42: 44642 | B42: Luna Restaurant | C42: Concord | D42: 44889 | E42: Installed | G42: sent email
A43: 44642 | B43: Jalisco's | C43: Watsonville | D43: 44730 | E43: Installed | G43: sent email
A44: 44648 | B44: Barbara's Fish Trap | C44: Half Moon Bay | D44: 44575 | E44: Installed | G44: sent email
A45: 44649 | B45: Dos Culturas | C45: Santa Rosa | D45: 44925 | E45: Installed | G45: sent email
F47: 14
A49: 44593 | B49: Arthur Mac's Tap & Snack | C49: Oakland | D49: 44883 | E49: Installed
A50: 44593 | B50: Aurora Sausalito | C50: Sausalito | D50: 44848 | E50: Installed
A51: 44595 | B51: Buena Vista Brewing Co. | C51: Santa Cruz | D51: 44922 | E51: Installed
A52: 44596 | B52: Chuck's Takeaway | C52: San Francisco | E52: Installed
A53: 44599 | B53: Little Lucca - SSF | C53: South S.F. | D53: 44807 | E53: Installed
A54: 44601 | B54: Silver's at the Wharf Anchor Lodge | C54: Fort Bragg | D54: 44915 | E54: Installed
A55: 44603 | B55: The Cheese Parlour | C55: Livermore | D55: 44466 | E55: Installed | G55: ordered
A56: 44607 | B56: Ace Wasabi's Rock N' Roll Sushi | C56: San Francisco | D56: 44922 | E56: Installed
A57: 44608 | B57: Mi Casa Grill | C57: Richmond | D57: 44868 | E57: Installed
A58: 44608 | B58: Tacos El Gordo | C58: Hayward | D58: 44918 | E58: Installed | G58: sent email
A59: 44614 | B59: Sally Tomatoes | C59: Rohnert Park | D59: 44915 | E59: Installed | G59: sent email
A60: 44614 | B60: Fattoria E Mare | C60: Half Moon Bay | D60: 44923 | E60: Installed | G60: sent email
A61: 44615 | B61: Cru | C61: Redwood City | D61: 44852 | E61: Installed
A62: 44616 | B62: El Brinquito | C62: Santa Rosa | D62: 44910 | E62: Installed
A63: 44616 | B63: Freekeh | C63: San Francisco | D63: 44916 | E63: Installed
A64: 44620 | B64: MoMo's | C64: San Francisco | D64: 44581 | E64: Installed | G64: sent email
A65: 44620 | B65: A Matter of Taste | C65: Ripon | D65: 44804 | E65: Installed
A66: 44620 | B66: San Pedro Social | C66: San Jose | D66: 44876 | E66: Installed
A67: 44614 | B67: White Rabbit- Win Win | C67: Tahoe | D67: 44585 | E67: Installed | F67: 19
A69: 44565 | B69: Patio Filipino | C69: Hayward | D69: 44861 | E69: Installed
A70: 44567 | B70: 18th Street Commissary | C70: San Francisco | D70: 44866 | E70: Installed
A71: 44571 | B71: Guava Sweets & Eats | C71: Walnut Creek | D71: 44870 | E71: Installed
A72: 44572 | B72: Aliment | C72: San Francisco | D72: 44863 | E72: Installed
A73: 44573 | B73: Sociale | C73: San Francisco | D73: 44835 | E73: Installed
A74: 44579 | B74: Little Lucca - Burlingame | C74: San Francisco | D74: 44807 | E74: Installed
A75: 44585 | B75: Giorgio's Italian & Pizza | C75: Milpitas | D75: 44637 | E75: Installed
A76: 44588 | B76: New York Pizza | C76: Corte Madera | D76: 44687 | E76: Installed
A77: 44592 | B77: Centro Pizza | C77: Burlingame | D77: 44456 | E77: Installed
A78: 44592 | B78: Blue Gingko | C78: Lafayette | D78: 44494 | E78: Installed
A79: 44592 | B79: Slanted Door San Ramon | C79: San Ramon | D79: 44439 | E79: Installed
A80: 44592 | B80: Rabalais Bistro | C80: Santa Paula | D80: 44518 | E80: Installed | F80: 12
E83: 2021 | F83: =SUM(F117:F249) -> 131
A85: 44531 | B85: The Slice | C85: San Francisco | D85: 44469 | E85: Installed
A86: 44532 | B86: Table Culture Provisions | C86: Petaluma | D86: 44490 | E86: Installed
A87: 44536 | B87: Hacienda El Rancho Viejo | C87: Vallejo | D87: 44494 | E87: Installed
A88: 44537 | B88: China Star | C88: Santa Rosa | D88: 44442 | E88: Installed
A89: 44537 | B89: The Club at Los Gatos | C89: Los Gatos | D89: 44509 | E89: Installed
A90: 44537 | B90: Twisted Times Restaurant | C90: Walnut Creek | D90: 44484 | E90: Installed
A91: 44538 | B91: Pho Hot | C91: Rocklin | D91: 44488 | E91: Installed
A92: 44539 | B92: Cantina Los Primos Y Cerveza | C92: Woodland | D92: 44495 | E92: Installed
A93: 44543 | B93: Rescate Coffee | C93: Elk Grove | D93: 44484 | E93: Installed
A94: 44543 | B94: Java Hut-Petaluma | C94: Petaluma | D94: 44288 | E94: Installed
A95: 44546 | B95: The Cheese Parlour | C95: Livermore | D95: 44466 | E95: Installed
A96: 44546 | B96: Samurai Sushi | C96: Turlock | D96: 44476 | E96: Installed
... A101: 44560 | B101: Pho Dublin | C101: Dublin | D101: 44532 | E101: Installed
F102: 17
A105: 44502 | B105: Viking Cocktail Lounge | C105: Novato | D105: 44406 | E105: Installed | G105: sent email
A106: 44507 | B106: Trailblazer Craft Pizza & Brews | C106: Grass Valley | D106: 44438 | E106: Installed | G106: sent email
A107: 44508 | B107: Yu Shang Mandarin | C107: San Rafael | D107: 44385 | E107: Installed | G107: sent email
A108: 44510 | B108: Baltic Spice House | C108: Richmond | D108: 44469 | E108: Installed | G108: sent email
A109: 44510 | B109: Salt and Pepper | C109: Tiburon | D109: 44466 | E109: Installed | G109: sent email
A110: 44517 | B110: Lepe's Taqueria | C110: Santa Rosa | D110: 44461 | E110: Installed | G110: sent email
A111: 44517 | B111: Perbacco | C111: San Fran | D111: 44375 | E111: Installed
A112: 44517 | B112: Java Hut-Fairfax | C112: Fairfax | D112: 44288 | E112: Installed
A113: 44519 | B113: SFSU Station Cafe | C113: San Francisco | D113: 44412 | E113: Installed
A114: 44522 | B114: Saucy Asian | C114: San Francisco | D114: 44341 | E114: Installed
A115: 44522 | B115: Slides Restaurant | C115: Manteca | D115: 44469 | E115: Installed
A116: 44523 | B116: Market & Main | C116: Martinez | D116: 44397 | E116: Installed
A117: 44529 | B117: Barbacco | C117: San Fran | D117: 44376 | E117: Installed
A118: 44529 | B118: Las Guitarras | C118: Novato | D118: 44545 | E118: Installed | G118: ordered
...

Sheet PPCL_2022
A1: 2 Star Market | B1: CASIO | C1: LG | D1: Qt-6600 | E1: NO | H1: NO | N1: 43927 | O1: Ali | P1: 510-531-3576 | R1: 0.1025 | T1: ALA | U1: 2020 MacArthur Blvd | V1: Oakland | W1: Ca | X1: 94602 | AV1: 2020 MacArthur Blvd | AX1: Oakland | AY1: Ca | AZ1: 94602 | BA1: 510-531-3576
A2: 3 Star Food & Liquor | B2: CASIO | C2: LG | D2: Casio TE7000 | E2: NO | H2: NO | N2: 43026 | O2: Mandeep | P2: 510-340-1366 | R2: 0.0975 | S2: 0.085 | T2: Concord | U2: 1140 Meadow Lane | V2: Concord | W2: Ca | X2: 94520 | AB2: Dependu | AV2: 1140 Meadow Lane | AX2: Concord | AY2: Ca | AZ2: 94520 | BA2: 510-340-1366 | BE2: 1 | BF2: TE7000 | BH2: DL3616
A3: 65th Street Market | B3: ECR | C3: AH | D3: Sam4s ER260 | E3: NO | H3: NO | N3: 44249 | O3: Murshed Adbul | P3: 510-655-6838 | R3: 0.105 | T3: Emery | U3: 6444 San Pablo Ave | V3: Emeryville | W3: Ca | X3: 94608 | AM3: 15157 | AV3: 6444 San Pablo Ave | AX3: Emeryville | AY3: Ca | AZ3: 94608 | BA3: 510-655-6838
A4: A Sweet Affair - California | B4: NCC | C4: DD | D4: Spt4500 | E4: NO | H4: NO | N4: 43859 | O4: Terry Babcock | P4: 925-943-2253 | Q4: 925-785-5931 | R4: 0.0875 | S4: 0.085 | T4: CC | U4: 1991 N California Blvd | V4: Walnut Creek | W4: Ca | X4: 94598 | Y4: asweetaffairbakery@usa.com | Z4: idreamofaruba@gmail.com | AA4: idreamofaruba@gmail.com | AB4: Sarah Torres -> | AC4: 925-395-1695 | AD4: EMAIL IDREAM | AV4: 1991 N California Blvd | AX4: Walnut Creek | AY4: Ca | AZ4: 94598 | BA4: 925-785-5931 | BE4: 2
A5: A Sweet Affair - Ygnacio | B5: SPOT ON | C5: RA | E5: 7 X 24 | F5: SPOT ON | L5: WORLDPAY | N5: 44372 | O5: Terry Babcock | P5: 925-944-1910 | R5: 0.0875 | S5: 0.085 | T5: CC | U5: 1815 Ygnacio Valley Road Ste F | V5: Walnut Creek | W5: Ca | X5: 94598 | Y5: bakerhot1@aol.com | Z5: idreamofaruba@gmail.com | AA5: idreamofaruba@gmail.com | AB5: Terry-owner | AC5: 925-785-5931 | AJ5: 925-947-6000 | AV5: 1815 Ygnacio Valley Road Ste F | AX5: Walnut Creek | AY5: Ca | AZ5: 94598 | BA5: 925-944-1910 | BE5: 5
A6: Agave - Healdsburg | B6: SUPPLY ONLY | C6: AH | E6: NO | H6: NO | N6: 44403 | O6: Octavio Diaz | P6: 707-433-2411 | R6: 0.09 | T6: SON | U6: 1063 Vine St | V6: Healdsburg | W6: Ca | X6: 95448 | Y6: daisy@merlobiz.com | Z6: mail@merlobiz.com | AA6: tishia@merlobiz.com | AV6: 1063 Vine St | AX6: Healdsburg | AY6: Ca | AZ6: 95448 | BA6: 707-433-2411
A7: Aguachiles El Tamarindo | B7: NCC | C7: LG | E7: NO | H7: NO | N7: 44606 | O7: Edgar | P7: 510-500-7552 | Q7: 510-393-2242 cell | R7: 0.1025 | T7: ALA | U7: 3053 International Blvd | V7: Oakland | W7: Ca | X7: 94601 | Z7: eg333366@gmail.com | AV7: 3053 International Blvd | AX7: Oakland | AY7: Ca | AZ7: 94601 | BA7: 510-500-7552
A8: Aji Limo Peruvian | B8: SUPPLY ONLY | C8: ME | E8: NO | H8: NO | O8: Max Lee | P8: 650-591-4156 | R8: 0.09875 | T8: Belmont | U8: 1000 Sixth Ave | V8: Belmont | W8: Ca | X8: 94002 | Y8: max+6@wbnorcal.com | Z8: max+6@wbnorcal.com | AA8: max+6@wbnorcal.com | AV8: 1000 Sixth Ave | AX8: Belmont | AY8: Ca | AZ8: 94002 | BA8: 650-591-4156
A9: Alberto's Mexican Food - San Bern | B9: MAITRE'D | C9: JS | D9: PT SP800 | E9: NO | H9: NO | L9: WORLDPAY | N9: 44300 | O9: Hector Navarro | P9: 909-882-5667 | Q9: 909-379-2720 | R9: 0.0875 | S9: 0.0825 | T9: San Bern | U9: 1008 West Highland | V9: San Bernadino | W9: Ca | X9: 92405 | Y9: jesdanger@aol.com | Z9: hmarnav@aol.com | AA9: jesdanger@aol.com | AV9: 1008 West Highland | AX9: San Bernadino | AY9: Ca | AZ9: 92405 | BA9: 909-822-5667 | BC9: 1413933 | BE9: 3 | BF9: SP800
A10: Alejandro's Taqueria - Sacramento | B10: ECR | C10: AH | D10: Sam ER940 flat | E10: NO | H10: NO | N10: 43581 | O10: Luis | P10: 916-459-0924 | R10: 0.0875 | T10: SacCity | U10: 911 K Street | V10: Sacramento | W10: Ca | X10: 95814 | Y10: lbarr@sbcglobal.net | AA10: lbarr@sbcglobal.net | AM10: 15157 | AV10: 911 K Street | AX10: Sacramento | AY10: Ca | AZ10: 95814 | BA10: 916-459-0924 | BE10: 2 | BF10: 1450/Sam4s ER940
A11: Alexanders Steakhouse | B11: SPOT ON | C11: MB | E11: 7 X 24 | F11: SPOT ON | O11: Manager | P11: 408-446-2222 | R11: 0.09125 | S11: 0.0875 | T11: SC | U11: 10330 N. Wolfe Road | V11: Cupertino | W11: Ca | X11: 95014 | Y11: CHEFSTOUT@ALEXANDERSSTEAKHOUSE.COM | Z11: accounting@alexandersteakhouse.com | AB11: Jeff Stout | AC11: 510-589-7077 | AD11: erin | AF11: Tim | AJ11: 408-446-2242 | AV11: =PROPER(AW11) -> 10330 N. Wolfe Road | AW11: 10330 N. WOLFE ROAD | AX11: Cupertino | AY11: Ca | AZ11: 95014 | BA11: 408-446-2222 | BE11: 7
A12: All Star Donut | B12: ECR | C12: AH | D12: SAM 260 | E12: NO | H12: NO | N12: 44858 | O12: Sem | P12: 510-525-7289 | R12: 0.1025 | S12: 0.095 | T12: El Cerr | U12: 3070 El Cerrito Plaza | V12: El Cerrito | W12: Ca | X12: 94530 | AV12: 3070 El Cerrito Plaza | AX12: El Cerrito | AY12: Ca | AZ12: 94530 | BA12: 510-525-7289
A13: Alotta's Deli & Catering | B13: NCC | C13: RA | E13: NO | H13: NO | N13: 44322 | O13: Mike Mansch | P13: 650-967-0299 | Q13: 408-807-0575 | R13: 0.0925 | T13: LosAltos | U13: 2249 Grant Road | V13: Los Altos | W13: Ca | X13: 94024 | Y13: alottasdeli@aol.com | Z13: alottasdeli@aol.com | AA13: alottasdeli@aol.com | AV13: 2249 Grant Road | AX13: Los Altos | AY13: Ca | AZ13: 94024 | BA13: 650-967-0299
A14: Amal's Deli | B14: NCC | C14: RA | E14: NO | H14: NO | N14: 44776 | O14: Rana | P14: 415-227-3797 | R14: 0.08625 | T14: SF | U14: 1416 Haight St | V14: San Francisco | W14: Ca | X14: 94117 | AV14: 1416 Haight St | AX14: San Francisco | AY14: Ca | AZ14: 94117 | BA14: 415-227-3797
A15: Antigua Cocina | B15: ECR | C15: AH | D15: SAM4S ER260 | E15: NO | H15: NO | N15: 44400 | O15: Marvin | P15: 415-879-6670 | R15: 0.085 | T15: Novato | U15: 1559 S. Novato Blvd, Suite J | V15: Novato | W15: Ca | X15: 94945 | AV15: 1559 S. Novato Blvd | AX15: Novato | AY15: Ca | AZ15: 94945 | BA15: 415-879-6670
A16: Antiguas Café | B16: ECR | C16: SG | D16: Sharp ER-407 | E16: NO | H16: NO | N16: 44147 | O16: Pablo | P16: 415-532-5012 | Q16: 415-240-1137 cell Pablo | R16: 0.0925 | T16: S.Raf | U16: 703 3rd Street | V16: San Rafael | W16: Ca | X16: 94901 | AV16: 703 3rd Street | AX16: San Rafael | AY16: Ca | AZ16: 94901 | BA16: 415-532-5012 | BE16: 1 | BF16: ER-A247
A17: Appian Food & Liquor | B17: CASIO | C17: LG | D17: QT6600 | E17: NO | H17: NO | N17: 44013 | O17: Chris/Ali | P17: 510-758-7543 | R17: 0.0875 | S17: 0.085 | T17: CC | U17: 4247 Appian Way | V17: El Sobrante | W17: Ca | X17: 94803 | AV17: 4247 Appian Way | AX17: El Sobrante | AY17: Ca | AZ17: 94803 | BA17: 510-758-7543 | BE17: 2
A18: Arby's - San Jose | B18: NCC | C18: DK | E18: NO | H18: NO | N18: 44071 | O18: Anoop Kang | P18: 408-249-4259 | Q18: 510-557-9123 | R18: 0.09375 | S18: 0.09 | T18: SanJose | U18: 3158 Stevens Creek Blvd | V18: San Jose | W18: Ca | X18: 95117 | Y18: anoopkang@yahoo.com | Z18: anoopkang@yahoo.com | AA18: anoopkang@yahoo.com | AV18: 3158 Stevens Creek Blvd | AX18: San Jose | AY18: Ca | AZ18: 95117 | BA18: 408-750-4433
A19: Arteaga's Food Center - Lodi | B19: SUPPLY ONLY | C19: AH | E19: NO | H19: NO | N19: 43551 | O19: Alonzo Lopez | P19: 209-339-0399 | Q19: 510-376-9832 | R19: 0.0825 | S19: 0.08 | T19: Lodi | U19: 200 E Oak Street | V19: Lodi | W19: Ca | X19: 95240 | Y19: alonzo@arteagas.com | AB19: Claudia | AC19: 707-318-6841 | AJ19: 408-885-0808 | AV19: 200 E Oak Street | AX19: Lodi | AY19: Ca | AZ19: 95240 | BA19: 209-339-0399
A20: Arya Steakhouse- Palo Alto | B20: SPOT ON | C20: NS | E20: 7 X 24 | F20: SPOT ON | N20: 44782 | O20: Fera | P20: 650-304-3119 | R20: 0.09125 | T20: SC | U20: 140 University Ave | V20: Palo Alto | W20: Ca | X20: 94301 | AM20: 54-230 | AV20: 140 University Ave | AX20: Palo Alto | AY20: Ca | AZ20: 94301 | BA20: 650-304-3119
A21: Back Of the House INC | B21: ALOHA | C21: RF | E21: NO | H21: NO | N21: 43775 | O21: Rodrigo | P21: 415-881-7020 | Q21: 415-271-3947 | R21: 0.08625 | S21: 0.0875 | T21: SF | U21: 1829 Union St | V21: San Francisco | W21: Ca | X21: 94123 | Y21: rodrigo@backofthehouseinc.com | Z21: mmalanog@backofthehouseinc.com | AA21: jtong@backofthehouseinc.com | AV21: 1829 Union St | AX21: San Francisco | AY21: Ca | AZ21: 94123 | BA21: 415-881-7020
A22: Bagel Street Café - Alameda | B22: CASIO | C22: LG | D22: QT6600 | E22: NO | H22: NO | N22: 43521 | O22: Hichan | P22: 510-219-5134 | R22: 0.1075 | S22: 0.095 | T22: Alameda | U22: 2212-F SouthShore Crt | V22: Alameda | W22: Ca | X22: 94501 | AV22: 2212-F SouthShore Crt | AX22: Alameda | AY22: Ca | AZ22: 94501 | BA22: 510-522-2838 | BE22: 2
A23: Barbacco Entrattoria | B23: SPOT ON | C23: DOB | E23: 7 X 24 | F23: SPOT ON | O23: Umberto Gibin | P23: 415-955-1919 | R23: 0.08625 | T23: SF | U23: 220 California St | V23: San Francisco | W23: Ca | X23: 94111 | Y23: umberto+1@perbaccosf.com | Z23: umberto+1@perbaccosf.com | AA23: umberto+1@perbaccosf.com | AV23: 220 California St | AX23: San Francisco | AY23: Ca | AZ23: 94111 | BA23: 415-955-1919
A24: Barzotto | B24: TOAST | C24: DD | E24: NO | H24: NO | N24: 44042 | O24: Marco | P24: 415-285-1200 | R24: 0.08625 | T24: SF | U24: 1270 Valencia St | V24: San Francisco | W24: Ca | X24: 94110 | Y24: marko@barzotto.com | AV24: 1270 Valencia St | AX24: San Francisco | AY24: Ca | AZ24: 94110 | BA24: 415-285-1200
A25: Bay Area Market & Liquor | B25: CASIO | C25: LG | D25: Casio TE7000 | E25: NO | H25: NO | N25: 44389 | O25: Yassir | P25: 510-658-4539 | R25: 0.1025 | S25: 0.095 | T25: ALA | U25: 3148 San Pablo Avenue | V25: Oakland | W25: Ca | X25: 94608 | AM25: 15157 | AV25: 3148 San Pablo Avenue | AX25: Oakland | AY25: Ca | AZ25: 94608 | BA25: 510-658-4539
A26: Bay Watch - Burlingame | B26: SUPPLY ONLY | C26: AH | E26: NO | H26: NO | N26: 43600 | O26: Daniel | P26: 650-347-6924 | R26: 0.09625 | S26: 0.09 | T26: Burl | U26: 1841 El Camino Real | V26: Burlingame | W26: Ca | X26: 94010 | Z26: baywatchb@gmail.com | AB26: Peter (Daniels dad) | AC26: 650-542-1445 | AV26: 1841 El Camino Real | AW26: burl | AX26: Burlingame | AY26: Ca | AZ26: 94010 | BA26: 650-692-2236 | BE26: 3
A27: Bay Watch - San Mateo | B27: SUPPLY ONLY | C27: AH | E27: NO | H27: NO | N27: 44242 | O27: Daniel(new owner) | P27: 650-342-2356 | R27: 0.09625 | S27: 0.0925 | T27: San Mat | U27: 201 2nd Avenue | V27: San Mateo | W27: Ca | X27: 94401 | Z27: baywatchb@gmail.com | AV27: 201 2nd Avenue | AX27: San Mateo | AY27: Ca | AZ27: 94401 | BA27: 650-342-2356 | BE27: 3
A28: Benton Market | B28: ECR | C28: AH | E28: NO | H28: NO | N28: 43636 | O28: Jay | P28: 707-526-5550 | R28: 0.0925 | T28: S.Rosa | U28: 801 Benton St | V28: Santa Rosa | W28: Ca | X28: 95404 | AV28: 801 Benton St | AX28: Santa Rosa | AY28: Ca | AZ28: 95404 | BA28: 707-526-5550
A29: Best Beverage - Bank of NH Pavillion | B29: NCC | C29: DF | E29: NO | H29: NO | N29: 43595 | O29: Mary | P29: 603-293-4700 | R29: 0 | T29: O/S | U29: 72 Meadowbrook Lane | V29: Gilford | W29: NH | X29: 3249 | AU29: Best Beverage- CORP | AV29: 485 Valley Drive, Suite A | AX29: Brisbane | AY29: Ca | AZ29: 94005 | BA29: 415-642-2410
A30: Best Beverage - Corp | B30: SUPPLY ONLY | C30: DF | E30: NO | H30: NO | N30: 43342 | O30: Jesse Gleuck | P30: 415-642-2410 | R30: 0.09375 | S30: 0.09 | T30: SM | U30: 485 Valley Drive, Suite A | V30: Brisbane | W30: Ca | X30: 94005 | Y30: jesse@bestbeverage.com | AB30: Jeff Darvell | AJ30: 415-642-2430 | AV30: 485 Valley Drive, Suite A | AX30: Brisbane | AY30: Ca | AZ30: 94005 | BA30: 415-642-2410 | BE30: 2
A31: Best Beverage - On the Rox | B31: SUPPLY ONLY | C31: DF | E31: NO | H31: NO | N31: 43279 | O31: Noah | P31: 310-278-9457 | Q31: 443-854-4373 | R31: 0.1025 | S31: 0.09 | T31: W.Holly | U31: 9009 West Sunset Blvd | V31: West Hollywood | W31: Ca | X31: 90069 | Y31: jesse@bestbeverage.com | AJ31: 415-642-2430 | AV31: 485 Valley Drive, Suite A | AX31: Brisbane | AY31: Ca | AZ31: 94005 | BA31: 415-642-2410 | BE31: 2 | BF31: SPT4740 | BG31: SNBC 880 | BH31: CRS 60 | BI31: 220b | BJ31: NONE | BK31: NONE | BL31: MBR1200 | BM31: GS305 | BN31: TRAN | BQ31: NONE | BR31: N/A | BS31: Quest 7" | BT31: EMV 805
A32: Bill's Market | B32: CASIO | C32: LG | D32: QT 6600 | E32: NO | H32: NO | N32: 44155 | O32: Sam | P32: 408-259-7271 | Q32: 408-644-9066 | R32: 0.09375 | S32: 0.09 | T32: SanJose | U32: 204 Oakland Ave | V32: San Jose | W32: Ca | X32: 95416 | AV32: 204 Oakland Ave | AX32: San Jose | AY32: Ca | AZ32: 95416 | BA32: 408-259-7271
A33: Black & White Market | B33: ECR | C33: LG | D33: Casio Te-2200 | E33: NO | H33: NO | N33: 44398 | O33: Judy/Hung | P33: 510-261-2681 | R33: 0.1025 | T33: ALA | U33: 2681 Fruitvale Blvd | V33: Oakland | W33: Ca | X33: 94601 | AV33: 2681 Fruitvale Blvd | AX33: Oakland | AY33: Ca | AZ33: 94601 | BA33: 510-261-2681
A34: Bonita Taqueria - 16th St | B34: SPOT ON | C34: NM | E34: 7 X 24 | F34: SPOT ON | O34: Issa Sweidan | P34: 415-552-2125 | Q34: 415-487-0551 | R34: 0.08625 | T34: SF | U34: 3600 16th St | V34: San Francisco | W34: Ca | X34: 94114 | Y34: jj@squatandgobble.com | Z34: jj@squatandgobble.com | AA34: jj@squatandgobble.com | AV34: 3600 16th St | AX34: San Francisco | AY34: Ca | AZ34: 94114 | BA34: 415-552-2125
A35: Bonita Taqueria - Chestnut | B35: SPOT ON | C35: NM | E35: 7 X 24 | F35: SPOT ON | O35: Jawad Sweidan | P35: 415-801-5599 | Q35: 415-702-6272 | R35: 0.0863 | T35: SF | U35: 2257 Chestnut St | V35: San Francisco | W35: Ca | X35: 94123 | Y35: jj+1@squatandgobble.com | Z35: jj+1@squatandgobble.com | AA35: jj+1@squatandgobble.com | AV35: 2257 Chestnut St | AX35: San Francisco | AY35: Ca | AZ35: 91423 | BA35: 415-801-5599
A36: Bottleneck Liquor | B36: ECR | C36: LG | D36: CASIO TE7000 | E36: NO | H36: NO | N36: 44223 | O36: Angrej | P36: 510-562-3612 | R36: 0.1025 | T36: ALA | U36: 3151 98th Ave | V36: Oakland | W36: Ca | X36: 94605 | AV36: 3151 98th Ave | AX36: Oakland | AY36: Ca | AZ36: 94605 | BA36: 510-562-3612
A37: Buon Aroma Deli & Liquors | B37: CASIO | C37: LG | E37: NO | H37: NO | N37: 43699 | O37: Owner | P37: 925-228-3857 | R37: 0.0975 | T37: Martinez | U37: 3314 Alhambra Ave | V37: Martinez | W37: Ca | X37: 94553 | AV37: 3314 Alhambra Ave | AX37: Martinez | AY37: Ca | AZ37: 94553 | BA37: 925-228-3857
A38: Buongiorno Gourmet Express | B38: ECR | C38: AH | D38: TEC MA-600 | E38: NO | H38: NO | N38: 43557 | O38: Ratha | P38: 510-832-7339 | Q38: 510-926-5566 | R38: 0.1025 | T38: ALA | U38: 1226 Broadway Avenue | V38: Oakland | W38: Ca | X38: 94612 | AV38: 1226 Broadway Avenue | AX38: Oakland | AY38: Ca | AZ38: 94612 | BA38: 510-926-5566
A39: Burmatown | B39: SUPPLY ONLY | C39: SC | E39: NO | H39: NO | O39: Jennifer Fujitani | P39: 415-312-8998 | R39: 0.09 | T39: CorteM | U39: 18 Tamalpais Dr | V39: Corte Madera | W39: Ca | X39: 94925 | Y39: jfujitani18@gmail.com | Z39: jfujitani18@gmail.com | AA39: jfujitani18@gmail.com | AV39: 18 Tamalpais Dr | AX39: Corte Madera | AY39: Ca | AZ39: 94925 | BA39: 415-312-8998
A40: Café Coda | B40: MAITRE'D | C40: JS | E40: M-F | F40: 44921 | G40: 57.82 | H40: NO | L40: WORLDPAY | N40: 44649 | O40: Eric | P40: 530-566-9476 | Q40: 530-566-9476 | R40: 0.0725 | S40: 0.075 | T40: BUTTE | U40: 265 Humbolt Avenue | V40: Chico | W40: Ca | X40: 95928 | Y40: bill@radioparadise.com | Z40: sbirkedal@aol.com | AA40: rebecca@radioparadise.com | AB40: BILL GOLDSM 9.25%ITH | AC40: 530-872-4993 | AV40: =PROPER(AW40) -> 265 Humbolt Avenue | AW40: 265 HUMBOLT AVENUE | AX40: Chico | AY40: Ca | AZ40: 95928 | BA40: 530-566-9476 | BC40: 1405444 | BD40: 7.05.040.002 | BE40: 2
A41: Café Rosso | B41: SUPPLY ONLY | C41: NM | E41: NO | H41: NO | O41: Allam Qadah | P41: 415-405-0923 | R41: 0.08625 | T41: SF | U41: 1600 Holloway Ave | V41: San Francisco | W41: Ca | X41: 94132 | Y41: sfsucare@sbcglobal.net | Z41: sfsucare@sbcglobal.net | AA41: sfsucare@sbcglobal.net | AV41: 1600 Holloway Ave | AX41: San Francisco | AY41: Ca | AZ41: 94132 | BA41: 415-405-0923
A42: Caffe Central - Valley Fair Mall | B42: NCC | C42: DD | E42: NO | H42: NO | L42: WORLDPAY | N42: 44630 | O42: Ramin | P42: 408-248-4451 | Q42: 415-271-3988 | R42: 0.09125 | S42: 0.0875 | T42: SC | U42: 2855 Stevens Creek Blvd, Space 2454 | V42: Santa Clara | W42: Ca | X42: 95050 | AV42: 2855 Stevens Creek Blvd, Space 2454 | AX42: Santa Clara | AY42: Ca | AZ42: 95050 | BA42: 415-271-3988 | BE42: 2
A43: Caffe Central - Westfield Mall | B43: NCC | C43: DD | E43: NO | H43: NO | L43: WORLDPAY | N43: 43815 | O43: Ramin | P43: 415-348-1070 | Q43: 415-271-3988 | R43: 0.08625 | S43: 0.0875 | T43: SF | U43: 865 Market Street | V43: San Francisco | W43: Ca | X43: 94103 | Y43: bdelightcorp@gmail.com | Z43: bdelightcorp@gmail.com | AA43: bdelightcorp@gmail.com | AV43: 865 Market Street | AX43: San Francisco | AY43: Ca | AZ43: 94103 | BA43: 415-348-1070
A44: Caffe Delucchi | B44: SUPPLY ONLY | C44: RF | D44: POS Itouch | E44: NO | H44: NO | N44: 42726 | O44: Matt | P44: 415-393-4515 | Q44: 650-243-4650 | R44: 0.08625 | S44: 0.0875 | T44: SF | U44: 500 Columbus Avenue | V44: San Francisco | W44: Ca | X44: 94109 | Y44: mattrazis@minametals.com | AV44: 500 Columbus Avenue | AX44: San Francisco | AY44: Ca | AZ44: 94109 | BA44: 415-393-4515 | BI44: 220b
A45: Cal Pacific Med Center- St Lukes | B45: MICROS | C45: RF | D45: MICROS | E45: NO | H45: NO | N45: 43337 | O45: George | P45: 415-600-6000 | R45: 0.08625 | T45: SF | U45: 3555 Cesar Chavez | V45: San Francisco | W45: Ca | X45: 94110 | AV45: 3555 Cesar Chavez | AX45: San Francisco | AY45: Ca | AZ45: 94110 | BA45: 415-600-6000
A46: Cal Pacific Med Center- Van Ness | B46: MICROS | C46: LG | E46: NO | H46: NO | N46: 43564 | O46: Ken Smith | P46: 415-218-3345 | R46: 0.08625 | T46: SF | U46: 1101 Van Ness Ave | V46: San Francisco | W46: Ca | X46: 94109 | Y46: smithk25@sutterhealth.org | Z46: wornerh@sutterhealth.org | AV46: 1101 Van Ness Ave | AX46: San Francisco | AY46: Ca | AZ46: 94109 | BA46: 415-218-3345
A47: Caliente Bistro Kitchen | B47: SPOT ON | C47: JPA | E47: 7 X 24 | F47: SPOT ON | O47: Raul Antolin | P47: 415-379-6250 | R47: 0.08625 | T47: SF | U47: 4828 Geary Blvd | V47: San Francisco | W47: Ca | X47: 94118 | Y47: rolly313@yahoo.com | Z47: rolly313@yahoo.com | AA47: rolly313@yahoo.com | AV47: 4828 Geary Blvd | AX47: San Francisco | AY47: Ca | AZ47: 94118 | BA47: 415-379-6250
A48: Cedar Market | B48: NCC | C48: RA | E48: NO | H48: NO | L48: SPOT ON | N48: 44113 | O48: Rana | P48: 415-225-3797 | R48: 0.08625 | T48: SF | U48: 1416 Haight Street | V48: San Francisco | W48: Ca | X48: 94117 | AV48: 1416 Haight Street | AX48: San Francisco | AY48: Ca | AZ48: 94117 | BA48: 415-225-3797
A49: Celia's - Daly City | B49: COMTREX | C49: AH | E49: NO | H49: NO | N49: 43560 | O49: Rafael | P49: 650-755-6213 | R49: 0.09875 | S49: 0.0875 | T49: Daly City | U49: 379 Gellert Blvd | V49: Daly City | W49: Ca | X49: 94015 | Y49: rafaelrodjr@yahoo.com | AV49: 379 Gellert Blvd | AX49: Daly City | AY49: Ca | AZ49: 94015 | BA49: 650-755-6213
A50: Celia's - Hayward | B50: NCC | C50: DD | D50: TEC 3700 2.53 | E50: NO | H50: NO | N50: 43292 | O50: Rafael | P50: 650-280-8704 | R50: 0.1075 | S50: 0.095 | T50: Hayward | U50: 25010 Hesperian Blvd | V50: Hayward | W50: Ca | X50: 94545 | Y50: rafaelrodjr@yahoo.com | AB50: Lalo | AC50: 650-280-8704 | AV50: =PROPER(AW50) -> 25010 Hesperian Blvd | AW50: 25010 HESPERIAN BLVD | AX50: Hayward | AY50: Ca | AZ50: 94545 | BA50: 650-280-8704 | BE50: 3
A51: Celia's - San Bruno | B51: COMTREX | C51: AH | E51: NO | H51: NO | N51: 44637 | O51: Isela | P51: 650-877-8245 | Q51: 650-280-8705 cell | R51: 0.09875 | S51: 0.09 | T51: SanBruno | U51: 201 El Camino Real | V51: San Bruno | W51: Ca | X51: 94066 | Y51: iselararias@aol.com | Z51: iselararias@aol.com | AA51: iselararias@aol.com | AB51: Carlos | AV51: 201 El Camino Real | AX51: San Bruno | AY51: Ca | AZ51: 94066 | BA51: 650-877-8245
A52: Center Plate - Cow Palace | B52: ECR | C52: AH | D52: Sam SPS-530 | E52: NO | H52: NO | N52: 43867 | O52: Joe | P52: 415-846-6026 | R52: 0.09875 | S52: 0.09 | T52: Daly City | U52: 2600 Geneva Avenue | V52: Daly City | W52: Ca | X52: 94014 | AV52: 2600 Geneva Avenue | AX52: Daly City | AY52: Ca | AZ52: 94014 | BA52: 415-846-6026 | BE52: 34
A53: Central Market & Liquor | B53: ECR | C53: LG | E53: NO | H53: NO | N53: 44111 | O53: Robie | P53: 925-680-7191 | Q53: 925-270-8779 cell | R53: 0.0975 | T53: Concord | U53: 2699 Monument Blvd E | V53: Concord | W53: Ca | X53: 94520 | AV53: 2699 Monument Blvd E | AX53: Concord | AY53: Ca | AZ53: 94520 | BA53: 925-270-8779
A54: Cheap Cigarettes | B54: ECR | C54: AH | E54: NO | H54: NO | N54: 43672 | O54: Mohammad | P54: 408-941-9966 | R54: 0.09375 | T54: Milpitas | U54: 1201 E. Calaveras Avenue | V54: Milpitas | W54: Ca | X54: 95035 | AV54: 1201 Calaveras Avenue | AX54: Milpitas | AY54: Ca | AZ54: 95035 | BA54: 408-941-9966
A55: Cheaper Cigarette - Clearlake | B55: CASIO | C55: LG | E55: NO | H55: NO | N55: 44054 | O55: Faisal | P55: 510-358-9148 | R55: 0.0875 | S55: 0.08 | T55: ClearLk | U55: 14962 Lakeshore Drive | V55: Clearlake | W55: Ca | X55: 95422 | AV55: 14962 Lakeshore Drive | AX55: Clearlake | AY55: Ca | AZ55: 95422 | BA55: 510-358-9148
A56: Cigar and Cigarette City | B56: CASIO | C56: LG | E56: NO | H56: NO | N56: 43775 | O56: Aaron | P56: 916-984-1223 | R56: 0.0775 | S56: 0.08 | T56: Folsom | U56: 711 E. Bidwell Street | V56: Folsom | W56: Ca | X56: 95630 | AV56: 711 E. Bidwell Street | AX56: Folsom | AY56: Ca | AZ56: 95630 | BA56: 916-984-1223
A57: Cigarette Payless - Fortuna | B57: ECR | C57: AH | D57: Sam4s ER520RT | E57: NO | H57: NO | N57: 43574 | O57: Shoib | P57: 415-258-4520 | R57: 0.085 | T57: Humb | U57: 745 S. Fortuna Blvd | V57: Fortuna | W57: Ca | X57: 95540 | AV57: 745 S. Fortuna Blvd | AX57: Fortuna | AY57: Ca | AZ57: 95540 | BA57: 415-258-4520
A58: Cigarettes Cheaper - Arcata | B58: CASIO | C58: LG | E58: NO | H58: NO | N58: 44419 | O58: Mohammad | P58: 707-826-0772 | Q58: 510-284-7546 | R58: 0.085 | S58: 0.0875 | T58: Humb | U58: 600 F Street | V58: Arcata | W58: Ca | X58: 95521 | AV58: 600 F Street | AX58: Arcata | AY58: Ca | AZ58: 95521 | BA58: 510-284-7546
A59: Clyde's Liquor | B59: NCC | C59: DF | D59: SPT4700 | E59: M-F | F59: 44927 | G59: 49 | H59: NO | N59: 44230 | O59: Paul | P59: 408-225-0800 | Q59: 408-612-1556 | R59: 0.09375 | T59: SanJose | U59: 3963 Snell Avenue | V59: San Jose | W59: Ca | X59: 95136 | Y59: clydesliquors@gmail.com | AA59: clydesliquors@gmail.com | AV59: 3963 Snell Avenue | AX59: San Jose | AY59: Ca | AZ59: 95136 | BA59: 408-225-0800 | BE59: 2 | BF59: SPT4700 | BG59: Samsung 350 | BH59: MS 405 | BJ59: Orbit-Ser | BL59: Cradlepoint
A60: Connie's Pond & Garden #2 | B60: CASIO | C60: LG | D60: Casio QT6600 | E60: NO | H60: NO | N60: 43704 | O60: Frank | P60: 510-690-7710 | R60: 0.1025 | S60: 0.095 | T60: ALA | U60: 2520 Castro Valley Blvd | V60: Castro Valley | W60: Ca | X60: 94546 | AV60: =U60 -> 2520 Castro Valley Blvd | AX60: Castro Valley | AY60: Ca | AZ60: 94546 | BA60: 510-690-7710
A61: Corey Fine | B61: SUPPLY ONLY | E61: NO | H61: NO | R61: 0.0925 | T61: S.Raf | U61: 101 Glacier Point Rd | V61: San Rafael | W61: Ca | X61: 94901 | AU61: Corey Fine
A62: Cork n Bottle Liquor | B62: CASIO | C62: LG | D62: QT6600 | E62: NO | H62: NO | N62: 43963 | O62: Rocky | P62: 925-798-1415 | R62: 0.0975 | S62: 0.0925 | T62: Concord | U62: 2970 Treat Blvd | V62: Concord | W62: Ca | X62: 94518 | AV62: 2970 Treat Blvd | AX62: Concord | AY62: Ca | AZ62: 94518 | BA62: 925-798-1415
A63: Country Corner Liquors | B63: ECR | C63: AH | D63: SAM4S SPS520 | E63: NO | H63: NO | N63: 44242 | O63: Monica | P63: 707-639-6929 | R63: 0.08375 | T63: SOL | U63: 1332 W Texas St | V63: Fairfield | W63: Ca | X63: 94533 | AV63: 1332 W Texas St | AX63: Fairfield | AY63: Ca | AZ63: 94533 | BA63: 707-639-6929
A64: Crossroads Specialty Foods | B64: ECR | C64: AH | D64: QT6600 | E64: NO | H64: NO | N64: 42907 | O64: Hani | P64: 650-858-6910 | R64: 0.09125 | T64: SC | U64: 720 San Antonio Road | V64: Palo Alto | W64: Ca | X64: 94303 | AV64: 720 San Antonio Road | AX64: Palo Alto | AY64: Ca | AZ64: 94303 | BA64: 650-858-6910
A65: Daly City Locksmith | B65: ECR | C65: AH | D65: Tec Ma600 | E65: NO | H65: NO | N65: 43658 | O65: Evette | P65: 650-992-2451 | R65: 0.09875 | S65: 0.085 | T65: Daly City | U65: 150 San Pedro Road | V65: Daly City | W65: Ca | X65: 94014 | AJ65: 650-992-2460 | AV65: 6692 Mission Street | AX65: Daly City | AY65: Ca | AZ65: 94014 | BA65: 650-952-2451 | BE65: 1
A66: Davis Plaza Market | B66: ECR | C66: AH | E66: NO | H66: NO | N66: 44245 | O66: Albert | P66: 510-638-9891 | R66: 0.1075 | T66: S.Lean | U66: 1288 Davis St | V66: San Leandro | W66: Ca | X66: 94577 | AV66: 1288 Davis St | AX66: San Leandro | AY66: Ca | AZ66: 94577 | BA66: 510-638-9891
A67: Discount Alley | B67: ECR | C67: AH | D67: SAM4S 5215 | E67: NO | H67: NO | N67: 44432 | O67: Nicole | P67: 510-335-6145 | R67: 0.0925 | T67: SON | U67: 1382 Gravenstein Hwy S | V67: Sebastopol | W67: Ca | X67: 95472 | AV67: 1382 Gravenstein Hwy S | AX67: Sebastopol | AY67: Ca | AZ67: 95472 | BA67: 510-335-6145
A68: Discount Fabrics - Berkeley | B68: CASIO | C68: LG | D68: Casio TE2200 | E68: NO | H68: NO | N68: 44230 | O68: Nicolas | P68: 510-548-2981 | R68: 0.1025 | T68: ALA | U68: 3006 San Pablo Avenue | V68: Berkeley | W68: Ca | X68: 94702 | AV68: 3006 San Pablo Avenue | AX68: Berkeley | AY68: Ca | AZ68: 94702 | BA68: 510-548-2981
A69: Dreams Down- Petaluma | B69: ECR | C69: AH | E69: NO | H69: NO | N69: 44369 | O69: Letsy | R69: 0.095 | T69: Petaluma | U69: 800 Lindberg Lane #120 | V69: Petaluma | W69: Ca | X69: 94952 | AV69: 800 Lindberg Lane | AX69: Petaluma | AY69: Ca | AZ69: 94952 | BA69: 415-543-1800
A70: El Agavero | B70: MICROSALE | C70: LG | E70: NO | H70: NO | N70: 44293 | O70: Fernando | P70: 510-339-3000 | R70: 0.1025 | S70: 0.095 | T70: ALA | U70: 2071 Mountain Road | V70: Oakland | W70: Ca | X70: 94611 | AV70: 2071 Mountain Road | AX70: Oakland | AY70: Ca | AZ70: 94611 | BA70: 510-339-3000
A71: El Caballo Wraps | B71: CASIO | C71: LG | D71: Casio 8500 | E71: NO | F71: ** COD ONLY *** | H71: NO | I71: ** COD ONLY *** | N71: 43659 | O71: Oscar | P71: 510-521-6527 | R71: 0.1075 | S71: 0.095 | T71: Alameda | U71: 1108 Lincoln Avenue | V71: Alameda | W71: Ca | X71: 94501 | AV71: 1108 Lincoln Avenue | AX71: Alameda | AY71: Ca | AZ71: 94501 | BA71: 510-521-6257
A72: El Capitan - San Bruno | B72: SPOT ON | C72: NM | E72: 7 X 24 | F72: SPOT ON
A73: El Grullense - El Camino Real | B73: CASIO | C73: LG | D73: QT 6600 | E73: NO | H73: NO | O73: Candy | P73: 650-474-9719 | Q73: 650-216-9206 | R73: 0.09875 | S73: 0.09 | T73: Redwood | U73: 2525 El Camino Real | V73: Redwood City | W73: Ca | X73: 94061 | AJ73: 650-216-0068 | AV73: 2525 El Camino Real | AX73: Redwood City | AY73: Ca | AZ73: 94061 | BA73: 650-474-9719
A74: El Grullense - Redwood City | B74: CASIO | C74: LG | E74: NO | H74: NO | O74: David | P74: 650-649-9326 | R74: 0.09875 | S74: 0.09 | T74: Redwood | U74: 1243 Middlefield Road | V74: Redwood City | W74: Ca | X74: 94063 | AV74: 1243 Middlefield Road | AX74: Redwood City | AY74: Ca | AZ74: 94063 | BA74: 650-649-9326
A75: El Mazatleco Marisqueria | B75: NCC | C75: RA | E75: NO | F75: *COD/PREPAY ONLY** | H75: NO | I75: *COD/PREPAY ONLY** | N75: 44705 | O75: Francisco | P75: 650-690-4830 | R75: 0.09375 | T75: SanJose | U75: 782 N. 13th Street | V75: San Jose | W75: Ca | X75: 95112 | AV75: 782 N. 13th Street | AX75: San Jose | AY75: Ca | AZ75: 95112 | BA75: 650-690-4830
A76: El Rey Mexican Bar & Grill | B76: Pioneer | C76: JS | E76: NO | H76: NO | N76: 44288 | O76: Carlos Gonzalez | P76: 415-892-1471 | Q76: 510-755-4723 | R76: 0.085 | T76: Novato | U76: 940 7th Street | V76: Novato | W76: Ca | X76: 94945 | AV76: 940 7th Street | AX76: Novato | AY76: Ca | AZ76: 94945 | BA76: 415-892-1471
A77: Ernie's Wine & Liquor | B77: CASIO | C77: LG | E77: NO | H77: NO | N77: 42781 | O77: Wahid | P77: 650-355-4770 | R77: 0.09375 | T77: SM | U77: 721 Hickey Blvd | V77: Pacifica | W77: Ca | X77: 94044 | AV77: 721 Hickey Blvd | AX77: Pacifica | AY77: Ca | AZ77: 94044 | BA77: 650-355-4770
A78: Europa Express | O78: Boris | R78: 0.0863 | T78: SF | U78: 750 La Playa | V78: San Francisco | W78: Ca | AU78: Europa Express | AV78: 750 La Playa | AX78: San Francisco | AY78: Ca
A79: Fairfax Liquor | B79: CASIO | C79: LG | D79: CASIO TE7000 | E79: NO | H79: NO | N79: 43435 | O79: Andre | P79: 510-532-1487 | R79: 0.1025 | S79: 0.095 | T79: ALA | U79: 5403 Foothill Blvd | V79: Oakland | W79: Ca | X79: 94601 | AV79: 5403 Foothill Blvd | AX79: Oakland | AY79: Ca | AZ79: 94601 | BA79: 510-532-1487 | BE79: 2
A80: Farfalla Westlake Village | B80: MAITRE'D | C80: JS | E80: GOLD | F80: 45280 | G80: 850 | H80: NO | N80: 44490 | O80: John Borghetti | P80: 805-497-2283 | Q80: 805-342-7330 | R80: 0.095 | S80: 0.09 | T80: LA | U80: 160 Promenade Way, Suite A | V80: Westlake Village | W80: Ca | X80: 91362 | Y80: johnborghetti@msn.com | AB80: Paolo | AJ80: 805-497-2297 | AV80: 160 Promenade Way, Suite A | AX80: Westlake Village | AY80: Ca | AZ80: 91362 | BA80: 805-497-2283 | BC80: 1411727 | BD80: 7.04.025.007 | BE80: 4 | BL80: MBR 1200 | BQ80: Dell T20 | BR80: 7 PRO | BY80: Computer Name: MaitredServer; User: MAITRED; PW: pos9957; workgroup: APPEL; IP: 10.10.10.100
A81: Farley's East | B81: SUPPLY ONLY | C81: AH | E81: NO | H81: NO | N81: 43775 | O81: Chris Hillyard | P81: 510-835-7898 | Q81: 415-846-2671 | R81: 0.1025 | T81: ALA | U81: 33 Grand Ave | V81: Oakland | W81: Ca | X81: 94612 | Y81: chris@farleyscoffee.com | AV81: 33 Grand Ave | AX81: Oakland | AY81: Ca | AZ81: 94612 | BA81: 510-835-7898
A82: Fat Angel | B82: SUPPLY ONLY | C82: AH | E82: NO | H82: NO | N82: 43712 | O82: Jenny | P82: 415-525-3013 | R82: 0.08625 | T82: SF | U82: 1740 O' Farrell Street | V82: San Francisco | W82: Ca | X82: 94115 | AV82: 1740 O'Farrell Street | AX82: San Francisco | AY82: Ca | AZ82: 94115 | BA82: 415-525-3013
A83: Fiesta Liquor | B83: ECR | C83: LG | D83: Sam4s ER-345 | E83: NO | H83: NO | N83: 43815 | O83: Simran Gill | P83: 805-407-1305 | R83: 0.09125 | T83: SC | U83: 672 North Fair Oaks Ave | V83: Sunnyvale | W83: Ca | X83: 94085 | AV83: 672 North Fair Oaks Ave | AX83: Sunnyvale | AY83: Ca | AZ83: 94085 | BA83: 805-407-1305
A84: Finnegan's | B84: ALOHA | C84: AH | E84: NO | H84: NO | O84: Sean | P84: 415-899-1516 | R84: 0.085 | S84: 0.09 | T84: Novato | U84: 877 Grant Avenue | V84: Novato | W84: Ca | X84: 94945 | Y84: mollhaut@aol.com | Z84: mollhaut@aol.com | AB84: Henry-owner | AD84: Mollie AP | AE84: 415-847-9232 | AF84: Beth Anne | AJ84: 415-225-7495 | AK84: 415-295-4145 | AL84: www.finnegansmarin.com/ | AV84: =PROPER(AW84) -> 877 Grant Avenue | AW84: 877 GRANT AVENUE | AX84: Novato | AY84: Ca | AZ84: 94945 | BA84: 415-899-1516 | BE84: 3
A85: Foresthill Market | B85: NCC | C85: LG | E85: NO | H85: NO | N85: 44320 | O85: Parm | P85: 707-865-5041 | Q85: 707-695-5206 cell | R85: 0.085 | T85: SON | U85: 20293 CA-116 | V85: Monte Rio | W85: Ca | X85: 95462 | AV85: 20293 CA-116 | AX85: Monte Rio | AY85: Ca | AZ85: 95462 | BA85: 707-865-5041
A86: Fosters Freeze - Pinole | B86: ECR | C86: AH | D86: Casio QT6600 | E86: NO | H86: NO | N86: 44046 | O86: Ming | P86: 510-724-8782 | R86: 0.0975 | S86: 0.0925 | T86: Pinole | U86: 993 San Pablo Avenue | V86: Pinole | W86: Ca | X86: 94564 | AB86: Serene | AV86: 993 San Pablo Avenue | AX86: Pinole | AY86: Ca | AZ86: 94564 | BA86: 510-724-8782 | BE86: 2 | BF86: QT6600
A87: Fountain Café | B87: NCC | C87: LG | D87: SPT4500 | E87: M-F | F87: 45117 | G87: 468 | H87: NO | N87: 44055 | O87: Elias | P87: 510-451-6400 | R87: 0.1025 | S87: 0.095 | T87: ALA | U87: 499 14th Street, Suite 125 | V87: Oakland | W87: Ca | X87: 94612 | Y87: elias499@sbcglogal.net | AJ87: 510-451-5480 | AV87: 499 14th Street, Suite 125 | AX87: Oakland | AY87: Ca | AZ87: 94612 | BA87: 510-451-6400 | BE87: 4
A88: Fred's Liquors - Valencia | B88: NCC | C88: DF | E88: ** NO SERVICE UNLESS PRE-PAID, SEE ROB | N88: 44016 | O88: Fred | P88: 415-621-2500 | Q88: 415-990-2500 | R88: 0.08625 | S88: 0.0875 | T88: SF | U88: 200 Valencia Street | V88: San Francisco | W88: Ca | X88: 94103 | Y88: e1030@aol.com | AV88: 200 Valencia Street | AX88: San Francisco | AY88: Ca | AZ88: 94103 | BA88: 415-990-2500 | BE88: 1
A89: Fred's Place | B89: SUPPLY ONLY | C89: AH | E89: NO | H89: NO | N89: 44194 | O89: Sergio Rodas | P89: 415-332-4575 | Q89: 707-980-0542 cell | R89: 0.0875 | T89: Saus | U89: 1917 Bridgeway | V89: Sausalito | W89: Ca | X89: 94965 | AV89: 1917 Bridgeway | AX89: Sausalito | AY89: Ca | AZ89: 94965 | BA89: 415-332-4575
A90: Fruit in Motion | B90: NCC | C90: DD | D90: TEC 3600 | E90: NO | H90: NO | N90: 44057 | O90: Grant Butler | P90: 707-776-4559 | Q90: 707-235-2276 | R90: 0.095 | S90: 0.0825 | T90: Petaluma | U90: 3 Fourth Street | V90: Petaluma | W90: Ca | X90: 94952 | AV90: =PROPER(AW90) -> 3 Fourth Street | AW90: 3 FOURTH STREET | AX90: Petaluma | AY90: Ca | AZ90: 94952 | BA90: 707-776-4559 | BE90: 1
A91: Fruitvale Bottle & Liquor | B91: NCC | C91: LG | E91: ** NO SERVICE UNLESS PRE-PAID, SEE ROB | N91: 44594 | O91: Ibrahim | P91: 510-677-2584 | R91: 0.1025 | S91: 0.095 | T91: ALA | U91: 3715 International Blvd | V91: Oakland | W91: Ca | X91: 94601 | AB91: Ray Ramos | AV91: 3715 International Blvd | AX91: Oakland | AY91: Ca | AZ91: 94601 | BA91: 510-677-2584 | BE91: 1 | BJ91: Orbit | BN91: Twin Tran | BP91: VX805-SER | BS91: ML700 multi-line display
A92: Glen Ellen Market | B92: ECR | E92: NO | H92: NO | N92: 44089 | O92: Sonya | P92: 707-996-6614 | R92: 0.085 | T92: SON | U92: 13710 Arnold Drive | V92: Glen Ellen | W92: Ca | X92: 95442 | AV92: 13710 Arnold Drive | AX92: Glen Ellen | AY92: Ca | AZ92: 95442 | BA92: 707-996-6614
A93: Golden Gate Ferry | B93: ECR | C93: AH | D93: Tec 600F | E93: NO | H93: NO | N93: 43536 | O93: Dwyer | P93: 415-457-3110 | Q93: 415-850-0334 | R93: 0.09 | S93: 0.09 | T93: Lark | U93: 101 East Sir Francis Drake | V93: Larkspur | W93: Ca | X93: 94939 | Y93: mwaterman@goldengate.org | AB93: Marianne | AC93: 415-925-5583 | AD93: Mike | AE93: 415-850-2576 | AF93: Marianne | AG93: 415-925-5583 | AH93: Cynthia-office | AI93: 415-716-6613 | AJ93: 415-925-5510 | AK93: 415-925-5511 | AV93: =PROPER(AW93) -> 101 East Sir Francis Drake | AW93: 101 EAST SIR FRANCIS DRAKE | AX93: Larkspur | AY93: Ca | AZ93: 94939 | BA93: 415-257-4400 | BE93: 8
A94: Golden Gate Market - Sausalito | B94: ECR | C94: AH | D94: Tec Ma1595 | E94: NO | H94: NO | N94: 42877 | O94: Robert | P94: 415-332-3040 | R94: 0.0875 | S94: 0.09 | T94: Saus | U94: 221 2nd Street | V94: Sausalito | W94: Ca | X94: 94965 | AJ94: 415-332-4033 | AV94: 221 2nd Street | AX94: Sausalito | AY94: Ca | AZ94: 94965 | BA94: 415-332-3040 | BE94: 2
A95: Golden Produce | B95: ECR | C95: AH | D95: TEC MA1650 | E95: NO | H95: NO | N95: 43452 | O95: Sally | P95: 415-431-1536 | Q95: 650-455-0814 | R95: 0.08625 | S95: 0.0875 | T95: SF | U95: 172 Church Street | V95: San Francisco | W95: Ca | X95: 94114 | AB95: Panica | AC95: 650-255-9269 | AD95: Other Store | AE95: 415-864-2107 | AJ95: 510-419-0660 | AV95: =PROPER(AW95) -> 172 Church Street | AW95: 172 CHURCH STREET | AX95: San Francisco | AY95: Ca | AZ95: 94114 | BA95: 415-431-1536 | BE95: 2 | BK95: SL47
A96: Gourmet Market | B96: ECR | C96: RF | D96: Sam4s 520 | E96: NO | H96: NO | N96: 44018 | O96: Davis | P96: 510-839-9989 | Q96: 808-227-1087 cell | R96: 0.1025 | T96: ALA | U96: 1549 Jackson St | V96: Oakland | W96: Ca | X96: 94612 | AV96: 1549 Jackson St | AX96: Oakland | AY96: Ca | AZ96: 94612 | BA96: 510-839-9989
A97: Grilly's - Mill Valley | B97: NCC | C97: RA | E97: NO | H97: NO | L97: SPOT ON | N97: 44755 | O97: Estuardo | P97: 415-381-3278 | R97: 0.0825 | S97: 0.085 | T97: Marin | U97: 493 Miller Road | V97: Mill Valley | W97: Ca | X97: 94941 | Y97: jim@grillys.com | Z97: manager@grillys.com | AA97: holly@grillys.com | AB97: Holly= Office | AC97: 415-454-2220 | AJ97: 415-381-4992 | AV97: 1744 Lincoln Avenue | AW97: 1 BOLINAS ROAD | AX97: San Rafael | AY97: Ca | AZ97: 94901 | BA97: 415-381-3278 | BE97: 3
A98: Hacienda Grill | B98: CASIO | C98: LG | D98: Casio TE 8500 | E98: NO | H98: NO | N98: 43329 | O98: Maria | P98: 510-233-0800 | R98: 0.0975 | S98: 0.09 | T98: Rich | U98: 1000 Nevin Avenue | V98: Richmond | W98: Ca | X98: 94801 | AV98: 1000 Nevin Avenue | AX98: Richmond | AY98: Ca | AZ98: 94801 | BA98: 510-233-0800
A99: Happy Donuts - San Jose | B99: NCC | C99: RA | E99: NO | H99: NO | N99: 44468 | O99: Gerald | P99: 408-255-6805 | R99: 0.09375 | T99: SanJose | U99: 1062 South DeAnza Blvd. | V99: San Jose | W99: Ca | X99: 95129 | AV99: 1062 South DeAnza Blvd | AX99: San Jose | AY99: Ca | AZ99: 95129 | BA99: 408-255-6805
A100: Harbor Bay Club | B100: ECR | C100: AH | E100: NO | H100: NO | N100: 43472 | O100: Julie Craig | P100: 510-521-5414 | R100: 0.1075 | S100: 0.095 | T100: Alameda | U100: 200 Packet Landing Road | V100: Alameda | W100: Ca | X100: 94502 | AJ100: 510-521-5535 | AV100: 200 Packet Landing Road | AX100: Alameda | AY100: Ca | AZ100: 94502 | BA100: 510-521-5414
...

Sheet Prime
B2: type | C2: AM | D2: WS | E2: Name | F2: Phone | G2: Cell | H2: 2017 | K2: STREET | L2: CITY | M2: ST | N2: ZIP | R2: Name | S2: Phone | T2: Name | U2: Phone | V2: Name | W2: Phone | X2: Name | Y2: Phone | Z2: Store | AA2: Corp or A/P | AC2: Supply Info | AL2: Billing Info | AT2: Hardware/Software Detail
A3: Java Hut - Petaluma | B3: NCC | C3: AF | D3: Sam4s SPT4700 | E3: Rick | F3: 707-763-5496 | G3: 415-706-4393 | H3: 0.0825 | I3: 0.0825 | J3: SON | K3: 100 Fairgrounds Drive | L3: Petaluma | M3: Ca | N3: 94952 | O3: lc.javahut@gmail.com | P3: lc.javahut@gmail.com | Q3: lc.javahut@gmail.com | R3: 2/25/20-Isabel- Manager 415-300-6737 | AC3: 54220 $58 | AJ3: NO | AM3: 488 Oak Manor Dr | AN3: 100 FAIRGROUNDS DRIVE | AO3: Petaluma | AP3: Ca | AQ3: 94930 | AR3: 707-763-5496 | AV3: 1
A4: Sam's Anchor Café | B4: SUPPLY ONLY | C4: SG | E4: Michelle | F4: 415-435-4527 | H4: 0.09 | J4: MARIN | K4: 27 Main St | L4: Belvedere Tiburon | M4: Ca | N4: 94920 | AC4: 13305 $35 | AJ4: PICKUP | AM4: 27 Main St | AO4: Belvedere Tiburon | AP4: Ca | AQ4: 94920 | AR4: 415-435-4527
A5: Epicurean @ Dolby | B5: DIGITAL DINING | C5: AH | E5: Michael Lin | F5: 415-645-4585 | G5: 408-509-0339 | H5: 0.085 | I5: 0.0875 | J5: SF | K5: 999 Brannon Street | L5: San Francisco | M5: Ca | N5: 94103 | R5: Jason-Mgr | T5: Alex | V5: Serry | AL5: Epicurean Corp | AM5: 111 Main Street | AN5: 999 BRANNON STREET | AO5: Los Altos | AP5: Ca | AQ5: 94022 | AR5: 415-895-2800 | AV5: 2
A6: Kitchen Door Restaurant | B6: TOAST | C6: RF | E6: Tim Seberson | F6: 707-226-1560 | G6: 707-287-7526 | H6: 0.0775 | I6: 0.08 | J6: NAPA | K6: 610 First Street | L6: Napa | M6: Ca | N6: 94559 | R6: Richard Miyashiro | S6: 415-515-6084 | T6: Todd Humphries | Z6: 707-226-1765 | AC6: 54220 $57 | AD6: 13305 $29 | AE6: 1612b $57 | AF6: 62245 $39 | AH6: CC235 $39 | AJ6: YES | AM6: 610 First Street | AO6: Napa | AP6: Ca | AQ6: 94559 | AR6: 707-226-1560 | AT6: 3100190 | AU6: 8.00.010.015 | AV6: 3
A7: Santa Fe Taqueria | B7: Reflections NCC | C7: LG | D7: Posiflex | E7: Jennifer | F7: 408-258-2599 | G7: 408-251-1033 | H7: 0.0925 | I7: 0.09 | J7: SanJose | K7: 942 S. White Road | L7: San Jose | M7: Ca | N7: 95127 | AM7: 942 S. White Road | AO7: San Jose | AP7: Ca | AQ7: 95127 | AR7: 408-258-2599 | AV7: 1
A8: Lungomare | B8: SUPPLY ONLY | C8: AH | E8: Saeed | F8: 510-444-7171 | G8: 510-379-2657 | H8: 0.0925 | I8: 0.095 | J8: ALA | K8: 1 Broadway | L8: Oakland | M8: Ca | N8: 94607 | R8: Chris | T8: Jasmin Noor | AM8: 1 Broadway | AO8: Oakland | AP8: Ca | AQ8: 94607 | AR8: 510-444-7171
A10: Teriyaki Madness | B10: SUPPLY ONLY | C10: AH | E10: Ting | F10: 303-771-5280 | H10: 0 | J10: O/S | K10: 8547 East Arapahoe Road Ste. F | L10: Greenwood Village | M10: Co | N10: 80112 | AC10: 54220 $55 | AJ10: YES
A11: Le Regency Deli | B11: ECR | C11: RF | D11: Tec Ma1450 | E11: Paul | F11: 415-982-4122 | H11: 0.085 | I11: 0.0875 | J11: SF | K11: 18 California Street | L11: San Francisco | M11: Ca | N11: 94111 | Z11: 415-982-0421 | AM11: 18 California Street | AO11: San Francisco | AP11: Ca | AQ11: 94111 | AR11: 415-982-0421
A12: Village Meats | B12: NCC | C12: RF | E12: Eric Halstead | F12: 775-831-6243 | H12: 0 | J12: O/S | K12: 770 Mays Blvd, Suite 2 (Attn: Meat Dept.) | L12: Incline Village | M12: NV | N12: 89450-3047 | AM12: 770 Mays Blvd, Suite 2 (Attn Meat Dept.) | AO12: Incline Village | AP12: NV | AQ12: 89450-3047 | AR12: 775-831-6243 | AV12: 1 | AW12: FS-3700
A13: Union St Coffee Roastery | B13: ECR | C13: AH | D13: TEC MA600R | E13: Michelle | F13: 415-922-9559 | H13: 0.085 | I13: 0.0875 | J13: SF | K13: 2191 Union Street | L13: San Francisco | M13: Ca | N13: 94123 | O13: michelleung711@gmail.com | Q13: michelleung711@gmail.com | AC13: 15157 $55 | AJ13: YES | AM13: 2191 Union Street | AO13: San Francisco | AP13: Ca | AQ13: 94123 | AR13: 415-922-9559
A14: Double Rainbow | B14: ECR | C14: AH | D14: Tec Fs1650 | E14: Forrest | F14: 415-457-0803 | H14: 0.09 | I14: 0.0925 | J14: San Raf | K14: 860 Fourth Street | L14: San Rafael | M14: Ca | N14: 94901 | AM14: 860 Fourth Street | AO14: San Rafael | AP14: Ca | AQ14: 94901 | AR14: 415-457-0803
A15: Smoking Pig BBQ | B15: ALOHA | C15: JS | E15: Paul Reddick | F15: 408-380-4784 | H15: 0.0925 | I15: 0.09 | J15: SanJose | K15: 1144 N. 4th Street | L15: San Jose | M15: Ca | N15: 95112 | O15: smokingpigbbq@gmail.com | R15: Jessica | AM15: 1144 N. 4th Street | AO15: San Jose | AP15: Ca | AQ15: 95112 | AR15: 408-380-4784 | AT15: 1420540 | AU15: 7.05.065 | AV15: 2
A16: Baja Fresh- Reno | B16: SUPPLY ONLY | C16: AH | E16: Adan | F16: 775-826-8900 | H16: 0 | J16: O/S | K16: 5140 Kietzke Lane Ste A | L16: Reno | M16: NV | N16: 89511 | O16: 30214@electrawarehouse.com | AC16: 54220 $49 | AD16: 13305 $31 | AF16: 62245 $41 | AH16: 27710P1606N $35 | AJ16: YES | AM16: 5140 Kietzke Lane Ste A | AO16: Reno | AP16: NV | AQ16: 89511 | AR16: 775-826-8900
A17: Los 3 Reyes Taqueria | B17: SUPPLY ONLY | C17: AH | E17: Jennifer | F17: 707-429-0120 | H17: 0.08375 | J17: SOL | K17: 603 Main Street | L17: Suisun | M17: Ca | N17: 94585 | O17: antonio199017@gmail.com | AF17: 62285 $39 | AJ17: YES | AM17: 603 Main Street | AO17: Suisun | AP17: Ca | AQ17: 94585 | AR17: 707-429-0120
A18: International Produce | B18: CASIO | C18: LG | D18: TE2200 | E18: Pablo | F18: 510-534-2877 | H18: 0.0925 | I18: 0.095 | J18: ALA | K18: 3851 International Blvd | L18: Oakland | M18: Ca | N18: 94601 | AC18: 63438 $49 | AD18: 15303 $25 | AJ18: YES | AM18: 3851 International Blvd | AO18: Oakland | AP18: Ca | AQ18: 94601 | AR18: 510-534-2877
A19: Island Pacific - Vallejo | B19: SUPPLY ONLY | C19: AH | E19: Max | F19: 707-552-6730 | H19: 0.08375 | I19: 0.0863 | J19: SOL | K19: 24 Springstowne Center | L19: Vallejo | M19: Ca | N19: 94591 | R19: Patrick | S19: 626-839-8285 | Z19: 626-839-6595 /CORP | AM19: 24 Springstowne Center | AO19: Vallejo | AP19: Ca | AQ19: 94591 | AR19: 707-552-6730
A20: Tomate Café | B20: SUPPLY ONLY | C20: AH | E20: Jack | F20: 510-549-9885 | H20: 0.0925 | I20: 0.095 | J20: ALA | K20: 2265 5th Street | L20: Berkeley | M20: Ca | N20: 94710 | P20: ruth_jimenez@150pelican.com | AM20: 2265 5th Street | AO20: Berkeley | AP20: Ca | AQ20: 94710 | AR20: 510-549-9885
A21: La Rosa Market y Taqueria | B21: NCC | C21: AF | E21: Pedro/Rosa | F21: 707-887-8375 | H21: 0.0825 | I21: 0.0825 | J21: SON | K21: 6555 Front Street, Hwy 116 | L21: Forestville | M21: Ca | N21: 95436 | O21: hernandez2588@gmail.com | Z21: 707-887-8375 | AC21: 54220 $58 | AD21: 15740 $55 | AE21: 13305 $35 | AF21: 62245 $39 | AJ21: NO | AM21: 6555 Front Street, Hwy 116 | AO21: Forestville | AP21: Ca | AQ21: 95436 | AR21: 707-887-8375 | AV21: 1
A22: Whole Spice | B22: ECR | C22: RF | E22: Debra | F22: 707-778-1750 x5 | H22: 0.0775 | I22: 0.08 | J22: NAPA | K22: 610 1st Street #13 | L22: Napa | M22: Ca | N22: 94559 | AM22: 610 1st Street #13 | AO22: Napa | AP22: Ca | AQ22: 94559 | AR22: 707-778-1750 x5
A23: Diekman's Market | B23: ECR | C23: AH | D23: MA1595 | E23: Gary | F23: 707-875-3517 | G23: 707-480-8117 | H23: 0.0825 | I23: 0.0825 | J23: SON | K23: 1275 Highway 1 | L23: Bodega Bay | M23: Ca | N23: 94923 | O23: gsingh071981@yahoo.com | R23: Gary – Call | S23: 916-647-7306 | AM23: =PROPER(AN23) -> 1275 Highway 1 | AN23: 1275 HIGHWAY 1 | AO23: Bodega Bay | AP23: Ca | AQ23: 94923 | AR23: 707-875-3517 | AV23: 2
A24: Dama Ethnic Beauty Supply | B24: SUPPLY ONLY | C24: AH | E24: Catherine | F24: 707-422-8694 | H24: 0.08375 | I24: 0.08625 | J24: SOL | K24: 711 Jackson Street | L24: Fairfield | M24: Ca | N24: 94533 | Z24: 707-442-8699 | AF24: 62345 $6.50 each | AJ24: YES | AM24: 711 Jackson Street | AO24: Fairfield | AP24: Ca | AQ24: 94533 | AR24: 707-422-8694
A25: Rancho Grande 3 | B25: SUPPLY ONLY | C25: AH | E25: Juan Silva | F25: 707-252-4495 | H25: 0.0775 | J25: NAPA | K25: 891 Silverado Trail | L25: Napa | M25: Ca | N25: 94559 | O25: elranchogrande3@hotmail.com | AC25: 54220 $58 | AD25: 15303 $25 | AJ25: NO | AM25: 891 Silverado Trail | AO25: Napa | AP25: Ca | AQ25: 94559 | AR25: 707-252-4495
A26: The Grotto | B26: SUPPLY ONLY | C26: AH | E26: Ray Chin | F26: 415-673-7025 | G26: 415-609-9938 | H26: 0.085 | J26: SF | K26: 2851 Taylor Street | L26: San Francisco | M26: CA | N26: 94133 | O26: info@thegrottosf.com | P26: apcorp@mosserco.com | AC26: 54220 $51 | AD26: CC235 $41 | AF26: 62245 $39 | AJ26: YES | AM26: 2851 Taylor Street | AO26: San Francisco | AP26: CA | AQ26: 94133 | AR26: 415-673-7025
A27: Discount Cigarettes - Vallejo | B27: SUPPLY ONLY | C27: AH | E27: Mgr | F27: 707-643-7037 | H27: 0.0875 | J27: SOL | K27: 601 Tennessee St | L27: Vallejo | M27: Ca | N27: 94590 | AC27: 15303 $29 | AJ27: NO | AM27: 601 Tennessee St | AO27: Vallejo | AP27: Ca | AQ27: 94590 | AR27: 707-643-7037
A28: Anderson Valley Brewing | B28: NCC | C28: AF | D28: TEC FS3700 | E28: Rebecca | F28: 707-895-2337 | H28: 0.07875 | I28: 0.0762 | J28: MENDO | K28: 17700 Highway 253 | L28: Boonville | M28: Ca | N28: 95415 | O28: reception@avbc.com | P28: rpaez@avbc.com | R28: Vicky ( A/P) | Z28: 707-895-2353 | AC28: 54220 $49 | AJ28: YES | AM28: P.O. Box 505 | AN28: 17700 HIGHWAY 253 | AO28: Boonville | AP28: Ca | AQ28: 95415 | AR28: 707-895-2337 | AV28: 2
A29: Bull Valley Roadhouse | B29: SUPPLY ONLY | C29: AH | E29: Paolo Gomez | F29: 510-787-1135 | H29: 0.08375 | J29: SOL | K29: 14 Canyon Lake Drive | L29: Port Costa | M29: Ca | N29: 94569 | O29: paolo@bullvalleyroadhouse.com | AC29: 54220 $58 | AD29: 13305 $39 | AE29: EPSON 30/34/38 $39 | AG29: 62245 $39 | AJ29: NO | AM29: 14 Canyon Lake Dr.PO Box 106 | AO29: Port Costa | AP29: Ca | AQ29: 94569 | AR29: 510-787-1135
A30: Alejandro's Taqueria - Fairfield | B30: ECR | C30: AH | D30: Sam ER940 flat | E30: Lety | F30: 707-429-2155 | H30: 0.08375 | J30: SOL | K30: 936 Texas Street | L30: Fairfield | M30: Ca | N30: 94533 | AC30: 15157 $49 | AD30: 44150 $27 | AF30: 67655 $39 | AJ30: YES | AM30: 936 Texas Street | AO30: Fairfield | AP30: Ca | AQ30: 94533 | AR30: 707-429-2155
A31: El Toro Taqueria | B31: SUPPLY ONLY | C31: AH | E31: Gary | F31: 415-431-3351 | H31: 0.085 | J31: SF | K31: 598 Valencia Street | L31: San Francisco | M31: Ca | N31: 94110 | O31: garyespinoza@gmail.com | R31: Estella | AC31: 54220 $55 | AH31: 187100450DP $90 | AI31: TN450 $55 | AJ31: NO | AM31: 598 Valencia Street | AO31: San Francisco | AP31: Ca | AQ31: 94110 | AR31: 415-431-3351
A32: Ada Café | B32: ECR | C32: AH | D32: TEC ma600 | E32: Dat | F32: 510-225-7062 | H32: 0.0925 | J32: ALA | K32: 3075 Adeline Street | L32: Berkeley | M32: Ca | N32: 94703 | AM32: 3075 Adeline Street | AO32: Berkeley | AP32: Ca | AQ32: 94703 | AR32: 510-225-7062 | AV32: 1 | AW32: TEC ma600
A33: Café Roma - Columbus | B33: ECR | C33: AH | E33: Tony | F33: 415-296-7942 | H33: 0.085 | I33: 0.0875 | J33: SF | K33: 526 Columbus Avenue | L33: San Francisco | M33: Ca | N33: 94133 | AM33: 526 Columbus Avenue | AO33: San Francisco | AP33: Ca | AQ33: 94133 | AR33: 415-296-7942
A34: Foodvale Market | B34: ECR | C34: AH | E34: Yvett | F34: 510-533-6806 | H34: 0.0925 | I34: 0.095 | J34: ALA | K34: 3401 International Blvd | L34: Oakland | M34: Ca | N34: 94601 | AM34: 3401 International Blvd | AO34: Oakland | AP34: Ca | AQ34: 94601 | AR34: 510-533-6806
A35: La Azteca Market #2 | B35: SUPPLY ONLY | C35: AH | E35: Fernando | F35: 415-457-2518 | H35: 0.095 | J35: MARIN | K35: 802 4th St | L35: San Rafael | M35: Ca | N35: 94901 | AM35: 802 4th St | AO35: San Rafael | AP35: Ca | AQ35: 94901 | AR35: 415-457-2518
A36: Lumpy's Diner Express | B36: SUPPLY ONLY | C36: AH | E36: Jeremy | F36: 925-420-5373 | H36: 0.0825 | I36: 0.09 | J36: CC | K36: 7160 Brentwood Blvd Ste E | L36: Brentwood | M36: Ca | N36: 94513 | AM36: 7160 Brentwood Blvd Ste E | AO36: Brentwood | AP36: Ca | AQ36: 94513 | AR36: 925-420-5373
A37: Over the Top Yogurt Shop | B37: SUPPLY ONLY | C37: AH | E37: Ted Ginn | F37: 707-554-8400 | G37: 707-260-5801 | H37: 0.0775 | I37: 0.08 | J37: NAPA | K37: 5075 Main Street #122 | L37: American Canyon | M37: Ca | N37: 94503 | O37: otoro1688@gmail.com | R37: Ginnie | S37: 707-260-5801 Ted Cell | Z37: 707-226-1617 Home Fax | AM37: =PROPER(AN37) -> 5075 Main Street, #122 | AN37: 5075 MAIN STREET, #122 | AO37: American Canyon | AP37: Ca | AQ37: 94503 | AR37: 707-554-8400 | AT37: 1411203 | AU37: 7.05.044.000 | AV37: 2
A38: Papillon Coffee | B38: ECR | C38: AH | D38: ER-347 | E38: Tom | F38: 925-283-0466 | H38: 0.0825 | I38: 0.085 | J38: CC | K38: 67 Lafayette Circle | L38: Lafayette | M38: Ca | N38: 94549 | AM38: 67 Lafayette Circle | AO38: Lafayette | AP38: Ca | AQ38: 94549 | AR38: 925-283-0466
A39: Eddie's Woodlands Mkt - Ross | B39: SYMPHONY | C39: RF | E39: Peter Ong | F39: 415-461-9343 | G39: 415-460-4846 | H39: 0.0825 | I39: 0.085 | J39: MARIN | K39: 1 Poplar Avenue | L39: Ross | M39: Ca | N39: 94957 | O39: petero@woodlandsmarket.com | Q39: info@woodlandsmarket.com | R39: Sue-owner | S39: 415-272-2766 | T39: Debbie | AL39: Woodlands Mkt- Corp | AM39: 802 College Avenue, Ste 101 | AN39: 16 ROSS COMMON | AO39: Kentfield | AP39: Ca | AQ39: 94904 | AR39: 415-461-9343 | AV39: 2
A40: Louie's Deli | B40: ECR | C40: RF | D40: Sam4s ER5240M | E40: Vivian | F40: 415-332-6070 | H40: 0.0875 | I40: 0.09 | J40: Saus | K40: 2656 Bridgeway | L40: Sausalito | M40: Ca | N40: 94965 | R40: Maurice | AM40: 2656 Bridgeway | AO40: Sausalito | AP40: Ca | AQ40: 94965 | AR40: 415-332-6070 | AV40: 2
A41: Mr. Smith's | B41: SUPPLY ONLY | C41: RF | E41: Kevin (kimo) | F41: 415-355-9991 | H41: 0.085 | I41: 0.0875 | J41: SF | K41: 34 7th Street | L41: San Francisco | M41: Ca | N41: 94103 | Z41: 415-386-6299 | AM41: 34 7th Street | AO41: San Francisco | AP41: Ca | AQ41: 94103 | AR41: 415-355-9991
A42: New York Bagel & Deli - Santa Monica | B42: ECR | C42: RF | D42: Panasonic | E42: Brian | F42: 310-828-3228 | G42: 310-460-8333 | H42: 0.1025 | I42: 0.095 | J42: S.Monica | K42: 2216 Wilshire Blvd | L42: Santa Monica | M42: Ca | N42: 90403 | O42: NYBD.SANTAMONICA@GMAIL.COM | AM42: 2216 Wilshire Blvd | AO42: Santa Monica | AP42: Ca | AQ42: 90403 | AR42: 310-828-3228
A43: Olema Farm House | B43: SQUIRREL | C43: RF | E43: Ashley | F43: 415-663-1264 | H43: 0.0825 | I43: 0.085 | J43: MARIN | K43: 1005 Highway One | L43: Olema | M43: Ca | N43: 94950 | AM43: 10005 Highway One | AO43: Olema | AP43: Ca | AQ43: 94950 | AR43: 415-663-1264
A44: Tacolicious - North Beach | B44: SUPPLY ONLY | C44: RF | E44: Michael | F44: 415-433-1800 | H44: =I44-0.25% -> 0.085 | I44: 0.0875 | J44: SF | K44: 1548 Stockton Street | L44: San Francisco | M44: Ca | N44: 94133 | AM44: 1548 Stockton Street | AO44: San Francisco | AP44: Ca | AQ44: 94133 | AR44: 415-433-1800
A45: Tacolocious- Palo Alto | B45: SUPPLY ONLY | C45: RF | E45: Alejo | F45: 650-838-0500 | H45: 0.09 | I45: 0.0875 | J45: SC | K45: 632 Emerson Street | L45: Palo Alto | M45: Ca | N45: 94301 | AM45: 632 Emerson Street | AO45: Palo Alto | AP45: Ca | AQ45: 94301 | AR45: 650-838-0500
A46: Western Boat Shop | B46: SUPPLY ONLY | C46: RF | E46: Scott | F46: 415-454-4177 | H46: 0.09 | I46: 0.0925 | J46: San Raf | K46: 101 3rd Street | L46: San Rafael | M46: Ca | N46: 94901 | AM46: 101 3rd Street | AO46: San Rafael | AP46: Ca | AQ46: 94901 | AR46: 415-454-4177
A47: El Valle Mexican Food | B47: ECR | C47: SG | D47: RP-500 | E47: Alvaro | F47: 415-256-9596 | H47: 0.09 | I47: 0.0925 | J47: San Raf | K47: 927 Lincoln Avenue | L47: San Rafael | M47: Ca | N47: 94901 | AM47: 927 Lincoln Avenue | AO47: San Rafael | AP47: Ca | AQ47: 94901 | AR47: 415-256-9596
A48: Fire Island Grill - Palmdale | B48: SUPPLY ONLY | C48: JS | E48: Patrick Burke | F48: 661-802-6071 | G48: 661-272-1402 | H48: 0.095 | I48: 0.09 | J48: LA | K48: 40117 10th Street West Suite B | L48: Palmdale | M48: Ca | N48: 93551 | O48: pburke@fireislandgrill.com | R48: Jim Carter | S48: 805-582-2550 | AC48: 54220 $49 | AJ48: YES | AM48: 40117 10th Street West Suite B | AO48: Palmdale | AP48: Ca | AQ48: 93551 | AR48: 661-802-6071 | AT48: 1411888 | AU48: 7.05.50 | AV48: 2
A49: Alana's - Burlingame | B49: NCC | C49: AF | E49: Francesca | F49: 650-348-0417 | G49: 650-799-9230 | H49: 0.09 | I49: 0.09 | J49: Burl | K49: 1408 Burlingame Avenue | L49: Burlingame | M49: Ca | N49: 94010 | O49: info@alanascafe.com | P49: francesca@alanascafe.com | R49: Teresa | T49: Tim | U49: 650-703-9981 | AC49: 54220 $47 | AE49: CC235 $37 | AF49: 62245 $29 | AJ49: YES | AM49: =PROPER(AN49) -> 1408 Burlingame Avenue | AN49: 1408 BURLINGAME AVENUE | AO49: Burlingame | AP49: Ca | AQ49: 94010 | AR49: 650-348-0417 | AV49: 2
A50: Mi Casa Café | B50: SUPPLY ONLY | C50: AH | E50: Alvaro | F50: 415-482-6581 | H50: 0.09 | I50: 0.0925 | J50: San Raf | K50: 85 Woodland Avenue | L50: San Rafael | M50: Ca | N50: 94901 | R50: Ingrid | AC50: 54220 $49 | AD50: 13305 $29 | AE50: CC235 $39 | AF50: 62245 $35 | AJ50: PICKUP | AM50: 85 Woodland Avenue | AO50: San Rafael | AP50: Ca | AQ50: 94901 | AR50: 415-482-6581
A51: Antiguas Café | B51: ECR | C51: SG | D51: Sharp ER-407 | E51: Dalia / Fabiola | F51: 415-532-5012 | H51: 0.09 | J51: San Raf | K51: 703 3rd Street | L51: San Rafael | M51: Ca | N51: 94901 | AM51: 703 3rd Street | AO51: San Rafael | AP51: Ca | AQ51: 94901 | AR51: 415-532-5012 | AV51: 1 | AW51: ER-A247
A52: Miracle Mile Café | B52: ECR | C52: SG | F52: 415-454-7700 | H52: 0.09 | I52: 0.0925 | J52: San Raf | K52: 2130 4th Street | L52: San Rafael | M52: Ca | N52: 94901 | AM52: 2130 4th Street | AO52: San Rafael | AP52: Ca | AQ52: 94901 | AR52: 415-454-7700
A53: Wine & Waffles | B53: SUPPLY ONLY | C53: AH | E53: Ken Monize | F53: 510-523-2301 | G53: 707-494-3609 | H53: 0.0975 | I53: 0.095 | J53: Alam | K53: 1505 Park Avenue | L53: Alameda | M53: Ca | N53: 94501 | O53: kmonize@olewaffleshop.com | Q53: cdutra@sonic.net | R53: Ryan | T53: Andrew | U53: Carol A/P | AC53: 54220 $49 | AD53: 13305 $29 | AF53: 62245 $39 | AJ53: YES | AM53: 1505 Park Avenue | AO53: Alameda | AP53: Ca | AQ53: 94501 | AR53: 510-522-8108 | AV53: 1 | AW53: SPT 4500 | BC53: MBR1200
A54: Duboce Park Café | B54: SUPPLY ONLY | C54: AH | E54: Jose | F54: 415-621-1108 | H54: 0.085 | I54: 0.0875 | J54: SF | K54: 2 Sanchez Street | L54: San Francisco | M54: Ca | N54: 94114 | O54: pablo@doloresparkcafe.com | P54: dan@doloresparkcafe.com | AC54: 54220 $52 | AD54: 13305 $31.50 | AF54: 62245 $39 | AJ54: NO | AM54: 2 Sanchez Street | AO54: San Francisco | AP54: Ca | AQ54: 94114 | AR54: 415-621-1108
A55: Taqueria De Amigos | B55: SUPPLY ONLY | C55: AH | E55: Norman | F55: 650-879-0232 | H55: 0.0875 | I55: 0.09 | J55: SM | K55: 1999 Pescadero Road | L55: Pescadero | M55: Ca | N55: 94060 | AM55: 1999 Pescadero Road | AO55: Pescadero | AP55: Ca | AQ55: 94060 | AR55: 650-879-0232
A56: Barzotto | B56: TOAST | C56: DD | E56: Marco | F56: 415-285-1200 | H56: 0.085 | J56: SF | K56: 1270 Valencia St | L56: San Francisco | M56: Ca | N56: 94110 | O56: marko@barzotto.com | AM56: 1270 Valencia St | AO56: San Francisco | AP56: Ca | AQ56: 94110 | AR56: 415-285-1200
A57: Wetzel's Pretzels - Concord (LL) | B57: Treat POS/ICS | C57: DK | E57: Gadi Asaraf | F57: 925-818-7765 | H57: 0.0875 | J57: CC | K57: 292 Sun Valley Mall (LL) | L57: Concord | M57: Ca | N57: 94520 | O57: gadia64@hotmail.com | AM57: 292 Sun Valley Mall | AO57: Concord | AP57: Ca | AQ57: 94520 | AR57: 925-818-7765
A58: Wetzel's Pretzels - Concord (UL) | B58: Treat POS/ICS | C58: JS | D58: Sharp UP5500 | E58: Gadi Asaraf | F58: 925-818-7765 | H58: 0.0875 | J58: Concord | K58: 185 Sun Valley Mall | L58: Concord | M58: Ca | N58: 94520 | O58: gadia64@hotmail.com | AM58: 292 Sun Valley Mall | AO58: Concord | AP58: Ca | AQ58: 94520 | AR58: 925-818-7765 | AT58: supp# 800.735.1436 | AU58: cust# 01482 | AV58: 2
A59: Zomsa | B59: SUPPLY ONLY | C59: AH | E59: Lodo | F59: 510-529-4008 | H59: 0.0975 | J59: ALA | K59: 10558 San Pablo Ave | L59: El Cerrito | M59: Ca | N59: 94530 | O59: eat@zomsa.us | P59: eat@zomsa.us | Q59: eat@zomsa.us | AC59: 54220 $54 | AD59: 13305 $29 | AE59: 33124F(IVORY) $22 | AJ59: NO | AM59: 10558 San Pablo Ave | AO59: El Cerrito | AP59: Ca | AQ59: 94530 | AR59: 510-529-4008
A60: Joe's Market | B60: SUPPLY ONLY | C60: AH | E60: Najeeb | F60: 510-235-5786 | G60: 510-932-9224 | H60: 0.0925 | J60: CC | K60: 95 Macdonald Avenue | L60: Richmond | M60: Ca | N60: 94801 | AC60: 54220 $49 | AD60: 15740 $49 | AJ60: YES | AM60: 95 Macdonald Avenue | AO60: Richmond | AP60: Ca | AQ60: 94801 | AR60: 510-235-5786
A61: Super Stop | B61: ECR | C61: AH | D61: Samsung 5115 | E61: Sing | F61: 510-799-6115 | H61: 0.0825 | I61: 0.085 | J61: CC | K61: 718 4th Street | L61: Rodeo | M61: Ca | N61: 94572 | AM61: 718 4th Street | AO61: Rodeo | AP61: Ca | AQ61: 94572 | AR61: 510-799-6115
A62: Café Roma - Millbrae | B62: ECR | C62: AH | E62: Frank | F62: 650-692-7700 | H62: 0.0875 | I62: 0.09 | J62: SM | K62: 143 South El Camino Real | L62: Millbrae | M62: Ca | N62: 94030 | AM62: 143 South El Camino Real | AO62: Millbrae | AP62: Ca | AQ62: 94030 | AR62: 650-692-7700
A63: Piggie's Charbroiled Burgers | B63: SUPPLY ONLY | C63: AH | E63: Jose | F63: 310-679-6326 | H63: 0.1025 | I63: 0.09 | J63: Hawth | K63: 4601 Rosecrans Avenue | L63: Hawthorne | M63: Ca | N63: 90250 | Z63: 310-679-6960 | AM63: 4601 Rosecrans Avenue | AO63: Hawthorne | AP63: Ca | AQ63: 90250 | AR63: 310-679-6326
A64: Taqueria Made en Tepa | B64: SUPPLY ONLY | C64: AH | D64: TEC 1450 | E64: Ramon | F64: 530-672-1549 | H64: 0.0725 | J64: EL DOR | K64: 3440 Palmer Dr | L64: Cameron Park | M64: Ca | N64: 95682 | AC64: 44150 $25 | AF64: 67655 $39 | AJ64: YES | AM64: 3440 Palmer Dr | AO64: Cameron Park | AP64: Ca | AQ64: 95682 | AR64: 530-672-1549
A65: Puerto Vallarta Market | B65: SUPPLY ONLY | C65: AH | E65: Jorge | F65: 707-942-4400 | H65: 0.0775 | I65: 0.08 | J65: NAPA | K65: 1009 Foothill Blvd | L65: Calistoga | M65: Ca | N65: 94515 | R65: Vicki | Z65: 707-942-1637 | AC65: 54220 $55 | AD65: 15740 $49 | AH65: #1493 $39 | AJ65: YES | AM65: 1237 Lincoln Avenue | AO65: Calistoga | AP65: Ca | AQ65: 94515 | AR65: 707-942-4400
A66: Ferraro Fairfax | B66: ECR | C66: AH | E66: Sue Ferraro | F66: 415-455-8919 | H66: 0.09 | I66: 0.09 | J66: Fairfax | K66: 1942 Sir Frances Drake Blvd | L66: Fairfax | M66: Ca | N66: 94930 | AM66: 1942 Sir Frances Drake Blvd | AO66: Fairfax | AP66: Ca | AQ66: 94930 | AR66: 415-455-8919
A67: Lama Beans | B67: SUPPLY ONLY | C67: AH | E67: Ninma | F67: 510-528-3435 | H67: 0.0925 | I67: 0.095 | J67: ALA | K67: 1290 6th Street | L67: Berkeley | M67: Ca | N67: 94710 | R67: Lodo | T67: Jimmy | AC67: 54220 $54 | AD67: 13305 $29 | AE67: 33124J yellow $17.50 | AF67: 1301697 $17.5 | AG67: 62245 $45 | AH67: 30111G ivory $15 | AI67: 33124F $22 | AJ67: NO | AK67: 1301650 $17.50 | AM67: 1290 6th Street | AO67: Berkeley | AP67: Ca | AQ67: 94710 | AR67: 510-528-3435
A68: Royal King Eggroll 1 | B68: CASIO | C68: LG | D68: TE2200 | E68: Steve | F68: 408-729-8307 | H68: 0.0925 | J68: SanJose | K68: 980 Lundy Avenue | L68: San Jose | M68: Ca | N68: 95133 | AC68: 15157 $55 | AJ68: NO | AM68: 980 Lundy Avenue | AO68: San Jose | AP68: Ca | AQ68: 95133 | AR68: 408-729-8307 | AV68: 2
A69: King Eggroll | B69: CASIO | C69: LG | D69: TE2200 | E69: Steve Tran | F69: 408-729-8307 | H69: 0.0925 | I69: 0.09 | J69: SanJose | K69: 980 Lundy Ave | L69: San Jose | M69: Ca | N69: 95133 | AM69: 980 Lundy Ave | AO69: San Jose | AP69: Ca | AQ69: 95133 | AR69: 408-729-8307
A70: King Eggroll 2 | B70: CASIO | C70: LG | D70: TE2200 | E70: Steve Tran | F70: 408-999-0798 | H70: 0.0925 | I70: 0.09 | J70: SanJose | K70: 1221 Story Road #10 | L70: San Jose | M70: Ca | N70: 95122 | AM70: 1221 Story Road #10 | AO70: San Jose | AP70: Ca | AQ70: 95122 | AR70: 408-999-0798
A71: Piggie's Charbroiled Burgers | B71: SUPPLY ONLY | C71: AH | E71: Francisco | F71: 626-575-1682 | H71: 0.1 | I71: 0.095 | J71: S.El Mon | K71: 1724 N. Durfee Avenue | L71: South El Monte | M71: Ca | N71: 91733 | AM71: 1724 N. Durfee Avenue | AO71: South El Monte | AP71: Ca | AQ71: 91733 | AR71: 626-575-1682
A72: Star Grocery | B72: ECR | C72: AH | D72: TEC MA1595, SAM4s 5240 | E72: Nick | F72: 510-652-2490 | G72: 510-540-1018 | H72: 0.0925 | I72: 0.095 | J72: ALA | K72: 3068 Claremont Ave | L72: Berkeley | M72: Ca | N72: 94705 | Z72: 510-652-2430 | AC72: 15157 $55 | AI72: 15740 $49 | AJ72: YES | AM72: =PROPER(AN72) -> 3068 Claremont Avenue | AN72: 3068 CLAREMONT AVENUE | AO72: Berkeley | AP72: Ca | AQ72: 94705 | AR72: 510-652-2490 | AV72: 1
A73: Beep's Burger | B73: SUPPLY ONLY | C73: AH | E73: Carter Nguyen | F73: 415-584-2650 | G73: 415-530-9875 | H73: 0.085 | I73: 0.0875 | J73: SF | K73: 1051 Ocean Avenue | L73: San Francisco | M73: Ca | N73: 94112 | AD73: 13305 $39 | AE73: 62245 $15 | AJ73: NO | AM73: 1051 Ocean Avenue | AO73: San Francisco | AP73: Ca | AQ73: 94112 | AR73: 415-584-2650
A74: Golden Years Medical | B74: ECR | C74: SG | E74: Manager | F74: 415-453-6500 | H74: 0.09 | I74: 0.0925 | J74: San Raf | K74: 1013 2nd Street | L74: San Rafael | M74: Ca | N74: 94901 | AB74: www.goldenyearsmedical.com | AM74: =K74 -> 1013 2nd Street | AO74: San Rafael | AP74: Ca | AQ74: 94901 | AR74: 415-453-6500
A75: Plaza Market | B75: SUPPLY ONLY | C75: SG | E75: Will | F75: 415-256-1146 | H75: 0.09 | J75: San Raf | K75: 3255 Kerner Blvd | L75: San Rafael | M75: Ca | N75: 94901 | AH75: X1909 $137 | AJ75: PICKUP | AM75: 3255 Kerner Blvd | AO75: San Rafael | AP75: Ca | AQ75: 94901 | AR75: 415-256-1146
A76: Caramba Restaurant | B76: ECR | C76: AH | D76: Tec 1350 | E76: Carmen | F76: 415-543-8228 | G76: 650-235-6653 | H76: 0.085 | I76: 0.0875 | J76: SF | K76: 78 2nd Street | L76: San Francisco | M76: Ca | N76: 94105 | R76: Maritza | S76: 650-454-0291 | AC76: 63544 $22.5 | AD76: 44150 $25 | AE76: 54220 $58 | AJ76: NO | AM76: 78 2nd Street | AO76: San Francisco | AP76: Ca | AQ76: 94105 | AR76: 415-543-8228
A77: Fosters Freeze - Pinole | B77: ECR | C77: AH | D77: Casio QT6600 | E77: Ming | F77: 510-724-8782 | H77: 0.0925 | I77: 0.0925 | J77: Pinole | K77: 993 San Pablo Avenue | L77: Pinole | M77: Ca | N77: 94564 | R77: Serene | AM77: 993 San Pablo Avenue | AO77: Pinole | AP77: Ca | AQ77: 94564 | AR77: 510-724-8782 | AV77: 2 | AW77: QT6600
A78: Marina Super | B78: SUPPLY ONLY | C78: AH | D78: SL5300 | E78: Ken | F78: 415-346-7470 | H78: 0.085 | I78: 0.0875 | J78: SF | K78: 2323 Chestnut Street | L78: San Francisco | M78: Ca | N78: 94123 | Z78: 415-346-7511 | AC78: 54220 $51 | AH78: 1612-B $49 | AJ78: NO | AM78: 2323 Chestnut Street | AN78: 2323 CHESTNUT STREET | AO78: San Francisco | AP78: Ca | AQ78: 94123 | AR78: 415-346-7470 | AV78: 2
A79: Dino's Burgers | B79: SUPPLY ONLY | C79: AH | E79: George | F79: 714-542-8927 | H79: 0.0925 | I79: 0.08 | J79: S. Ana | K79: 2217 W. First Street | L79: Santa Ana | M79: Ca | N79: 92703 | AC79: 54220 $49 | AD79: 13305 $29 | AE79: 13305C $39 | AF79: 62245 $39 | AJ79: YES | AM79: 2217 W. First Street | AO79: Santa Ana | AP79: Ca | AQ79: 92703 | AR79: 714-542-8927
A80: Café La Haye | B80: NCC | C80: MB | D80: TEC 3700 | E80: Saul | F80: 707-935-5994 | G80: 707-480-1339 | H80: 0.0875 | I80: 0.0875 | J80: Sonoma | K80: 140 E. Napa Street | L80: Sonoma | M80: Ca | N80: 95476 | Z80: 707-963-1920 | AC80: 54220 $49 | AJ80: YES | AM80: =PROPER(AN80) -> 140 East Napa Street | AN80: 140 EAST NAPA STREET | AO80: Sonoma | AP80: Ca | AQ80: 95476 | AR80: 707-935-5994 | AV80: 2
A81: Z Café & Bar | B81: SUPPLY ONLY | C81: AH | E81: Mehdi | F81: 510-451-2905 | H81: 0.0925 | J81: ALA | K81: 2735 Broadway | L81: Oakland | M81: Ca | N81: 94610 | AE81: 15740 $55 | AJ81: YES | AM81: 2735 Broadway | AO81: Oakland | AP81: Ca | AQ81: 94610 | AR81: 510-451-2905
A82: Sweeney's Grill & Bar | B82: SUPPLY ONLY | C82: AH | E82: Peter | F82: 925-634-5192 | H82: 0.0825 | I82: 0.085 | J82: CC | K82: 301 Oak Street | L82: Brentwood | M82: Ca | N82: 94513 | Z82: 925-634-2420 | AC82: 54220 $49 | AJ82: YES | AM82: 301 Oak Street | AO82: Brentwood | AP82: Ca | AQ82: 94513 | AR82: 925-634-5192
A83: Insalata's | B83: MAITRE'D | C83: DK | D83: UPV5500 | E83: Cindy or Beth | F83: 415-457-7700 | H83: 0.0875 | I83: 0.09 | J83: S.Ansel | K83: 120 Sir Francis Drake Blvd | L83: San Anselmo | M83: Ca | N83: 94960 | O83: insalatasrestaurant@comcast.net | P83: christa@insalatas.com | R83: Carrie | T83: Heidi-owner | V83: RBS merch help | W83: 866-545-5965 | Z83: 415-457-8375 | AC83: 54220 $56 | AD83: 13305 $29 | AE83: CC235 $45 | AF83: 62245 $45 | AJ83: NO | AM83: =PROPER(AN83) -> 120 Sir Francis Drake Blvd | AN83: 120 SIR FRANCIS DRAKE BLVD | AO83: San Anselmo | AP83: Ca | AQ83: 94960 | AR83: 415-457-7700 | AT83: 1409889 | AV83: 5
A84: Java Hut - Fairfax | B84: NCC | C84: AF | D84: Sam4s SPT 4700 | E84: Rick | F84: 415-457-4581 | G84: 415-706-4393 | H84: 0.09 | I84: 0.09 | J84: Fairfax | K84: 760 Center Blvd | L84: Fairfax | M84: Ca | N84: 94930 | O84: lc.javahut@gmail.com | P84: lc.javahut@gmail.com | Q84: lc.javahut@gmail.com | R84: Becky | AC84: 54220 $58 | AJ84: NO | AM84: 488 Oak Manor Dr | AN84: 760 CENTER BLVD | AO84: Fairfax | AP84: Ca | AQ84: 94930 | AR84: 415-457-4581 | AV84: 1
A85: Food Stop Market | B85: ECR | C85: AH | D85: TEC 1595 | E85: Sarup | F85: 650-366-2917 | G85: 650-534-4116 | H85: 0.0925 | I85: 0.09 | J85: Redwood | K85: 916 Whipple Avenue | L85: Redwood City | M85: Ca | N85: 94063 | AC85: 15157 $56 | AJ85: NO | AM85: =PROPER(AN85) -> 916 Whipple Avenue | AN85: 916 WHIPPLE AVENUE | AO85: Redwood City | AP85: Ca | AQ85: 94063 | AR85: 650-366-2917 | AV85: 2
A86: Le Croissant | B86: NCC | C86: AF | D86: SPT 4740 | E86: Erica | F86: 415-456-0164 | H86: 0.09 | I86: 0.0925 | J86: San Raf | K86: 150 Bellam Road, #210 | L86: San Rafael | M86: Ca | N86: 94901 | R86: Bob | Z86: 707-824-8270 | AC86: 54220 $59 | AD86: 13305 $35 | AE86: 15740 $55 | AF86: 62245 $45 | AJ86: NO | AM86: 150 Bellam Road, #210 | AN86: 150 BELLAM RD #210 | AO86: San Rafael | AP86: Ca | AQ86: 94901 | AR86: 415-456-0164 | AV86: 2
A87: Picante | B87: NCC | C87: AF | D87: TEC 3700 | E87: Erica Schmidt | F87: 415-485-6050 | G87: 707-318-8998 | H87: 0.09 | I87: 0.0925 | J87: San Raf | K87: 340 Bellam Blvd | L87: San Rafael | M87: Ca | N87: 94901 | AC87: 54220 $58 | AD87: 13305 $29 | AE87: 15740 $55 | AF87: 62245 $39 | AJ87: PICKUP | AM87: =PROPER(AN87) -> 340 Bellam Blvd | AN87: 340 BELLAM BLVD | AO87: San Francisco | AP87: Ca | AQ87: 94901 | AR87: 415-485-6050 | AV87: 2
A88: Sam's Hof Brau | B88: SUPPLY ONLY | C88: DK | E88: Cecil | F88: 916-482-2175 | H88: 0.0875 | J88: SAC | K88: 2500 Watt Ave | L88: Sacramento | M88: Ca | N88: 95821 | O88: mickeyschle@gmail.com | P88: sarahpitzen6@gmail.com | Q88: info@originalsamshofbrau.com | R88: cjackson@originalsamhofbrau.com | AC88: 54220 $58 | AD88: 13305 $35 | AJ88: NO | AM88: 2500 Watt Ave | AO88: Sacramento | AP88: Ca | AQ88: 95821 | AR88: 916-482-2175
A89: Baja Fresh- S. Lake Tahoe | B89: SUPPLY ONLY | C89: AH | E89: Adan | F89: 530-544-1886 | H89: 0.0775 | J89: EL DOR | K89: 4000 Lake Tahoe Blvd #25 | L89: S. Lake Tahoe | M89: Ca | N89: 96150 | O89: adan@electrawarehouse.com | AC89: 54220 $49 | AD89: 13305 $31 | AH89: L90-2T $64 | AJ89: YES | AM89: 4000 Lake Tahoe Blvd #25 | AO89: S. Lake Tahoe | AP89: Ca | AQ89: 96150 | AR89: 530-544-1886
A90: Papermill Creek Saloon | B90: ECR | C90: RF | D90: Sam ER945 | E90: Jared | F90: 415-488-9235 | H90: 0.0825 | I90: 0.085 | J90: MARIN | K90: 1 Castro Avenue | L90: Forest Knolls | M90: Ca | N90: 94933 | R90: Rebecca=owner | AC90: 15157 $49 | AJ90: YES | AM90: =K90 -> 1 Castro Avenue | AO90: Forest Knolls | AP90: Ca | AQ90: 94933 | AR90: 415-488-9235 | AV90: 1 | AW90: Sam Er945
A91: Marin Alano Club | B91: ECR | C91: SG | D91: SAM ER940 | E91: Juan | F91: 415-456-8479 | H91: 0.09 | I91: 0.0925 | J91: San Raf | K91: 1360 Lincoln Avenue | L91: San Rafael | M91: Ca | N91: 94901 | O91: susanrogin@comcast.net | R91: George | S91: 415-721-7987 | AC91: 15157 $49 | AM91: 1360 Lincoln Avenue | AO91: San Rafael | AP91: Ca | AQ91: 94901 | AR91: 415-456-8479
A173: Palio Caffe - Parnassus | B173: SUPPLY ONLY | C173: AH | E173: Bettie Scodel | F173: 415-681-9925 | H173: 0.085 | I173: 0.0875 | J173: SF | K173: 500 Parnassus | L173: San Francisco | M173: Ca | N173: 94143 | R173: Gabriella | S173: 415-531-2046 | T173: Gabriella fax | U173: 415-634-1666 | Z173: 415-681-9927 | AM173: =PROPER(AN173) -> 500 Parnasus | AN173: 500 PARNASUS | AO173: San Francisco | AP173: Ca | AQ173: 94143 | AR173: 415-681-9925 | AT173: 1414263 | AU173: 7.05.040.002 | AV173: 4
A174: Setereh Market | B174: SUPPLY ONLY | C174: AH | E174: Givo | F174: 408-979-0634 | G174: Givo | H174: 0.0925 | I174: 0.09 | J174: SanJose | K174: 4644 Meridian Avenue | L174: San Jose | M174: Ca | N174: 95124 | AH174: 1681 $59 | AI174: 1477 $45 | AJ174: YES | AM174: 4644 Meridian Avenue | AO174: San Jose | AP174: Ca | AQ174: 95124 | AR174: 408-979-0634
A175: La Fusion | B175: NCC | C175: RF | E175: New Owner | F175: 415-781-0894 | G175: 415-574-8028 | H175: 0.085 | I175: 0.0875 | J175: SF | K175: 475 Pine Street | L175: San Francisco | M175: Ca | N175: 94104 | O175: javiermaderoz@yahoo.com | AM175: 475 Pine Street | AO175: San Francisco | AP175: Ca | AQ175: 94104 | AR175: 415-781-0894 | AV175: 2
A176: Jug Shop Liquor | C176: LG | E176: Keshav | F176: 925-689-1320 | G176: 925-487-5326 | H176: 0.0875 | J176: CC | K176: 1630 Contra Costa Blvd Suite E | L176: Pleasant Hill | M176: Ca | N176: 94523 | O176: kmalani@gmail.com | P176: jugshop.phill@gmail.com | AM176: 1630 Contra Costa Blvd Suite E | AO176: Pleasant Hill | AP176: Ca | AQ176: 94523 | AR176: 925-689-1320
A177: Missouri Lounge | B177: NCC | C177: AF | E177: Nima | F177: 510-644-2922 | G177: 510-717-1003 | H177: 0.0925 | J177: ALA | K177: 2600 San Pablo Avenue | L177: Berkeley | M177: Ca | N177: 94702 | O177: ali.eslami@outlook.com | Q177: analogbooks@gmail.com | AC177: 54220 $57 | AJ177: NO | AM177: 2600 San Pablo Avenue | AO177: Berkeley | AP177: Ca | AQ177: 94702 | AR177: 510-644-2922 | AV177: 2 | AW177: Acrobat
A178: Elbo Room | B178: ECR | C178: AH | D178: ER 945 | E178: Erik | F178: 415-522-7788 | G178: 415-216-3448 | H178: 0.085 | J178: SF | K178: 647 Valencia Street | L178: San Francisco | M178: Ca | N178: 94110 | O178: erik@elbo.com | AC178: 15517 $55 | AJ178: YES | AM178: 647 Valencia Street | AO178: San Francisco | AP178: Ca | AQ178: 94110 | AR178: 415-552-7788
A179: Peter's Beacon | B179: SUPPLY ONLY | C179: AH | E179: Sam | F179: 415-457-3020 | G179: 415-898-4832 | H179: 0.09 | J179: MARIN | K179: 108 Bellam Blvd | L179: San Rafael | M179: Ca | N179: 94901 | AC179: 54220 $55 | AD179: 15157 $55 | AJ179: PICKUP | AM179: 108 Bellam Blvd | AO179: San Rafael | AP179: Ca | AQ179: 94901 | AR179: 415-898-4832
A180: Taqueria El Tejaban - Fairfield | B180: ECR | C180: AH | D180: Sam4s ER 940 flat | E180: Felipe | F180: 707-425-2174 | H180: 0.08375 | I180: 0.0863 | J180: SOL | K180: 890 E. Travis Blvd #C | L180: Fairfield | M180: Ca | N180: 94533 | R180: Jose | S180: 415-265-0102 | AC180: 15303 $25 | AD180: 15157 $55 | AJ180: YES | AM180: 890 E. Travis Blvd #C | AO180: Fairfield | AP180: Ca | AQ180: 94533 | AR180: 707-425-2174
A181: Nordic House | B181: SUPPLY ONLY | C181: AH | E181: Pia | F181: 510-705-1932 | H181: 0.0925 | I181: 0.095 | J181: ALA | K181: 2709 San Pablo Avenue | L181: Berkeley | M181: Ca | N181: 94702 | AC181: 54220 $49 | AH181: 1681 $65 | AJ181: YES | AM181: 2709 San Pablo Avenue | AO181: Berkeley | AP181: Ca | AQ181: 94702 | AR181: 510-705-1932
A182: Oakland Kosher | B182: SUPPLY ONLY | C182: AH | E182: Yuval | F182: 510-839-0177 | G182: 925-698-9803 Jerry | H182: 0.0925 | J182: ALA | K182: 3419 Lakeshore Ave | L182: Oakland | M182: Ca | N182: 94610 | AC182: 54220 $57 | AJ182: NO | AM182: 3419 Lakeshore Ave | AO182: Oakland | AP182: Ca | AQ182: 94610 | AR182: 510-839-0177
A183: Precita Park Café | B183: SUPPLY ONLY | C183: AH | E183: Jose | F183: 415-647-7702 | H183: 0.085 | I183: 0.0875 | J183: SF | K183: 500 Precita Avenue | L183: San Francisco | M183: Ca | N183: 94110 | O183: dan@doloresparkcafe.com | P183: dan@doloresparkcafe.com | R183: Brian | AC183: 54220 $52 | AD183: 13305 $31.5 | AF183: 62245 $39 | AJ183: NO | AM183: 500 Precita Avenue | AO183: San Francisco | AP183: Ca | AQ183: 94110 | AR183: 415-647-7702
...

Sheet Top 165
A1: GROUP 1 | B1: SYSTEM | C1: STATUS / Notes | D1: Annual Projection | E1: Contact | F1: Phone | G1: 2nd Phone
A2: 26 Mix | B2: ECR | C2: Hilda called about register | E2: William Mayorga | F2: 415-826-7378 | G2: 510-734-5931 | H2: 3024 Mission Street | I2: San Francisco | J2: Ca
A3: 5th Street Steakhouse | B3: SUPPLY ONLY | C3: Called left message | E3: Traci | F3: 530-891-6328 | H3: 345 W. 5th Street | I3: Chico | J3: Ca | K3: wearschico@yahoo.com | L3: wearschico@yahoo.com | N3: Angela | P3: 54220 $55 | Q3: 13305 $31 | R3: CC235 $45 | S3: 62245 $39 | T3: 62235 $39 | W3: NO
A4: 9th Street Market | B4: ECR | C4: annual check in | E4: Nav Singh | F4: 707-542-5903 | G4: 559-260-5848 cell | H4: 766 Wilson Street | I4: Santa Rosa | J4: Ca | K4: mail4navsingh.nps@gmail.com | L4: mail4navsingh.nps@gmail.com | M4: mail4navsingh.nps@gmail.com | P4: 15157 $58 | W4: NO
A5: a Mano | B5: ALOHA | E5: Rodrigo | F5: 415-506-7401 | G5: 415-271-3947 | H5: 450 Hayes Street | I5: San Francisco | J5: Ca | K5: info@amanosf.com | L5: iberdougo@backofthehouseinc.com | M5: rodrigo@backofthehouseinc.com | P5: 54220 $54 | Q5: 13305 $34 | R5: CC235 $44 | S5: 62245 $34 | W5: YES
A6: Alley & Vine | B6: TOAST | C6: Last order 7/2021 | E6: Casey | F6: 510-227-5006 | H6: 1332 Park St Suite D | I6: Alameda | J6: Ca
A7: Anaheim White House | B7: SUPPLY ONLY | C7: sent email 8/18 | E7: Sylvano | F7: 714-772-1381 | H7: 887 S. Anaheim Blvd | I7: Anaheim | J7: Ca | L7: katie@anaheimwhitehouse.com | P7: 54220 $58 | Q7: CC235 $39 | S7: 62245 $39 | W7: NO
A8: Andi's Market | B8: NCC | C8: Morris | E8: Morris | F8: 415-648-4656 | G8: 559-960-2025 cell | H8: 820 Cortland Avenue | I8: San Francisco | J8: Ca | K8: mlmanji@gmail.com | L8: mlmanji@gmail.com | M8: mlmanji@gmail.com | P8: 15157 $55 | Q8: 15185 $35 | R8: 54220 $49 | U8: GoDex $24/roll | W8: YES
A9: Angela's Kitchen | B9: SUPPLY ONLY | C9: Last order 4/29 | E9: Saboor | F9: 510-263-8788 | G9: 510-333-4874 | H9: 1640 Park Street | I9: Alameda | J9: Ca | K9: zboor58@gmail.com | L9: zboor58@gmail.com | N9: Lisa | P9: 54220 $58 | Q9: 18333 $76 | S9: 67240 $45 | U9: 1301651 $21 | V9: 33124D $22 | W9: YES
A10: Arteaga's Food Center - Newark | B10: NCC | C10: Every 2 months | E10: Geraldo Lopez | F10: 510-791-1252 | G10: 510-364-8854 | H10: 5524 Thornton Avenue | I10: Newark | J10: Ca | K10: glopez@arteagasfoodcenter.com | L10: nelson@arteagas.com | N10: Lorena= A/P | Q10: 13305 $31.50 | S10: 62245 $37 | W10: NO
A11: Atwater Tavern | B11: SUPPLY ONLY | C11: sent email to John orders every two months | E11: John Caine | F11: 415-512-7153 | H11: 295 Terry A Francois Blvd | I11: San Francisco | J11: Ca | K11: fanny@atwatertavern.com | L11: debbie@mas.us.com | M11: john@atwatertavern.com | N11: Fanny Murith | P11: 54220 $55 | Q11: 13305 $35 | R11: CC235 $39 | S11: 62245 $27 | W11: YES
A12: Bacco Ristorante Italiano | B12: SUPPLY ONLY | C12: No call needed | E12: Shari | F12: 415-370-2191 | H12: 3913 24th Street | I12: San Francisco | J12: Ca | S12: 62245 $39 | W12: YES
A13: Baja Fresh- Reno | B13: SUPPLY ONLY | C13: AH | E13: Leanne | F13: 775-826-8900 | H13: 0 | J13: O/S | K13: 5140 Kietzke Lane Ste A | L13: Reno | M13: NV | N13: 89511 | O13: hamlet@electrawarehouse.com | AC13: 54220 $49 | AD13: 13305 $31 | AF13: 62245 $41 | AH13: 27710P1606N $35 | AJ13: YES | AM13: 5140 Kietzke Lane Ste A | AO13: Reno | AP13: NV | AQ13: 89511 | AR13: 775-826-8900
A14: Baker St Café | B14: SUPPLY ONLY | C14: Last order 6/2021 | E14: Kevin | F14: 650-593-0103 | H14: 254 Redwood Shores Pkwy | I14: Redwood City | J14: Ca
A15: Bar Bocce | B15: SUPPLY ONLY | C15: Last order 3/2021 | E15: Gary Newman | F15: 415-331-0555 | H15: 1250 Bridgeway Blvd | I15: Sausalito | J15: Ca | K15: gary@barbocce.com | L15: gary@barbocce.com | M15: info@barbocce.com | N15: Lauren GM | O15: www.barbocce.com | P15: 54220 $55 | Q15: 13305 $35 | S15: 62245 $39 | T15: 62235 $39 | U15: HL-3170CDW (B,Y,M,C) $49 each | V15: MICROS $2.5 | W15: NO
A16: Barrel Head Brewhouse | B16: SUPPLY ONLY | E16: Natasha Gatto | F16: 415-416-6989 | H16: 1785 Fulton Street | I16: San Francisco | J16: Ca | K16: natasha@barrelheadsf.com | P16: 54220 $55 | Q16: 13305 $31.50 | R16: CC235 $45 | S16: 62245 $37 | W16: NO
A17: Bay Watch - Burlingame | B17: NCC | E17: Peter | F17: 650-347-6924 | G17: 650-542-1445 | H17: 0.09625 | I17: 0.09 | J17: Burl | K17: 1841 El Camino Real | L17: Burlingame | M17: Ca | N17: 94010 | P17: baywatchb@gmail.com | AM17: 1841 El Camino Real | AN17: burl | AO17: Burlingame | AP17: Ca | AQ17: 94010 | AR17: 650-692-2236 | AV17: 3
A18: Bay Watch - San Mateo | B18: NCC | E18: Daniel(new owner) | F18: 650-342-2356 | H18: 0.09625 | I18: 0.0925 | J18: San Mat | K18: 201 2nd Avenue | L18: San Mateo | M18: Ca | N18: 94401 | P18: baywatchb@gmail.com | AM18: 201 2nd Avenue | AO18: San Mateo | AP18: Ca | AQ18: 94401 | AR18: 650-342-2356 | AV18: 3
A19: Bellam Produce | B19: ECR | C19: 415-902-8812 Thomas | E19: Julie Long | F19: 415-256-8086 | G19: 707-315-5078 | H19: 151 Bellam Blvd | I19: San Rafael | J19: Ca | N19: Tom | P19: 63438 $63 | Q19: 44150 $30 | R19: 15740 $55 | S19: 67655 $39 | U19: 15157 $49 | W19: pickup
A20: Bellam Self Storage | B20: SUPPLY ONLY | C20: set call back schedule | E20: Andree | F20: 415-454-1983 | H20: 24 Bellam Blvd | I20: San Rafael | J20: Ca | P20: 13305 $35 | Q20: 91192 $78 | R20: CC235 $47 | U20: 9542 $55 | W20: NO
A21: Ben Franklin | B21: SUPPLY ONLY | C21: flup set for 3 months | E21: Jennifer | F21: 530-273-1348 | H21: 598 Sutton Way | I21: Grass Valley | J21: Ca | N21: Jeannie DeGruccio | P21: 54220 $55 | W21: NO
A22: Beretta | B22: ALOHA | C22: sent email to Gloria last order in January 2021 | E22: Marko | F22: 415-695-1199 | H22: 1199 Valencia Street | I22: San Francisco | J22: Ca | K22: rodrigo@backofthehouseinc.com | L22: info@berettasf.com | P22: 54220 $54 | Q22: 13305 $34 | R22: CC235 $44 | S22: 62245 $34 | W22: YES
A23: Bistro 45 | B23: SUPPLY ONLY | E23: Robert Simon | F23: 626-795-2478 | G23: 626-644-9387 cell | H23: 45 South Mentor Avenue | I23: Pasadena | J23: Ca | K23: edward@welldonebooks.com | P23: 54220 $49 | Q23: 13305 $27 | R23: CC235 $39 | S23: 62245 $49 | W23: YES
A24: Blue Heron | B24: NCC | C24: last order 5/25/2021 | E24: Tom | F24: 707-865-2261 | G24: 530-220-2475 | H24: 25275 Steelhead Blvd | I24: Jenner | J24: Ca | K24: blueheronlive@gmail.com | P24: 54220 $49 | Q24: CC235 $39 | R24: 15185 $29 | S24: 62245 $39 | W24: YES
A25: Boca Pizza - Corte Madera | B25: SUPPLY ONLY | C25: Will check on supplies | E25: George | F25: 415-924-3021 | G25: 510-734-9054 | H25: 1544 Redwood Highway | I25: Corte Madera | J25: Ca | N25: Manny | O25: www.bocapizzeria.com/contact_cm.html | P25: 54220 $49 | Q25: 13305 $29 | R25: CC235 $39 | S25: 62245 $29 | W25: YES
A26: Bolinas Peoples Store | B26: SPOT ON | C26: call schedule 1 per month | E26: Claire | F26: 415-868-1433 | H26: 14 Wharf Rd | I26: Bolinas | J26: Ca | P26: 54220 $49 | W26: YES
A27: Bret Harte Market | B27: ECR | C27: Called for Jesse call back on Monday | E27: Monti | F27: 415-456-0163 | G27: 415-240-1759 | H27: 93 Woodland Avenue | I27: San Rafael | J27: Ca | K27: JASWINDERSINGH101@YAHOO.COM | L27: Mohammad | N27: Jesse | P27: 15157 $55 | R27: 15740 $55 | U27: GL2003 $24 | W27: PICKUP
A28: Bruno's Deli, Market, Café | B28: SUPPLY ONLY | C28: Last order 3/2021 | E28: Steve | F28: 415-785-7487 | H28: 1304 2nd St | I28: San Rafael | J28: Ca | P28: 54220 $49 | W28: PICK UP
A29: Buckeye Roadhouse | B29: SUPPLY ONLY | C29: Order every 6 weeks | E29: Peter Schumacher | F29: 415-331-2600 | G29: 415-990-2013 | H29: 15 Shoreline Highway | I29: Mill Valley | J29: Ca | K29: peterschumacher2@gmail.com | P29: 54220 $55 | Q29: 13305 $29.5 | R29: CC235 $42.5 | S29: 62245 $39 | U29: 15185 $27.5 | V29: 15160 $22.5 | W29: NO
A30: Buffalo Billiards Pool Hall | B30: SPOT ON | C30: monthly check in | E30: Mike Bombace | F30: 707-585-8992 | H30: 246 Petaluma Blvd N | I30: Petaluma | J30: Ca | P30: 13305 $39 | Q30: 62245 $42 | W30: YES
A31: Bungalow 44 | B31: SUPPLY ONLY | C31: Orders every 10 weeks | E31: Peter Schumacher | F31: 415-381-2500 | G31: 415-990-2013 | H31: 44 E. Blithedale Road | I31: Mill Valley | J31: Ca | K31: peterschumacher2@gmail.com | N31: Leslie Morgan=mgr | P31: 54220 $51 | Q31: 13305 $29.5 | R31: CC235 $42.5 | S31: 62245 $37 | W31: NO
A32: Café Lotus | B32: NCC | C32: Orders monthly last order 7/5/2021 | E32: Paul | F32: 415-457-7836 | H32: 1912 Sir Francis Drake Blvd | I32: Fairfax | J32: Ca | R32: CC235 $39 | W32: YES
A33: Caffe Greco | B33: ECR | E33: Hanna | F33: 415-397-6261 | G33: 415-990-7613 | H33: 423 Columbus Avenue | I33: San Francisco | J33: Ca | K33: hanna12@msn.com | M33: hanna12@msn.com | P33: 15157 $45 | W33: YES
A34: Caffé Macaroni | B34: SUPPLY ONLY | C34: will order as needed no call back requested – monitor for next order. | E34: Mario | F34: 415-956-9737 | G34: 415-602-4930 | H34: 59 Columbus Avenue | I34: San Francisco | J34: Ca | K34: mistermacaroni@yahoo.com | L34: mistermacaroni@yahoo.com | N34: Stephanie | P34: 54220 $49 | W34: YES
A35: Calistoga Inn | B35: NCC | C35: Spoke to Rose – she will continue to place orders by email. She requested no call back | E35: Michael Dunsford | F35: 707-942-4101 | G35: 707-695-8556 | H35: 1250 Lincoln Avenue | I35: Calistoga | J35: Ca | K35: michael@calistogainn.com | L35: rose@calistogainn.com | M35: info@calistogainn.com | N35: Rose Devera | O35: http://www.calistogainn.com/ | P35: 54220 $57 | Q35: CC235 $47 | R35: 13305 $37 | S35: 62245 $45 | W35: NO
A36: Caramba Restaurant | B36: ECR | E36: Carmen | F36: 415-543-8228 | G36: 650-235-6653 | H36: 78 2nd Street | I36: San Francisco | J36: Ca | N36: Maritza | P36: 63544 $22.5 | Q36: 44150 $25 | R36: 54220 $58 | W36: NO
