Workbook
Name ADDRESS: Master!#REF!
Name CC: Master!$M:$M
Name CD: Master!#REF!
Name CITY: Master!#REF!
Name CLIENT: Master!$A:$A
Name CONTACT_2: Master!$AD:$AD
Name COUNTY: Master!#REF!
Name EQUIP: Master!$B:$B
Name INSTALL: Master!#REF!
Name LICENSE: Master!#REF!
Name NAME: Master!$Q:$Q
Name PHONE: Master!$R:$R
Name PHONE_2: Master!$AE:$AE
Name REC: Master!#REF!
Name REM: Master!#REF!
Name STATE: Master!$Y:$Y
Name TERMS: Master!#REF!
Name VERS: Master!#REF!
Name ZIP: Master!$Z:$Z

Sheet New Client
B1: 0
J2: Invoice No:
C4: 100 Pelican Way, Suite "A" | J4: Date:
C5: San Rafael, Ca 94901 | J5: TERMS:
C6: 415-451-4861 | E6: Fax: 415-451-4866 | J6: Ordered by:
J7: Rep:
A8: ************************************************ | C8: ************************************ | F8: INVOICE | J8: *******************************
B10: Bill To | I10: Ship To:
B11: Client:
B12: c/o
B13: Address:
B14: City:
B16: Phone:
B17: Email:
C19: Products:
B20: Qty: | E20: Description: | J20: Unit Price | K20: Total
K21: =B21*J21 -> 0
K22: =B22*J22 -> 0
K23: =B23*J23 -> 0
K24: =B24*J24 -> 0
K25: =B25*J25 -> 0
K26: =B26*J26 -> 0
K27: =B27*J27 -> 0
I28: Taxable Subtotal: | K28: =SUM(K21:K27) -> 0
I29: Shipping & Handling:
I30: Sales Tax | J30: 0.09 | K30: =K28*J30 -> 0
C31: Services:
B32: Unit | E32: Description: | J32: Rate
K33: =B33*J33 -> 0
K34: =B34*J34 -> 0
K35: =B35*J35 -> 0
K36: =B36*J36 -> 0
K37: =B37*J37 -> 0
C39: Payment Details
J40: TOTAL: | K40: =SUM(K28:K39) -> 0
J42: office use only:
C46: I agree to the above charges and to pay this invoice according to the stated terms
C48: Client Signature
D50: This is your invoice. Kindly Pay from this invoice

Sheet Svc_Inv
J2: Invoice No:
C4: 100 Pelican Way, Suite "A" | J4: Date:
C5: San Rafael, Ca 94901 | J5: TERMS:
C6: 415-451-4861 | E6: Fax: 415-451-4866 | J6: Ordered by:
J7: Rep:
A8: ************************************************ | C8: ************************************ | F8: SERVICE INVOICE | J8: ***************************************
B10: Bill To | I10: Ship To:
B11: Client: | C11: Las Montanas Mkt - San Pablo | I11: =C11 -> Las Montanas Mkt - San Pablo
B12: c/o | C12: =LOOKUP(C11,Master!A:A,Master!AX:AX) | I12: =LOOKUP(C11,Master!A:A,Master!AW:AW)
B13: Address: | C13: =LOOKUP(C11,Master!A:A,Master!AY:AY) -> 13901 San Pablo Avenue | I13: =LOOKUP(C11,Master!A:A,Master!W:W) -> 13901 San Pablo Avenue
B14: City: | C14: =LOOKUP(C11,Master!A:A,Master!BA:BA) -> San Pablo | E14: =LOOKUP(C11,Master!A:A,Master!BB:BB) -> Ca | F14: =LOOKUP(C11,Master!A:A,Master!BC:BC) -> 94806 | I14: =LOOKUP(C11,Master!A:A,Master!X:X) -> San Pablo | J14: =LOOKUP(C11,Master!A:A,Master!Y:Y) -> Ca | K14: =LOOKUP(C11,Master!A:A,Master!Z:Z) -> 94806
B15: Phone: | C15: =LOOKUP(C11,Master!A:A,Master!BD:BD) -> 510-236-3397 | I15: =LOOKUP(C11,Master!A:A,Master!R:R) -> 510-236-3397
B16: Email: | C16: =LOOKUP(C11,Master!A:A,Master!#REF!) -> #REF!
B17: System | F17: Model# | J17: Serial#
B18: MICROS
B20: Problem As Reported:
B23: Work Performed
C26: Parts Billing:
B27: Qty: | E27: Description: | J27: Unit Price | K27: Total
K28: =B28*J28 -> 0
K29: =B29*J29 -> 0
K30: =B30*J30 -> 0
K31: =B31*J31 -> 0
K32: =B32*J32 -> 0
I33: Taxable Subtotal: | K33: =SUM(K28:K32) -> 0
B34: =LOOKUP(C11,Master!A:A,Master!C:C) -> LG | I34: Shipping & Handling:
B35: =LOOKUP(C11,Master!A:A,Master!V:V) -> San Pab | I35: Sales Tax | J35: =LOOKUP(C11,Master!A:A,Master!T:T) -> 0.0875 | K35: =J35*K33 -> 0
C36: Labor Billing:
E37: Description:
K38: =SUM(B38*J38) -> 0
K39: =SUM(B39*J39) -> 0
K40: =SUM(B40*J40) -> 0
K41: =SUM(B41*J41) -> 0
I42: Travel
C44: Payment Details
J45: TOTAL: | K45: =SUM(K33:K42) -> 0
J47: office use only:
C51: I agree to the above charges and to pay this invoice according to the stated terms
C54: Client Signature
D56: This is your invoice. Kindly Pay from this invoice

Sheet Prod_Inv
J2: Invoice No: | K2: 09150105
C4: 100 Pelican Way, Suite "A" | J4: Date: | K4: 44089
C5: San Rafael, Ca 94901 | J5: TERMS: | K5: Net 30
C6: 415-451-4861 | E6: Fax: 415-451-4866 | J6: Ordered by: | K6: Garret
J7: Rep: | K7: Antonio
A8: ************************************************ | C8: ************************************ | F8: INVOICE | J8: *******************************
B10: Bill To | I10: Deliver To
B11: Client: | C11: Layla at MacAthur Place | I11: =C11 -> Layla at MacAthur Place
B12: c/o
B13: Address: | C13: =LOOKUP(C11,Master!A:A,Master!AY:AY) -> 29 E MacArthur Street | I13: =LOOKUP(C11,Master!A:A,Master!W:W) -> 29 E MacArthur Street
B14: City: | C14: =LOOKUP(C11,Master!A:A,Master!BA:BA) -> Sonoma | E14: =LOOKUP(C11,Master!A:A,Master!BB:BB) -> Ca | F14: =LOOKUP(C11,Master!A:A,Master!BC:BC) -> 95476 | I14: =LOOKUP(C11,Master!A:A,Master!X:X) -> Sonoma | J14: =LOOKUP(C11,Master!A:A,Master!Y:Y) -> Ca | K14: =LOOKUP(C11,Master!A:A,Master!Z:Z) -> 95476
B15: Phone: | C15: =LOOKUP(C11,Master!A:A,Master!BD:BD) -> 707-933-3191 | I15: =LOOKUP(C11,Master!A:A,Master!R:R) -> 707-933-3191
B16: Email:
C18: Products:
B19: Qty: | E19: Description: | J19: Unit Price | K19: Total
K20: =B20*J20 -> 0
B21: 2 | C21: # CC-235 | D21: Epson Impact | F21: 3" two ply x 95' | I21: 50 rolls | J21: 45 | K21: =B21*J21 -> 90
K22: =B22*J22 -> 0
K23: =B23*J23 -> 0
K24: =B24*J24 -> 0
K25: =B25*J25 -> 0
K26: =B26*J26 -> 0
K27: =B27*J27 -> 0
B28: =LOOKUP(C11,Master!A:A,Master!C:C) -> AH | I28: Taxable Subtotal: | K28: =SUM(K20:K27) -> 90
B29: =LOOKUP(C11,Master!A:A,Master!V:V) -> SON | I29: Shipping
I30: Sales Tax | J30: =LOOKUP(C11,Master!A:A,Master!T:T) -> 0.0825 | K30: =K28*J30 -> 7.425
C31: Services:
B32: Unit | E32: Description: | J32: Rate
K33: =B33*J33 -> 0
K34: =B34*J34 -> 0
K35: =B35*J35 -> 0
K36: =SUM(B36*J36) -> 0
K37: =SUM(B37*J37) -> 0
K38: =B38*J38 -> 0
I39: Travel
C41: Payment Details
J42: TOTAL: | K42: =SUM(K28:K39) -> 97.425
J44: office use only:
C48: I agree to the above charges and to pay this invoice according to the stated terms
C50: Client Signature
D52: This is your invoice. Kindly Pay from this invoice

Sheet Master
A1: 44088 | B1: SYSTEM | E1: CORONA STATUS | F1: HELP DESK | I1: HARDWARE MAINT | L1: REVENUE TRACKING | Q1: PRIMARY CONTACT | T1: TAX% | U1: Tax % | V1: Tax Dist | W1: STORE ADDRESS | AA1: Ops Email | AB1: Billing Email | AC1: Other Email | AD1: CONTACT #2 | AF1: CONTACT #3 | AH1: CONTACT #4 | AJ1: CONTACT #5 | AL1: FAX | AN1: website | AO1: Paper #1 | AP1: Paper #2 | AQ1: Paper #3 | AR1: Ribbon #1 | AS1: Ribbon #2 | AT1: Label/Other | AU1: Other | AV1: freight ? | AX1: Bill To Name | AY1: Street | BA1: City | BB1: St | BC1: Zip | BD1: Phone | BF1: License # | BG1: Version | BH1: # Terms | BI1: WS | BJ1: RECEIPT | BK1: CD | BL1: REMOTE | BM1: SCANNER | BN1: SCALE | BO1: ROUTER | BP1: SWITCH | BQ1: TRAN / EPAY | BR1: TRAN VERSION | BS1: EMV DEVICE | BT1: FILE SERVER | BU1: OP SYS | BV1: HW OTHER | BW1: HW OTHER | BX1: HW OTHER | BY1: HW OTHER | BZ1: SW OTHER | CA1: SW OTHER | CB1: ***NOTES***
B2: type | C2: AM | D2: WS | F2: y/n ? | G2: exp | H2: $$ | I2: y/n ? | J2: exp | K2: $$ | L2: LAST SUPPLY?? | M2: MERCHANT | N2: RHQ? | O2: ONLINE ? | P2: LAST T&M ?? | Q2: Name | R2: Phone | S2: Cell | T2: 2017 | W2: STREET | X2: CITY | Y2: ST | Z2: ZIP | AD2: Name | AE2: Phone | AF2: Name | AG2: Phone | AH2: Name | AI2: Phone | AJ2: Name | AK2: Phone | AL2: Store | AM2: Corp or A/P | AO2: Supply Info | AX2: Billing Info | BF2: Hardware/Software Detail
A3: 19 Broadway | B3: SUPPLY ONLY | C3: DK | F3: NO | I3: NO | L3: 43208 | Q3: Garry Graham | R3: 415-459-1091 | S3: 415-459-0293 | T3: 0.09 | U3: 0.09 | V3: Fairfax | W3: 17 Broadway | X3: Fairfax | Y3: Ca | Z3: 94930 | AO3: 54220 $49 | AV3: YES | AY3: 17 Broadway | BA3: Fairfax | BB3: Ca | BC3: 94930 | BD3: 415-459-1091
A4: 2 Star Market | B4: Casio QT 6600 | C4: LG | F4: NO | I4: NO | P4: 43927 | Q4: Ali | R4: 510-531-3576 | T4: 0.0975 | V4: ALA | W4: 2020 MacArthur Blvd | X4: Oakland | Y4: Ca | Z4: 94602 | AY4: 2020 MacArthur Blvd | BA4: Oakland | BB4: Ca | BC4: 94602 | BD4: 510-531-3576
A5: 26 Mix | B5: ECR | C5: AH | D5: Sam4s ER945 raised | F5: NO | I5: NO | L5: 43355 | P5: 43355 | Q5: William Mayorga | R5: 415-826-7378 | S5: 510-734-5931 | T5: 0.085 | U5: 0.0875 | V5: SF | W5: 3024 Mission Street | X5: San Francisco | Y5: Ca | Z5: 94110 | AY5: 3024 Mission Street | BA5: San Francisco | BB5: Ca | BC5: 94110 | BD5: 415-826-7378 | BH5: 2 | BI5: Sam4s 945 raised
A6: 3 Star Food & Liquor | B6: CASIO | C6: LG | D6: Casio TE7000 | F6: NO | I6: NO | P6: 43026 | Q6: Mandeep | R6: 510-340-1366 | T6: 0.0875 | U6: 0.085 | V6: Concord | W6: 1140 Meadow Lane | X6: Concord | Y6: Ca | Z6: 94520 | AD6: Dependu | AY6: 1140 Meadow Lane | BA6: Concord | BB6: Ca | BC6: 94520 | BD6: 510-340-1366 | BH6: 1 | BI6: TE7000 | BK6: DL3616
A7: 420 Smoke Palace | B7: ECR | C7: AH | D7: Sam4s SAP-630RT | F7: NO | I7: NO | L7: 43878 | P7: 43878 | Q7: Abassi | R7: 408-880-4200 | T7: 0.0925 | V7: SC | W7: 396 S. Bascom Avenue | X7: San Jose | Y7: Ca | Z7: 95128 | AO7: 54220 $57 | AV7: NO | AY7: 396 S. Bacom Avenue | BA7: San Jose | BB7: Ca | BC7: 95128 | BD7: 408-880-4200
A8: 5 Star Enterprises | B8: ECR | C8: AH | D8: Sam4s ER285 | F8: NO | I8: NO | L8: 42691 | Q8: Phil | R8: 707-391-6581 | T8: 0.08875 | U8: 0.08125 | V8: Ukiah | W8: 595 North State Street | X8: Ukiah | Y8: Ca | Z8: 95482 | AA8: fivestarphil21@yahoo.com | AY8: 595 North State Street | BA8: Ukiah | BB8: Ca | BC8: 95482 | BD8: 707-391-6581
A9: 5th Street Steakhouse | B9: SUPPLY ONLY | C9: AH | F9: NO | I9: NO | L9: 44011 | Q9: Traci | R9: 530-891-6328 | T9: 0.0725 | U9: 0.075 | V9: BUTTE | W9: 345 W. 5th Street | X9: Chico | Y9: Ca | Z9: 95928 | AA9: wearschico@yahoo.com | AB9: wearschico@yahoo.com | AD9: Angela | AL9: 530-891-8339 | AO9: 54220 $55 | AP9: 13305 $31 | AQ9: CC235 $45 | AR9: 62245 $39 | AS9: 62235 $39 | AV9: NO | AY9: 345 W. 5th Street | BA9: Chico | BB9: Ca | BC9: 95928 | BD9: 530-891-6328
A10: 6 To Late Food & Liquor | B10: CASIO. | C10: LG | D10: Casio TE7000 | F10: NO | I10: NO | L10: 42881 | P10: 43172 | Q10: Ramesh | R10: 510-789-9537 | T10: 0.0925 | U10: 0.09 | V10: SanJose | W10: 5138 Monterey Hwy, Suite D | X10: San Jose | Y10: Ca | Z10: 95111 | AO10: 15157 $46.55 | AV10: NO | AY10: =W10 -> 5138 Monterey Hwy, Suite D | BA10: San Jose | BB10: =Y10 -> Ca | BC10: =Z10 -> 95111 | BD10: =R10 -> 510-789-9537 | BH10: 1 | BI10: TE7000 | BJ10: inc | BK10: DL3616 | BL10: none | BM10: Orbit 232 | BN10: none | BO10: none | BP10: none | BQ10: none | BT10: none | BU10: none
A11: 7 Mile House | B11: SUPPLY ONLY | C11: AH | F11: NO | I11: NO | Q11: Lory Marquez | R11: 415-467-2343 | T11: 0.0875 | U11: 0.09 | V11: SM | W11: 2800 Bayshore Blvd | X11: Brisbane | Y11: Ca | Z11: 94005 | AA11: lvgloriani@yahoo.com | AD11: Lory A/P | AE11: 415-269-5452 | AF11: Vanessa (owner) | AY11: 2800 Bayshore Blvd | BA11: Brisbane | BB11: Ca | BC11: 94005 | BD11: 415-467-2343
A12: 76 Auto Care Service | B12: SUPPLY ONLY | C12: AH | F12: NO | I12: NO | L12: 43544 | Q12: Babu | R12: 510-530-5605 | T12: 0.0925 | V12: ALA | W12: 4500 Park Blvd | X12: Oakland | Y12: Ca | Z12: 94602 | AO12: 54220 $55 | AP12: 15153 $49 | AV12: YES | AY12: 4500 Park Blvd | BA12: Oakland | BB12: Ca | BC12: 94602 | BD12: 510-530-5605
A13: 9th Street Café | B13: SUPPLY ONLY | C13: AH | F13: NO | I13: NO | L13: 43243 | M13: WORLDPAY | P13: 43038 | Q13: Ala | R13: 510-845-4852 | T13: 0.0925 | U13: 0.095 | V13: ALA | W13: 2570 9th Street | X13: Berkeley | Y13: Ca | Z13: 94710 | AL13: 510-549-2522 | AO13: 54220 $57 | AP13: 13305 $31 | AV13: NO | AY13: =PROPER(AZ13) -> 2570 9Th Street | AZ13: 2570 9TH STREET | BA13: Berkeley | BB13: Ca | BC13: 94710 | BD13: 510-845-4852 | BH13: 3 | CB13: Formerly Westside Bakery FYI
A14: a Mano | B14: ALOHA | C14: RF | F14: 7x24 | G14: 44089 | H14: 300 | I14: NO | L14: 44082 | P14: 44057 | Q14: Rodrigo | R14: 415-506-7401 | S14: 415-271-3947 | T14: 0.085 | V14: SF | W14: 450 Hayes Street | X14: San Francisco | Y14: Ca | Z14: 94102 | AA14: info@amanosf.com | AB14: iberdougo@backofthehouseinc.com | AC14: rodrigo@backofthehouseinc.com | AL14: 415-506-7401 | AO14: 54220 $54 | AP14: 13305 $34 | AQ14: CC235 $44 | AR14: 62245 $34 | AV14: YES | AY14: 450 Hayes St | BA14: San Francisco | BB14: Ca | BC14: 94102 | BD14: 415-881-7020 | BK14: MS-460 | CB14: Email all future invocies to email on file (info one)
A15: A Sweet Affair - California | B15: NCC | C15: DF | D15: Spt4500 | F15: NO | I15: NO | P15: 43859 | Q15: Terry | R15: 925-943-2253 | S15: 925-785-5931 | T15: 0.0825 | U15: 0.085 | V15: CC | W15: 1991 N California Blvd | X15: Walnut Creek | Y15: Ca | Z15: 94598 | AA15: asweetaffairbakery@usa.com | AB15: idreamofaruba@gmail.com | AD15: Sarah Torres -> | AE15: 925-395-1695 | AF15: EMAIL IDREAM | AY15: 1991 N California Blvd | BA15: Walnut Creek | BB15: Ca | BC15: 94598 | BD15: 925-785-5931 | BH15: 2
A16: A Sweet Affair - Ygnacio | B16: NCC | C16: AF | D16: Acrobat | F16: NO | I16: NO | M16: WORLDPAY | P16: 43206 | Q16: Jennifer | R16: 925-944-1910 | T16: 0.0825 | U16: 0.085 | V16: CC | W16: 1815F Ygnacio Valley Road | X16: Walnut Creek | Y16: Ca | Z16: 94598 | AA16: bakerhot1@aol.com | AD16: Terry-owner | AE16: 925-785-5931 | AL16: 925-947-6000 | AY16: 1815 Ygnacio Valley Road #F | BA16: Walnut Creek | BB16: Ca | BC16: 94598 | BD16: 925-944-1910 | BH16: 5
A17: A&W - San Rafael | B17: BRINK | C17: DK | F17: M-F | G17: 44089 | H17: 49 | I17: DEPOT | J17: 44089 | K17: 108 | L17: 43747 | P17: 43887 | Q17: Mark/David | R17: 415-479-9652 | S17: D.415-450-8300 | T17: 0.09 | V17: SR | W17: 3741 Redwood Highway | X17: San Rafael | Y17: Ca | Z17: 94903 | AA17: bigbromberger@gmail.com | AB17: brombergerville@hotmail.com | AO17: 15303 $35 | AV17: PICKUP | AY17: 3741 Redwood Highway | BA17: San Rafael | BB17: Ca | BC17: 94903 | BD17: 415-479-9652
A18: Abe's Liquor & Market | B18: CASIO | C18: LG | D18: Casio TE7000 | F18: NO | I18: NO | Q18: Rafique | R18: 415-552-4245 | T18: 0.0925 | U18: 0.09 | V18: SanJose | W18: 1939 Alum Rock Avenue | X18: San Jose | Y18: Ca | Z18: 95116 | AY18: 1939 Alum Rock Avenue | BA18: San Jose | BB18: Ca | BC18: 95116 | BD18: 415-552-4245
A19: AC Liquor and Food Mart | B19: CASIO | C19: LG | D19: Casio TE7000 | F19: NO | I19: NO | Q19: Manager | R19: 707-561-0115 | T19: 0.0775 | U19: 0.08 | V19: NAPA | W19: 3915 Broadway Street | X19: AmerIcan Canyon | Y19: Ca | Z19: 94503 | AY19: 3915 Broadway Street | BA19: AmerIcan Canyon | BB19: Ca | BC19: 94503 | BD19: 707-561-0115
A20: Ace Wasabi | B20: MAITRE'D | C20: JS | F20: M-F | G20: 44412 | H20: 500 | I20: NO | L20: 44054 | Q20: Ken Lowe | R20: 415-567-4903 | S20: 415-819-8477 | T20: 0.085 | U20: 0.0875 | V20: SF | W20: 3339 Steiner Street | X20: San Francisco | Y20: Ca | Z20: 94123 | AA20: klowe1414@yahoo.com | AB20: klowe1234@gmail.com | AD20: vicas | AE20: 415-850-7530 | AL20: 415-749-1873 | AO20: 54220 $56 | AP20: 13305 $31 | AR20: 62245 $39 | AV20: NO | AY20: 3339 Steiner Street | AZ20: 3339 STEINER STREET | BA20: San Francisco | BB20: Ca | BC20: 94123 | BD20: 415-576-4903 | BF20: 1007764 | BG20: 7.05.065.003 | BH20: 2
A21: Ada Café | B21: ECR | C21: AH | D21: TEC ma600 | F21: NO | I21: NO | P21: 42977 | Q21: Dat | R21: 510-225-7062 | T21: 0.0925 | V21: ALA | W21: 3075 Adeline Street | X21: Berkeley | Y21: Ca | Z21: 94703 | AY21: 3075 Adeline Street | BA21: Berkeley | BB21: Ca | BC21: 94703 | BD21: 510-225-7062 | BH21: 1 | BI21: TEC ma600
A22: Adam's Restaurant (CLOSED) | B22: NCC | C22: AF | F22: NO | I22: NO | L22: 43089 | P22: 43213 | Q22: Adam | R22: 707-456-9226 | T22: 0.08375 | U22: 0.08125 | V22: Willit | W22: 50 South Main Street | X22: Willits | Y22: Ca | Z22: 95490 | AA22: defchefcater@hotmail.com | AR22: 62245 $39 | AV22: YES | AY22: 50 South Main Street | BA22: Willits | BB22: Ca | BC22: 95490 | BD22: 707-456-9226 | BH22: 1
A23: Adobe Road Winery | B23: SUPPLY ONLY | C23: AH | F23: NO | I23: NO | L23: 42781 | Q23: Larry | R23: 650-464-9502 | T23: 0.0825 | V23: SON | W23: 6 Petaluma Blvd N. Ste A1 | X23: Petaluma | Y23: Ca | Z23: 94954 | AU23: cleaner $7.50 | AV23: YES | AY23: 6 Petaluma Blvd N. Ste A1 | BA23: Petaluma | BB23: Ca | BC23: 94954 | BD23: 650-464-9502
A24: Akane Japanese Cuisine | B24: SUPPLY ONLY | C24: AH | F24: NO | I24: NO | L24: 43329 | Q24: Frances | R24: 650-941-8150 | T24: 0.09 | U24: 0.0875 | V24: SC | W24: 250 Third Street | X24: Los Altos | Y24: Ca | Z24: 94022 | AL24: 650-941-3007 | AO24: 46175 $75 | AV24: YES | AY24: 250 Third Street | BA24: Los Altos | BB24: Ca | BC24: 94022 | BD24: 650-941-8150
A25: Alameda Cellars | B25: ECR | C25: AH | D25: Sam4s SPS2000 | F25: NO | I25: NO | Q25: Matt | R25: 510-521-3100 | T25: 0.0975 | U25: 0.095 | V25: Alam | W25: 2425 Encinal Avenue | X25: Alameda | Y25: Ca | Z25: 94501 | AY25: 2425 Encinal Avenue | BA25: Alameda | BB25: Ca | BC25: 94501 | BD25: 510-521-3100 | BH25: 2
A26: Alana's - Burlingame | B26: NCC | C26: AF | F26: 7x24 | G26: 44105 | H26: 49 | I26: M-F | J26: 44105 | K26: 39 | L26: 42843 | M26: WORLDPAY | N26: RHQ | P26: 44077 | Q26: Francesca | R26: 650-348-0417 | S26: 650-799-9230 | T26: 0.09 | U26: 0.09 | V26: Burl | W26: 1408 Burlingame Avenue | X26: Burlingame | Y26: Ca | Z26: 94010 | AA26: info@alanascafe.com | AB26: francesca@alanascafe.com | AD26: Teresa | AF26: Tim | AG26: 650-703-9981 | AO26: 54220 $47 | AQ26: CC235 $37 | AR26: 62245 $29 | AV26: YES | AY26: =PROPER(AZ26) -> 1408 Burlingame Avenue | AZ26: 1408 BURLINGAME AVENUE | BA26: Burlingame | BB26: Ca | BC26: 94010 | BD26: 650-348-0417 | BH26: 2
A27: Alana's - Redwood City | B27: NCC | C27: AF | E27: CLOSED | F27: NO | I27: NO | M27: WORLDPAY | N27: RHQ | P27: 43552 | Q27: Teresa | R27: 650-366-1498 | S27: 650-799-9210 | T27: 0.0925 | U27: 0.09 | V27: Redwood | W27: 1020 Main Street | X27: Redwood City | Y27: Ca | Z27: 94063 | AA27: info@alanascafe.com | AB27: teresa@alanascafe.com | AD27: Francesca | AF27: Tim | AG27: 650-703-9981 | AL27: 650-366-2117 | AY27: =PROPER(AZ27) -> 1020 Main Street | AZ27: 1020 MAIN STREET | BA27: Redwood City | BB27: Ca | BC27: 94063 | BD27: 650-366-1498
A28: Alberto's Mexican Food - Oak Hills | B28: MAITRE'D | C28: JS | F28: 7 X 24 | G28: 44234 | H28: 900 | I28: NO | L28: 42835 | M28: WORLDPAY | P28: 43842 | Q28: Gerardo Navarro | R28: 760-244-0026 | S28: 909-379-2951 | T28: 0.0775 | U28: 0.0825 | V28: S.BERN | W28: 13374 Ranchero Road | X28: Oak Hills | Y28: Ca | Z28: 92344 | AF28: Sean (outside help) | AG28: 951-823-9428 | AO28: 54220 $49 | AV28: YES | AY28: 13374 Ranchero Road | BA28: Oak Hills | BB28: Ca | BC28: 92344 | BD28: 909-882-5667 | BF28: 1409705 | BG28: 7.04.032.005 | BH28: 3 | BK28: MS 460-epson | BV28: Oneac UPS
A29: Alberto's Mexican Food - San Bern | B29: MAITRE'D | C29: JS | D29: PT SP800 | F29: 7 X 24 | G29: 44126 | H29: 900 | I29: NO | M29: WORLDPAY | P29: 44019 | Q29: Hector Navarro | R29: 909-882-5667 | S29: 909-379-2720 | T29: 0.08 | U29: 0.0825 | V29: San Bern | W29: 1008 West Highland | X29: San Bernadino | Y29: Ca | Z29: 92405 | AA29: jesdanger@aol.com | AY29: 1008 West Highland | BA29: San Bernadino | BB29: Ca | BC29: 92405 | BD29: 909-822-5667 | BF29: 1413933 | BH29: 3 | BI29: SP800
A30: Alegria's | B30: SUPPLY ONLY | C30: AH | F30: NO | I30: NO | L30: 43077 | P30: 43668 | Q30: Angelynne | R30: 415-929-8888 | T30: 0.085 | U30: 0.0875 | V30: SF | W30: 2018 Lombard Street | X30: San Francisco | Y30: Ca | Z30: 94123 | AA30: info@alegraissf.com | AD30: Arman | AP30: CC235 $39 | AR30: 62245 $39 | AV30: NO | AY30: =PROPER(AZ30) -> 2018 Lombard Street | AZ30: 2018 LOMBARD STREET | BA30: San Francisco | BB30: Ca | BC30: 94123 | BD30: 415-929-8888 | BH30: 2
A31: Alejandro's Taqueria - Fairfield | B31: ECR | C31: AH | D31: Sam ER940 flat | F31: NO | I31: NO | L31: 43906 | P31: 42929 | Q31: Lety | R31: 707-429-2155 | T31: 0.08375 | V31: SOL | W31: 936 Texas Street | X31: Fairfield | Y31: Ca | Z31: 94533 | AO31: 15157 $49 | AP31: 44150 $27 | AR31: 67655 $39 | AV31: YES | AY31: 936 Texas Street | BA31: Fairfield | BB31: Ca | BC31: 94533 | BD31: 707-429-2155
A32: Alejandro's Taqueria - Sacramento | B32: ECR | C32: AH | D32: Sam ER940 flat | F32: NO | I32: NO | P32: 43581 | Q32: Luis | R32: 916-459-0924 | T32: 0.0875 | V32: Sacmen | W32: 911 K Street | X32: Sacramento | Y32: Ca | Z32: 95814 | AA32: lbarr@sbcglobal.net | AC32: lbarr@sbcglobal.net | AO32: 15157 $49 | AV32: YES | AY32: 911 K Street | BA32: Sacramento | BB32: Ca | BC32: 95814 | BD32: 916-459-0924 | BH32: 2 | BI32: 1450/Sam4s ER940
A33: Alejandro's Taqueria - Vacaville | B33: ECR | C33: AH | D33: TEC FS1450 | F33: NO | I33: NO | Q33: Javier | R33: 707-448-8899 | T33: 0.08125 | U33: 0.07875 | V33: Vaca | W33: 348 Merchant Street | X33: Vacaville | Y33: Ca | Z33: 94568 | AD33: ALEJANDRO | AL33: 707-448-8899 | AY33: =PROPER(AZ33) -> 348 Merchant Street | AZ33: 348 MERCHANT STREET | BA33: Vacaville | BB33: Ca | BC33: 94568 | BD33: 707-448-8899 | BH33: 1
A34: Alexanders Steakhouse | B34: SUPPLY ONLY | C34: AH | F34: NO | I34: NO | Q34: Manager | R34: 408-446-2222 | T34: 0.09 | U34: 0.0875 | V34: Cuper | W34: 10330 N. Wolfe Road | X34: Cupertino | Y34: Ca | Z34: 95014 | AA34: CHEFSTOUT@ALEXANDERSSTEAKHOUSE.COM | AB34: accounting@alexandersteakhouse.com | AD34: Jeff Stout | AE34: 510-589-7077 | AF34: erin | AH34: Tim | AL34: 408-446-2242 | AY34: =PROPER(AZ34) -> 10330 N. Wolfe Road | AZ34: 10330 N. WOLFE ROAD | BA34: Cupertino | BB34: Ca | BC34: 95014 | BD34: 408-446-2222 | BH34: 7
A35: Alioto's | B35: SQUIRREL | C35: RF | F35: NO | I35: NO | P35: 43882 | Q35: Steven Fine | R35: 415-673-8300 | S35: Ext 1300 | T35: 0.085 | U35: 0.0875 | V35: SF | W35: 360A Jefferson Street | X35: San Francisco | Y35: Ca | Z35: 94113 | AA35: deesf888@yahoo.com | AB35: francesca@aliotos.com | AC35: steven@aliotos.com | AL35: 415-931-6792 | AN35: www.aliotos.com | AY35: 360A Jefferson Street | BA35: San Francisco | BB35: Ca | BC35: 94113 | BD35: 415-673-8300 | BH35: 1
A36: All Star Donut | B36: ECR | C36: AH | D36: SAM 260 | F36: NO | I36: NO | P36: 43756 | Q36: Sem | R36: 510-525-7289 | T36: 0.0925 | U36: 0.095 | V36: El Cerr | W36: 3070 El Cerrito Plaza | X36: El Cerrito | Y36: Ca | Z36: 94530 | AY36: 3070 El Cerrito Plaza | BA36: El Cerrito | BB36: Ca | BC36: 94530 | BD36: 510-525-7289
A37: Alma de la Rosa Restaurant | B37: SUPPLY ONLY | C37: AH | F37: NO | I37: NO | L37: 42990 | Q37: Max | R37: 626-564-8111 | T37: 0.1025 | U37: 0.09 | V37: Pasa | W37: 41 Hugus Alley | X37: Pasadena | Y37: Ca | Z37: 91103 | AD37: Max | AF37: Michael Moore | AH37: Noelle | AO37: 54220 $49 | AP37: 13305 $27 | AQ37: CC235 $37 | AR37: 62245 $25 | AV37: YES | AY37: 41 Hugus Alley | BA37: Pasadena | BB37: Ca | BC37: 91103 | BD37: 626-564-8111
A38: Alotta's Deli | B38: SUPPLY ONLY | C38: RA | F38: NO | I38: NO | P38: 43888 | Q38: Mike | R38: 650-967-0299 | S38: 408-807-0575 | T38: 0.085 | V38: SC | W38: 2249 Grant Road | X38: Los Altos | Y38: Ca | Z38: 94024 | AY38: 2249 Grant Road | BA38: Los Altos | BB38: Ca | BC38: 94024 | BD38: 650-967-0299
A39: Al's Liquor | B39: ECR | C39: AH | D39: Sam4s SPS520 | F39: NO | I39: NO | P39: 43049 | Q39: Jas | R39: 650-583-8920 | S39: 718-866-8232 | T39: 0.0925 | U39: 0.0875 | V39: So.Sf | W39: 479 Grand Avenue | X39: South San Francisco | Y39: Ca | Z39: 94080 | AY39: 479 Grand Avenue | BA39: South San Francisco | BB39: Ca | BC39: 94080 | BD39: 650-583-8920 | BI39: SPS520
A40: Amakara | B40: SUPPLY ONLY | C40: AH | F40: NO | I40: NO | L40: 43829 | P40: 43032 | Q40: Myly | R40: 925-803-8485 | S40: 925-992-9819 | T40: 0.0925 | U40: 0.095 | V40: ALA | W40: 7222 Regional Street | X40: Dublin | Y40: Ca | Z40: 94568 | AA40: amakaracompany@gmail.com | AD40: Eddie (owner) | AE40: 209-601-8923 | AF40: Tae Oh | AG40: 408-981-6142 | AO40: 54273 $65 | AP40: 13305 $34 | AQ40: CC235 $45 | AR40: 62245 $35 | AV40: NO | AY40: =PROPER(AZ40) -> 7222 Regional Street | AZ40: 7222 REGIONAL STREET | BA40: Dublin | BB40: Ca | BC40: 94568 | BD40: 925-803-8485 | BF40: 1410096 | BG40: 2005 | BH40: 3 | BQ40: ePay FDMS Nashville
A41: American Bull | B41: NCC | C41: RA | F41: M-F | G41: 44377 | H41: 390 | I41: M-F | J41: 44377 | K41: 600 | L41: 43363 | M41: WORLDPAY | P41: 43955 | Q41: Liz Jones | R41: 650-652-4908 | S41: 650-504-3947 | T41: 0.09 | U41: 0.09 | V41: Burl | W41: 1819 El Camino Real | X41: Burlingame | Y41: Ca | Z41: 94010 | AA41: theamericanbullbarandgrill@gmail.com | AD41: SUSAN-ACCT | AE41: 650-652-4908 | AF41: Freddy | AL41: 650-652-9825 | AO41: 54220 $56 | AP41: 13305 $29 | AR41: 62245 $34 | AV41: NO | AY41: =PROPER(AZ41) -> 1819 El Camino Real | AZ41: 1819 EL CAMINO REAL | BA41: Burlingame | BB41: Ca | BC41: 94010 | BD41: 650-652-4908 | BH41: 3
A42: AmeriPark | B42: SUPPLY ONLY | C42: AH | F42: NO | I42: NO | L42: 43747 | Q42: Armando | R42: 925-287-5048 | T42: 0.0825 | V42: CC | W42: 1275 Broadway Plaza Mgmt Office | X42: Walnut Creek | Y42: Ca | Z42: 94596 | AA42: ap@lanierparking.com | AT42: 27710M452XKIT $220 | AV42: YES | AY42: 1275 Broadway Plaza Mgmt Office | BA42: Walnut Creek | BB42: Ca | BC42: 94596 | BD42: 925-287-5048
A43: Ampco Parking - Downtown Plaza | B43: SUPPLY ONLY | C43: AH | F43: NO | I43: NO | Q43: Mark | R43: 916-441-5213 | T43: 0.0875 | U43: 0.085 | V43: Sacmen | W43: 597 L Street | X43: Sacramento | Y43: Ca | Z43: 95814 | AA43: tabdulkade@abm.com | AD43: Tahi | AL43: 916-441-5894 | AY43: 597 L Street | BA43: Sacramento | BB43: Ca | BC43: 95814 | BD43: 916-443-9094
A44: Anaheim White House | B44: SUPPLY ONLY | C44: AH | F44: NO | I44: NO | L44: 44018 | Q44: Sylvano | R44: 714-772-1381 | T44: 0.0775 | V44: OC | W44: 887 S. Anaheim Blvd | X44: Anaheim | Y44: Ca | Z44: 92805 | AB44: katie@anaheimwhitehouse.com | AO44: 54220 $58 | AP44: CC235 $39 | AR44: 62245 $39 | AV44: NO | AY44: 887 S. Anaheim Blvd | BA44: Anaheim | BB44: Ca | BC44: 92805 | BD44: 714-772-1381
A45: Ananda Fuara | B45: NCC | C45: DF | F45: NO | I45: NO | L45: 43839 | M45: WORLDPAY | P45: 43649 | Q45: Golapendu | R45: 415-621-1994 | S45: 415-812-1327 | T45: 0.085 | U45: 0.0875 | V45: SF | W45: 1298 Market Street | X45: San Francisco | Y45: Ca | Z45: 94102 | AO45: 54220 $49 | AP45: 13305 $27 | AR45: 62245 $29 | AV45: YES | AY45: 1298 Market Street | BA45: San Francisco | BB45: Ca | BC45: 94102 | BD45: 415-621-1994 | BH45: 2
A46: Anderson Valley Brewing | B46: NCC | C46: AF | D46: TEC FS3700 | F46: NO | I46: NO | L46: 43675 | Q46: Rebecca | R46: 707-895-2337 | T46: 0.07875 | U46: 0.0762 | V46: MENDO | W46: 17700 Highway 253 | X46: Boonville | Y46: Ca | Z46: 95415 | AA46: reception@avbc.com | AB46: rpaez@avbc.com | AD46: Vicky ( A/P) | AL46: 707-895-2353 | AO46: 54220 $49 | AV46: YES | AY46: P.O. Box 505 | AZ46: 17700 HIGHWAY 253 | BA46: Boonville | BB46: Ca | BC46: 95415 | BD46: 707-895-2337 | BH46: 2
A47: Andi's Market | B47: NCC | C47: LG | D47: 570-2 | F47: NO | I47: NO | L47: 44035 | P47: 44019 | Q47: Morris | R47: 415-648-4656 | S47: 559-960-2025 cell | T47: 0.085 | U47: 0.0875 | V47: SF | W47: 820 Cortland Avenue | X47: San Francisco | Y47: Ca | Z47: 94110 | AO47: 15157 $55 | AP47: 15185 $35 | AQ47: 54220 $49 | AV47: YES | AY47: 820 Cortland Avenue | BA47: San Francisco | BB47: Ca | BC47: 94110 | BD47: 415-648-4656
A48: Angela's Kitchen | B48: SUPPLY ONLY | C48: AH | F48: NO | I48: NO | L48: 43845 | Q48: Saboor | R48: 510-263-8788 | S48: 510-333-4874 | T48: 0.0975 | U48: 0.095 | V48: Alam | W48: 1640 Park Street | X48: Alameda | Y48: Ca | Z48: 94501 | AA48: zboor58@gmail.com | AB48: zboor58@gmail.com | AD48: Lisa | AL48: 510-864-0803 | AO48: 54220 $58 | AP48: 18333 $76 | AR48: 67240 $45 | AT48: 1301651 $21 | AU48: 33124D $22 | AV48: YES | AY48: 1640 Park Street | BA48: Alameda | BB48: Ca | BC48: 94501 | BD48: 510-522-5822
A49: Antiguas Café | B49: ECR | C49: SG | D49: Sharp ER-407 | F49: NO | I49: NO | P49: 43719 | Q49: Mario | R49: 415-532-5012 | T49: 0.09 | V49: San Raf | W49: 703 3rd Street | X49: San Rafael | Y49: Ca | Z49: 94901 | AY49: 703 3rd Street | BA49: San Rafael | BB49: Ca | BC49: 94901 | BD49: 415-532-5012 | BH49: 1 | BI49: ER-A247
A50: Antioch Water Park | B50: CASIO | C50: LG | D50: CASIO | F50: NO | I50: NO | Q50: Larry Montoya | R50: 925-776-3070 | S50: 925-776-3076 | T50: 0.0925 | U50: 0.095 | V50: Antioch | W50: 4701 Lone Tree Way | X50: Antioch | Y50: Ca | Z50: 94531 | AD50: Lori | AY50: 4701 Lone Tree Way | BA50: Antioch | BB50: Ca | BC50: 94531 | BD50: 925-776-3070 | BH50: 6
A51: Antonella's | B51: NCC | C51: DF | F51: NO | I51: NO | Q51: Lyle Koch | R51: 408-279-4922 | S51: 650-619-5742 | T51: 0.0925 | U51: 0.09 | V51: SanJose | W51: 1701 Park Avenue | X51: San Jose | Y51: Ca | Z51: 95126 | AA51: lylekoch@sbcglobal.net | AC51: lylekoch@sbcglobal.net | AY51: 1701 Park Avenue | BA51: San Jose | BB51: Ca | BC51: 95126 | BD51: 408-279-4922 | BH51: 2
A52: Antonella's @ EFI | B52: MAITRE'D | C52: JS | F52: NO | I52: NO | L52: 43418 | M52: WORLDPAY | P52: 43725 | Q52: Lyle Koch | R52: 650-504-3574 | S52: 650-619-5742 | T52: 0.0925 | U52: 0.095 | V52: ALA | W52: 6750 Dumbarton Circle | X52: Fremont | Y52: Ca | Z52: 94536 | AA52: lylekoch@sbcglobal.net | AC52: lylekoch@sbcglobal.net | AO52: 54220 $45 | AV52: NO | AY52: 1701 Park Avenue | BA52: San Jose | BB52: Ca | BC52: 95126 | BD52: 650-504-3574 | BF52: 1422705 | BG52: 7.05 | BH52: 1
A53: Antonio's Quick Lunch | B53: MAITRE'D | C53: JS | D53: CAS X750 | F53: M-F | G53: 44180 | H53: 600 | I53: NO | L53: 43742 | P53: 43712 | Q53: Antonio | R53: 530-763-4009 | S53: 530-751-6902 | T53: 0.0725 | U53: 0.075 | V53: SUTTER | W53: 716 Colusa Avenue | X53: Yuba City | Y53: Ca | Z53: 95991 | AA53: aql761@hotmail.com | AD53: Mayra | AE53: 530-300-3551 cell | AO53: 54220 $57 | AP53: 13305 $32 | AR53: 62245 $35 | AV53: NO | AY53: 716 Colusa Avenue | BA53: Yuba City | BB53: Ca | BC53: 95991 | BD53: 530-751-6902 | BF53: 1424784 | BH53: 4 | BI53: SP850 | CB53: SP850: workgroup: MAITRED, computer name: WS01 IP 192.168.15.11, user: maitred, pw: 7166Colusa9599!
A54: Appian Food & Liquor | B54: CASIO | C54: LG | D54: QT6600 | F54: NO | I54: NO | P54: 44013 | Q54: Chris/Ali | R54: 510-758-7543 | T54: 0.0825 | U54: 0.085 | V54: CC | W54: 4247 Appian Way | X54: El Sobrante | Y54: Ca | Z54: 94803 | AY54: 4247 Appian Way | BA54: El Sobrante | BB54: Ca | BC54: 94803 | BD54: 510-758-7543 | BH54: 2
A55: Arby's - Brea | B55: MAITRE'D | C55: JS | F55: NO | I55: NO | P55: 43515 | Q55: Ambrose Lam | R55: 714-671-6888 | S55: 714-264-2928 | T55: 0.0775 | U55: 0.08 | V55: OR | W55: 2525 East Imperial Hwy | X55: Brea | Y55: Ca | Z55: 92821 | AA55: ambrose168@aol.com | AD55: home office | AE55: 714-838-2688 | AY55: 2525 East Imperial Hwy | BA55: Brea | BB55: Ca | BC55: 92821 | BD55: 714-838-2688 | BF55: 1408297 | BG55: 7.05.105 | BH55: 7 | BI55: SP850(1/17) | BV55: KVM CPU Only; ip: 10.10.10.242 | BZ55: FDMS CARDNET | CA55: Gift ePay Vantiv Core (Fifth Third) FIG 5.05.05 | CB55: Computer Name: MaitreD, Workgroup: APPEL, User: svcacct, PW: svcacct Server IP: 10.10.10100, Commerece Name: Arby's #6802
A56: Arby's - Madison | B56: MAITRE'D | C56: JS | F56: M-F | G56: 44089 | H56: 79 | I56: NO | P56: 43952 | Q56: Teghvir Toor | R56: 916-344-8381 | S56: 916-832-3810 | T56: 0.0775 | U56: 0.08 | V56: SAC | W56: 5845 Madison Avenue | X56: Fair Oaks | Y56: Ca | Z56: 95841 | AA56: ptoor6@aol.com | AC56: ghrestaurants@gmail.com | AL56: 916-419-3302 | AY56: 5845 Madison Avenue | BA56: Fair Oaks | BB56: Ca | BC56: 95841 | BD56: 916-344-8381 | BH56: 4 | BI56: JS960 | BJ56: TMT88IV | BK56: Epson | BO56: MBR12000B | BP56: GS116 | BT56: T20 | BU56: 7 PRO | BV56: Oneac 250e | BW56: AOC LED KVM | BX56: DT166CR | CB56: Server: MAITRED-SERVER 192.168.16.100 workgroup: PERFORMANCE, user: MAITRED pw: pos9957; WS01 order taker - 192.168.16.110; WS02 order close - 192.168.16.120; WS03 counter - 192.168.16.130; WS04 counter - 192.168.16.140
A57: Arby's - Orange | B57: SUPPLY ONLY | C57: AH | F57: NO | I57: NO | Q57: April Matthews | R57: 714-496-2830 | S57: 714-282-9313 | T57: 0.0775 | U57: 0.08 | V57: OR | W57: 1107 N. Tustin | X57: Orange | Y57: Ca | Z57: 92867 | AA57: amatthews@at-properties.com | AD57: Maria | AL57: 714-538-5054 | AY57: 1107 N. Tustin | BA57: Orange | BB57: Ca | BC57: 92867 | BD57: 714-538-5407 | BF57: 1412760 | BG57: 7.05.067.004 | BH57: 4
A58: Arby's - Rocklin | B58: NCC | C58: DF | F58: NO | I58: NO | P58: 43194 | Q58: Gurmeet | R58: 916-952-9512 | T58: 0.0725 | V58: PLACER | W58: 4400 Rocklin Road | X58: Rocklin | Y58: Ca | Z58: 95677 | AA58: smilelike2003@yahoo.com | AE58: 916-624-5442 | AX58: Jazz Enterprises, Inc. | AY58: 441 Knowelton Ct. | BA58: Roseville | BB58: Ca | BC58: 95747 | BD58: 916-772-1729 | BH58: 4 | BS58: ZX805
A59: Arby's - San Jose | B59: NCC | C59: DF | F59: NO | I59: NO | N59: RHQ | P59: 44071 | Q59: Anoop Kang | R59: 408-249-4259 | S59: 510-557-9123 | T59: 0.0925 | U59: 0.09 | V59: SanJose | W59: 3158 Stevens Creek Blvd | X59: San Jose | Y59: Ca | Z59: 95117 | AA59: anoopkang@yahoo.com | AB59: anoopkang@yahoo.com | AC59: anoopkang@yahoo.com | AY59: 3158 Stevens Creek Blvd | BA59: San Jose | BB59: Ca | BC59: 95117 | BD59: 408-750-4433
A60: Arby's - Sunnyvale | B60: NCC | C60: DF | D60: SPT 4700 | F60: NO | I60: NO | L60: 43073 | N60: RHQ | P60: 44019 | Q60: Anoop Kang | R60: 408-733-6434 | S60: 510-557-9123 | T60: 0.09 | U60: 0.0875 | V60: SC | W60: 601 S. Bernardo Avenue | X60: Sunnyvale | Y60: Ca | Z60: 94087 | AA60: anoopkang@yahoo.com | AB60: anoopkang@yahoo.com | AC60: anoopkang@yahoo.com | AO60: 13305 $29 | AR60: 62245 $39 | AV60: YES | AY60: =W60 -> 601 S. Bernardo Avenue | BA60: Sunnyvale | BB60: =Y60 -> Ca | BC60: =Z60 -> 94087 | BD60: =R60 -> 408-733-6434 | BH60: 2 | BI60: SPT4700 | BJ60: 2 | BK60: 2 | BL60: 2 | BO60: 1 | BP60: 1 | BZ60: RHQ
A61: Arby's - Tustin | B61: MAITRE'D | C61: JS | F61: NO | I61: NO | P61: 43489 | Q61: Ken Wan | R61: 714-838-3830 | S61: 949-246-9100 | T61: 0.0775 | U61: 0.08 | V61: OR | W61: 13982 Newport Avenue | X61: Tustin | Y61: Ca | Z61: 92780 | AA61: bsumman@sbcglobal.net | AC61: akarbys@gmail.com | AY61: 13982 Newport Avenue | BA61: Tustin | BB61: Ca | BC61: 92780 | BD61: 714-838-3830 | BF61: 1411645 | BG61: 7.05 50 | BH61: 4 | BO61: mbr1200 | BQ61: Net ePay (sn: 8660.55.317846 | BR61: FDMS Cardnet CIT 5.06
A62: Arcangeli Grocery | B62: NCC | C62: AF | D62: SPT 4740 Win | F62: M-F | G62: 44196 | H62: 750 | I62: NO | L62: 43336 | M62: WORLDPAY | P62: 43620 | Q62: Chris | R62: 650-879-0147 | T62: 0.0875 | U62: 0.09 | V62: SM | W62: 287 Stage Road | X62: Pescadero | Y62: Ca | Z62: 94060 | AA62: mike@normsmarket.com | AD62: Mike Benedetti-owner | AF62: Umberto | AL62: 650-879-1825 | AO62: 54220 $51 | AV62: NO | AY62: 287 Stage Road | BA62: Pescadero | BB62: Ca | BC62: 94060 | BD62: 650-879-0147 | BH62: 3 | BI62: Spt4740 Win | BJ62: snbc 880 | BL62: none | BM62: client | BN62: client | BO62: mbr1200 | BP62: gs308 | BQ62: tran svr | BT62: dell t20 | BU62: win 7pro | BV62: Quest Tablet | BW62: L580 label | BX62: ics250 | BZ62: Insight
A63: Archive Bar & Kitchen | C63: RF | F63: NO | I63: NO | L63: 43473 | M63: STERLING | N63: RHQ | P63: 43206 | Q63: Gabe Bryant | R63: 415-987-5770 | S63: 415-385-2891 | T63: 0.085 | U63: 0.0875 | V63: SF | W63: 602 Mission Street | X63: San Francisco | Y63: Ca | Z63: 94105 | AA63: GABRIEL@ARCHIVEBARSF.COM | AO63: 54220 $49 | AQ63: CC235 $39 | AR63: 62245 $37 | AV63: PICKUP/YES | AY63: 602 Mission Street | BA63: San Francisco | BB63: Ca | BC63: 94105 | BD63: 415-987-5770 | BH63: 2
A64: Arizmendi Bakery - Emeryville | B64: ECR | C64: AH | F64: NO | I64: NO | Q64: Manager | R64: 510-547-0550 | T64: 0.095 | U64: 0.095 | V64: Emery | W64: 4301 San Pablo Avenue | X64: Emeryville | Y64: Ca | Z64: 94608 | AY64: 4301 San Pablo Avenue | BA64: Emeryville | BB64: Ca | BC64: 94608 | BD64: 510-547-0550
A65: Arizmendi Bakery - Oakland | B65: ECR | C65: AH | D65: Sharp UP-700 | F65: NO | I65: NO | L65: 43025 | Q65: James Haddow | R65: 510-268-8849 | T65: 0.0925 | U65: 0.095 | V65: ALA | W65: 3265 Lakeshore Avenue | X65: Oakland | Y65: Ca | Z65: 94610 | AO65: 54220 $49 | AV65: YES | AY65: 3265 Lakeshore Avenue | BA65: Oakland | BB65: Ca | BC65: 94610 | BD65: 510-268-8849
A66: Armando's Bar & Grill | B66: MAITRE'D | C66: JS | F66: NO | I66: NO | L66: 44022 | P66: 44000 | Q66: Armando Alvarez | R66: 760-346-0744 | S66: 760-972-7118 | T66: 0.0775 | U66: 0.08 | V66: RIVER | W66: 73260 El Paseo #1A | X66: Palm Desert | Y66: Ca | Z66: 92260 | AA66: armandononi@hotmail.com | AC66: jysrosales2@msn.com | AL66: 760-346-0741 | AN66: amandaalvarez89@gmail.com | AO66: 54220 $57 | AP66: 13305 $29 | AQ66: 15185 $35 | AR66: 62245 $45 | AV66: YES | AY66: 73260 El Paseo #1A | BA66: Palm Desert | BB66: Ca | BC66: 92260 | BD66: 760-346-0744 | BF66: 1413296 | BH66: 2
A67: A'Roma Ristorante | B67: MAITRE'D | C67: JS | F67: NO | I67: NO | P67: 42758 | Q67: Louis R. Ferrari | R67: 714-523-3729 | T67: 0.0875 | U67: 0.08 | V67: LaPalma | W67: 30 Center Pointe Drive #1 | X67: La Palma | Y67: Ca | Z67: 90623 | AA67: info@aromalapalma.com | AL67: 714-523-0014 | AY67: 30 Center Pointe Drive #1 | BA67: La Palma | BB67: Ca | BC67: 90623 | BD67: (714) 523-3729 | BF67: 1404780 | BG67: 2005 SP4 HF11 | BH67: 4
A68: Art Without Labels | B68: ECR | C68: AH | D68: TEC MA600 | F68: NO | I68: NO | Q68: Susan | R68: 707-775-3794 | T68: 0.0825 | U68: 0.0825 | V68: SON | W68: 111 Kentucky Street | X68: Petaluma | Y68: Ca | Z68: 94952 | AD68: Lorin | AY68: 111 Kentucky Street | BA68: Petaluma | BB68: Ca | BC68: 94952 | BD68: 707-775-3794 | BH68: 1
A69: Arteaga's Food Center - Lodi | B69: NCC | C69: AS | D69: 4740 | F69: M-F | G69: 44223 | H69: 450 | I69: NO | P69: 43551 | Q69: Alonzo Lopez | R69: 209-339-0399 | S69: 510-376-9832 | T69: 0.0825 | U69: 0.08 | V69: Lodi | W69: 200 E Oak Street | X69: Lodi | Y69: Ca | Z69: 95240 | AA69: alonzo@arteagas.com | AD69: Claudia | AE69: 707-318-6841 | AL69: 408-885-0808 | AY69: 200 E Oak Street | BA69: Lodi | BB69: Ca | BC69: 95240 | BD69: 209-339-0399
A70: Arteaga's Food Center - Newark | B70: NCC | C70: AS | F70: NO | I70: NO | L70: 44057 | P70: 43875 | Q70: Geraldo Lopez | R70: 510-791-1252 | S70: 510-364-8854 | T70: 0.0975 | U70: 0.095 | V70: Newark | W70: 5524 Thornton Avenue | X70: Newark | Y70: Ca | Z70: 94560 | AA70: glopez@arteagasfoodcenter.com | AD70: Lorena= A/P | AF70: Jose | AL70: 408-899-6939 | AM70: 510-744-0776 | AP70: 13305 $31.50 | AR70: 62245 $37 | AV70: NO | AY70: 5524 Thornton Avenue | BA70: Newark | BB70: Ca | BC70: 94560 | BD70: 510-791-1252 | BK70: model 57 | BV70: KVU
A71: Arya Global Cuisine - Cupertino | B71: MAITRE'D | C71: JS | D71: PT SP850 | F71: NO | I71: NO | L71: 43858 | P71: 43187 | Q71: Fera | R71: 408-996-9606 | S71: 408-334-3244 | T71: 0.09 | U71: 0.0875 | V71: Cuper | W71: 19930 Stevens Creek Blvd | X71: Cupertino | Y71: Ca | Z71: 95014 | AA71: aryaglobalcuisine@gmail.com | AB71: fera@aryarestaurant.com | AD71: Mike | AE71: 408-334-9399 | AF71: Vino | AG71: 714-425-1927 | AL71: 408-996-9607 | AO71: 54220 $58 | AP71: 13305 $31 | AQ71: CC235 $45 | AR71: 62245 $39 | AV71: NO | AY71: =PROPER(AZ71) -> 19930 Stevens Creek Blvd | AZ71: 19930 STEVENS CREEK BLVD | BA71: Cupertino | BB71: Ca | BC71: 95014 | BD71: 408-996-9606 | BF71: 1402542 | BG71: 7.05 | BH71: 2
A72: Arya Global Cuisine - RWC | B72: SUPPLY ONLY | C72: AH | F72: NO | I72: NO | L72: 43738 | Q72: Mike | R72: 650-367-4939 | T72: 0.0925 | U72: 0.0875 | V72: Redwood | W72: 885 Middlefield Road | X72: Redwood City | Y72: Ca | Z72: 94063 | AA72: aryaglobalcuisine@gmail.com | AB72: fera@aryarestaurant.com | AD72: Mike | AE72: 408-334-9399 | AL72: 408-996-9607 | AO72: 54220 $58 | AP72: 13305 $31 | AQ72: CC235 $45 | AR72: 62245 $39 | AV72: NO | AY72: 885 Middlefield Road | AZ72: 19930 STEVENS CREEK BLVD | BA72: Redwood City | BB72: Ca | BC72: 94063 | BD72: 650-367-4939
A73: Ashbury Tobacco Center | B73: SUPPLY ONLY | C73: AH | F73: NO | I73: NO | L73: 42829 | Q73: Mark | R73: 415-552-5556 | T73: 0.085 | U73: 0.0875 | V73: SF | W73: 1524 Haight Street | X73: San Francisco | Y73: Ca | Z73: 94117 | AO73: 54220 $49 | AV73: YES | AY73: 1524 Haight Street | BA73: San Francisco | BB73: Ca | BC73: 94117 | BD73: 415-552-5556
A74: Ashby Supermarket | B74: CASIO | C74: LG | D74: Casio QT6600 | F74: NO | I74: NO | Q74: Andre Hussein | R74: 510-647-3672 | S74: 510-213-1868 | T74: 0.0925 | U74: 0.095 | V74: ALA | W74: 2948 Martin Luther King Way | X74: Berkeley | Y74: Ca | Z74: 94703 | AY74: 2948 Martin Luther King Way | BA74: Berkeley | BB74: Ca | BC74: 94703 | BD74: 510-647-3672 | BH74: 1
A75: Atlas Café | B75: NCC | C75: AF | D75: SPT3000 | F75: NO | I75: NO | L75: 43333 | M75: WORLDPAY | P75: 43178 | Q75: Bill Stone | R75: 415-648-1047 | S75: 415-999-6274 | T75: 0.085 | U75: 0.0875 | V75: SF | W75: 3049 20th Street | X75: San Francisco | Y75: Ca | Z75: 94110 | AO75: 54220 $59 | AP75: 13305 $39 | AQ75: 54170 $75 | AR75: 62245 $37 | AV75: NO | AY75: =PROPER(AZ75) -> 3049 20Th Street | AZ75: 3049 20TH STREET | BA75: San Francisco | BB75: Ca | BC75: 94110 | BD75: 415-648-1047 | BH75: 1 | BK75: CRS 57
A76: Atwater Tavern | B76: SUPPLY ONLY | C76: RF | D76: Aloha | F76: NO | I76: NO | L76: 44068 | Q76: John Caine | R76: 415-512-7153 | T76: 0.085 | U76: 0.0875 | V76: SF | W76: 295 Terry A Francois Blvd | X76: San Francisco | Y76: Ca | Z76: 94158 | AA76: fanny@atwatertavern.com | AB76: jameson@mas.us.com | AC76: john@atwatertavern.com | AD76: Fanny Murith | AM76: Jameson AP | AO76: 54220 $55 | AP76: 13305 $35 | AQ76: CC235 $39 | AR76: 62245 $27 | AV76: YES | AY76: 289 Terry A Francois Blvd | BA76: San Francisco | BB76: Ca | BC76: 94158 | BD76: 415-512-7153
A77: Auto City | B77: SUPPLY ONLY | C77: AH | F77: NO | I77: NO | L77: 43844 | P77: 43844 | Q77: Roberto | R77: 415-713-5409 | T77: 0.085 | V77: SF | W77: 501 South Van Ness Avenue | X77: San Francisco | Y77: Ca | Z77: 94110 | AO77: 63544 $25 | AP77: 15157 $57 | AR77: 61085 $6ea | AV77: YES | AY77: 501 South Van Ness Avenue | BA77: San Francisco | BB77: Ca | BC77: 94110 | BD77: 415-713-5409
A78: Avedano's Meats | B78: ECR | C78: RF | D78: Sam 520RT | F78: NO | I78: NO | Q78: Angela | R78: 415-285-6328 | T78: 0.085 | U78: 0.0875 | V78: SF | W78: 325 Cortland Avenue | X78: San Francisco | Y78: Ca | Z78: 94110 | AD78: Melanie | AY78: 325 Cortland Avenue | BA78: San Francisco | BB78: Ca | BC78: 94110 | BD78: 415-285-6328 | BH78: 1
A79: Back Of the House INC | B79: ALOHA | C79: RF | F79: 7x24 | G79: 44089 | I79: NO | P79: 43775 | Q79: Rodrigo | R79: 415-881-7020 | S79: 415-271-3947 | T79: 0.085 | U79: 0.0875 | V79: SF | W79: 1829 Union St | X79: San Francisco | Y79: Ca | Z79: 94123 | AA79: rodrigo@backofthehouseinc.com | AY79: 1829 Union St | BA79: San Francisco | BB79: Ca | BC79: 94123 | BD79: 415-881-7020
A80: Bagdad Café | B80: SUPPLY ONLY | C80: AH | F80: NO | I80: NO | L80: 43173 | Q80: Gilbert | R80: 760-257-3101 | T80: 0.0775 | V80: S BERN | W80: 46548 National Trails Hwy | X80: Newberry Springs | Y80: Ca | Z80: 92365 | AO80: 15303 $25 | AP80: 15157 $49 | AV80: YES | AY80: 46548 National Trails Hwy | BA80: Newberry Springs | BB80: Ca | BC80: 92365 | BD80: 760-257-3101
A81: Bagel Street Café - Alameda | B81: CASIO | C81: LG | D81: QT6600 | F81: NO | I81: NO | P81: 43521 | Q81: Hichan | R81: 510-219-5134 | T81: 0.0975 | U81: 0.095 | V81: Alam | W81: 2212-F SouthShore Crt | X81: Alameda | Y81: Ca | Z81: 94501 | AY81: 2212-F SouthShore Crt | BA81: Alameda | BB81: Ca | BC81: 94501 | BD81: 510-522-2838 | BH81: 2
A82: Bagel Street Café - Alamo | B82: CASIO | C82: LG | F82: NO | I82: NO | Q82: Thu Duong | R82: 925-552-0155 | T82: 0.0825 | U82: 0.085 | V82: CC | W82: 124 Alamo Plaza | X82: Alamo | Y82: Ca | Z82: 94507 | AY82: 124 Alamo Plaza | BA82: Alamo | BB82: Ca | BC82: 94507 | BD82: 925-552-0155
A83: Bagel Street Café - Berkeley | B83: CASIO | C83: LG | F83: NO | I83: NO | Q83: Sam | R83: 510-704-0199 | T83: 0.0925 | U83: 0.095 | V83: ALA | W83: 2148 Center St | X83: Berkeley | Y83: Ca | Z83: 94704 | AY83: 2148 Center St | BA83: Berkeley | BB83: Ca | BC83: 94704 | BD83: 510-704-0199
A84: Bagel Street Café - Cupertino | B84: CASIO | C84: LG | F84: NO | I84: NO | Q84: Manager | R84: 408-873-7882 | T84: 0.09 | U84: 0.095 | V84: Cuper | W84: 10591 N Deanza Blvd | X84: Cupertino | Y84: Ca | Z84: 95014 | AY84: 10591 N Deanza Blvd | BA84: Cupertino | BB84: Ca | BC84: 95014 | BD84: 408-873-7882
A85: Bagel Street Café - Cupertino | B85: CASIO | C85: LG | D85: TE 8500 | F85: NO | I85: NO | Q85: Porlay Phal | R85: 408-596-0548 | T85: 0.09 | U85: 0.0875 | V85: Cuper | W85: 10591 N. De Anza Blvd | X85: Cupertino | Y85: Ca | Z85: 95014 | AY85: 10591 N De Anza Blvd. | BA85: Cupertino | BB85: Ca | BC85: 95014 | BD85: 408-596-0548
A86: Bagel Street Café - Danville | B86: CASIO | C86: LG | D86: Casio TE8500 | F86: NO | I86: NO | Q86: Connie/Tony | R86: 925-831-9318 | T86: 0.0825 | U86: 0.095 | V86: CC | W86: 316 Sycamore Valley Road W | X86: Danville | Y86: Ca | Z86: 94526 | AY86: 316 Sycamore Valley Road W | BA86: Danville | BB86: Ca | BC86: 94526 | BD86: 925-831-9318 | BH86: 1
A87: Bagel Street Café - Dublin | B87: CASIO | C87: LG | F87: NO | I87: NO | Q87: Davi Lune | R87: 925-829-5758 | T87: 0.0925 | U87: 0.095 | V87: ALA | W87: 4101 Dublin Blvd Suite A | X87: Dublin | Y87: Ca | Z87: 94568 | AY87: 4101 Dublin Blvd Suite A | BA87: Dublin | BB87: Ca | BC87: 94568 | BD87: 925-829-5758
A88: Bagel Street Café - Menlo Park | B88: CASIO | C88: LG | F88: NO | I88: NO | Q88: Kien Ly | R88: 650-328-8809 | T88: 0.0875 | U88: 0.09 | V88: SM | W88: 746 Santa Cruz Ave | X88: Menlo Park | Y88: Ca | Z88: 94025 | AY88: 746 Santa Cruz Ave | BA88: Menlo Park | BB88: Ca | BC88: 94025 | BD88: 650-328-8809
A89: Bagel Street Café - Millbrae | B89: ECR | C89: AH | D89: TEC FS1450 | F89: NO | I89: NO | L89: 43266 | Q89: Sun Huynh | R89: 650-652-9700 | T89: 0.0875 | U89: 0.09 | V89: SM | W89: 537 Broadway | X89: Millbrae | Y89: Ca | Z89: 94030 | AE89: 650-652-9400 | AO89: 15185 $58 | AR89: 67655 $39 | AV89: YES | AY89: =PROPER(AZ89) -> 537 Broadway | AZ89: 537 BROADWAY | BA89: Millbrae | BB89: Ca | BC89: 94030 | BD89: 650-652-9700 | BH89: 1
A90: Bagel Street Café - Mountain View | B90: CASIO | C90: LG | F90: NO | I90: NO | Q90: Manager | R90: 650-988-0288 | T90: 0.0875 | U90: 0.09 | V90: SM | W90: 1049 El Monte Ave. Ste. E | X90: Mountain View | Y90: Ca | Z90: 94040 | AY90: 1049 El Monte Ave. Ste. E | BA90: Mountain View | BB90: Ca | BC90: 94040 | BD90: 650-988-0288
A91: Bagel Street Café - Northgate | B91: CASIO | C91: LG | F91: NO | I91: NO | Q91: Manager | R91: 415-479-5000 | T91: 0.09 | U91: 0.0925 | V91: San Raf | W91: 208 Northgate One | X91: San Rafael | Y91: Ca | Z91: 94903 | AY91: 208 Northgate One | BA91: San Rafael | BB91: Ca | BC91: 94903 | BD91: 415-479-5000
A92: Bagel Street Café - Oakland | B92: CASIO | C92: LG | F92: NO | I92: NO | Q92: Connie | R92: 510-891-9831 | T92: 0.0925 | U92: 0.095 | V92: ALA | W92: 501 14th St | X92: Oakland | Y92: Ca | Z92: 94612 | AY92: 501 14th St | BA92: Oakland | BB92: Ca | BC92: 94612 | BD92: 510-891-9831
A93: Bagel Street Café - Pleasanton | B93: CASIO | C93: LG | D93: Casio TE8500 | F93: NO | I93: NO | Q93: Evelyn | R93: 925-462-6100 | T93: 0.0925 | U93: 0.095 | V93: ALA | W93: 3550 Sany Blvd Suite 4 | X93: Pleasanton | Y93: Ca | Z93: 94566 | AY93: 3550 Sany Blvd Suite 4 | BA93: Pleasanton | BB93: Ca | BC93: 94566 | BD93: 925-462-6100
A94: Bagel Street Café - San Jose | B94: CASIO | C94: LG | F94: NO | I94: NO | Q94: Manager | R94: 408-873-7882 | T94: 0.0925 | U94: 0.09 | V94: SanJose | W94: 3821 Higuera Rd | X94: San Jose | Y94: Ca | Z94: 95148 | AY94: 3821 Higuera Rd | BA94: San Jose | BB94: Ca | BC94: 95148 | BD94: 408-873-7882
A95: Bagel Street Café - San Ramon | B95: SUPPLY ONLY | C95: RF | F95: NO | I95: NO | Q95: Danielle | R95: 925-973-9888 | S95: 408-768-8053 | T95: 0.0825 | U95: 0.095 | V95: CC | W95: 142 Sunset Drive | X95: San Ramon | Y95: Ca | Z95: 94583 | AY95: 142 Sunset Drive | BA95: San Ramon | BB95: Ca | BC95: 94583 | BD95: 925-973-9888 | BH95: 1 | BI95: SPT3000 | BJ95: BTP-R880NP (USB) | BK95: 60 | BL95: TMU220B (ser) | BM95: Fusion (USB)
A96: Bagel Street Café - Sunnyvale | B96: CASIO | C96: LG | D96: Casio TE8500 | F96: NO | I96: NO | Q96: Connie | R96: 418-738-1856 | T96: 0.09 | U96: 0.0875 | V96: SC | W96: 346 W Maude Ave | X96: Sunnyvale | Y96: Ca | Z96: 94085 | AY96: 346 W Maude Ave | BA96: Sunnyvale | BB96: Ca | BC96: 94085 | BD96: 418-738-1856 | BH96: 1
A97: Bagel Street Café - Tracy | B97: CASIO | C97: LG | D97: Casio QT6600 | F97: NO | I97: NO | Q97: Minh | R97: 925-785-6443 | T97: 0.0825 | U97: 0.08 | V97: Tracy | W97: 1875 Eleventh St | X97: Tracy | Y97: Ca | Z97: 95376 | AY97: 1875 Eleventh St | BA97: Tracy | BB97: Ca | BC97: 95376 | BD97: 925-785-6443 | BH97: 2
A98: Baja Fresh- Corte Madera | B98: SUPPLY ONLY | C98: AH | F98: NO | I98: NO | L98: 43626 | Q98: Adan | R98: 415-924-8522 | T98: 0.0875 | V98: CM | W98: 205 Corte Madera Town Center | X98: Corte Madera | Y98: Ca | Z98: 94925 | AA98: adan@electrawarehouse.com | AO98: 54220 $49 | AP98: 13305 $31 | AR98: 62245 $41 | AT98: L100 $35 | AV98: YES | AY98: 205 Corte Madera Town Center | BA98: Corte Madera | BB98: Ca | BC98: 94925 | BD98: 415-924-8522
A99: Baja Fresh- Reno | B99: SUPPLY ONLY | C99: AH | F99: NO | I99: NO | L99: 43544 | Q99: Adan | R99: 775-826-8900 | T99: 0 | V99: O/S | W99: 5140 Kietzke Lane Ste A | X99: Reno | Y99: NV | Z99: 89511 | AA99: adan@electrawarehouse.com | AO99: 54220 $49 | AP99: 13305 $31 | AR99: 62245 $41 | AT99: 27710P1606N $35 | AV99: YES | AY99: 5140 Kietzke Lane Ste A | BA99: Reno | BB99: NV | BC99: 89511 | BD99: 775-826-8900
A100: Baja Fresh- S. Lake Tahoe | B100: SUPPLY ONLY | C100: AH | F100: NO | I100: NO | L100: 43528 | Q100: Adan | R100: 530-544-1886 | T100: 0.0775 | V100: EL DOR | W100: 4000 Lake Tahoe Blvd #25 | X100: S. Lake Tahoe | Y100: Ca | Z100: 96150 | AA100: adan@electrawarehouse.com | AO100: 54220 $49 | AP100: 13305 $31 | AT100: L90-2T $64 | AV100: YES | AY100: 4000 Lake Tahoe Blvd #25 | BA100: S. Lake Tahoe | BB100: Ca | BC100: 96150 | BD100: 530-544-1886
...

Sheet SUPPLY ITEMS
C1: SUPPLY ITEMS
A4: Note: | B4: All prices are for pickup. Please add shipping fees below when using FEDEX
B5: Contact Supply dept for customized/discounted pricing schedule based on volume annual purchases
A8: MOST COMMON | D8: All prices are for pickup. Please add shipping fees below
B10: 1 | C10: # 54-220 | D10: Epson Thermal | F10: 3 1/8 x 220' | I10: 50 rolls | J10: 49 | K10: =B10*J10 -> 49
B11: 1 | C11: # 13-305 | D11: Epson Impact | F11: 3" one ply x 165 | I11: 50 rolls | J11: 29 | K11: =B11*J11 -> 29
B12: 1 | C12: # 62245 | D12: Epson 220 Ink | F12: black/red ribbons | I12: Per Dozen | J12: 39 | K12: =B12*J12 -> 39
B14: 1 | C14: # CC-235 | D14: Epson Impact | F14: 3" two ply x 95' | I14: 50 rolls | J14: 39 | K14: =B14*J14 -> 39
B16: 1 | C16: # 15-157 | D16: Cash Reg- Thermal | F16: 2.25" x 230 feet | I16: 50 rolls | J16: 49 | K16: =B16*J16 -> 49
B17: 1 | C17: # 44-150 | D17: Cash Reg- Impact | F17: 44mm x 150 ft | I17: 80 rolls | J17: 25 | K17: =B17*J17 -> 25
B19: 1 | C19: # 15-740 | D19: CC Machine | F19: 2.25" x 70 feet | I19: 100 rolls | J19: 49 | K19: =B19*J19 -> 49
B20: 1 | C20: # 15-745 | D20: CC Machine | F20: 2.25" x 70 feet | I20: 50 rolls | J20: 29 | K20: =B20*J20 -> 29
B21: 1 | C21: # 15-185 | D21: CC Machine | F21: 2 1/4 x 85' thermal | I21: 50 rolls | J21: 35 | K21: =B21*J21 -> 35
B23: 1 | C23: # 46-175 | D23: Epson Thermal | F23: 3 1/8" heavy duty | I23: 50 rolls | J23: 69 | K23: =B23*J23 -> 69
B24: 1 | C24: # 54-273 | D24: Epson Thermal | F24: 3 1/8 x 273'- xlong | I24: 50 rolls | J24: 69 | K24: =B24*J24 -> 69
B26: 1 | C26: # 62235 | D26: Epson 220 Ink | F26: black ribbons | I26: Per Dozen | J26: 39 | K26: =B26*J26 -> 39
B27: 1 | C27: # 67240 | D27: STAR SP700/712 | F27: black/red ribbons | I27: Per Dozen | J27: 39 | K27: =B27*J27 -> 39
A30: PAPER | D30: All prices are for pickup. Please add shipping fees below
B31: 1 | C31: # 12-100 | D31: one ply paper | F31: 2 1/4" x 150 feet | I31: 100 rolls | J31: 49 | K31: =B31*J31 -> 49
B32: 1 | C32: # 13-304 | D32: one ply paper | F32: 2 3/4" x 165 feet | I32: 50 rolls | J32: 29 | K32: =B32*J32 -> 29
B33: 1 | C33: # 13-305C | D33: one ply paper | F33: 3" one ply canary | I33: 50 rolls | J33: 49 | K33: =B33*J33 -> 49
B34: 1 | C34: # 13-305G | D34: one ply paper | F34: 3" one ply green | I34: 50 rolls | J34: 49 | K34: =B34*J34 -> 49
B35: 1 | C35: # 13-450 | D35: one ply paper | F35: 4 1/2" x 165 feet | I35: 50 rolls | J35: 52.5 | K35: =B35*J35 -> 52.5
B36: 1 | C36: # 15-044 | D36: thermal paper | F36: 44mm x 230 feet | I36: 50 rolls | J36: 39 | K36: =B36*J36 -> 39
B37: 1 | C37: # 15-157 | D37: 2 1/4 x 230'thermal | F37: Cash Reg- Thermal | I37: 50 rolls | J37: 49 | K37: =B37*J37 -> 49
B38: 1 | C38: # 15-160 | D38: 2 1/4 x 60' thermal | F38: Verifone Thermal | I38: 50 rolls | J38: 29 | K38: =B38*J38 -> 29
B39: 1 | C39: # 15-185 | D39: 2 1/4 x 85' thermal | F39: Verifone Thermal | I39: 50 rolls | J39: 35 | K39: =B39*J39 -> 35
B40: 1 | C40: # 15-303 | D40: thermal paper | F40: 2.25" x 42 feet | I40: 48 rolls | J40: 29 | K40: =B40*J40 -> 29
B41: 1 | C41: # 15-740 | D41: CC Machine | F41: 2.25" x 70 feet | I41: 100 rolls | J41: 49 | K41: =B41*J41 -> 49
B42: 1 | C42: # 15-745 | D42: CC Machine | F42: 2.25" x 70 feet | I42: 50 rolls | J42: 29 | K42: =B42*J42 -> 29
... B63: 1 | C63: # CC-235 | D63: 3" TWO ply | F63: Epson TMU-220 | I63: 50 rolls | J63: 39 | K63: =B63*J63 -> 39
B65: 1 | C65: # 80340 | D65: Std Printer paper, 8 1/2 x 11", 500 sheet | I65: ea | J65: 10 | K65: =B65*J65 -> 10
B66: 1 | C66: # 80342 | D66: Legal Size Printer paper, 8 1/2 x 14", 500 sheet | I66: ea | J66: 12.5 | K66: =B66*J66 -> 12.5
B67: 1 | C67: # 85000 | D67: Colored Menu Paper | F67: 500 sheet | I67: ea | J67: 19.5 | K67: =B67*J67 -> 19.5
A70: RIBBONS | D70: All prices are for pickup. Please add shipping fees below
B71: 1 | C71: # 68915 | D71: purple ribbons | F71: Victor 600 | I71: Per Dozen | J71: 39 | K71: =B71*J71 -> 39
B72: 1 | C72: # 68905 | D72: black/red ribbons | F72: Victor 600 | I72: Per Dozen | J72: 39 | K72: =B72*J72 -> 39
B73: 1 | C73: # 68715 | D73: purple/red ribbons | F73: Veriphone 900 | I73: Per Dozen | J73: 39 | K73: =B73*J73 -> 39
B74: 1 | C74: # 68710 | D74: black/red ribbons | F74: Veriphone 900 | I74: Per Dozen | J74: 39 | K74: =B74*J74 -> 39
B75: 1 | C75: # 68705 | D75: purple ribbons | F75: Veriphone 900 | I75: Per Dozen | J75: 39 | K75: =B75*J75 -> 39
B76: 1 | C76: # 68045 | D76: purple/red ribbons | F76: Universal C Wind | I76: Per Dozen | J76: 39 | K76: =B76*J76 -> 39
B77: 1 | C77: # 68035 | D77: purple ribbons | F77: Universal C Wind | I77: Per Dozen | J77: 39 | K77: =B77*J77 -> 39
B78: 1 | C78: # 68015 | D78: black/red ribbons | F78: Tec RKP 200 | I78: Per Dozen | J78: 39 | K78: =B78*J78 -> 39
B79: 1 | C79: # 67655 | D79: #POS- 053 | F79: Tec 1450/1650 | I79: Per Dozen | J79: 39 | K79: =B79*J79 -> 39
B80: 1 | C80: # 67515 | D80: #POS-032 | F80: Tec 1040/1400 | I80: Per Dozen | J80: 39 | K80: =B80*J80 -> 39
B81: 1 | C81: # 67240 | D81: black/red ribbons | F81: STAR SP700/712 | I81: Per Dozen | J81: 39 | K81: =B81*J81 -> 39
B82: 1 | C82: # 67215 | D82: # POS-029 | F82: Tec RKP300 | I82: Per Dozen | J82: 39 | K82: =B82*J82 -> 39
... B135: 1 | C135: # 40093 | D135: black/red ribbons | F135: Cit IR 41 | I135: Per Dozen | J135: 39 | K135: =B135*J135 -> 39
K136: =B136*J136 -> 0
B137: 1 | C137: # 70155 | D137: ink roller | F137: m-93 | I137: Each | J137: 8 | K137: =B137*J137 -> 8
B138: 1 | C138: # 70105 | D138: ink roller | F138: IR 40 | I138: Each | J138: 8 | K138: =B138*J138 -> 8
B139: 1 | C139: # 70135 | D139: ink roller IR 90/91 | F139: Sharp ER-320 | I139: Each | J139: 8 | K139: =B139*J139 -> 8
B140: 1 | C140: # 70195 | D140: ink roller | F140: NCR 2113/2123/2127 | I140: Each | J140: 8 | K140: =B140*J140 -> 8
B141: 1 | C141: # 70145 | D141: ink roller | F141: IR 74 | I141: Each | J141: 8 | K141: =B141*J141 -> 8
B142: 1 | C142: # 70215 | D142: ink roller | F142: NCR 2114 | I142: Each | J142: 8 | K142: =B142*J142 -> 8
B143: 1 | C143: # 70175 | D143: ink roller | F143: Casio M2122 | I143: Each | J143: 8 | K143: =B143*J143 -> 8
B144: 1 | C144: # 70225 | D144: ink roller | F144: NCR 2117 | I144: Each | J144: 8 | K144: =B144*J144 -> 8
B145: 1 | C145: # 70245 | D145: ink roller | F145: IR 212 | I145: Each | J145: 8 | K145: =B145*J145 -> 8
B146: 1 | C146: # 70255 | D146: ink roller | F146: IR 213 Tec230/290 | I146: Each | J146: 8 | K146: =B146*J146 -> 8
B147: 1 | C147: # 70265 | D147: ink roller | F147: IR 214 Tec 140/190 | I147: Each | J147: 8 | K147: =B147*J147 -> 8
B148: 1 | C148: # 70275 | D148: ink roller | F148: IR 208 Tec 2200 | I148: Each | J148: 8 | K148: =B148*J148 -> 8
A151: TONER | D151: All prices are for pickup. Please add shipping fees below
B153: 1 | C153: # 27710M225N | E153: Toner | F153: HE-7-CF283A | I153: ea | J153: 55 | K153: =B153*J153 -> 55
B154: 1 | C154: # 177101260 | E154: Toner | F154: DELL 7-331-7328 | I154: ea | J154: 55 | K154: =B154*J154 -> 55
B155: 1 | C155: # 27710M102N | E155: Toner | F155: HE-7-CF-217A-N | I155: ea | J155: 55 | K155: =B155*J155 -> 55
B156: 1 | C156: # 70245 | E156: Toner | F156: RICOH 320 | I156: ea | J156: 55 | K156: =B156*J156 -> 55
B157: 1 | C157: # 408288 | E157: Toner | F157: RICOH 330 | I157: ea | J157: 125 | K157: =B157*J157 -> 125
B159: 1 | C159: 27721M102N | E159: Drum | F159: CF-219A 12K Yield | I159: ea | J159: 70 | K159: =B159*J159 -> 70
A162: LABELS | D162: All prices are for pickup. Please add shipping fees below
B163: 1 | C163: # 1612-B | D163: Tec Sl9000/SL5300 | F163: continuous | J163: 49 | K163: =B163*J163 -> 49
B164: 1 | C164: # 1681 | D164: Tec Sl9000/SL5300 | F164: 57mm x 49.2 mm | H164: UPC | J164: 49 | K164: =B164*J164 -> 49
B166: 1 | C166: # 1478 | D166: Cas | F166: 58mm x 60mm | H166: S/H | J166: 39 | K166: =B166*J166 -> 39
B167: 1 | C167: # 1493 | D167: Cas | F167: 58mm x 40 mm | J167: 39 | K167: =B167*J167 -> 39
B168: 1 | C168: # 1477 | D168: Cas | F168: 58mm x 60mm | H168: Ingredient | J168: 39 | K168: =B168*J168 -> 39
B170: 1 | C170: # 1433B | D170: Berkel 65mm | F170: Scale Labels | J170: 49 | K170: =B170*J170 -> 49
B172: 1 | C172: # TH-379 | D172: Hobart- Quantum | F172: Continuous 2.25" x 3250 | J172: 149 | K172: =B172*J172 -> 149
B173: 1 | C173: # TH-382 | D173: Hobart- Quantum | F173: Continuous 1.625" x 3420 | J173: 149 | K173: =B173*J173 -> 149
B174: 1 | C174: # 1909 | D174: Hobart- Quantum | F174: 1.75" | H174: 1600/roll | J174: 139 | K174: =B174*J174 -> 139
B175: 1 | C175: # 1911 | D175: Hobart- Quantum | F175: 3" | H175: 1000/roll | J175: 139 | K175: =B175*J175 -> 139
B177: 1 | C177: # 61670 | D177: Datamax- Direct Thermal | I177: 4 rolls/cs | J177: 89 | K177: =B177*J177 -> 89
B178: 1 | C178: # 61670 | D178: Datamax- Direct Thermal | I178: per roll | J178: 25 | K178: =B178*J178 -> 25
B180: 1 | C180: # MaxStick | F180: 3 1/8" x 3.25 diam | H180: per roll | J180: 15 | K180: =B180*J180 -> 15
B181: 1 | C181: # Shelf Tag Labels 3" x 1" | F181: 3" x 1" | H181: per roll | J181: 7.5 | K181: =B181*J181 -> 7.5
B182: 1 | C182: # Shelf Tag -Godex 2.25" x 1.25" | F182: 3" x 1" | H182: per roll | J182: 19.5 | K182: =B182*J182 -> 19.5
A184: ID CARDS/BADGE/misc | D184: All prices are for pickup. Please add shipping fees below
B185: 1 | C185: # CARD-MD | F185: Mag swipe ID card | J185: 1.95 | K185: =B185*J185 -> 1.95
B186: 1 | C186: # CARD-NCC | F186: Mag swipe ID card | J186: 1.95 | K186: =B186*J186 -> 1.95
B187: 1 | C187: # CARD-MICROS | F187: Mag swipe ID card | J187: 1.95 | K187: =B187*J187 -> 1.95
B189: 1 | C189: # REEL-BLACK | F189: Black retractable reel for ID card | J189: 1.95 | K189: =B189*J189 -> 1.95
B191: 1 | C191: # HOLDER | F191: Clear plastic holder for ID card | J191: 1.95 | K191: =B191*J191 -> 1.95
B193: 1 | C193: # MSR CLEANER CARDS | I193: ea | J193: 1.5 | K193: =B193*J193 -> 1.5
B194: 1 | C194: # DATAMAX CLEANER CARDS | I194: ea | J194: 1.5 | K194: =B194*J194 -> 1.5
B195: 1 | C195: # THERMAL PRT CLEANER CARDS | I195: ea | J195: 1.5 | K195: =B195*J195 -> 1.5
B196: 1 | C196: # THERMAL HEAD CLEANING PEN | I196: ea | J196: 4.75 | K196: =B196*J196 -> 4.75
B197: 1 | C197: # COMPRESSED GAS CLEANER CAN | I197: ea | J197: 9.5 | K197: =B197*J197 -> 9.5
B198: 1 | C198: # PCK PRINTER CLEANING KIT | I198: ea | J198: 15 | K198: =B198*J198 -> 15
A201: Tills | D201: All prices are for pickup. Please add shipping fees below
B203: 1 | C203: MS-CF460 Till | E203: Black Plastic Money Tray | J203: 50 | K203: =B203*J203 -> 50
B204: 1 | C204: MS-SP103 Till | E204: Black Plastic Money Tray | J204: 50 | K204: =B204*J204 -> 50
B205: 1 | C205: Sam4S | D205: Model 57 | E205: Black Plastic Money Tray | J205: 50 | K205: =B205*J205 -> 50
...

Sheet EQUIP
B1: Qty | D1: Equipment (Taxable) | J1: Price | K1: Ext
C3: Note: The following are the standard, everyday unit pricing for each individual item.
C4: Discounts are available when compiling a quote for a full system with many components.
C5: Please seek assistance in preparing such a full system quote
C7: NCC embedded POS Workstations (does not include sw)
B8: 1 | C8: NCC /CRS Touchscreen station, embedded | J8: 1095 | K8: =B8*J8 -> 1095
B9: 1 | C9: NCC / Acrobat Touchscreen station, embedded | J9: 1095 | K9: =B9*J9 -> 1095
B11: 1 | C11: NCC Reflections R4 POS software (purchase option) | J11: 650 | K11: =B11*J11 -> 650
B12: 1 | C12: NCC Reflections R4 EFT Interface (purchase option) | J12: 475 | K12: =B12*J12 -> 475
B14: 1 | C14: NCC Retail Bundle, inc WS, Prt, Cd, Scan,POS sw, Msr, Std Database | J14: 2995 | K14: =B14*J14 -> 2995
B15: 1 | C15: NCC Hosp Bundle, inc WS, Prt, Cd ,Rkp, POS sw, Msr, Std Database | J15: 2995 | K15: =B15*J15 -> 2995
B17: 1 | C17: NCC SPT 45/47 workstation, with R4 software, reconditioned | J17: 695 | K17: =B17*J17 -> 695
B18: 1 | C18: NCC SPT3000 15" POS workstation, inc msr & POS SW, reconditioned | J18: 695 | K18: =B18*J18 -> 695
B19: 1 | C19: NCC BREEZE 15" POS workstation, inc msr & POS SW, reconditioned | J19: 695 | K19: =B19*J19 -> 695
B20: 1 | C20: NCC Acrobat POS workstation, inc msr & POS SW, reconditioned | J20: 695 | K20: =B20*J20 -> 695
B21: 1 | C21: NCC 5700 15" POS workstation, inc msr & POS SW, reconditioned | J21: 695 | K21: =B21*J21 -> 695
B22: 1 | C22: NCC Protech 10" POS workstation, inc msr & POS SW, reconditioned | J22: 695 | K22: =B22*J22 -> 695
B24: 1 | C24: Trade-In Credit for NCC workstation, repairable condition | J24: -325 | K24: =B24*J24 -> -325
C27: Windows POS Workstations ( does not include software)
B29: 1 | C29: Partnertech SP850 POS workstation, Win 10 | J29: 1695 | K29: =B29*J29 -> 1695
B30: 1 | C30: PAR 6155 Landscape workstation, Win 10 | J30: 1495 | K30: =B30*J30 -> 1495
B31: 1 | C31: CRS Windows Touchscreen station, Win 10 | J31: 1295 | K31: =B31*J31 -> 1295
B33: 1 | C33: CAS RX-750 POS workstation, reconditioned, POS Ready 7 | J33: 695 | K33: =B33*J33 -> 695
B34: 1 | C34: SHARP RX-650 POS workstation, reconsitioned, POS Ready 9 | J34: 495 | K34: =B34*J34 -> 495
B35: 1 | C35: PARTNERTECH SP800, reconditioned, POS Ready 7 | J35: 695 | K35: =B35*J35 -> 695
B36: 1 | C36: PIONEER WORKSTATION, reconditioned, POS Ready 7 | J36: 695 | K36: =B36*J36 -> 695
B38: 1 | C38: Swap Credit for Windows POS Ready 7 workstation, repairable | J38: -325 | K38: =B38*J38 -> -325
B39: 1 | C39: Swap Credit for Windows POS Ready 9 workstation, repairable | J39: -100 | K39: =B39*J39 -> -100
C41: Windows POS Tablets ( does not include software)
B42: 1 | C42: NCC Hisense Tablet station, Windows w/strap | J42: 995 | K42: =B42*J42 -> 995
B43: 1 | C43: NCC Hisense Tablet- docking station | J43: 195 | K43: =B43*J43 -> 195
B44: 1 | C44: NCC Hisense Tablet- add scanner | J44: 195 | K44: =B44*J44 -> 195
B46: 1 | C46: Touchdynamic Quest Tablet Station, Windows, w/strap | J46: 1495 | K46: =B46*J46 -> 1495
B47: 1 | C47: Touchdynamic Quest - Docking Station | J47: 295 | K47: =B47*J47 -> 295
B48: 1 | C48: Touchdynamic Quest - Add EMV | J48: 295 | K48: =B48*J48 -> 295
B49: 1 | C49: Touchdynamic Quest - Add Scanner | J49: 195 | K49: =B49*J49 -> 195
C52: POS Printers
B54: 1 | C54: SNBC Thermal Receipt Printer, serial / USB/ ether | J54: 250 | K54: =B54*J54 -> 250
B55: 1 | C55: Epson TMT88 VI thermal receipt printer, serial / usb/ ether | J55: 325 | K55: =B55*J55 -> 325
B57: 1 | C57: Epson TMU220b SERIAL impact remote printer (cut) | J57: 295 | K57: =B57*J57 -> 295
B58: 1 | C58: Epson TMU220b ETHERNET impact remote printer (cut) | J58: 345 | K58: =B58*J58 -> 345
B59: 1 | C59: Epson TMU220d SERIAL impact remote printer (tear) | J59: 250 | K59: =B59*J59 -> 250
B62: 1 | C62: SNBC Thermal Receipt Printer, serial, RECONDITIONED | J62: 175 | K62: =B62*J62 -> 175
B63: 1 | C63: Epson TMT88 V thermal receipt printer, serial, RECONDITIONED | J63: 245 | K63: =B63*J63 -> 245
B64: 1 | C64: Epson TMT88 IV thermal receipt printer, serial, RECONDITIONED | J64: 195 | K64: =B64*J64 -> 195
B65: 1 | C65: Epson TMT88 iii thermal receipt printer, serial, RECONDITIONED | J65: 150 | K65: =B65*J65 -> 150
B67: 1 | C67: Epson 220b impact remote printer, serial, RECONDITIONED | J67: 225 | K67: =B67*J67 -> 225
B68: 1 | C68: Epson 220d impact remote printer, serial, RECONDITIONED | J68: 175 | K68: =B68*J68 -> 175
B70: 1 | C70: Trade-In Credit for EPSON TMT88 VI printer, repairable condition | J70: -95 | K70: =B70*J70 -> -95
... B83: 1 | C83: Datamax M-Class 4" Label Printer, RECONDITIONED | J83: 895 | K83: =B83*J83 -> 895
C86: POS Cash Drawers
B88: 1 | C88: MS 460 cash drawer, epson interface | J88: 175 | K88: =B88*J88 -> 175
B89: 1 | C89: MS 125 cash drawer, epson interface | J89: 225 | K89: =B89*J89 -> 225
B90: 1 | C90: MS 1313 cash drawer, epson interface | J90: 150 | K90: =B90*J90 -> 150
B91: 1 | C91: MS 405 cash drawer, epson interface | J91: 150 | K91: =B91*J91 -> 150
B93: 1 | C93: CRS cash drawer, epson interface | J93: 145 | K93: =B93*J93 -> 145
B95: 1 | C95: MS 460 cash drawer, epson interface, RECONDITIONED | J95: 95 | K95: =B95*J95 -> 95
B96: 1 | C96: CRS cash drawer, epson interface, RECONDITIONED | J96: 75 | K96: =B96*J96 -> 75
B98: 1 | C98: Dual Drawer Splitter Cable | J98: 15 | K98: =B98*J98 -> 15
C100: POS Peripherals
B102: 1 | C102: Internal Rear Customer Display, 2 x 20 | J102: 175 | K102: =B102*J102 -> 175
B103: 1 | C103: Internal Rear Customer Display, Multi-Line LCD | J103: 395 | K103: =B103*J103 -> 395
B104: 1 | C104: External Post Display, 2 x 20 | J104: 195 | K104: =B104*J104 -> 195
B105: 1 | C105: External Post Display, CRS multi-line | J105: 295 | K105: =B105*J105 -> 295
B107: 1 | C107: Integrated POS scale | J107: 795 | K107: =B107*J107 -> 795
B108: 1 | C108: Integrated Hand scanner, single line | J108: 295 | K108: =B108*J108 -> 295
B109: 1 | C109: Integrated Hand scanner, multi-line | J109: 395 | K109: =B109*J109 -> 395
B110: 1 | C110: Integrated Hand scanner, Wireless | J110: 595 | K110: =B110*J110 -> 595
B111: 1 | C111: Integrated Scanner/Scale | J111: 1995 | K111: =B111*J111 -> 1995
B113: 1 | C113: Biometric Fingerprint ID unit | J113: 195 | K113: =B113*J113 -> 195
B114: 1 | C114: INSIGHT inventory wireless management device with comm sw | J114: 2750 | K114: =B114*J114 -> 2750
B116: 1 | C116: Kitchen Video station with Bump Bar and LCD Monitor (non-touch) | J116: 1500 | K116: =B116*J116 -> 1500
... B121: 1 | C121: ELO Touchscreen AIO 22" widescreen, Win 10 ( req cvm sw added) | J121: 1895 | K121: =B121*J121 -> 1895
C124: Payments Processing
B126: 1 | C126: Datacap Twin-Tran Credit Auth Unit | J126: 1495 | K126: =B126*J126 -> 1495
B127: 1 | C127: Net-Epay CC processing Software | J127: 1495 | K127: =B127*J127 -> 1495
B129: 1 | C129: discount for choosing WorldPay/ Evo as payments processor | J129: -1495 | K129: =B129*J129 -> -1495
B131: 1 | C131: Datacap Gift E-Pay processing interface ( non-mercury) | J131: 495 | K131: =B131*J131 -> 495
B133: 1 | C133: Datacap Tran Cloud Processing Unit, Lane #1 , PER MONTH | J133: 49 | K133: =B133*J133 -> 49
B134: 1 | C134: Datacap Tran Cloud Processing Unit, Lane #2-x , PER MONTH | J134: 29 | K134: =B134*J134 -> 29
B136: 1 | C136: EMV- VX 805 with PDC | J136: 395 | K136: =B136*J136 -> 395
B137: 1 | C137: EMV- PAX S300 | J137: 495 | K137: =B137*J137 -> 495
B138: 1 | C138: EMV- PAX 920 Maitre'd Pay at Table, purchase | J138: 750 | K138: =B138*J138 -> 750
B139: 1 | C139: EMV- PAX 920 Maitre'd Pay at Table, per lane, per month | J139: 20 | K139: =B139*J139 -> 20
B141: 1 | C141: EMV- Ingenico Lane 3000 | J141: 495 | K141: =B141*J141 -> 495
B142: 1 | C142: EMV- Ingenico Tetra | J142: 495 | K142: =B142*J142 -> 495
... B145: 1 | C145: EMV- stand alone payment station | J145: 495 | K145: =B145*J145 -> 495
C147: Power Conditioner/UPS
B149: 1 | C149: Power Conditioner for Remote Printer, reconditioned | J149: 45 | K149: =B149*J149 -> 45
B150: 1 | C150: Power Conditioner for Workstation, reconditioned | J150: 75 | K150: =B150*J150 -> 75
B151: 1 | C151: Power Conditioner for Office/Server, reconditioned | J151: 195 | K151: =B151*J151 -> 195
B152: 1 | C152: Power Conditioner w/UPS for Office/Server, reconditioned | J152: 295 | K152: =B152*J152 -> 295
C154: Office Equipment
B156: 1 | C156: Dell File Server, Windows 10 Pro, kb,mouse, | J156: 995 | K156: =B156*J156 -> 995
B157: 1 | C157: Dell File Server,Windows 10 Pro, kb,mouse, reconditioned | J157: 495 | K157: =B157*J157 -> 495
B158: 1 | C158: NCC online ordering Gateway device | J158: 695 | K158: =B158*J158 -> 695
B160: 1 | C160: LCD monitor | J160: 175 | K160: =B160*J160 -> 175
B161: 1 | C161: Inkjet report printer | J161: 95 | K161: =B161*J161 -> 95
B162: 1 | C162: Dell Mono Laserjet printer | J162: 245 | K162: =B162*J162 -> 245
B163: 1 | C163: Brother Multi-Function Mono Laserjet printer ( Prt/Fax/Scan) | J163: 295 | K163: =B163*J163 -> 295
...

Sheet SOFTWARE
B1: Qty | D1: SOFTWARE (Taxable) | J1: Price | K1: Ext
C3: Note: The following are the standard, everyday unit pricing for each individual item.
C4: Discounts are available when compiling a quote for a full system with many components.
C5: Please seek assistance in preparing such a full system quote
C7: NCC SW MONTHLY
B9: 1 | C9: NCC Reflections R4 POS software, Per lane, per month | J9: 29 | K9: =B9*J9 -> 29
B10: 1 | C10: NCC Reflections EFT Payments Interface, Per lane, per month | J10: 29 | K10: =B10*J10 -> 29
B11: 1 | C11: NCC PCWS back office software, per month | J11: 29 | K11: =B11*J11 -> 29
B13: 1 | C13: NCC RHQ cloud reporting software, billed by NCC @ $50/mo/store | J13: 50 | K13: =B13*J13 -> 50
B15: 1 | C15: NCC INSIGHT management software ( includes PCWS) | J15: 125 | K15: =B15*J15 -> 125
C17: Maitre'd SW MONTHLY
B20: 1 | C20: MAITRE'D POS software, per WS 1-3, inc EFT, Gift, per month | J20: 69 | K20: =B20*J20 -> 69
B21: 1 | C21: MAITRE'D POS software, per WS 4-9, inc EFT, Gift, per month | J21: 49 | K21: =B21*J21 -> 49
B23: 1 | C23: MAITRE'D POS software, up to 4 workstations, inc EFT, Gift, per month | J23: 199 | K23: =B23*J23 -> 199
B24: 1 | C24: MAITRE'D POS software, MAX workstations, inc EFT, Gift, per month | J24: 299 | K24: =B24*J24 -> 299
B26: 1 | C26: MAITRE'D MPOS software, per Mobile Tablet,, inc EFT, Gift, per month | J26: 29 | K26: =B26*J26 -> 29
B28: 1 | C28: MAITRE'D Add-On Modules Package, per store, per month | J28: 49 | K28: =B28*J28 -> 49
C29: inc. PAT, cloud app, T/A, Acct, House, Hotel, Delivery, CCM, Scale
B31: 1 | C31: MAITRE'D Enterprise Management Corp Software, per store, per month | J31: TBD | K31: TBD
C34: Brink SW MONTHLY
B36: 1 | C36: BRINK POS Software, Ws #1, per month | J36: 90 | K36: =B36*J36 -> 90
B37: 1 | C37: BRINK POS Software, Ws # 2-4, per month | J37: 50 | K37: =B37*J37 -> 50
B38: 1 | C38: BRINK POS Software, Ws # 5-10, per month | J38: 30 | K38: =B38*J38 -> 30
B39: 1 | C39: BRINK POS Software, Ws #11+ , per month | J39: 20 | K39: =B39*J39 -> 20
C41: ( Note: Brink requires initial setup fee of $ 250 per store)
B43: 1 | C43: BRINK PAR PAY Software, First station , per month | J43: 39 | K43: =B43*J43 -> 39
B44: 1 | C44: BRINK PAR PAY Software, 2- x station , per month | J44: 15 | K44: =B44*J44 -> 15
C46: ( Par Pay requires initial setup fee of $ 175 per pinpad + cost of pinpad)
B48: 1 | C48: BRINK Kitchen Video Software, per station, per month | J48: 20 | K48: =B48*J48 -> 20
B50: 1 | C50: BRINK Future Date Ordering Software, per store, per month | J50: 15 | K50: =B50*J50 -> 15
B52: 1 | C52: BRINK Loyalty Software, per store, per month | J52: 75 | K52: =B52*J52 -> 75
B54: 1 | C54: BRINK POS Survey Software, per store, per month | J54: 15 | K54: =B54*J54 -> 15
B56: 1 | C56: BRINK Online Ordering 0-250 orders per month | J56: 75 | K56: =B56*J56 -> 75
B57: 1 | C57: BRINK Online Ordering 250-500 orders per month | J57: 125 | K57: =B57*J57 -> 125
B58: 1 | C58: BRINK Online Ordering 500-1000 orders per month | J58: 200 | K58: =B58*J58 -> 200
B59: 1 | C59: BRINK Online Ordering 1000-1500 orders per month | J59: 250 | K59: =B59*J59 -> 250
B60: 1 | C60: BRINK Online Ordering 1500-2000 orders per month | J60: 300 | K60: =B60*J60 -> 300
B61: 1 | C61: BRINK Online Ordering 2000-2500 orders per month | J61: 350 | K61: =B61*J61 -> 350
C64: Office/ Misc SW
B66: 1 | C66: Microsoft Windows 10 Pro | J66: 295 | K66: =B66*J66 -> 295
C73: Payments Processing
B75: 1 | C75: Datacap Twin-Tran Credit Auth Unit | J75: 1495 | K75: =B75*J75 -> 1495
B76: 1 | C76: Net-Epay CC processing Software, first workstation | J76: 1495 | K76: =B76*J76 -> 1495
B78: 1 | C78: discount for choosing WorldPay/ Evo as payments processor | J78: -1495 | K78: =B78*J78 -> -1495
B80: 1 | C80: Datacap Gift E-Pay processing interface ( non-mercury) | J80: 495 | K80: =B80*J80 -> 495
B82: 1 | C82: Datacap Tran Cloud Processing Unit, Lane #1 , PER MONTH | J82: 49 | K82: =B82*J82 -> 49
B83: 1 | C83: Datacap Tran Cloud Processing Unit, Lane #2-x , PER MONTH | J83: 29 | K83: =B83*J83 -> 29
B85: 1 | C85: Datacap Net E-Pay Processing SW, Lane #1 , per month | J85: 49 | K85: =B85*J85 -> 49
B86: 1 | C86: Datacap Net E-Pay Processing SW, Lane #2-x , per month | J86: 29 | K86: =B86*J86 -> 29

Sheet PARTS
B1: Qty | D1: Taxable Items | J1: Price | K1: Ext
C4: POS Printer Parts
B6: 1 | C6: External Power Supply | J6: 59 | K6: =B6*J6 -> 59
B7: 1 | C7: Thermal Print Head | J7: 95 | K7: =B7*J7 -> 95
B8: 1 | C8: Impact Dot Head | J8: 75 | K8: =B8*J8 -> 75
B9: 1 | C9: Printer Interface Card- Serial/Parallel | J9: 45 | K9: =B9*J9 -> 45
B10: 1 | C10: Printer Interface Card- Ethernet | J10: 95 | K10: =B10*J10 -> 95
B11: 1 | C11: External Plastic Casing | J11: 45 | K11: =B11*J11 -> 45
B12: 1 | C12: Printer Feed Assembly/Rollers | J12: 45 | K12: =B12*J12 -> 45
B13: 1 | C13: Printer Cutter Assembly | J13: 95 | K13: =B13*J13 -> 95
B14: 1 | C14: Printer Main CPU Board | J14: 95 | K14: =B14*J14 -> 95
C16: POS Workstation/PC Parts
B18: 1 | C18: Touchscreen- 15" | J18: 275 | K18: =B18*J18 -> 275
B19: 1 | C19: Touchscreen Assembly- Acrobat 14" | J19: 325 | K19: =B19*J19 -> 325
B20: 1 | C20: Touchscreen- 10" or 12" | J20: 195 | K20: =B20*J20 -> 195
B22: 1 | C22: External Power Supply- Workstation | J22: 75 | K22: =B22*J22 -> 75
B23: 1 | C23: Internal Power Supply | J23: 65 | K23: =B23*J23 -> 65
K24: =B24*J24 -> 0
B25: 1 | C25: Hard Drive | J25: 150 | K25: =B25*J25 -> 150
B26: 1 | C26: Ram Memory Chip | J26: 75 | K26: =B26*J26 -> 75
B27: 1 | C27: Compact Flash Card ( no sw) | J27: 45 | K27: =B27*J27 -> 45
B28: 1 | C28: Fan- PC/POS | J28: 45 | K28: =B28*J28 -> 45
B29: 1 | C29: Power Distribution Board | J29: 75 | K29: =B29*J29 -> 75
B30: 1 | C30: LCD Invertor | J30: 75 | K30: =B30*J30 -> 75
B31: 1 | C31: LCD Backlights | J31: 75 | K31: =B31*J31 -> 75
B32: 1 | C32: LCD Full assembly | J32: 375 | K32: =B32*J32 -> 375
B33: 1 | C33: Network Card | J33: 50 | K33: =B33*J33 -> 50
B34: 1 | C34: Main CPU Board Replace | J34: 295 | K34: =B34*J34 -> 295
B35: 1 | C35: Capacitor/Resistor/Transistor | J35: 5 | K35: =B35*J35 -> 5
B36: 1 | C36: CMOS Battery | J36: 25 | K36: =B36*J36 -> 25
... B45: 1 | C45: NCR WS RJ11- RJ45 Serial Port Adaptor | J45: 22.5 | K45: =B45*J45 -> 22.5
C47: Power Conditioner/UPS
B49: 1 | C49: Replacement Battery Set for UPS | J49: 95 | K49: =B49*J49 -> 95
B50: 1 | C50: Replacement Housing Panel- Oneac | J50: 19.5 | K50: =B50*J50 -> 19.5
C52: Cash Drawers
B54: 1 | C54: Replacement Cash Drawer, reconditioned (no till) | J54: 75 | K54: =B54*J54 -> 75
B55: 1 | C55: Replacement Cash Drawer, reconditioned (with till) | J55: 95 | K55: =B55*J55 -> 95
B56: 1 | C56: Epson Cash Drawer interface cable | J56: 9.5 | K56: =B56*J56 -> 9.5
B57: 1 | C57: Sharp Cash Drawer interface cable | J57: 9.5 | K57: =B57*J57 -> 9.5
B58: 1 | C58: Casio Cash Drawer interface cable | J58: 15 | K58: =B58*J58 -> 15
B60: 1 | C60: Dual Drawer Splitter Cable | J60: 15 | K60: =B60*J60 -> 15
B62: 1 | C62: Cash Drawer Plastic Till insert | J62: 50 | K62: =B62*J62 -> 50
B63: 1 | C63: Cash Drawer Metal Sliding Insert, reconditioned | J63: 50 | K63: =B63*J63 -> 50
B64: 1 | C64: Cash Drawer Rollers | J64: 5 | K64: =B64*J64 -> 5
B65: 1 | C65: Cash Drawer Till clip, springs,or bill weight | J65: 5 | K65: =B65*J65 -> 5
B66: 1 | C66: Cash Drawer Solenoid | J66: 45 | K66: =B66*J66 -> 45
B67: 1 | C67: Cash Drawer Lock Mechanism | J67: 25 | K67: =B67*J67 -> 25
... B69: 1 | C69: Cash Drawer Key, MMF, NCR Sharp, or Other | J69: 15 | K69: =B69*J69 -> 15
C71: Cash Registers
B73: 1 | C73: Printer Swap- whole unit | J73: 250 | K73: =B73*J73 -> 250
B74: 1 | C74: Printer Motor | J74: 75 | K74: =B74*J74 -> 75
B75: 1 | C75: Printer Gears/Misc Part | J75: 5 | K75: =B75*J75 -> 5
B76: 1 | C76: Printer Rollers | J76: 25 | K76: =B76*J76 -> 25
B77: 1 | C77: Printer - Clutch Assembly | J77: 50 | K77: =B77*J77 -> 50
B78: 1 | C78: Printer Belt | J78: 17.5 | K78: =B78*J78 -> 17.5
B79: 1 | C79: Printer Cutter Assembly | J79: 175 | K79: =B79*J79 -> 175
B80: 1 | C80: Printer Take-Up spool | J80: 27.5 | K80: =B80*J80 -> 27.5
B81: 1 | C81: Printer -Low paper sensor | J81: 19.5 | K81: =B81*J81 -> 19.5
K82: =B82*J82 -> 0
B83: 1 | C83: Mode Lock- Cash Register | J83: 75 | K83: =B83*J83 -> 75
B84: 1 | C84: Mode Lock Key | J84: 7.5 | K84: =B84*J84 -> 7.5
B86: 1 | C86: External Plastic Casing | J86: 45 | K86: =B86*J86 -> 45
B87: 1 | C87: Cash Register Power Supply | J87: 45 | K87: =B87*J87 -> 45
B88: 1 | C88: Cash Register Fuse | J88: 2.5 | K88: =B88*J88 -> 2.5
B89: 1 | C89: Cash Register Keyboard membrane/circuit | J89: 75 | K89: =B89*J89 -> 75
B90: 1 | C90: Cash Register Keyswitch | J90: 7.5 | K90: =B90*J90 -> 7.5
B91: 1 | C91: Cash Register Keyboard Cover, silicone | J91: 32 | K91: =B91*J91 -> 32
B92: 1 | C92: Cash Register Keyboard Menu Item template | J92: 45 | K92: =B92*J92 -> 45
B94: 1 | C94: Cash Register Battery | J94: 25 | K94: =B94*J94 -> 25
B95: 1 | C95: Cash Register Op/Cust Display circuit | J95: 75 | K95: =B95*J95 -> 75
B96: 1 | C96: Cash Register CPU board swap | J96: 275 | K96: =B96*J96 -> 275
C98: Cables/Connectors
B100: 1 | C100: Patch Cable- 1-3ft | J100: 5 | K100: =B100*J100 -> 5
B101: 1 | C101: Patch Cable- 7ft | J101: 7.5 | K101: =B101*J101 -> 7.5
B102: 1 | C102: Patch Cable- 14ft | J102: 15 | K102: =B102*J102 -> 15
B103: 1 | C103: Patch Cable- 25ft | J103: 25 | K103: =B103*J103 -> 25
B104: 1 | C104: Patch Cable- 50ft | J104: 45 | K104: =B104*J104 -> 45
B105: 1 | C105: Keystone Jack, RJ 45 | J105: 5 | K105: =B105*J105 -> 5
B106: 1 | C106: DB/RJ adaptor, each end | J106: 5 | K106: =B106*J106 -> 5
B107: 1 | C107: Pigtail RJ45- DB convertor- Tec 36/3700 | J107: 37.5 | K107: =B107*J107 -> 37.5
B108: 1 | C108: Printer to Workstation Cable, with ends | J108: 12.5 | K108: =B108*J108 -> 12.5
B109: 1 | C109: Raw Network Cable, per foot | J109: 0.4 | K109: =B109*J109 -> 0.4
B110: 1 | C110: RG59 DVR siamese cable | J110: 0.8 | K110: =B110*J110 -> 0.8
B111: 1 | C111: Patch Panel | J111: 50 | K111: =B111*J111 -> 50
... B119: 1 | C119: Power Strip | J119: 12.5 | K119: =B119*J119 -> 12.5
C121: Datamax
B122: 1 | C122: Thermal Head for Datamax | J122: 375 | K122: =B122*J122 -> 375
B123: 1 | C123: Platen for Datamax | J123: 75 | K123: =B123*J123 -> 75
C126: Pager Items
B128: 1 | C128: Pager Base Station, reconditioned | J128: 299 | K128: =B128*J128 -> 299
B129: 1 | C129: Pager, reconditioned | J129: 29 | K129: =B129*J129 -> 29
B130: 1 | C130: Charging station for Pagers, max 30 pagers per station, recon | J130: 45 | K130: =B130*J130 -> 45
B132: 1 | C132: Power Supply for Base or Charging Station, recon | J132: 17.5 | K132: =B132*J132 -> 17.5
B133: 1 | C133: Charging Station- Ind. Base Pad Only, recon | J133: 15 | K133: =B133*J133 -> 15
B134: 1 | C134: Charging Station- Jumper Cable Only, recon | J134: 5 | K134: =B134*J134 -> 5
C137: Apple Ipad Parts
B139: 1 | C139: Ipad MSR | J139: 57.5 | K139: =B139*J139 -> 57.5
B140: 1 | C140: Ipad Dockstub+ | J140: 37.5 | K140: =B140*J140 -> 37.5
B141: 1 | C141: Ipad Startech adaptor cable | J141: 7.5 | K141: =B141*J141 -> 7.5
B142: 1 | C142: Ipad "Y" cable | J142: 50 | K142: =B142*J142 -> 50
...

Sheet LABOR
B1: Qty | D1: Description | J1: Price | K1: Ext
B4: Labor Billing:
E5: Description: | J5: Hrly Rate
B6: 1 | C6: in-shop labor, business hours M-F | J6: 180 | K6: =SUM(B6*J6) -> 180
B7: 1 | C7: on-site labor, business hours M-F | J7: 180 | K7: =SUM(B7*J7) -> 180
B9: 1 | C9: in-shop labor- after hours rate | J9: 270 | K9: =SUM(B9*J9) -> 270
B10: 1 | C10: on-site labor- after hours rate | J10: 270 | K10: =SUM(B10*J10) -> 270
B12: 1 | C12: Minimum In-Shop Labor Rate, up to 30min | K12: 90
B13: 1 | C13: Minimum Business Hours Phone Support, up to 15min | K13: 45
B14: 1 | C14: Minimum After Hours Phone Support, up to 15min | K14: 75
B16: 1 | C16: Pickup/Delivery/Drop Off Fee | K16: 90
B18: 0.5 | C18: Travel Time | J18: 180 | K18: =SUM(B18*J18) -> 90
B20: 1 | C20: discount on hourly labor- BOH | J20: -60 | K20: =SUM(B20*J20) -> -60
B21: 1 | C21: discount on travel- BOH | J21: -30 | K21: =SUM(B21*J21) -> -30
B24: Installation Billing:
E25: Description: | J25: Rate
B26: 1 | C26: in-shop setup of POS, per station | J26: 75 | K26: =B26*J26 -> 75
B27: 1 | C27: in-shop initial setup/program of cash register | J27: 90 | K27: =B27*J27 -> 90
B28: 1 | C28: in-shop initial menu programming for NCC | J28: 480 | K28: =B28*J28 -> 480
B29: 1 | C29: in-shop initial menu programming for Maitre'd | J29: 960 | K29: =B29*J29 -> 960
B30: 1 | C30: in-shop initial menu programming for Brink | J30: 960 | K30: =B30*J30 -> 960
B31: 1 | C31: delivery, installation, per workstation | J31: 150 | K31: =B31*J31 -> 150
C32: Note: Client to provide adequate counters, electrical, net. cabling, internet
B33: 1 | C33: Training class , up to four hours ea | J33: 480 | K33: =B33*J33 -> 480
B34: 1 | C34: Discounted Day Rate for training, standby, or installation services | J34: 720 | K34: =B34*J34 -> 720
B35: 1 | C35: Post install followup training and/or add-on module implementation | J35: 360 | K35: =B35*J35 -> 360
B39: Help Desk Billing:
E40: Description: | J40: Rate
C41: Help Desk - Business Hours
B43: 1 | C43: Annual POS system Help Desk Support- Level One- NCC | J43: 500 | K43: =J43*B43 -> 500
B44: 1 | C44: Monthly POS system Help Desk Support- Level One- NCC | J44: 49 | K44: =J44*B44 -> 49
B46: 1 | C46: Annual POS system Help Desk Support- Level One- Maitre'd | J46: 600 | K46: =J46*B46 -> 600
B47: 1 | C47: MonthlyPOS system Help Desk Support- Level One- Maitre'd | J47: 69 | K47: =J47*B47 -> 69
C49: Allows for unlimited calls Mon-Fri business hours for routine operational
C50: software assistance and troubleshooting.
C51: Does not cover new manager training or significant system re-programming | K51: =J51*B51 -> 0
C53: Help Desk 7 x 24
B55: 1 | C55: Annual POS system Help Desk Support- Level Two- NCC | J55: 750 | K55: =J55*B55 -> 750
B56: 1 | C56: Monthly POS system Help Desk Support- Level Two- NCC | J56: 69 | K56: =J56*B56 -> 69
B58: 1 | C58: Annual POS system Help Desk Support- Level Two- Maitre'd | J58: 900 | K58: =J58*B58 -> 900
B59: 1 | C59: Monthly POS system Help Desk Support- Level Two-- Maitre'd | J59: 89 | K59: =J59*B59 -> 89
C62: Allows for unlimited calls Mon-Sun 7 x 24 hour for routine operational
C63: software assistance and troubleshooting.
C64: Does not cover new manager training or significant system re-programming | K64: =J64*B64 -> 0

Sheet MAINT
B1: Qty | D1: Service Contracts | J1: Price | K1: Ext
C3: All support plan options listed below are at standard pricing, payable upon receipt
C4: All support plans are auto-renewing until cancelled by client.
C5: No pro-rated refunds for unused periods
E7: Description: | J7: Rate
C8: Help Desk - Business Hours
B10: 1 | C10: Annual POS system Help Desk Support- Level One- NCC | J10: 500 | K10: =J10*B10 -> 500
B11: 1 | C11: Monthly POS system Help Desk Support- Level One- NCC | J11: 49 | K11: =J11*B11 -> 49
B13: 1 | C13: Annual POS system Help Desk Support- Level One- Maitre'd | J13: 600 | K13: =J13*B13 -> 600
B14: 1 | C14: MonthlyPOS system Help Desk Support- Level One- Maitre'd | J14: 69 | K14: =J14*B14 -> 69
C16: Allows for unlimited calls Mon-Fri business hours for routine operational
C17: software assistance and troubleshooting.
C18: Does not cover new manager training or significant system re-programming | K18: =J18*B18 -> 0
C20: Help Desk 7 x 24
B22: 1 | C22: Annual POS system Help Desk Support- Level Two- NCC | J22: 750 | K22: =J22*B22 -> 750
B23: 1 | C23: Monthly POS system Help Desk Support- Level Two- NCC | J23: 69 | K23: =J23*B23 -> 69
B25: 1 | C25: Annual POS system Help Desk Support- Level Two- Maitre'd | J25: 900 | K25: =J25*B25 -> 900
B26: 1 | C26: Monthly POS system Help Desk Support- Level Two-- Maitre'd | J26: 89 | K26: =J26*B26 -> 89
C29: Allows for unlimited calls Mon-Sun 7 x 24 hour for routine operational
C30: software assistance and troubleshooting.
C31: Does not cover new manager training or significant system re-programming | K31: =J31*B31 -> 0
C34: Annual POS Hardware Depot Repair Coverage
B36: 1 | C36: Office Server + peripherals | J36: 250 | K36: =B36*J36 -> 250
B37: 1 | C37: Workstations+ peripherals | J37: 250 | K37: =B37*J37 -> 250
B38: 1 | C38: Monthly Depot Repair Coverage, per workstation, 12 mo min | J38: 25 | K38: =B38*J38 -> 25
C40: Note: Client pays to ship to repair center, Performance pays to ship back ground
C41: Coverage applies to wear & tear resulting from normal operation of equipment
C43: Annual POS Hardware Onsite Repair Coverage- SF BAY Area only
B45: 1 | C45: Office Server + peripherals | J45: 500 | K45: =B45*J45 -> 500
B46: 1 | C46: Workstations+ peripherals | J46: 500 | K46: =B46*J46 -> 500
B47: 1 | C47: Monthly Onsite Repair Coverage, per workstation, 12 month min | J47: 49 | K47: =B47*J47 -> 49
C49: Note: All work to be performed during bus.hours M-F
C50: Coverage applies to wear & tear resulting from normal operation of equipment

Sheet TAX RATES 2020
A1: All Cities
A3: Effective April 1, 2019
A5: * Indicates incorporated city or incorporated town
A7: City | B7: Rate | C7: County
A9: Acampo | B9: 0.0775 | C9: San Joaquin
A10: Acton | B10: 0.095 | C10: Los Angeles
A11: Adelaida | B11: 0.0725 | C11: San Luis Obispo
A12: Adelanto* | B12: 0.0775 | C12: San Bernardino
A13: Adin | B13: 0.0725 | C13: Modoc
A14: Agoura | B14: 0.095 | C14: Los Angeles
A15: Agoura Hills* | B15: 0.095 | C15: Los Angeles
A16: Agua Caliente | B16: 0.0825 | C16: Sonoma
A17: Agua Caliente Springs | B17: 0.0775 | C17: San Diego
A18: Agua Dulce | B18: 0.095 | C18: Los Angeles
A19: Aguanga | B19: 0.0775 | C19: Riverside
A20: Ahwahnee | B20: 0.0775 | C20: Madera
... A1793: Zenia | B1793: 0.0725 | C1793: Trinity

Sheet EMPLOYEES
A1: Performance POS 415-451-4861 100-A Pelican Way, San Rafael CA 94901
A2: Toll-Free Support: 888-411-3375 support@performancepos.com
A3: Toll-Free Supplies: 800-581-2274 supplies@performancepos.com
A4: Fax 415-451-4866
A5: Employee | C5: Ext | D5: Desk | E5: Cell | F5: Email
A6: Angel Solorzano | B6: AS | C6: 1019 | D6: 415-960-3270 | E6: 908-357-8442 | F6: angel@performancepos.com
A7: Antonio Hudnall | B7: AH | C7: 1009 | E7: 415-532-6834 | F7: antonio@performancepos.com
A8: Dennis Fees | B8: DF | C8: 1012 | D8: 415-688-2721 | E8: 415-515-2483 | F8: dennisfees@performancepos.com
A9: Denny Deyerle | B9: DD | C9: 1010 | D9: 415-688-2602 | E9: 925-956-9245 | F9: denny@performancepos.com
A10: Doug Kelly | B10: DK | C10: 1005 | D10: 415-688-2354 | E10: 415-432-0630 | F10: dougkelly@performancepos.com
A11: Eltjon Lala | B11: EL | C11: 1015 | D11: 415-688-2724 | E11: 978-608-3975 | F11: eltjon@performancepos.com
A12: Jose Santos | B12: JS | C12: 1007 | D12: 415-688-2358 | E12: 415-747-2564 | F12: josesantos@performancepos.com
A13: Lowell Galang | B13: LG | C13: 1016 | D13: 415-870-2036 | E13: 650-278-2997 | F13: lgalang@performancepos.com
A14: Milton Bland | B14: MB | C14: 1006 | D14: 415-688-2357 | E14: 415-747-0039 | F14: milton@performancepos.com
A15: Nikaela King | B15: NK | C15: 1018 | D15: 415-960-3272 | E15: 510-323-5209 | F15: nikaela@performancepos.com
A16: Rich Alden | B16: RA | C16: 1008 | D16: 415-688-2599 | E16: 415-747-0038 | F16: richalden@performancepos.com
A17: Rob Freaney | B17: RF | C17: 1001 | D17: 415-688-2348 | E17: 415-747-2568 | F17: robfreaney@performancepos.com
A18: Sandy Gonzalez | B18: SG | C18: 1011 | D18: 415-688-2603 | E18: 415-312-4175 | F18: sandy@performancepos.com
A19: Showroom | C19: 1004
A20: Shipping Desk | C20: 1013
A21: Install Room | C21: 1014
A23: Outside Tech Resources
A25: Pete Pizzino | B25: PP | D25: 510-506-6316 | F25: cashreg@sbcglobal.net
A26: Alain Rousseau | B26: AR | D26: 514-730-9995 | F26: arousseau2020@gmail.com
A27: POS & ECR
A28: NCC & RHQ | D28: 866-944-5164 | F28: nccusa.com & nccusa.com/rhq
A29: Posera Maitre'd | D29: 888-404-2662 | F29: distributors.maitredpos.com
A30: Casio | D30: 800-633-5586 | F30: casio.com
A31: Credit Cards
A32: Datacap | D32: 215-997-8989 | F32: datacapsystems.com
A33: Mercury Vantiv | D33: 800-846-4472 | F33: techsupport@mercurypay.com
A34: Sterling | D34: 800-591-6098 | F34: sterlingpayment.com
